Workbook

Sheet Résumé
A1: Récapitulatif des charges — Compte BRED EJ 2026
A2: Période couverte : 02/01/2026 au 10/07/2026 — 889 opérations
A4: Total encaissements | B4: =SUMIF(Détail!F:F,"Encaissement*",Détail!E:E) -> 643902.63
A5: Total charges (hors encaissements, hors chèques/saisie à vérifier) | B5: =SUMIFS(Détail!E:E,Détail!F:F,"<>Encaissement (hors périmètre charges)",Détail!F:F,"<>Paiement par chèque (à vérifier)",Détail!F:F,"<>Saisie administrative") -> -636709.75
A6: Solde net (encaissements + charges + à vérifier) | B6: =SUMIF(Détail!F:F,"<>",Détail!E:E) -> 5217.88
A8: Détail par catégorie de charge
A9: Catégorie | B9: Nb opérations | C9: Montant total (€) | D9: % du total charges
A10: Fournisseurs matières premières & emballage (France) | B10: =COUNTIF(Détail!F:F,A10) -> 24 | C10: =SUMIF(Détail!F:F,A10,Détail!E:E) -> -244170.98 | D10: =C10/$B$5 -> 0.38348868
A11: Usine de conditionnement et macération | B11: =COUNTIF(Détail!F:F,A11) -> 12 | C11: =SUMIF(Détail!F:F,A11,Détail!E:E) -> -136758.73 | D11: =C11/$B$5 -> 0.21478975
A12: Fournisseurs internationaux (Chine/Import) | B12: =COUNTIF(Détail!F:F,A12) -> 13 | C12: =SUMIF(Détail!F:F,A12,Détail!E:E) -> -57342.97 | D12: =C12/$B$5 -> 0.090061398
A13: Transport / livraison (colis, courrier) | B13: =COUNTIF(Détail!F:F,A13) -> 48 | C13: =SUMIF(Détail!F:F,A13,Détail!E:E) -> -42914.9 | D13: =C13/$B$5 -> 0.067401041
A14: Salaires (salariés) | B14: =COUNTIF(Détail!F:F,A14) -> 25 | C14: =SUMIF(Détail!F:F,A14,Détail!E:E) -> -33658.99 | D14: =C14/$B$5 -> 0.052863946
A15: Charges sociales & cotisations | B15: =COUNTIF(Détail!F:F,A15) -> 24 | C15: =SUMIF(Détail!F:F,A15,Détail!E:E) -> -25681.14 | D15: =C15/$B$5 -> 0.04033414
A16: Rémunération gérant | B16: =COUNTIF(Détail!F:F,A16) -> 11 | C16: =SUMIF(Détail!F:F,A16,Détail!E:E) -> -24300 | D16: =C16/$B$5 -> 0.038164957
A17: Carburant, péages, parking, leasing | B17: =COUNTIF(Détail!F:F,A17) -> 197 | C17: =SUMIF(Détail!F:F,A17,Détail!E:E) -> -13245.95 | D17: =C17/$B$5 -> 0.020803749
A18: Frais professionnels divers | B18: =COUNTIF(Détail!F:F,A18) -> 55 | C18: =SUMIF(Détail!F:F,A18,Détail!E:E) -> -12908.5 | D18: =C18/$B$5 -> 0.020273759
A19: Voyages / déplacements | B19: =COUNTIF(Détail!F:F,A19) -> 44 | C19: =SUMIF(Détail!F:F,A19,Détail!E:E) -> -10275.06 | D19: =C19/$B$5 -> 0.016137746
A20: Téléphone / Internet / Logiciels | B20: =COUNTIF(Détail!F:F,A20) -> 99 | C20: =SUMIF(Détail!F:F,A20,Détail!E:E) -> -7501.73 | D20: =C20/$B$5 -> 0.011782025
A21: Électricité / Gaz | B21: =COUNTIF(Détail!F:F,A21) -> 13 | C21: =SUMIF(Détail!F:F,A21,Détail!E:E) -> -5559.55 | D21: =C21/$B$5 -> 0.0087316866
... A31: Restauration | B31: =COUNTIF(Détail!F:F,A31) -> 18 | C31: =SUMIF(Détail!F:F,A31,Détail!E:E) -> -410.79 | D31: =C31/$B$5 -> 0.00064517624
A32: TOTAL | B32: =SUM(B10:B31) -> 820 | C32: =SUM(C10:C31) -> -638684.75

Sheet Revenus
A1: Revenus — Compte BRED EJ 2026
A2: Période couverte : 02/01/2026 au 08/07/2026 — 69 encaissements
A4: Total encaissements | B4: =SUM('Détail Revenus'!E:E) -> 643902.63
A6: Détail par source de revenu
A7: Source | B7: Nb opérations | C7: Montant total (€) | D7: % du total
A8: NB Evolution FZCO (factures NB...) | B8: =COUNTIF('Détail Revenus'!F:F,A8) -> 16 | C8: =SUMIF('Détail Revenus'!F:F,A8,'Détail Revenus'!E:E) -> 395976.38 | D8: =C8/$B$4 -> 0.61496314
A9: Usine Algérie (Jade Création — sans marge) | B9: =COUNTIF('Détail Revenus'!F:F,A9) -> 5 | C9: =SUMIF('Détail Revenus'!F:F,A9,'Détail Revenus'!E:E) -> 101673.36 | D9: =C9/$B$4 -> 0.15790176
A10: Al Muftah | B10: =COUNTIF('Détail Revenus'!F:F,A10) -> 3 | C10: =SUMIF('Détail Revenus'!F:F,A10,'Détail Revenus'!E:E) -> 71936.54 | D10: =C10/$B$4 -> 0.11171959
A11: Autres clients (probables, non confirmés) | B11: =COUNTIF('Détail Revenus'!F:F,A11) -> 0 | C11: =SUMIF('Détail Revenus'!F:F,A11,'Détail Revenus'!E:E) -> 0 | D11: =C11/$B$4 -> 0
A12: Encaissements non identifiés | B12: =COUNTIF('Détail Revenus'!F:F,A12) -> 0 | C12: =SUMIF('Détail Revenus'!F:F,A12,'Détail Revenus'!E:E) -> 0 | D12: =C12/$B$4 -> 0
A13: Arzum Group Mmc | B13: =COUNTIF('Détail Revenus'!F:F,A13) -> 1 | C13: =SUMIF('Détail Revenus'!F:F,A13,'Détail Revenus'!E:E) -> 10142 | D13: =C13/$B$4 -> 0.015750829
A14: Passion Parfum | B14: =COUNTIF('Détail Revenus'!F:F,A14) -> 7 | C14: =SUMIF('Détail Revenus'!F:F,A14,'Détail Revenus'!E:E) -> 37140 | D14: =C14/$B$4 -> 0.057679528
A15: Mb Tressoria | B15: =COUNTIF('Détail Revenus'!F:F,A15) -> 3 | C15: =SUMIF('Détail Revenus'!F:F,A15,'Détail Revenus'!E:E) -> 13067 | D15: =C15/$B$4 -> 0.020293441
A16: Stf Perfumeria | B16: =COUNTIF('Détail Revenus'!F:F,A16) -> 2 | C16: =SUMIF('Détail Revenus'!F:F,A16,'Détail Revenus'!E:E) -> 2777 | D16: =C16/$B$4 -> 0.0043127639
A17: Alfa Group Srls | B17: =COUNTIF('Détail Revenus'!F:F,A17) -> 1 | C17: =SUMIF('Détail Revenus'!F:F,A17,'Détail Revenus'!E:E) -> 2394 | D17: =C17/$B$4 -> 0.0037179534
A18: Ventes en ligne (boutique Shopify) | B18: =COUNTIF('Détail Revenus'!F:F,A18) -> 28 | C18: =SUMIF('Détail Revenus'!F:F,A18,'Détail Revenus'!E:E) -> 1638.75 | D18: =C18/$B$4 -> 0.0025450277
A19: Firm Rheds | B19: =COUNTIF('Détail Revenus'!F:F,A19) -> 1 | C19: =SUMIF('Détail Revenus'!F:F,A19,'Détail Revenus'!E:E) -> 624 | D19: =C19/$B$4 -> 0.00096909062
... A21: Frais de dossier facturés (client) | B21: =COUNTIF('Détail Revenus'!F:F,A21) -> 1 | C21: =SUMIF('Détail Revenus'!F:F,A21,'Détail Revenus'!E:E) -> 303.6 | D21: =C21/$B$4 -> 0.00047149986
A22: TOTAL | B22: =SUM(B8:B21) -> 69 | C22: =SUM(C8:C21) -> 643902.63
A24: 🟠 En orange : sources pas encore confirmées avec Mounir

Sheet Revenus détail
A1: Revenus — détail par source et par mois (2026)
A3: NB Evolution FZCO (factures NB...) | C3: =SUMIF('Détail Revenus'!$F:$F,"NB Evolution FZCO (factures NB...)",'Détail Revenus'!$E:$E) -> 395976.38
A4: Mois | B4: Montant
A5: Janvier 2026 | B5: =SUMIFS('Détail Revenus'!$E:$E,'Détail Revenus'!$F:$F,"NB Evolution FZCO (factures NB...)",'Détail Revenus'!$A:$A,">="&DATE(2026,1,1),'Détail Revenus'!$A:$A,"<"&EDATE(DATE(2026,1,1),1)) -> 45807.68
A6: Février 2026 | B6: =SUMIFS('Détail Revenus'!$E:$E,'Détail Revenus'!$F:$F,"NB Evolution FZCO (factures NB...)",'Détail Revenus'!$A:$A,">="&DATE(2026,2,1),'Détail Revenus'!$A:$A,"<"&EDATE(DATE(2026,2,1),1)) -> 55968.7
A7: Mars 2026 | B7: =SUMIFS('Détail Revenus'!$E:$E,'Détail Revenus'!$F:$F,"NB Evolution FZCO (factures NB...)",'Détail Revenus'!$A:$A,">="&DATE(2026,3,1),'Détail Revenus'!$A:$A,"<"&EDATE(DATE(2026,3,1),1)) -> 48000
A8: Avril 2026 | B8: =SUMIFS('Détail Revenus'!$E:$E,'Détail Revenus'!$F:$F,"NB Evolution FZCO (factures NB...)",'Détail Revenus'!$A:$A,">="&DATE(2026,4,1),'Détail Revenus'!$A:$A,"<"&EDATE(DATE(2026,4,1),1)) -> 72200
A9: Mai 2026 | B9: =SUMIFS('Détail Revenus'!$E:$E,'Détail Revenus'!$F:$F,"NB Evolution FZCO (factures NB...)",'Détail Revenus'!$A:$A,">="&DATE(2026,5,1),'Détail Revenus'!$A:$A,"<"&EDATE(DATE(2026,5,1),1)) -> 59200
A10: Juin 2026 | B10: =SUMIFS('Détail Revenus'!$E:$E,'Détail Revenus'!$F:$F,"NB Evolution FZCO (factures NB...)",'Détail Revenus'!$A:$A,">="&DATE(2026,6,1),'Détail Revenus'!$A:$A,"<"&EDATE(DATE(2026,6,1),1)) -> 94800
A11: Juillet 2026 | B11: =SUMIFS('Détail Revenus'!$E:$E,'Détail Revenus'!$F:$F,"NB Evolution FZCO (factures NB...)",'Détail Revenus'!$A:$A,">="&DATE(2026,7,1),'Détail Revenus'!$A:$A,"<"&EDATE(DATE(2026,7,1),1)) -> 20000
A14: Usine Algérie (Jade Création — sans marge) | C14: =SUMIF('Détail Revenus'!$F:$F,"Usine Algérie (Jade Création — sans marge)",'Détail Revenus'!$E:$E) -> 101673.36
A15: Noms bancaires d'origine : | B15: SARL JADE CREATION SALGDZALXXX, JADE CREATION SARL
A16: Mois | B16: Montant
A17: Janvier 2026 | B17: =SUMIFS('Détail Revenus'!$E:$E,'Détail Revenus'!$F:$F,"Usine Algérie (Jade Création — sans marge)",'Détail Revenus'!$A:$A,">="&DATE(2026,1,1),'Détail Revenus'!$A:$A,"<"&EDATE(DATE(2026,1,1),1)) -> 5284.36
A18: Février 2026 | B18: =SUMIFS('Détail Revenus'!$E:$E,'Détail Revenus'!$F:$F,"Usine Algérie (Jade Création — sans marge)",'Détail Revenus'!$A:$A,">="&DATE(2026,2,1),'Détail Revenus'!$A:$A,"<"&EDATE(DATE(2026,2,1),1)) -> 0
A19: Mars 2026 | B19: =SUMIFS('Détail Revenus'!$E:$E,'Détail Revenus'!$F:$F,"Usine Algérie (Jade Création — sans marge)",'Détail Revenus'!$A:$A,">="&DATE(2026,3,1),'Détail Revenus'!$A:$A,"<"&EDATE(DATE(2026,3,1),1)) -> 0
A20: Avril 2026 | B20: =SUMIFS('Détail Revenus'!$E:$E,'Détail Revenus'!$F:$F,"Usine Algérie (Jade Création — sans marge)",'Détail Revenus'!$A:$A,">="&DATE(2026,4,1),'Détail Revenus'!$A:$A,"<"&EDATE(DATE(2026,4,1),1)) -> 0
A21: Mai 2026 | B21: =SUMIFS('Détail Revenus'!$E:$E,'Détail Revenus'!$F:$F,"Usine Algérie (Jade Création — sans marge)",'Détail Revenus'!$A:$A,">="&DATE(2026,5,1),'Détail Revenus'!$A:$A,"<"&EDATE(DATE(2026,5,1),1)) -> 46714
A22: Juin 2026 | B22: =SUMIFS('Détail Revenus'!$E:$E,'Détail Revenus'!$F:$F,"Usine Algérie (Jade Création — sans marge)",'Détail Revenus'!$A:$A,">="&DATE(2026,6,1),'Détail Revenus'!$A:$A,"<"&EDATE(DATE(2026,6,1),1)) -> 49675
A23: Juillet 2026 | B23: =SUMIFS('Détail Revenus'!$E:$E,'Détail Revenus'!$F:$F,"Usine Algérie (Jade Création — sans marge)",'Détail Revenus'!$A:$A,">="&DATE(2026,7,1),'Détail Revenus'!$A:$A,"<"&EDATE(DATE(2026,7,1),1)) -> 0
A26: Al Muftah | C26: =SUMIF('Détail Revenus'!$F:$F,"Al Muftah",'Détail Revenus'!$E:$E) -> 71936.54
A27: Noms bancaires d'origine : | B27: ALMUFTAH MARKETING, ALMUFTAH TRADING AND CONT CO.
A28: Mois | B28: Montant
A29: Janvier 2026 | B29: =SUMIFS('Détail Revenus'!$E:$E,'Détail Revenus'!$F:$F,"Al Muftah",'Détail Revenus'!$A:$A,">="&DATE(2026,1,1),'Détail Revenus'!$A:$A,"<"&EDATE(DATE(2026,1,1),1)) -> 21555.14
A30: Février 2026 | B30: =SUMIFS('Détail Revenus'!$E:$E,'Détail Revenus'!$F:$F,"Al Muftah",'Détail Revenus'!$A:$A,">="&DATE(2026,2,1),'Détail Revenus'!$A:$A,"<"&EDATE(DATE(2026,2,1),1)) -> 0
A31: Mars 2026 | B31: =SUMIFS('Détail Revenus'!$E:$E,'Détail Revenus'!$F:$F,"Al Muftah",'Détail Revenus'!$A:$A,">="&DATE(2026,3,1),'Détail Revenus'!$A:$A,"<"&EDATE(DATE(2026,3,1),1)) -> 0
A32: Avril 2026 | B32: =SUMIFS('Détail Revenus'!$E:$E,'Détail Revenus'!$F:$F,"Al Muftah",'Détail Revenus'!$A:$A,">="&DATE(2026,4,1),'Détail Revenus'!$A:$A,"<"&EDATE(DATE(2026,4,1),1)) -> 25223
A33: Mai 2026 | B33: =SUMIFS('Détail Revenus'!$E:$E,'Détail Revenus'!$F:$F,"Al Muftah",'Détail Revenus'!$A:$A,">="&DATE(2026,5,1),'Détail Revenus'!$A:$A,"<"&EDATE(DATE(2026,5,1),1)) -> 0
A34: Juin 2026 | B34: =SUMIFS('Détail Revenus'!$E:$E,'Détail Revenus'!$F:$F,"Al Muftah",'Détail Revenus'!$A:$A,">="&DATE(2026,6,1),'Détail Revenus'!$A:$A,"<"&EDATE(DATE(2026,6,1),1)) -> 25158.4
A35: Juillet 2026 | B35: =SUMIFS('Détail Revenus'!$E:$E,'Détail Revenus'!$F:$F,"Al Muftah",'Détail Revenus'!$A:$A,">="&DATE(2026,7,1),'Détail Revenus'!$A:$A,"<"&EDATE(DATE(2026,7,1),1)) -> 0
A38: Autres clients (probables, non confirmés) | C38: =SUMIF('Détail Revenus'!$F:$F,"Autres clients (probables, non confirmés)",'Détail Revenus'!$E:$E) -> 0
A39: Noms bancaires d'origine : | B39: FLASHCONNECT, GLOBAL AUTO 94
A40: Mois | B40: Montant
A41: Janvier 2026 | B41: =SUMIFS('Détail Revenus'!$E:$E,'Détail Revenus'!$F:$F,"Autres clients (probables, non confirmés)",'Détail Revenus'!$A:$A,">="&DATE(2026,1,1),'Détail Revenus'!$A:$A,"<"&EDATE(DATE(2026,1,1),1)) -> 0
A42: Février 2026 | B42: =SUMIFS('Détail Revenus'!$E:$E,'Détail Revenus'!$F:$F,"Autres clients (probables, non confirmés)",'Détail Revenus'!$A:$A,">="&DATE(2026,2,1),'Détail Revenus'!$A:$A,"<"&EDATE(DATE(2026,2,1),1)) -> 0
A43: Mars 2026 | B43: =SUMIFS('Détail Revenus'!$E:$E,'Détail Revenus'!$F:$F,"Autres clients (probables, non confirmés)",'Détail Revenus'!$A:$A,">="&DATE(2026,3,1),'Détail Revenus'!$A:$A,"<"&EDATE(DATE(2026,3,1),1)) -> 0
A44: Avril 2026 | B44: =SUMIFS('Détail Revenus'!$E:$E,'Détail Revenus'!$F:$F,"Autres clients (probables, non confirmés)",'Détail Revenus'!$A:$A,">="&DATE(2026,4,1),'Détail Revenus'!$A:$A,"<"&EDATE(DATE(2026,4,1),1)) -> 0
A45: Mai 2026 | B45: =SUMIFS('Détail Revenus'!$E:$E,'Détail Revenus'!$F:$F,"Autres clients (probables, non confirmés)",'Détail Revenus'!$A:$A,">="&DATE(2026,5,1),'Détail Revenus'!$A:$A,"<"&EDATE(DATE(2026,5,1),1)) -> 0
A46: Juin 2026 | B46: =SUMIFS('Détail Revenus'!$E:$E,'Détail Revenus'!$F:$F,"Autres clients (probables, non confirmés)",'Détail Revenus'!$A:$A,">="&DATE(2026,6,1),'Détail Revenus'!$A:$A,"<"&EDATE(DATE(2026,6,1),1)) -> 0
A47: Juillet 2026 | B47: =SUMIFS('Détail Revenus'!$E:$E,'Détail Revenus'!$F:$F,"Autres clients (probables, non confirmés)",'Détail Revenus'!$A:$A,">="&DATE(2026,7,1),'Détail Revenus'!$A:$A,"<"&EDATE(DATE(2026,7,1),1)) -> 0
A50: Encaissements non identifiés | C50: =SUMIF('Détail Revenus'!$F:$F,"Encaissements non identifiés",'Détail Revenus'!$E:$E) -> 0
A51: Noms bancaires d'origine : | B51: SIE MARNE ET BOIS, UZDAROJI AKCINE BENDROVE "VILARTINA", ODA PRESTIGE, nan
A52: Mois | B52: Montant
A53: Janvier 2026 | B53: =SUMIFS('Détail Revenus'!$E:$E,'Détail Revenus'!$F:$F,"Encaissements non identifiés",'Détail Revenus'!$A:$A,">="&DATE(2026,1,1),'Détail Revenus'!$A:$A,"<"&EDATE(DATE(2026,1,1),1)) -> 0
A54: Février 2026 | B54: =SUMIFS('Détail Revenus'!$E:$E,'Détail Revenus'!$F:$F,"Encaissements non identifiés",'Détail Revenus'!$A:$A,">="&DATE(2026,2,1),'Détail Revenus'!$A:$A,"<"&EDATE(DATE(2026,2,1),1)) -> 0
A55: Mars 2026 | B55: =SUMIFS('Détail Revenus'!$E:$E,'Détail Revenus'!$F:$F,"Encaissements non identifiés",'Détail Revenus'!$A:$A,">="&DATE(2026,3,1),'Détail Revenus'!$A:$A,"<"&EDATE(DATE(2026,3,1),1)) -> 0
A56: Avril 2026 | B56: =SUMIFS('Détail Revenus'!$E:$E,'Détail Revenus'!$F:$F,"Encaissements non identifiés",'Détail Revenus'!$A:$A,">="&DATE(2026,4,1),'Détail Revenus'!$A:$A,"<"&EDATE(DATE(2026,4,1),1)) -> 0
A57: Mai 2026 | B57: =SUMIFS('Détail Revenus'!$E:$E,'Détail Revenus'!$F:$F,"Encaissements non identifiés",'Détail Revenus'!$A:$A,">="&DATE(2026,5,1),'Détail Revenus'!$A:$A,"<"&EDATE(DATE(2026,5,1),1)) -> 0
A58: Juin 2026 | B58: =SUMIFS('Détail Revenus'!$E:$E,'Détail Revenus'!$F:$F,"Encaissements non identifiés",'Détail Revenus'!$A:$A,">="&DATE(2026,6,1),'Détail Revenus'!$A:$A,"<"&EDATE(DATE(2026,6,1),1)) -> 0
A59: Juillet 2026 | B59: =SUMIFS('Détail Revenus'!$E:$E,'Détail Revenus'!$F:$F,"Encaissements non identifiés",'Détail Revenus'!$A:$A,">="&DATE(2026,7,1),'Détail Revenus'!$A:$A,"<"&EDATE(DATE(2026,7,1),1)) -> 0
A62: Arzum Group Mmc | C62: =SUMIF('Détail Revenus'!$F:$F,"Arzum Group Mmc",'Détail Revenus'!$E:$E) -> 10142
A63: Mois | B63: Montant
A64: Janvier 2026 | B64: =SUMIFS('Détail Revenus'!$E:$E,'Détail Revenus'!$F:$F,"Arzum Group Mmc",'Détail Revenus'!$A:$A,">="&DATE(2026,1,1),'Détail Revenus'!$A:$A,"<"&EDATE(DATE(2026,1,1),1)) -> 0
A65: Février 2026 | B65: =SUMIFS('Détail Revenus'!$E:$E,'Détail Revenus'!$F:$F,"Arzum Group Mmc",'Détail Revenus'!$A:$A,">="&DATE(2026,2,1),'Détail Revenus'!$A:$A,"<"&EDATE(DATE(2026,2,1),1)) -> 0
A66: Mars 2026 | B66: =SUMIFS('Détail Revenus'!$E:$E,'Détail Revenus'!$F:$F,"Arzum Group Mmc",'Détail Revenus'!$A:$A,">="&DATE(2026,3,1),'Détail Revenus'!$A:$A,"<"&EDATE(DATE(2026,3,1),1)) -> 0
A67: Avril 2026 | B67: =SUMIFS('Détail Revenus'!$E:$E,'Détail Revenus'!$F:$F,"Arzum Group Mmc",'Détail Revenus'!$A:$A,">="&DATE(2026,4,1),'Détail Revenus'!$A:$A,"<"&EDATE(DATE(2026,4,1),1)) -> 0
A68: Mai 2026 | B68: =SUMIFS('Détail Revenus'!$E:$E,'Détail Revenus'!$F:$F,"Arzum Group Mmc",'Détail Revenus'!$A:$A,">="&DATE(2026,5,1),'Détail Revenus'!$A:$A,"<"&EDATE(DATE(2026,5,1),1)) -> 0
A69: Juin 2026 | B69: =SUMIFS('Détail Revenus'!$E:$E,'Détail Revenus'!$F:$F,"Arzum Group Mmc",'Détail Revenus'!$A:$A,">="&DATE(2026,6,1),'Détail Revenus'!$A:$A,"<"&EDATE(DATE(2026,6,1),1)) -> 0
A70: Juillet 2026 | B70: =SUMIFS('Détail Revenus'!$E:$E,'Détail Revenus'!$F:$F,"Arzum Group Mmc",'Détail Revenus'!$A:$A,">="&DATE(2026,7,1),'Détail Revenus'!$A:$A,"<"&EDATE(DATE(2026,7,1),1)) -> 10142
A73: Passion Parfum | C73: =SUMIF('Détail Revenus'!$F:$F,"Passion Parfum",'Détail Revenus'!$E:$E) -> 37140
A74: Mois | B74: Montant
A75: Janvier 2026 | B75: =SUMIFS('Détail Revenus'!$E:$E,'Détail Revenus'!$F:$F,"Passion Parfum",'Détail Revenus'!$A:$A,">="&DATE(2026,1,1),'Détail Revenus'!$A:$A,"<"&EDATE(DATE(2026,1,1),1)) -> 0
A76: Février 2026 | B76: =SUMIFS('Détail Revenus'!$E:$E,'Détail Revenus'!$F:$F,"Passion Parfum",'Détail Revenus'!$A:$A,">="&DATE(2026,2,1),'Détail Revenus'!$A:$A,"<"&EDATE(DATE(2026,2,1),1)) -> 0
A77: Mars 2026 | B77: =SUMIFS('Détail Revenus'!$E:$E,'Détail Revenus'!$F:$F,"Passion Parfum",'Détail Revenus'!$A:$A,">="&DATE(2026,3,1),'Détail Revenus'!$A:$A,"<"&EDATE(DATE(2026,3,1),1)) -> 0
A78: Avril 2026 | B78: =SUMIFS('Détail Revenus'!$E:$E,'Détail Revenus'!$F:$F,"Passion Parfum",'Détail Revenus'!$A:$A,">="&DATE(2026,4,1),'Détail Revenus'!$A:$A,"<"&EDATE(DATE(2026,4,1),1)) -> 8420
A79: Mai 2026 | B79: =SUMIFS('Détail Revenus'!$E:$E,'Détail Revenus'!$F:$F,"Passion Parfum",'Détail Revenus'!$A:$A,">="&DATE(2026,5,1),'Détail Revenus'!$A:$A,"<"&EDATE(DATE(2026,5,1),1)) -> 23720
A80: Juin 2026 | B80: =SUMIFS('Détail Revenus'!$E:$E,'Détail Revenus'!$F:$F,"Passion Parfum",'Détail Revenus'!$A:$A,">="&DATE(2026,6,1),'Détail Revenus'!$A:$A,"<"&EDATE(DATE(2026,6,1),1)) -> 5000
A81: Juillet 2026 | B81: =SUMIFS('Détail Revenus'!$E:$E,'Détail Revenus'!$F:$F,"Passion Parfum",'Détail Revenus'!$A:$A,">="&DATE(2026,7,1),'Détail Revenus'!$A:$A,"<"&EDATE(DATE(2026,7,1),1)) -> 0
A84: Mb Tressoria | C84: =SUMIF('Détail Revenus'!$F:$F,"Mb Tressoria",'Détail Revenus'!$E:$E) -> 13067
A85: Mois | B85: Montant
A86: Janvier 2026 | B86: =SUMIFS('Détail Revenus'!$E:$E,'Détail Revenus'!$F:$F,"Mb Tressoria",'Détail Revenus'!$A:$A,">="&DATE(2026,1,1),'Détail Revenus'!$A:$A,"<"&EDATE(DATE(2026,1,1),1)) -> 6186
A87: Février 2026 | B87: =SUMIFS('Détail Revenus'!$E:$E,'Détail Revenus'!$F:$F,"Mb Tressoria",'Détail Revenus'!$A:$A,">="&DATE(2026,2,1),'Détail Revenus'!$A:$A,"<"&EDATE(DATE(2026,2,1),1)) -> 0
A88: Mars 2026 | B88: =SUMIFS('Détail Revenus'!$E:$E,'Détail Revenus'!$F:$F,"Mb Tressoria",'Détail Revenus'!$A:$A,">="&DATE(2026,3,1),'Détail Revenus'!$A:$A,"<"&EDATE(DATE(2026,3,1),1)) -> 0
A89: Avril 2026 | B89: =SUMIFS('Détail Revenus'!$E:$E,'Détail Revenus'!$F:$F,"Mb Tressoria",'Détail Revenus'!$A:$A,">="&DATE(2026,4,1),'Détail Revenus'!$A:$A,"<"&EDATE(DATE(2026,4,1),1)) -> 4786
A90: Mai 2026 | B90: =SUMIFS('Détail Revenus'!$E:$E,'Détail Revenus'!$F:$F,"Mb Tressoria",'Détail Revenus'!$A:$A,">="&DATE(2026,5,1),'Détail Revenus'!$A:$A,"<"&EDATE(DATE(2026,5,1),1)) -> 2095
A91: Juin 2026 | B91: =SUMIFS('Détail Revenus'!$E:$E,'Détail Revenus'!$F:$F,"Mb Tressoria",'Détail Revenus'!$A:$A,">="&DATE(2026,6,1),'Détail Revenus'!$A:$A,"<"&EDATE(DATE(2026,6,1),1)) -> 0
A92: Juillet 2026 | B92: =SUMIFS('Détail Revenus'!$E:$E,'Détail Revenus'!$F:$F,"Mb Tressoria",'Détail Revenus'!$A:$A,">="&DATE(2026,7,1),'Détail Revenus'!$A:$A,"<"&EDATE(DATE(2026,7,1),1)) -> 0
A95: Stf Perfumeria | C95: =SUMIF('Détail Revenus'!$F:$F,"Stf Perfumeria",'Détail Revenus'!$E:$E) -> 2777
A96: Mois | B96: Montant
A97: Janvier 2026 | B97: =SUMIFS('Détail Revenus'!$E:$E,'Détail Revenus'!$F:$F,"Stf Perfumeria",'Détail Revenus'!$A:$A,">="&DATE(2026,1,1),'Détail Revenus'!$A:$A,"<"&EDATE(DATE(2026,1,1),1)) -> 0
A98: Février 2026 | B98: =SUMIFS('Détail Revenus'!$E:$E,'Détail Revenus'!$F:$F,"Stf Perfumeria",'Détail Revenus'!$A:$A,">="&DATE(2026,2,1),'Détail Revenus'!$A:$A,"<"&EDATE(DATE(2026,2,1),1)) -> 0
A99: Mars 2026 | B99: =SUMIFS('Détail Revenus'!$E:$E,'Détail Revenus'!$F:$F,"Stf Perfumeria",'Détail Revenus'!$A:$A,">="&DATE(2026,3,1),'Détail Revenus'!$A:$A,"<"&EDATE(DATE(2026,3,1),1)) -> 1048
A100: Avril 2026 | B100: =SUMIFS('Détail Revenus'!$E:$E,'Détail Revenus'!$F:$F,"Stf Perfumeria",'Détail Revenus'!$A:$A,">="&DATE(2026,4,1),'Détail Revenus'!$A:$A,"<"&EDATE(DATE(2026,4,1),1)) -> 1729
A101: Mai 2026 | B101: =SUMIFS('Détail Revenus'!$E:$E,'Détail Revenus'!$F:$F,"Stf Perfumeria",'Détail Revenus'!$A:$A,">="&DATE(2026,5,1),'Détail Revenus'!$A:$A,"<"&EDATE(DATE(2026,5,1),1)) -> 0
A102: Juin 2026 | B102: =SUMIFS('Détail Revenus'!$E:$E,'Détail Revenus'!$F:$F,"Stf Perfumeria",'Détail Revenus'!$A:$A,">="&DATE(2026,6,1),'Détail Revenus'!$A:$A,"<"&EDATE(DATE(2026,6,1),1)) -> 0
A103: Juillet 2026 | B103: =SUMIFS('Détail Revenus'!$E:$E,'Détail Revenus'!$F:$F,"Stf Perfumeria",'Détail Revenus'!$A:$A,">="&DATE(2026,7,1),'Détail Revenus'!$A:$A,"<"&EDATE(DATE(2026,7,1),1)) -> 0
A106: Alfa Group Srls | C106: =SUMIF('Détail Revenus'!$F:$F,"Alfa Group Srls",'Détail Revenus'!$E:$E) -> 2394
A107: Mois | B107: Montant
A108: Janvier 2026 | B108: =SUMIFS('Détail Revenus'!$E:$E,'Détail Revenus'!$F:$F,"Alfa Group Srls",'Détail Revenus'!$A:$A,">="&DATE(2026,1,1),'Détail Revenus'!$A:$A,"<"&EDATE(DATE(2026,1,1),1)) -> 0
A109: Février 2026 | B109: =SUMIFS('Détail Revenus'!$E:$E,'Détail Revenus'!$F:$F,"Alfa Group Srls",'Détail Revenus'!$A:$A,">="&DATE(2026,2,1),'Détail Revenus'!$A:$A,"<"&EDATE(DATE(2026,2,1),1)) -> 2394
A110: Mars 2026 | B110: =SUMIFS('Détail Revenus'!$E:$E,'Détail Revenus'!$F:$F,"Alfa Group Srls",'Détail Revenus'!$A:$A,">="&DATE(2026,3,1),'Détail Revenus'!$A:$A,"<"&EDATE(DATE(2026,3,1),1)) -> 0
A111: Avril 2026 | B111: =SUMIFS('Détail Revenus'!$E:$E,'Détail Revenus'!$F:$F,"Alfa Group Srls",'Détail Revenus'!$A:$A,">="&DATE(2026,4,1),'Détail Revenus'!$A:$A,"<"&EDATE(DATE(2026,4,1),1)) -> 0
A112: Mai 2026 | B112: =SUMIFS('Détail Revenus'!$E:$E,'Détail Revenus'!$F:$F,"Alfa Group Srls",'Détail Revenus'!$A:$A,">="&DATE(2026,5,1),'Détail Revenus'!$A:$A,"<"&EDATE(DATE(2026,5,1),1)) -> 0
A113: Juin 2026 | B113: =SUMIFS('Détail Revenus'!$E:$E,'Détail Revenus'!$F:$F,"Alfa Group Srls",'Détail Revenus'!$A:$A,">="&DATE(2026,6,1),'Détail Revenus'!$A:$A,"<"&EDATE(DATE(2026,6,1),1)) -> 0
A114: Juillet 2026 | B114: =SUMIFS('Détail Revenus'!$E:$E,'Détail Revenus'!$F:$F,"Alfa Group Srls",'Détail Revenus'!$A:$A,">="&DATE(2026,7,1),'Détail Revenus'!$A:$A,"<"&EDATE(DATE(2026,7,1),1)) -> 0
A117: Ventes en ligne (boutique Shopify) | C117: =SUMIF('Détail Revenus'!$F:$F,"Ventes en ligne (boutique Shopify)",'Détail Revenus'!$E:$E) -> 1638.75
A118: Mois | B118: Montant
A119: Janvier 2026 | B119: =SUMIFS('Détail Revenus'!$E:$E,'Détail Revenus'!$F:$F,"Ventes en ligne (boutique Shopify)",'Détail Revenus'!$A:$A,">="&DATE(2026,1,1),'Détail Revenus'!$A:$A,"<"&EDATE(DATE(2026,1,1),1)) -> 387.17
A120: Février 2026 | B120: =SUMIFS('Détail Revenus'!$E:$E,'Détail Revenus'!$F:$F,"Ventes en ligne (boutique Shopify)",'Détail Revenus'!$A:$A,">="&DATE(2026,2,1),'Détail Revenus'!$A:$A,"<"&EDATE(DATE(2026,2,1),1)) -> 137.38
A121: Mars 2026 | B121: =SUMIFS('Détail Revenus'!$E:$E,'Détail Revenus'!$F:$F,"Ventes en ligne (boutique Shopify)",'Détail Revenus'!$A:$A,">="&DATE(2026,3,1),'Détail Revenus'!$A:$A,"<"&EDATE(DATE(2026,3,1),1)) -> 176.43
...

Sheet Salaires détail
A1: Salaires & rémunération gérant — détail par personne (2026)
A3: Mr Boudjada Said (Gérant — rémunération libre) | C3: =SUMIF(Détail!$D:$D,"MR BOUDJADA SAID",Détail!$E:$E) -> -24300
A4: Mois | B4: Montant
A5: Janvier 2026 | B5: =SUMIFS(Détail!$E:$E,Détail!$D:$D,"MR BOUDJADA SAID",Détail!$A:$A,">="&DATE(2026,1,1),Détail!$A:$A,"<"&EDATE(DATE(2026,1,1),1)) -> -4700
A6: Février 2026 | B6: =SUMIFS(Détail!$E:$E,Détail!$D:$D,"MR BOUDJADA SAID",Détail!$A:$A,">="&DATE(2026,2,1),Détail!$A:$A,"<"&EDATE(DATE(2026,2,1),1)) -> -3600
A7: Mars 2026 | B7: =SUMIFS(Détail!$E:$E,Détail!$D:$D,"MR BOUDJADA SAID",Détail!$A:$A,">="&DATE(2026,3,1),Détail!$A:$A,"<"&EDATE(DATE(2026,3,1),1)) -> 0
A8: Avril 2026 | B8: =SUMIFS(Détail!$E:$E,Détail!$D:$D,"MR BOUDJADA SAID",Détail!$A:$A,">="&DATE(2026,4,1),Détail!$A:$A,"<"&EDATE(DATE(2026,4,1),1)) -> -7000
A9: Mai 2026 | B9: =SUMIFS(Détail!$E:$E,Détail!$D:$D,"MR BOUDJADA SAID",Détail!$A:$A,">="&DATE(2026,5,1),Détail!$A:$A,"<"&EDATE(DATE(2026,5,1),1)) -> -5000
A10: Juin 2026 | B10: =SUMIFS(Détail!$E:$E,Détail!$D:$D,"MR BOUDJADA SAID",Détail!$A:$A,">="&DATE(2026,6,1),Détail!$A:$A,"<"&EDATE(DATE(2026,6,1),1)) -> 0
A11: Juillet 2026 | B11: =SUMIFS(Détail!$E:$E,Détail!$D:$D,"MR BOUDJADA SAID",Détail!$A:$A,">="&DATE(2026,7,1),Détail!$A:$A,"<"&EDATE(DATE(2026,7,1),1)) -> -4000
A14: Mr Boudaja Nassim (Salarié) | C14: =SUMIF(Détail!$D:$D,"MR BOUDAJA NASSIM",Détail!$E:$E) -> -14792.28
A15: Mois | B15: Montant
A16: Janvier 2026 | B16: =SUMIFS(Détail!$E:$E,Détail!$D:$D,"MR BOUDAJA NASSIM",Détail!$A:$A,">="&DATE(2026,1,1),Détail!$A:$A,"<"&EDATE(DATE(2026,1,1),1)) -> -2465.38
A17: Février 2026 | B17: =SUMIFS(Détail!$E:$E,Détail!$D:$D,"MR BOUDAJA NASSIM",Détail!$A:$A,">="&DATE(2026,2,1),Détail!$A:$A,"<"&EDATE(DATE(2026,2,1),1)) -> -2465.38
A18: Mars 2026 | B18: =SUMIFS(Détail!$E:$E,Détail!$D:$D,"MR BOUDAJA NASSIM",Détail!$A:$A,">="&DATE(2026,3,1),Détail!$A:$A,"<"&EDATE(DATE(2026,3,1),1)) -> -2465.38
A19: Avril 2026 | B19: =SUMIFS(Détail!$E:$E,Détail!$D:$D,"MR BOUDAJA NASSIM",Détail!$A:$A,">="&DATE(2026,4,1),Détail!$A:$A,"<"&EDATE(DATE(2026,4,1),1)) -> -2465.38
A20: Mai 2026 | B20: =SUMIFS(Détail!$E:$E,Détail!$D:$D,"MR BOUDAJA NASSIM",Détail!$A:$A,">="&DATE(2026,5,1),Détail!$A:$A,"<"&EDATE(DATE(2026,5,1),1)) -> -2465.38
A21: Juin 2026 | B21: =SUMIFS(Détail!$E:$E,Détail!$D:$D,"MR BOUDAJA NASSIM",Détail!$A:$A,">="&DATE(2026,6,1),Détail!$A:$A,"<"&EDATE(DATE(2026,6,1),1)) -> -2465.38
A22: Juillet 2026 | B22: =SUMIFS(Détail!$E:$E,Détail!$D:$D,"MR BOUDAJA NASSIM",Détail!$A:$A,">="&DATE(2026,7,1),Détail!$A:$A,"<"&EDATE(DATE(2026,7,1),1)) -> 0
A25: Mme Machado Natali (Salarié) | C25: =SUMIF(Détail!$D:$D,"MME MACHADO NATALI",Détail!$E:$E) -> -8456.58
A26: Mois | B26: Montant
A27: Janvier 2026 | B27: =SUMIFS(Détail!$E:$E,Détail!$D:$D,"MME MACHADO NATALI",Détail!$A:$A,">="&DATE(2026,1,1),Détail!$A:$A,"<"&EDATE(DATE(2026,1,1),1)) -> -1287.51
A28: Février 2026 | B28: =SUMIFS(Détail!$E:$E,Détail!$D:$D,"MME MACHADO NATALI",Détail!$A:$A,">="&DATE(2026,2,1),Détail!$A:$A,"<"&EDATE(DATE(2026,2,1),1)) -> -1284.87
A29: Mars 2026 | B29: =SUMIFS(Détail!$E:$E,Détail!$D:$D,"MME MACHADO NATALI",Détail!$A:$A,">="&DATE(2026,3,1),Détail!$A:$A,"<"&EDATE(DATE(2026,3,1),1)) -> -1282.23
A30: Avril 2026 | B30: =SUMIFS(Détail!$E:$E,Détail!$D:$D,"MME MACHADO NATALI",Détail!$A:$A,">="&DATE(2026,4,1),Détail!$A:$A,"<"&EDATE(DATE(2026,4,1),1)) -> -1532.23
A31: Mai 2026 | B31: =SUMIFS(Détail!$E:$E,Détail!$D:$D,"MME MACHADO NATALI",Détail!$A:$A,">="&DATE(2026,5,1),Détail!$A:$A,"<"&EDATE(DATE(2026,5,1),1)) -> -1537.51
A32: Juin 2026 | B32: =SUMIFS(Détail!$E:$E,Détail!$D:$D,"MME MACHADO NATALI",Détail!$A:$A,">="&DATE(2026,6,1),Détail!$A:$A,"<"&EDATE(DATE(2026,6,1),1)) -> -1532.23
A33: Juillet 2026 | B33: =SUMIFS(Détail!$E:$E,Détail!$D:$D,"MME MACHADO NATALI",Détail!$A:$A,">="&DATE(2026,7,1),Détail!$A:$A,"<"&EDATE(DATE(2026,7,1),1)) -> 0
A36: Mr Boudjada Mounir (Salarié) | C36: =SUMIF(Détail!$D:$D,"MR BOUDJADA MOUNIR",Détail!$E:$E) -> -7740.99
A37: Mois | B37: Montant
A38: Janvier 2026 | B38: =SUMIFS(Détail!$E:$E,Détail!$D:$D,"MR BOUDJADA MOUNIR",Détail!$A:$A,">="&DATE(2026,1,1),Détail!$A:$A,"<"&EDATE(DATE(2026,1,1),1)) -> -1233.82
A39: Février 2026 | B39: =SUMIFS(Détail!$E:$E,Détail!$D:$D,"MR BOUDJADA MOUNIR",Détail!$A:$A,">="&DATE(2026,2,1),Détail!$A:$A,"<"&EDATE(DATE(2026,2,1),1)) -> -1233.82
A40: Mars 2026 | B40: =SUMIFS(Détail!$E:$E,Détail!$D:$D,"MR BOUDJADA MOUNIR",Détail!$A:$A,">="&DATE(2026,3,1),Détail!$A:$A,"<"&EDATE(DATE(2026,3,1),1)) -> -1233.82
A41: Avril 2026 | B41: =SUMIFS(Détail!$E:$E,Détail!$D:$D,"MR BOUDJADA MOUNIR",Détail!$A:$A,">="&DATE(2026,4,1),Détail!$A:$A,"<"&EDATE(DATE(2026,4,1),1)) -> -1233.82
A42: Mai 2026 | B42: =SUMIFS(Détail!$E:$E,Détail!$D:$D,"MR BOUDJADA MOUNIR",Détail!$A:$A,">="&DATE(2026,5,1),Détail!$A:$A,"<"&EDATE(DATE(2026,5,1),1)) -> -1829.82
A43: Juin 2026 | B43: =SUMIFS(Détail!$E:$E,Détail!$D:$D,"MR BOUDJADA MOUNIR",Détail!$A:$A,">="&DATE(2026,6,1),Détail!$A:$A,"<"&EDATE(DATE(2026,6,1),1)) -> -975.89
A44: Juillet 2026 | B44: =SUMIFS(Détail!$E:$E,Détail!$D:$D,"MR BOUDJADA MOUNIR",Détail!$A:$A,">="&DATE(2026,7,1),Détail!$A:$A,"<"&EDATE(DATE(2026,7,1),1)) -> 0
A47: Mme Sabrina Mahmoudi (Salarié) | C47: =SUMIF(Détail!$D:$D,"MME SABRINA MAHMOUDI",Détail!$E:$E) -> -2669.14
A48: Mois | B48: Montant
A49: Janvier 2026 | B49: =SUMIFS(Détail!$E:$E,Détail!$D:$D,"MME SABRINA MAHMOUDI",Détail!$A:$A,">="&DATE(2026,1,1),Détail!$A:$A,"<"&EDATE(DATE(2026,1,1),1)) -> 0
A50: Février 2026 | B50: =SUMIFS(Détail!$E:$E,Détail!$D:$D,"MME SABRINA MAHMOUDI",Détail!$A:$A,">="&DATE(2026,2,1),Détail!$A:$A,"<"&EDATE(DATE(2026,2,1),1)) -> 0
A51: Mars 2026 | B51: =SUMIFS(Détail!$E:$E,Détail!$D:$D,"MME SABRINA MAHMOUDI",Détail!$A:$A,">="&DATE(2026,3,1),Détail!$A:$A,"<"&EDATE(DATE(2026,3,1),1)) -> 0
A52: Avril 2026 | B52: =SUMIFS(Détail!$E:$E,Détail!$D:$D,"MME SABRINA MAHMOUDI",Détail!$A:$A,">="&DATE(2026,4,1),Détail!$A:$A,"<"&EDATE(DATE(2026,4,1),1)) -> 0
A53: Mai 2026 | B53: =SUMIFS(Détail!$E:$E,Détail!$D:$D,"MME SABRINA MAHMOUDI",Détail!$A:$A,">="&DATE(2026,5,1),Détail!$A:$A,"<"&EDATE(DATE(2026,5,1),1)) -> -1281.61
A54: Juin 2026 | B54: =SUMIFS(Détail!$E:$E,Détail!$D:$D,"MME SABRINA MAHMOUDI",Détail!$A:$A,">="&DATE(2026,6,1),Détail!$A:$A,"<"&EDATE(DATE(2026,6,1),1)) -> -1387.53
A55: Juillet 2026 | B55: =SUMIFS(Détail!$E:$E,Détail!$D:$D,"MME SABRINA MAHMOUDI",Détail!$A:$A,">="&DATE(2026,7,1),Détail!$A:$A,"<"&EDATE(DATE(2026,7,1),1)) -> 0

Sheet Fournisseurs France détail
A1: Fournisseurs matières premières & emballage (France) — détail par fournisseur (2026)
A3: Cpl Aromas France | C3: =SUMIF(Détail!$D:$D,"CPL AROMAS FRANCE",Détail!$E:$E) -> -105066.75
A4: Mois | B4: Montant
A5: Janvier 2026 | B5: =SUMIFS(Détail!$E:$E,Détail!$D:$D,"CPL AROMAS FRANCE",Détail!$A:$A,">="&DATE(2026,1,1),Détail!$A:$A,"<"&EDATE(DATE(2026,1,1),1)) -> -13893
A6: Février 2026 | B6: =SUMIFS(Détail!$E:$E,Détail!$D:$D,"CPL AROMAS FRANCE",Détail!$A:$A,">="&DATE(2026,2,1),Détail!$A:$A,"<"&EDATE(DATE(2026,2,1),1)) -> -4860
A7: Avril 2026 | B7: =SUMIFS(Détail!$E:$E,Détail!$D:$D,"CPL AROMAS FRANCE",Détail!$A:$A,">="&DATE(2026,4,1),Détail!$A:$A,"<"&EDATE(DATE(2026,4,1),1)) -> -25538.75
A8: Mai 2026 | B8: =SUMIFS(Détail!$E:$E,Détail!$D:$D,"CPL AROMAS FRANCE",Détail!$A:$A,">="&DATE(2026,5,1),Détail!$A:$A,"<"&EDATE(DATE(2026,5,1),1)) -> -34580
A9: Juin 2026 | B9: =SUMIFS(Détail!$E:$E,Détail!$D:$D,"CPL AROMAS FRANCE",Détail!$A:$A,">="&DATE(2026,6,1),Détail!$A:$A,"<"&EDATE(DATE(2026,6,1),1)) -> -26195
A10: Juillet 2026 | B10: =SUMIFS(Détail!$E:$E,Détail!$D:$D,"CPL AROMAS FRANCE",Détail!$A:$A,">="&DATE(2026,7,1),Détail!$A:$A,"<"&EDATE(DATE(2026,7,1),1)) -> 0
A13: Aromascent | C13: =SUMIF(Détail!$D:$D,"AROMASCENT",Détail!$E:$E) -> -85707
A14: Mois | B14: Montant
A15: Janvier 2026 | B15: =SUMIFS(Détail!$E:$E,Détail!$D:$D,"AROMASCENT",Détail!$A:$A,">="&DATE(2026,1,1),Détail!$A:$A,"<"&EDATE(DATE(2026,1,1),1)) -> -5222
A16: Février 2026 | B16: =SUMIFS(Détail!$E:$E,Détail!$D:$D,"AROMASCENT",Détail!$A:$A,">="&DATE(2026,2,1),Détail!$A:$A,"<"&EDATE(DATE(2026,2,1),1)) -> -13638
A17: Avril 2026 | B17: =SUMIFS(Détail!$E:$E,Détail!$D:$D,"AROMASCENT",Détail!$A:$A,">="&DATE(2026,4,1),Détail!$A:$A,"<"&EDATE(DATE(2026,4,1),1)) -> -13484
A18: Mai 2026 | B18: =SUMIFS(Détail!$E:$E,Détail!$D:$D,"AROMASCENT",Détail!$A:$A,">="&DATE(2026,5,1),Détail!$A:$A,"<"&EDATE(DATE(2026,5,1),1)) -> 0
A19: Juin 2026 | B19: =SUMIFS(Détail!$E:$E,Détail!$D:$D,"AROMASCENT",Détail!$A:$A,">="&DATE(2026,6,1),Détail!$A:$A,"<"&EDATE(DATE(2026,6,1),1)) -> -53363
A20: Juillet 2026 | B20: =SUMIFS(Détail!$E:$E,Détail!$D:$D,"AROMASCENT",Détail!$A:$A,">="&DATE(2026,7,1),Détail!$A:$A,"<"&EDATE(DATE(2026,7,1),1)) -> 0
A23: Firmenich | C23: =SUMIF(Détail!$D:$D,"FIRMENICH",Détail!$E:$E) -> -19500.6
A24: Mois | B24: Montant
A25: Janvier 2026 | B25: =SUMIFS(Détail!$E:$E,Détail!$D:$D,"FIRMENICH",Détail!$A:$A,">="&DATE(2026,1,1),Détail!$A:$A,"<"&EDATE(DATE(2026,1,1),1)) -> 0
A26: Février 2026 | B26: =SUMIFS(Détail!$E:$E,Détail!$D:$D,"FIRMENICH",Détail!$A:$A,">="&DATE(2026,2,1),Détail!$A:$A,"<"&EDATE(DATE(2026,2,1),1)) -> 0
A27: Avril 2026 | B27: =SUMIFS(Détail!$E:$E,Détail!$D:$D,"FIRMENICH",Détail!$A:$A,">="&DATE(2026,4,1),Détail!$A:$A,"<"&EDATE(DATE(2026,4,1),1)) -> 0
A28: Mai 2026 | B28: =SUMIFS(Détail!$E:$E,Détail!$D:$D,"FIRMENICH",Détail!$A:$A,">="&DATE(2026,5,1),Détail!$A:$A,"<"&EDATE(DATE(2026,5,1),1)) -> -19500.6
A29: Juin 2026 | B29: =SUMIFS(Détail!$E:$E,Détail!$D:$D,"FIRMENICH",Détail!$A:$A,">="&DATE(2026,6,1),Détail!$A:$A,"<"&EDATE(DATE(2026,6,1),1)) -> 0
A30: Juillet 2026 | B30: =SUMIFS(Détail!$E:$E,Détail!$D:$D,"FIRMENICH",Détail!$A:$A,">="&DATE(2026,7,1),Détail!$A:$A,"<"&EDATE(DATE(2026,7,1),1)) -> 0
A33: Cartonnages Du Val D Orge | C33: =SUMIF(Détail!$D:$D,"CARTONNAGES DU VAL D ORGE",Détail!$E:$E) -> -7922.52
A34: Mois | B34: Montant
A35: Janvier 2026 | B35: =SUMIFS(Détail!$E:$E,Détail!$D:$D,"CARTONNAGES DU VAL D ORGE",Détail!$A:$A,">="&DATE(2026,1,1),Détail!$A:$A,"<"&EDATE(DATE(2026,1,1),1)) -> -1828.8
A36: Février 2026 | B36: =SUMIFS(Détail!$E:$E,Détail!$D:$D,"CARTONNAGES DU VAL D ORGE",Détail!$A:$A,">="&DATE(2026,2,1),Détail!$A:$A,"<"&EDATE(DATE(2026,2,1),1)) -> 0
A37: Avril 2026 | B37: =SUMIFS(Détail!$E:$E,Détail!$D:$D,"CARTONNAGES DU VAL D ORGE",Détail!$A:$A,">="&DATE(2026,4,1),Détail!$A:$A,"<"&EDATE(DATE(2026,4,1),1)) -> 0
A38: Mai 2026 | B38: =SUMIFS(Détail!$E:$E,Détail!$D:$D,"CARTONNAGES DU VAL D ORGE",Détail!$A:$A,">="&DATE(2026,5,1),Détail!$A:$A,"<"&EDATE(DATE(2026,5,1),1)) -> -6093.72
A39: Juin 2026 | B39: =SUMIFS(Détail!$E:$E,Détail!$D:$D,"CARTONNAGES DU VAL D ORGE",Détail!$A:$A,">="&DATE(2026,6,1),Détail!$A:$A,"<"&EDATE(DATE(2026,6,1),1)) -> 0
A40: Juillet 2026 | B40: =SUMIFS(Détail!$E:$E,Détail!$D:$D,"CARTONNAGES DU VAL D ORGE",Détail!$A:$A,">="&DATE(2026,7,1),Détail!$A:$A,"<"&EDATE(DATE(2026,7,1),1)) -> 0
A43: Sleeve Concept | C43: =SUMIF(Détail!$D:$D,"SLEEVE CONCEPT",Détail!$E:$E) -> -7707.85
A44: Mois | B44: Montant
A45: Janvier 2026 | B45: =SUMIFS(Détail!$E:$E,Détail!$D:$D,"SLEEVE CONCEPT",Détail!$A:$A,">="&DATE(2026,1,1),Détail!$A:$A,"<"&EDATE(DATE(2026,1,1),1)) -> -7707.85
A46: Février 2026 | B46: =SUMIFS(Détail!$E:$E,Détail!$D:$D,"SLEEVE CONCEPT",Détail!$A:$A,">="&DATE(2026,2,1),Détail!$A:$A,"<"&EDATE(DATE(2026,2,1),1)) -> 0
A47: Avril 2026 | B47: =SUMIFS(Détail!$E:$E,Détail!$D:$D,"SLEEVE CONCEPT",Détail!$A:$A,">="&DATE(2026,4,1),Détail!$A:$A,"<"&EDATE(DATE(2026,4,1),1)) -> 0
A48: Mai 2026 | B48: =SUMIFS(Détail!$E:$E,Détail!$D:$D,"SLEEVE CONCEPT",Détail!$A:$A,">="&DATE(2026,5,1),Détail!$A:$A,"<"&EDATE(DATE(2026,5,1),1)) -> 0
A49: Juin 2026 | B49: =SUMIFS(Détail!$E:$E,Détail!$D:$D,"SLEEVE CONCEPT",Détail!$A:$A,">="&DATE(2026,6,1),Détail!$A:$A,"<"&EDATE(DATE(2026,6,1),1)) -> 0
A50: Juillet 2026 | B50: =SUMIFS(Détail!$E:$E,Détail!$D:$D,"SLEEVE CONCEPT",Détail!$A:$A,">="&DATE(2026,7,1),Détail!$A:$A,"<"&EDATE(DATE(2026,7,1),1)) -> 0
A53: Neroli France | C53: =SUMIF(Détail!$D:$D,"NEROLI FRANCE",Détail!$E:$E) -> -6837.75
A54: Mois | B54: Montant
A55: Janvier 2026 | B55: =SUMIFS(Détail!$E:$E,Détail!$D:$D,"NEROLI FRANCE",Détail!$A:$A,">="&DATE(2026,1,1),Détail!$A:$A,"<"&EDATE(DATE(2026,1,1),1)) -> 0
A56: Février 2026 | B56: =SUMIFS(Détail!$E:$E,Détail!$D:$D,"NEROLI FRANCE",Détail!$A:$A,">="&DATE(2026,2,1),Détail!$A:$A,"<"&EDATE(DATE(2026,2,1),1)) -> 0
A57: Avril 2026 | B57: =SUMIFS(Détail!$E:$E,Détail!$D:$D,"NEROLI FRANCE",Détail!$A:$A,">="&DATE(2026,4,1),Détail!$A:$A,"<"&EDATE(DATE(2026,4,1),1)) -> 0
A58: Mai 2026 | B58: =SUMIFS(Détail!$E:$E,Détail!$D:$D,"NEROLI FRANCE",Détail!$A:$A,">="&DATE(2026,5,1),Détail!$A:$A,"<"&EDATE(DATE(2026,5,1),1)) -> 0
A59: Juin 2026 | B59: =SUMIFS(Détail!$E:$E,Détail!$D:$D,"NEROLI FRANCE",Détail!$A:$A,">="&DATE(2026,6,1),Détail!$A:$A,"<"&EDATE(DATE(2026,6,1),1)) -> -6837.75
A60: Juillet 2026 | B60: =SUMIFS(Détail!$E:$E,Détail!$D:$D,"NEROLI FRANCE",Détail!$A:$A,">="&DATE(2026,7,1),Détail!$A:$A,"<"&EDATE(DATE(2026,7,1),1)) -> 0
A63: Sleeve Concept | C63: =SUMIF(Détail!$D:$D,"SLEEVE CONCEPT",Détail!$E:$E) -> -5828.01
A64: Mois | B64: Montant
A65: Janvier 2026 | B65: =SUMIFS(Détail!$E:$E,Détail!$D:$D,"SLEEVE CONCEPT",Détail!$A:$A,">="&DATE(2026,1,1),Détail!$A:$A,"<"&EDATE(DATE(2026,1,1),1)) -> 0
A66: Février 2026 | B66: =SUMIFS(Détail!$E:$E,Détail!$D:$D,"SLEEVE CONCEPT",Détail!$A:$A,">="&DATE(2026,2,1),Détail!$A:$A,"<"&EDATE(DATE(2026,2,1),1)) -> 0
A67: Avril 2026 | B67: =SUMIFS(Détail!$E:$E,Détail!$D:$D,"SLEEVE CONCEPT",Détail!$A:$A,">="&DATE(2026,4,1),Détail!$A:$A,"<"&EDATE(DATE(2026,4,1),1)) -> -3176.4
A68: Mai 2026 | B68: =SUMIFS(Détail!$E:$E,Détail!$D:$D,"SLEEVE CONCEPT",Détail!$A:$A,">="&DATE(2026,5,1),Détail!$A:$A,"<"&EDATE(DATE(2026,5,1),1)) -> 0
A69: Juin 2026 | B69: =SUMIFS(Détail!$E:$E,Détail!$D:$D,"SLEEVE CONCEPT",Détail!$A:$A,">="&DATE(2026,6,1),Détail!$A:$A,"<"&EDATE(DATE(2026,6,1),1)) -> -2651.61
A70: Juillet 2026 | B70: =SUMIFS(Détail!$E:$E,Détail!$D:$D,"SLEEVE CONCEPT",Détail!$A:$A,">="&DATE(2026,7,1),Détail!$A:$A,"<"&EDATE(DATE(2026,7,1),1)) -> 0
A73: Nasmir Europe Fragrances | C73: =SUMIF(Détail!$D:$D,"NASMIR EUROPE FRAGRANCES",Détail!$E:$E) -> -2432
A74: Mois | B74: Montant
A75: Janvier 2026 | B75: =SUMIFS(Détail!$E:$E,Détail!$D:$D,"NASMIR EUROPE FRAGRANCES",Détail!$A:$A,">="&DATE(2026,1,1),Détail!$A:$A,"<"&EDATE(DATE(2026,1,1),1)) -> 0
A76: Février 2026 | B76: =SUMIFS(Détail!$E:$E,Détail!$D:$D,"NASMIR EUROPE FRAGRANCES",Détail!$A:$A,">="&DATE(2026,2,1),Détail!$A:$A,"<"&EDATE(DATE(2026,2,1),1)) -> 0
A77: Avril 2026 | B77: =SUMIFS(Détail!$E:$E,Détail!$D:$D,"NASMIR EUROPE FRAGRANCES",Détail!$A:$A,">="&DATE(2026,4,1),Détail!$A:$A,"<"&EDATE(DATE(2026,4,1),1)) -> 0
A78: Mai 2026 | B78: =SUMIFS(Détail!$E:$E,Détail!$D:$D,"NASMIR EUROPE FRAGRANCES",Détail!$A:$A,">="&DATE(2026,5,1),Détail!$A:$A,"<"&EDATE(DATE(2026,5,1),1)) -> -2432
A79: Juin 2026 | B79: =SUMIFS(Détail!$E:$E,Détail!$D:$D,"NASMIR EUROPE FRAGRANCES",Détail!$A:$A,">="&DATE(2026,6,1),Détail!$A:$A,"<"&EDATE(DATE(2026,6,1),1)) -> 0
A80: Juillet 2026 | B80: =SUMIFS(Détail!$E:$E,Détail!$D:$D,"NASMIR EUROPE FRAGRANCES",Détail!$A:$A,">="&DATE(2026,7,1),Détail!$A:$A,"<"&EDATE(DATE(2026,7,1),1)) -> 0
A83: Nasmir Europe Fragrances | C83: =SUMIF(Détail!$D:$D,"NASMIR EUROPE FRAGRANCES",Détail!$E:$E) -> -1738.5
A84: Mois | B84: Montant
A85: Janvier 2026 | B85: =SUMIFS(Détail!$E:$E,Détail!$D:$D,"NASMIR EUROPE FRAGRANCES",Détail!$A:$A,">="&DATE(2026,1,1),Détail!$A:$A,"<"&EDATE(DATE(2026,1,1),1)) -> 0
A86: Février 2026 | B86: =SUMIFS(Détail!$E:$E,Détail!$D:$D,"NASMIR EUROPE FRAGRANCES",Détail!$A:$A,">="&DATE(2026,2,1),Détail!$A:$A,"<"&EDATE(DATE(2026,2,1),1)) -> 0
A87: Avril 2026 | B87: =SUMIFS(Détail!$E:$E,Détail!$D:$D,"NASMIR EUROPE FRAGRANCES",Détail!$A:$A,">="&DATE(2026,4,1),Détail!$A:$A,"<"&EDATE(DATE(2026,4,1),1)) -> 0
A88: Mai 2026 | B88: =SUMIFS(Détail!$E:$E,Détail!$D:$D,"NASMIR EUROPE FRAGRANCES",Détail!$A:$A,">="&DATE(2026,5,1),Détail!$A:$A,"<"&EDATE(DATE(2026,5,1),1)) -> 0
A89: Juin 2026 | B89: =SUMIFS(Détail!$E:$E,Détail!$D:$D,"NASMIR EUROPE FRAGRANCES",Détail!$A:$A,">="&DATE(2026,6,1),Détail!$A:$A,"<"&EDATE(DATE(2026,6,1),1)) -> -1738.5
A90: Juillet 2026 | B90: =SUMIFS(Détail!$E:$E,Détail!$D:$D,"NASMIR EUROPE FRAGRANCES",Détail!$A:$A,">="&DATE(2026,7,1),Détail!$A:$A,"<"&EDATE(DATE(2026,7,1),1)) -> 0
A93: Scentis | C93: =SUMIF(Détail!$D:$D,"SCENTIS",Détail!$E:$E) -> -1188
A94: Mois | B94: Montant
A95: Janvier 2026 | B95: =SUMIFS(Détail!$E:$E,Détail!$D:$D,"SCENTIS",Détail!$A:$A,">="&DATE(2026,1,1),Détail!$A:$A,"<"&EDATE(DATE(2026,1,1),1)) -> -1188
A96: Février 2026 | B96: =SUMIFS(Détail!$E:$E,Détail!$D:$D,"SCENTIS",Détail!$A:$A,">="&DATE(2026,2,1),Détail!$A:$A,"<"&EDATE(DATE(2026,2,1),1)) -> 0
A97: Avril 2026 | B97: =SUMIFS(Détail!$E:$E,Détail!$D:$D,"SCENTIS",Détail!$A:$A,">="&DATE(2026,4,1),Détail!$A:$A,"<"&EDATE(DATE(2026,4,1),1)) -> 0
A98: Mai 2026 | B98: =SUMIFS(Détail!$E:$E,Détail!$D:$D,"SCENTIS",Détail!$A:$A,">="&DATE(2026,5,1),Détail!$A:$A,"<"&EDATE(DATE(2026,5,1),1)) -> 0
A99: Juin 2026 | B99: =SUMIFS(Détail!$E:$E,Détail!$D:$D,"SCENTIS",Détail!$A:$A,">="&DATE(2026,6,1),Détail!$A:$A,"<"&EDATE(DATE(2026,6,1),1)) -> 0
A100: Juillet 2026 | B100: =SUMIFS(Détail!$E:$E,Détail!$D:$D,"SCENTIS",Détail!$A:$A,">="&DATE(2026,7,1),Détail!$A:$A,"<"&EDATE(DATE(2026,7,1),1)) -> 0
A103: Natural Solter | C103: =SUMIF(Détail!$D:$D,"NATURAL SOLTER",Détail!$E:$E) -> -242
A104: Mois | B104: Montant
A105: Janvier 2026 | B105: =SUMIFS(Détail!$E:$E,Détail!$D:$D,"NATURAL SOLTER",Détail!$A:$A,">="&DATE(2026,1,1),Détail!$A:$A,"<"&EDATE(DATE(2026,1,1),1)) -> 0
A106: Février 2026 | B106: =SUMIFS(Détail!$E:$E,Détail!$D:$D,"NATURAL SOLTER",Détail!$A:$A,">="&DATE(2026,2,1),Détail!$A:$A,"<"&EDATE(DATE(2026,2,1),1)) -> 0
A107: Avril 2026 | B107: =SUMIFS(Détail!$E:$E,Détail!$D:$D,"NATURAL SOLTER",Détail!$A:$A,">="&DATE(2026,4,1),Détail!$A:$A,"<"&EDATE(DATE(2026,4,1),1)) -> 0
A108: Mai 2026 | B108: =SUMIFS(Détail!$E:$E,Détail!$D:$D,"NATURAL SOLTER",Détail!$A:$A,">="&DATE(2026,5,1),Détail!$A:$A,"<"&EDATE(DATE(2026,5,1),1)) -> 0
A109: Juin 2026 | B109: =SUMIFS(Détail!$E:$E,Détail!$D:$D,"NATURAL SOLTER",Détail!$A:$A,">="&DATE(2026,6,1),Détail!$A:$A,"<"&EDATE(DATE(2026,6,1),1)) -> 0
A110: Juillet 2026 | B110: =SUMIFS(Détail!$E:$E,Détail!$D:$D,"NATURAL SOLTER",Détail!$A:$A,">="&DATE(2026,7,1),Détail!$A:$A,"<"&EDATE(DATE(2026,7,1),1)) -> -242

Sheet Usine conditionnement détail
A1: Usine de conditionnement et macération — détail (2026)
A3: France Conditionnement Parfum | C3: =SUMIF(Détail!$D:$D,"FRANCE CONDITIONNEMENT PARFUM",Détail!$E:$E) -> -136758.73
A4: Mois | B4: Montant
A5: Janvier 2026 | B5: =SUMIFS(Détail!$E:$E,Détail!$D:$D,"FRANCE CONDITIONNEMENT PARFUM",Détail!$A:$A,">="&DATE(2026,1,1),Détail!$A:$A,"<"&EDATE(DATE(2026,1,1),1)) -> -23997.81
A6: Février 2026 | B6: =SUMIFS(Détail!$E:$E,Détail!$D:$D,"FRANCE CONDITIONNEMENT PARFUM",Détail!$A:$A,">="&DATE(2026,2,1),Détail!$A:$A,"<"&EDATE(DATE(2026,2,1),1)) -> -5639.86
A7: Avril 2026 | B7: =SUMIFS(Détail!$E:$E,Détail!$D:$D,"FRANCE CONDITIONNEMENT PARFUM",Détail!$A:$A,">="&DATE(2026,4,1),Détail!$A:$A,"<"&EDATE(DATE(2026,4,1),1)) -> -24999.66
A8: Mai 2026 | B8: =SUMIFS(Détail!$E:$E,Détail!$D:$D,"FRANCE CONDITIONNEMENT PARFUM",Détail!$A:$A,">="&DATE(2026,5,1),Détail!$A:$A,"<"&EDATE(DATE(2026,5,1),1)) -> -26556.5
A9: Juin 2026 | B9: =SUMIFS(Détail!$E:$E,Détail!$D:$D,"FRANCE CONDITIONNEMENT PARFUM",Détail!$A:$A,">="&DATE(2026,6,1),Détail!$A:$A,"<"&EDATE(DATE(2026,6,1),1)) -> -55564.9

Sheet Fournisseurs intl détail
A1: Fournisseurs internationaux (Chine/Import) — détail par fournisseur (2026)
A3: Gold Rock Company Limited | C3: =SUMIF(Détail!$D:$D,"GOLD ROCK COMPANY LIMITED",Détail!$E:$E) -> -21026.95
A4: Mois | B4: Montant
A5: Janvier 2026 | B5: =SUMIFS(Détail!$E:$E,Détail!$D:$D,"GOLD ROCK COMPANY LIMITED",Détail!$A:$A,">="&DATE(2026,1,1),Détail!$A:$A,"<"&EDATE(DATE(2026,1,1),1)) -> 0
A6: Février 2026 | B6: =SUMIFS(Détail!$E:$E,Détail!$D:$D,"GOLD ROCK COMPANY LIMITED",Détail!$A:$A,">="&DATE(2026,2,1),Détail!$A:$A,"<"&EDATE(DATE(2026,2,1),1)) -> 0
A7: Mars 2026 | B7: =SUMIFS(Détail!$E:$E,Détail!$D:$D,"GOLD ROCK COMPANY LIMITED",Détail!$A:$A,">="&DATE(2026,3,1),Détail!$A:$A,"<"&EDATE(DATE(2026,3,1),1)) -> -21026.95
A8: Avril 2026 | B8: =SUMIFS(Détail!$E:$E,Détail!$D:$D,"GOLD ROCK COMPANY LIMITED",Détail!$A:$A,">="&DATE(2026,4,1),Détail!$A:$A,"<"&EDATE(DATE(2026,4,1),1)) -> 0
A9: Mai 2026 | B9: =SUMIFS(Détail!$E:$E,Détail!$D:$D,"GOLD ROCK COMPANY LIMITED",Détail!$A:$A,">="&DATE(2026,5,1),Détail!$A:$A,"<"&EDATE(DATE(2026,5,1),1)) -> 0
A10: Juin 2026 | B10: =SUMIFS(Détail!$E:$E,Détail!$D:$D,"GOLD ROCK COMPANY LIMITED",Détail!$A:$A,">="&DATE(2026,6,1),Détail!$A:$A,"<"&EDATE(DATE(2026,6,1),1)) -> 0
A13: Leaders Hardware Plastic Co Limited | C13: =SUMIF(Détail!$D:$D,"LEADERS HARDWARE PLASTIC CO LIMITED",Détail!$E:$E) -> -15497.84
A14: Mois | B14: Montant
A15: Janvier 2026 | B15: =SUMIFS(Détail!$E:$E,Détail!$D:$D,"LEADERS HARDWARE PLASTIC CO LIMITED",Détail!$A:$A,">="&DATE(2026,1,1),Détail!$A:$A,"<"&EDATE(DATE(2026,1,1),1)) -> 0
A16: Février 2026 | B16: =SUMIFS(Détail!$E:$E,Détail!$D:$D,"LEADERS HARDWARE PLASTIC CO LIMITED",Détail!$A:$A,">="&DATE(2026,2,1),Détail!$A:$A,"<"&EDATE(DATE(2026,2,1),1)) -> 0
A17: Mars 2026 | B17: =SUMIFS(Détail!$E:$E,Détail!$D:$D,"LEADERS HARDWARE PLASTIC CO LIMITED",Détail!$A:$A,">="&DATE(2026,3,1),Détail!$A:$A,"<"&EDATE(DATE(2026,3,1),1)) -> -3489.28
A18: Avril 2026 | B18: =SUMIFS(Détail!$E:$E,Détail!$D:$D,"LEADERS HARDWARE PLASTIC CO LIMITED",Détail!$A:$A,">="&DATE(2026,4,1),Détail!$A:$A,"<"&EDATE(DATE(2026,4,1),1)) -> -4373.08
A19: Mai 2026 | B19: =SUMIFS(Détail!$E:$E,Détail!$D:$D,"LEADERS HARDWARE PLASTIC CO LIMITED",Détail!$A:$A,">="&DATE(2026,5,1),Détail!$A:$A,"<"&EDATE(DATE(2026,5,1),1)) -> -3057.38
A20: Juin 2026 | B20: =SUMIFS(Détail!$E:$E,Détail!$D:$D,"LEADERS HARDWARE PLASTIC CO LIMITED",Détail!$A:$A,">="&DATE(2026,6,1),Détail!$A:$A,"<"&EDATE(DATE(2026,6,1),1)) -> -4578.1
A23: Fu Hui Paper Product Limited | C23: =SUMIF(Détail!$D:$D,"FU HUI PAPER PRODUCT LIMITED",Détail!$E:$E) -> -13613.22
A24: Mois | B24: Montant
A25: Janvier 2026 | B25: =SUMIFS(Détail!$E:$E,Détail!$D:$D,"FU HUI PAPER PRODUCT LIMITED",Détail!$A:$A,">="&DATE(2026,1,1),Détail!$A:$A,"<"&EDATE(DATE(2026,1,1),1)) -> -8573.6
A26: Février 2026 | B26: =SUMIFS(Détail!$E:$E,Détail!$D:$D,"FU HUI PAPER PRODUCT LIMITED",Détail!$A:$A,">="&DATE(2026,2,1),Détail!$A:$A,"<"&EDATE(DATE(2026,2,1),1)) -> -5039.62
A27: Mars 2026 | B27: =SUMIFS(Détail!$E:$E,Détail!$D:$D,"FU HUI PAPER PRODUCT LIMITED",Détail!$A:$A,">="&DATE(2026,3,1),Détail!$A:$A,"<"&EDATE(DATE(2026,3,1),1)) -> 0
A28: Avril 2026 | B28: =SUMIFS(Détail!$E:$E,Détail!$D:$D,"FU HUI PAPER PRODUCT LIMITED",Détail!$A:$A,">="&DATE(2026,4,1),Détail!$A:$A,"<"&EDATE(DATE(2026,4,1),1)) -> 0
A29: Mai 2026 | B29: =SUMIFS(Détail!$E:$E,Détail!$D:$D,"FU HUI PAPER PRODUCT LIMITED",Détail!$A:$A,">="&DATE(2026,5,1),Détail!$A:$A,"<"&EDATE(DATE(2026,5,1),1)) -> 0
A30: Juin 2026 | B30: =SUMIFS(Détail!$E:$E,Détail!$D:$D,"FU HUI PAPER PRODUCT LIMITED",Détail!$A:$A,">="&DATE(2026,6,1),Détail!$A:$A,"<"&EDATE(DATE(2026,6,1),1)) -> 0
A33: Leaders Hardware Plastic Co Limit | C33: =SUMIF(Détail!$D:$D,"LEADERS HARDWARE PLASTIC CO LIMIT",Détail!$E:$E) -> -6224.84
A34: Mois | B34: Montant
A35: Janvier 2026 | B35: =SUMIFS(Détail!$E:$E,Détail!$D:$D,"LEADERS HARDWARE PLASTIC CO LIMIT",Détail!$A:$A,">="&DATE(2026,1,1),Détail!$A:$A,"<"&EDATE(DATE(2026,1,1),1)) -> -6224.84
A36: Février 2026 | B36: =SUMIFS(Détail!$E:$E,Détail!$D:$D,"LEADERS HARDWARE PLASTIC CO LIMIT",Détail!$A:$A,">="&DATE(2026,2,1),Détail!$A:$A,"<"&EDATE(DATE(2026,2,1),1)) -> 0
A37: Mars 2026 | B37: =SUMIFS(Détail!$E:$E,Détail!$D:$D,"LEADERS HARDWARE PLASTIC CO LIMIT",Détail!$A:$A,">="&DATE(2026,3,1),Détail!$A:$A,"<"&EDATE(DATE(2026,3,1),1)) -> 0
A38: Avril 2026 | B38: =SUMIFS(Détail!$E:$E,Détail!$D:$D,"LEADERS HARDWARE PLASTIC CO LIMIT",Détail!$A:$A,">="&DATE(2026,4,1),Détail!$A:$A,"<"&EDATE(DATE(2026,4,1),1)) -> 0
A39: Mai 2026 | B39: =SUMIFS(Détail!$E:$E,Détail!$D:$D,"LEADERS HARDWARE PLASTIC CO LIMIT",Détail!$A:$A,">="&DATE(2026,5,1),Détail!$A:$A,"<"&EDATE(DATE(2026,5,1),1)) -> 0
A40: Juin 2026 | B40: =SUMIFS(Détail!$E:$E,Détail!$D:$D,"LEADERS HARDWARE PLASTIC CO LIMIT",Détail!$A:$A,">="&DATE(2026,6,1),Détail!$A:$A,"<"&EDATE(DATE(2026,6,1),1)) -> 0
A43: Zhejiang Bi Industrial Co Ltd | C43: =SUMIF(Détail!$D:$D,"ZHEJIANG BI INDUSTRIAL CO LTD",Détail!$E:$E) -> -980.12
A44: Mois | B44: Montant
A45: Janvier 2026 | B45: =SUMIFS(Détail!$E:$E,Détail!$D:$D,"ZHEJIANG BI INDUSTRIAL CO LTD",Détail!$A:$A,">="&DATE(2026,1,1),Détail!$A:$A,"<"&EDATE(DATE(2026,1,1),1)) -> 0
A46: Février 2026 | B46: =SUMIFS(Détail!$E:$E,Détail!$D:$D,"ZHEJIANG BI INDUSTRIAL CO LTD",Détail!$A:$A,">="&DATE(2026,2,1),Détail!$A:$A,"<"&EDATE(DATE(2026,2,1),1)) -> -715.69
A47: Mars 2026 | B47: =SUMIFS(Détail!$E:$E,Détail!$D:$D,"ZHEJIANG BI INDUSTRIAL CO LTD",Détail!$A:$A,">="&DATE(2026,3,1),Détail!$A:$A,"<"&EDATE(DATE(2026,3,1),1)) -> -264.43
A48: Avril 2026 | B48: =SUMIFS(Détail!$E:$E,Détail!$D:$D,"ZHEJIANG BI INDUSTRIAL CO LTD",Détail!$A:$A,">="&DATE(2026,4,1),Détail!$A:$A,"<"&EDATE(DATE(2026,4,1),1)) -> 0
A49: Mai 2026 | B49: =SUMIFS(Détail!$E:$E,Détail!$D:$D,"ZHEJIANG BI INDUSTRIAL CO LTD",Détail!$A:$A,">="&DATE(2026,5,1),Détail!$A:$A,"<"&EDATE(DATE(2026,5,1),1)) -> 0
A50: Juin 2026 | B50: =SUMIFS(Détail!$E:$E,Détail!$D:$D,"ZHEJIANG BI INDUSTRIAL CO LTD",Détail!$A:$A,">="&DATE(2026,6,1),Détail!$A:$A,"<"&EDATE(DATE(2026,6,1),1)) -> 0

Sheet Charges sociales détail
A1: Charges sociales & cotisations — détail par organisme (2026)
A3: Urssaf D'Ile De France | C3: =SUMIF(Détail!$D:$D,"URSSAF D'ILE DE FRANCE",Détail!$E:$E) -> -20330
A4: Mois | B4: Montant
A5: Janvier 2026 | B5: =SUMIFS(Détail!$E:$E,Détail!$D:$D,"URSSAF D'ILE DE FRANCE",Détail!$A:$A,">="&DATE(2026,1,1),Détail!$A:$A,"<"&EDATE(DATE(2026,1,1),1)) -> -5040
A6: Février 2026 | B6: =SUMIFS(Détail!$E:$E,Détail!$D:$D,"URSSAF D'ILE DE FRANCE",Détail!$A:$A,">="&DATE(2026,2,1),Détail!$A:$A,"<"&EDATE(DATE(2026,2,1),1)) -> -2961
A7: Mars 2026 | B7: =SUMIFS(Détail!$E:$E,Détail!$D:$D,"URSSAF D'ILE DE FRANCE",Détail!$A:$A,">="&DATE(2026,3,1),Détail!$A:$A,"<"&EDATE(DATE(2026,3,1),1)) -> -2958
A8: Avril 2026 | B8: =SUMIFS(Détail!$E:$E,Détail!$D:$D,"URSSAF D'ILE DE FRANCE",Détail!$A:$A,">="&DATE(2026,4,1),Détail!$A:$A,"<"&EDATE(DATE(2026,4,1),1)) -> -2955
A9: Mai 2026 | B9: =SUMIFS(Détail!$E:$E,Détail!$D:$D,"URSSAF D'ILE DE FRANCE",Détail!$A:$A,">="&DATE(2026,5,1),Détail!$A:$A,"<"&EDATE(DATE(2026,5,1),1)) -> -3038
A10: Juin 2026 | B10: =SUMIFS(Détail!$E:$E,Détail!$D:$D,"URSSAF D'ILE DE FRANCE",Détail!$A:$A,">="&DATE(2026,6,1),Détail!$A:$A,"<"&EDATE(DATE(2026,6,1),1)) -> -3378
A13: Ag2R Reunica | C13: =SUMIF(Détail!$D:$D,"AG2R REUNICA",Détail!$E:$E) -> -3934.14
A14: Mois | B14: Montant
A15: Janvier 2026 | B15: =SUMIFS(Détail!$E:$E,Détail!$D:$D,"AG2R REUNICA",Détail!$A:$A,">="&DATE(2026,1,1),Détail!$A:$A,"<"&EDATE(DATE(2026,1,1),1)) -> -1107.3
A16: Février 2026 | B16: =SUMIFS(Détail!$E:$E,Détail!$D:$D,"AG2R REUNICA",Détail!$A:$A,">="&DATE(2026,2,1),Détail!$A:$A,"<"&EDATE(DATE(2026,2,1),1)) -> -552.44
A17: Mars 2026 | B17: =SUMIFS(Détail!$E:$E,Détail!$D:$D,"AG2R REUNICA",Détail!$A:$A,">="&DATE(2026,3,1),Détail!$A:$A,"<"&EDATE(DATE(2026,3,1),1)) -> -551.83
A18: Avril 2026 | B18: =SUMIFS(Détail!$E:$E,Détail!$D:$D,"AG2R REUNICA",Détail!$A:$A,">="&DATE(2026,4,1),Détail!$A:$A,"<"&EDATE(DATE(2026,4,1),1)) -> -551.36
A19: Mai 2026 | B19: =SUMIFS(Détail!$E:$E,Détail!$D:$D,"AG2R REUNICA",Détail!$A:$A,">="&DATE(2026,5,1),Détail!$A:$A,"<"&EDATE(DATE(2026,5,1),1)) -> -551.35
A20: Juin 2026 | B20: =SUMIFS(Détail!$E:$E,Détail!$D:$D,"AG2R REUNICA",Détail!$A:$A,">="&DATE(2026,6,1),Détail!$A:$A,"<"&EDATE(DATE(2026,6,1),1)) -> -619.86
A23: Direction Generale Des Finances Publiques (Dgfip) | C23: =SUMIF(Détail!$D:$D,"DIRECTION GENERALE DES FINANCES PUBLIQUES (DGFIP)",Détail!$E:$E) -> -1417
A24: Mois | B24: Montant
A25: Janvier 2026 | B25: =SUMIFS(Détail!$E:$E,Détail!$D:$D,"DIRECTION GENERALE DES FINANCES PUBLIQUES (DGFIP)",Détail!$A:$A,">="&DATE(2026,1,1),Détail!$A:$A,"<"&EDATE(DATE(2026,1,1),1)) -> -237
A26: Février 2026 | B26: =SUMIFS(Détail!$E:$E,Détail!$D:$D,"DIRECTION GENERALE DES FINANCES PUBLIQUES (DGFIP)",Détail!$A:$A,">="&DATE(2026,2,1),Détail!$A:$A,"<"&EDATE(DATE(2026,2,1),1)) -> -236
A27: Mars 2026 | B27: =SUMIFS(Détail!$E:$E,Détail!$D:$D,"DIRECTION GENERALE DES FINANCES PUBLIQUES (DGFIP)",Détail!$A:$A,">="&DATE(2026,3,1),Détail!$A:$A,"<"&EDATE(DATE(2026,3,1),1)) -> -236
A28: Avril 2026 | B28: =SUMIFS(Détail!$E:$E,Détail!$D:$D,"DIRECTION GENERALE DES FINANCES PUBLIQUES (DGFIP)",Détail!$A:$A,">="&DATE(2026,4,1),Détail!$A:$A,"<"&EDATE(DATE(2026,4,1),1)) -> -236
A29: Mai 2026 | B29: =SUMIFS(Détail!$E:$E,Détail!$D:$D,"DIRECTION GENERALE DES FINANCES PUBLIQUES (DGFIP)",Détail!$A:$A,">="&DATE(2026,5,1),Détail!$A:$A,"<"&EDATE(DATE(2026,5,1),1)) -> -236
A30: Juin 2026 | B30: =SUMIFS(Détail!$E:$E,Détail!$D:$D,"DIRECTION GENERALE DES FINANCES PUBLIQUES (DGFIP)",Détail!$A:$A,">="&DATE(2026,6,1),Détail!$A:$A,"<"&EDATE(DATE(2026,6,1),1)) -> -236

Sheet Voyages détail
A1: Voyages / déplacements — détail par prestataire (2026)
A3: Emirates | C3: =SUMIF(Détail!$D:$D,"EMIRATES",Détail!$E:$E) -> -3743.41
A4: Mois | B4: Montant
A5: Janvier 2026 | B5: =SUMIFS(Détail!$E:$E,Détail!$D:$D,"EMIRATES",Détail!$A:$A,">="&DATE(2026,1,1),Détail!$A:$A,"<"&EDATE(DATE(2026,1,1),1)) -> -202
A6: Mars 2026 | B6: =SUMIFS(Détail!$E:$E,Détail!$D:$D,"EMIRATES",Détail!$A:$A,">="&DATE(2026,3,1),Détail!$A:$A,"<"&EDATE(DATE(2026,3,1),1)) -> 0
A7: Avril 2026 | B7: =SUMIFS(Détail!$E:$E,Détail!$D:$D,"EMIRATES",Détail!$A:$A,">="&DATE(2026,4,1),Détail!$A:$A,"<"&EDATE(DATE(2026,4,1),1)) -> -1011.86
A8: Mai 2026 | B8: =SUMIFS(Détail!$E:$E,Détail!$D:$D,"EMIRATES",Détail!$A:$A,">="&DATE(2026,5,1),Détail!$A:$A,"<"&EDATE(DATE(2026,5,1),1)) -> -590.91
A9: Juin 2026 | B9: =SUMIFS(Détail!$E:$E,Détail!$D:$D,"EMIRATES",Détail!$A:$A,">="&DATE(2026,6,1),Détail!$A:$A,"<"&EDATE(DATE(2026,6,1),1)) -> -757.12
A10: Juillet 2026 | B10: =SUMIFS(Détail!$E:$E,Détail!$D:$D,"EMIRATES",Détail!$A:$A,">="&DATE(2026,7,1),Détail!$A:$A,"<"&EDATE(DATE(2026,7,1),1)) -> -1181.52
A13: Five Luxe Hotel | C13: =SUMIF(Détail!$D:$D,"FIVE LUXE HOTEL",Détail!$E:$E) -> -1859.74
A14: Mois | B14: Montant
A15: Janvier 2026 | B15: =SUMIFS(Détail!$E:$E,Détail!$D:$D,"FIVE LUXE HOTEL",Détail!$A:$A,">="&DATE(2026,1,1),Détail!$A:$A,"<"&EDATE(DATE(2026,1,1),1)) -> 0
A16: Mars 2026 | B16: =SUMIFS(Détail!$E:$E,Détail!$D:$D,"FIVE LUXE HOTEL",Détail!$A:$A,">="&DATE(2026,3,1),Détail!$A:$A,"<"&EDATE(DATE(2026,3,1),1)) -> 0
A17: Avril 2026 | B17: =SUMIFS(Détail!$E:$E,Détail!$D:$D,"FIVE LUXE HOTEL",Détail!$A:$A,">="&DATE(2026,4,1),Détail!$A:$A,"<"&EDATE(DATE(2026,4,1),1)) -> 0
A18: Mai 2026 | B18: =SUMIFS(Détail!$E:$E,Détail!$D:$D,"FIVE LUXE HOTEL",Détail!$A:$A,">="&DATE(2026,5,1),Détail!$A:$A,"<"&EDATE(DATE(2026,5,1),1)) -> 0
A19: Juin 2026 | B19: =SUMIFS(Détail!$E:$E,Détail!$D:$D,"FIVE LUXE HOTEL",Détail!$A:$A,">="&DATE(2026,6,1),Détail!$A:$A,"<"&EDATE(DATE(2026,6,1),1)) -> -1860.01
A20: Juillet 2026 | B20: =SUMIFS(Détail!$E:$E,Détail!$D:$D,"FIVE LUXE HOTEL",Détail!$A:$A,">="&DATE(2026,7,1),Détail!$A:$A,"<"&EDATE(DATE(2026,7,1),1)) -> 0.27
A23: Air France | C23: =SUMIF(Détail!$D:$D,"AIR FRANCE",Détail!$E:$E) -> -1460.32
A24: Mois | B24: Montant
A25: Janvier 2026 | B25: =SUMIFS(Détail!$E:$E,Détail!$D:$D,"AIR FRANCE",Détail!$A:$A,">="&DATE(2026,1,1),Détail!$A:$A,"<"&EDATE(DATE(2026,1,1),1)) -> 0
A26: Mars 2026 | B26: =SUMIFS(Détail!$E:$E,Détail!$D:$D,"AIR FRANCE",Détail!$A:$A,">="&DATE(2026,3,1),Détail!$A:$A,"<"&EDATE(DATE(2026,3,1),1)) -> -440.58
A27: Avril 2026 | B27: =SUMIFS(Détail!$E:$E,Détail!$D:$D,"AIR FRANCE",Détail!$A:$A,">="&DATE(2026,4,1),Détail!$A:$A,"<"&EDATE(DATE(2026,4,1),1)) -> 0
A28: Mai 2026 | B28: =SUMIFS(Détail!$E:$E,Détail!$D:$D,"AIR FRANCE",Détail!$A:$A,">="&DATE(2026,5,1),Détail!$A:$A,"<"&EDATE(DATE(2026,5,1),1)) -> 0
A29: Juin 2026 | B29: =SUMIFS(Détail!$E:$E,Détail!$D:$D,"AIR FRANCE",Détail!$A:$A,">="&DATE(2026,6,1),Détail!$A:$A,"<"&EDATE(DATE(2026,6,1),1)) -> -995.74
A30: Juillet 2026 | B30: =SUMIFS(Détail!$E:$E,Détail!$D:$D,"AIR FRANCE",Détail!$A:$A,">="&DATE(2026,7,1),Détail!$A:$A,"<"&EDATE(DATE(2026,7,1),1)) -> -24
A33: Airbnb | C33: =SUMIF(Détail!$D:$D,"AIRBNB",Détail!$E:$E) -> -1207.64
A34: Mois | B34: Montant
A35: Janvier 2026 | B35: =SUMIFS(Détail!$E:$E,Détail!$D:$D,"AIRBNB",Détail!$A:$A,">="&DATE(2026,1,1),Détail!$A:$A,"<"&EDATE(DATE(2026,1,1),1)) -> 0
A36: Mars 2026 | B36: =SUMIFS(Détail!$E:$E,Détail!$D:$D,"AIRBNB",Détail!$A:$A,">="&DATE(2026,3,1),Détail!$A:$A,"<"&EDATE(DATE(2026,3,1),1)) -> 0
A37: Avril 2026 | B37: =SUMIFS(Détail!$E:$E,Détail!$D:$D,"AIRBNB",Détail!$A:$A,">="&DATE(2026,4,1),Détail!$A:$A,"<"&EDATE(DATE(2026,4,1),1)) -> -1207.64
A38: Mai 2026 | B38: =SUMIFS(Détail!$E:$E,Détail!$D:$D,"AIRBNB",Détail!$A:$A,">="&DATE(2026,5,1),Détail!$A:$A,"<"&EDATE(DATE(2026,5,1),1)) -> 0
A39: Juin 2026 | B39: =SUMIFS(Détail!$E:$E,Détail!$D:$D,"AIRBNB",Détail!$A:$A,">="&DATE(2026,6,1),Détail!$A:$A,"<"&EDATE(DATE(2026,6,1),1)) -> 0
A40: Juillet 2026 | B40: =SUMIFS(Détail!$E:$E,Détail!$D:$D,"AIRBNB",Détail!$A:$A,">="&DATE(2026,7,1),Détail!$A:$A,"<"&EDATE(DATE(2026,7,1),1)) -> 0
A43: Hotel Le Royal | C43: =SUMIF(Détail!$D:$D,"HOTEL LE ROYAL",Détail!$E:$E) -> -757
A44: Mois | B44: Montant
A45: Janvier 2026 | B45: =SUMIFS(Détail!$E:$E,Détail!$D:$D,"HOTEL LE ROYAL",Détail!$A:$A,">="&DATE(2026,1,1),Détail!$A:$A,"<"&EDATE(DATE(2026,1,1),1)) -> 0
A46: Mars 2026 | B46: =SUMIFS(Détail!$E:$E,Détail!$D:$D,"HOTEL LE ROYAL",Détail!$A:$A,">="&DATE(2026,3,1),Détail!$A:$A,"<"&EDATE(DATE(2026,3,1),1)) -> 0
A47: Avril 2026 | B47: =SUMIFS(Détail!$E:$E,Détail!$D:$D,"HOTEL LE ROYAL",Détail!$A:$A,">="&DATE(2026,4,1),Détail!$A:$A,"<"&EDATE(DATE(2026,4,1),1)) -> -757
A48: Mai 2026 | B48: =SUMIFS(Détail!$E:$E,Détail!$D:$D,"HOTEL LE ROYAL",Détail!$A:$A,">="&DATE(2026,5,1),Détail!$A:$A,"<"&EDATE(DATE(2026,5,1),1)) -> 0
A49: Juin 2026 | B49: =SUMIFS(Détail!$E:$E,Détail!$D:$D,"HOTEL LE ROYAL",Détail!$A:$A,">="&DATE(2026,6,1),Détail!$A:$A,"<"&EDATE(DATE(2026,6,1),1)) -> 0
A50: Juillet 2026 | B50: =SUMIFS(Détail!$E:$E,Détail!$D:$D,"HOTEL LE ROYAL",Détail!$A:$A,">="&DATE(2026,7,1),Détail!$A:$A,"<"&EDATE(DATE(2026,7,1),1)) -> 0
A53: Uber | C53: =SUMIF(Détail!$D:$D,"UBER",Détail!$E:$E) -> -504.71
A54: Mois | B54: Montant
A55: Janvier 2026 | B55: =SUMIFS(Détail!$E:$E,Détail!$D:$D,"UBER",Détail!$A:$A,">="&DATE(2026,1,1),Détail!$A:$A,"<"&EDATE(DATE(2026,1,1),1)) -> -9.36
A56: Mars 2026 | B56: =SUMIFS(Détail!$E:$E,Détail!$D:$D,"UBER",Détail!$A:$A,">="&DATE(2026,3,1),Détail!$A:$A,"<"&EDATE(DATE(2026,3,1),1)) -> -12.98
A57: Avril 2026 | B57: =SUMIFS(Détail!$E:$E,Détail!$D:$D,"UBER",Détail!$A:$A,">="&DATE(2026,4,1),Détail!$A:$A,"<"&EDATE(DATE(2026,4,1),1)) -> -120.86
A58: Mai 2026 | B58: =SUMIFS(Détail!$E:$E,Détail!$D:$D,"UBER",Détail!$A:$A,">="&DATE(2026,5,1),Détail!$A:$A,"<"&EDATE(DATE(2026,5,1),1)) -> -34.39
A59: Juin 2026 | B59: =SUMIFS(Détail!$E:$E,Détail!$D:$D,"UBER",Détail!$A:$A,">="&DATE(2026,6,1),Détail!$A:$A,"<"&EDATE(DATE(2026,6,1),1)) -> -327.12
A60: Juillet 2026 | B60: =SUMIFS(Détail!$E:$E,Détail!$D:$D,"UBER",Détail!$A:$A,">="&DATE(2026,7,1),Détail!$A:$A,"<"&EDATE(DATE(2026,7,1),1)) -> 0
A63: Doubletree By H | C63: =SUMIF(Détail!$D:$D,"DOUBLETREE BY H",Détail!$E:$E) -> -350
A64: Mois | B64: Montant
A65: Janvier 2026 | B65: =SUMIFS(Détail!$E:$E,Détail!$D:$D,"DOUBLETREE BY H",Détail!$A:$A,">="&DATE(2026,1,1),Détail!$A:$A,"<"&EDATE(DATE(2026,1,1),1)) -> 0
A66: Mars 2026 | B66: =SUMIFS(Détail!$E:$E,Détail!$D:$D,"DOUBLETREE BY H",Détail!$A:$A,">="&DATE(2026,3,1),Détail!$A:$A,"<"&EDATE(DATE(2026,3,1),1)) -> 0
A67: Avril 2026 | B67: =SUMIFS(Détail!$E:$E,Détail!$D:$D,"DOUBLETREE BY H",Détail!$A:$A,">="&DATE(2026,4,1),Détail!$A:$A,"<"&EDATE(DATE(2026,4,1),1)) -> 0
A68: Mai 2026 | B68: =SUMIFS(Détail!$E:$E,Détail!$D:$D,"DOUBLETREE BY H",Détail!$A:$A,">="&DATE(2026,5,1),Détail!$A:$A,"<"&EDATE(DATE(2026,5,1),1)) -> 0
A69: Juin 2026 | B69: =SUMIFS(Détail!$E:$E,Détail!$D:$D,"DOUBLETREE BY H",Détail!$A:$A,">="&DATE(2026,6,1),Détail!$A:$A,"<"&EDATE(DATE(2026,6,1),1)) -> -350
A70: Juillet 2026 | B70: =SUMIFS(Détail!$E:$E,Détail!$D:$D,"DOUBLETREE BY H",Détail!$A:$A,">="&DATE(2026,7,1),Détail!$A:$A,"<"&EDATE(DATE(2026,7,1),1)) -> 0
A73: Hotel At Bookin | C73: =SUMIF(Détail!$D:$D,"HOTEL AT BOOKIN",Détail!$E:$E) -> -177.81
A74: Mois | B74: Montant
A75: Janvier 2026 | B75: =SUMIFS(Détail!$E:$E,Détail!$D:$D,"HOTEL AT BOOKIN",Détail!$A:$A,">="&DATE(2026,1,1),Détail!$A:$A,"<"&EDATE(DATE(2026,1,1),1)) -> 0
A76: Mars 2026 | B76: =SUMIFS(Détail!$E:$E,Détail!$D:$D,"HOTEL AT BOOKIN",Détail!$A:$A,">="&DATE(2026,3,1),Détail!$A:$A,"<"&EDATE(DATE(2026,3,1),1)) -> -177.81
A77: Avril 2026 | B77: =SUMIFS(Détail!$E:$E,Détail!$D:$D,"HOTEL AT BOOKIN",Détail!$A:$A,">="&DATE(2026,4,1),Détail!$A:$A,"<"&EDATE(DATE(2026,4,1),1)) -> 0
A78: Mai 2026 | B78: =SUMIFS(Détail!$E:$E,Détail!$D:$D,"HOTEL AT BOOKIN",Détail!$A:$A,">="&DATE(2026,5,1),Détail!$A:$A,"<"&EDATE(DATE(2026,5,1),1)) -> 0
A79: Juin 2026 | B79: =SUMIFS(Détail!$E:$E,Détail!$D:$D,"HOTEL AT BOOKIN",Détail!$A:$A,">="&DATE(2026,6,1),Détail!$A:$A,"<"&EDATE(DATE(2026,6,1),1)) -> 0
A80: Juillet 2026 | B80: =SUMIFS(Détail!$E:$E,Détail!$D:$D,"HOTEL AT BOOKIN",Détail!$A:$A,">="&DATE(2026,7,1),Détail!$A:$A,"<"&EDATE(DATE(2026,7,1),1)) -> 0
A83: Dubai Marina Ho | C83: =SUMIF(Détail!$D:$D,"DUBAI MARINA HO",Détail!$E:$E) -> -141.76
A84: Mois | B84: Montant
A85: Janvier 2026 | B85: =SUMIFS(Détail!$E:$E,Détail!$D:$D,"DUBAI MARINA HO",Détail!$A:$A,">="&DATE(2026,1,1),Détail!$A:$A,"<"&EDATE(DATE(2026,1,1),1)) -> 0
A86: Mars 2026 | B86: =SUMIFS(Détail!$E:$E,Détail!$D:$D,"DUBAI MARINA HO",Détail!$A:$A,">="&DATE(2026,3,1),Détail!$A:$A,"<"&EDATE(DATE(2026,3,1),1)) -> 0
A87: Avril 2026 | B87: =SUMIFS(Détail!$E:$E,Détail!$D:$D,"DUBAI MARINA HO",Détail!$A:$A,">="&DATE(2026,4,1),Détail!$A:$A,"<"&EDATE(DATE(2026,4,1),1)) -> -141.76
A88: Mai 2026 | B88: =SUMIFS(Détail!$E:$E,Détail!$D:$D,"DUBAI MARINA HO",Détail!$A:$A,">="&DATE(2026,5,1),Détail!$A:$A,"<"&EDATE(DATE(2026,5,1),1)) -> 0
A89: Juin 2026 | B89: =SUMIFS(Détail!$E:$E,Détail!$D:$D,"DUBAI MARINA HO",Détail!$A:$A,">="&DATE(2026,6,1),Détail!$A:$A,"<"&EDATE(DATE(2026,6,1),1)) -> 0
A90: Juillet 2026 | B90: =SUMIFS(Détail!$E:$E,Détail!$D:$D,"DUBAI MARINA HO",Détail!$A:$A,">="&DATE(2026,7,1),Détail!$A:$A,"<"&EDATE(DATE(2026,7,1),1)) -> 0
A93: Terme Milano S. | C93: =SUMIF(Détail!$D:$D,"TERME MILANO S.",Détail!$E:$E) -> -122
A94: Mois | B94: Montant
A95: Janvier 2026 | B95: =SUMIFS(Détail!$E:$E,Détail!$D:$D,"TERME MILANO S.",Détail!$A:$A,">="&DATE(2026,1,1),Détail!$A:$A,"<"&EDATE(DATE(2026,1,1),1)) -> 0
A96: Mars 2026 | B96: =SUMIFS(Détail!$E:$E,Détail!$D:$D,"TERME MILANO S.",Détail!$A:$A,">="&DATE(2026,3,1),Détail!$A:$A,"<"&EDATE(DATE(2026,3,1),1)) -> 0
A97: Avril 2026 | B97: =SUMIFS(Détail!$E:$E,Détail!$D:$D,"TERME MILANO S.",Détail!$A:$A,">="&DATE(2026,4,1),Détail!$A:$A,"<"&EDATE(DATE(2026,4,1),1)) -> 0
A98: Mai 2026 | B98: =SUMIFS(Détail!$E:$E,Détail!$D:$D,"TERME MILANO S.",Détail!$A:$A,">="&DATE(2026,5,1),Détail!$A:$A,"<"&EDATE(DATE(2026,5,1),1)) -> 0
A99: Juin 2026 | B99: =SUMIFS(Détail!$E:$E,Détail!$D:$D,"TERME MILANO S.",Détail!$A:$A,">="&DATE(2026,6,1),Détail!$A:$A,"<"&EDATE(DATE(2026,6,1),1)) -> -122
A100: Juillet 2026 | B100: =SUMIFS(Détail!$E:$E,Détail!$D:$D,"TERME MILANO S.",Détail!$A:$A,">="&DATE(2026,7,1),Détail!$A:$A,"<"&EDATE(DATE(2026,7,1),1)) -> 0
A103: Relais Millau L | C103: =SUMIF(Détail!$D:$D,"RELAIS MILLAU L",Détail!$E:$E) -> -11.75
A104: Mois | B104: Montant
A105: Janvier 2026 | B105: =SUMIFS(Détail!$E:$E,Détail!$D:$D,"RELAIS MILLAU L",Détail!$A:$A,">="&DATE(2026,1,1),Détail!$A:$A,"<"&EDATE(DATE(2026,1,1),1)) -> 0
A106: Mars 2026 | B106: =SUMIFS(Détail!$E:$E,Détail!$D:$D,"RELAIS MILLAU L",Détail!$A:$A,">="&DATE(2026,3,1),Détail!$A:$A,"<"&EDATE(DATE(2026,3,1),1)) -> 0
A107: Avril 2026 | B107: =SUMIFS(Détail!$E:$E,Détail!$D:$D,"RELAIS MILLAU L",Détail!$A:$A,">="&DATE(2026,4,1),Détail!$A:$A,"<"&EDATE(DATE(2026,4,1),1)) -> -11.75
A108: Mai 2026 | B108: =SUMIFS(Détail!$E:$E,Détail!$D:$D,"RELAIS MILLAU L",Détail!$A:$A,">="&DATE(2026,5,1),Détail!$A:$A,"<"&EDATE(DATE(2026,5,1),1)) -> 0
A109: Juin 2026 | B109: =SUMIFS(Détail!$E:$E,Détail!$D:$D,"RELAIS MILLAU L",Détail!$A:$A,">="&DATE(2026,6,1),Détail!$A:$A,"<"&EDATE(DATE(2026,6,1),1)) -> 0
A110: Juillet 2026 | B110: =SUMIFS(Détail!$E:$E,Détail!$D:$D,"RELAIS MILLAU L",Détail!$A:$A,">="&DATE(2026,7,1),Détail!$A:$A,"<"&EDATE(DATE(2026,7,1),1)) -> 0
A113: Istanbul 62 | C113: =SUMIF(Détail!$D:$D,"ISTANBUL 62",Détail!$E:$E) -> -10
A114: Mois | B114: Montant
A115: Janvier 2026 | B115: =SUMIFS(Détail!$E:$E,Détail!$D:$D,"ISTANBUL 62",Détail!$A:$A,">="&DATE(2026,1,1),Détail!$A:$A,"<"&EDATE(DATE(2026,1,1),1)) -> -10
A116: Mars 2026 | B116: =SUMIFS(Détail!$E:$E,Détail!$D:$D,"ISTANBUL 62",Détail!$A:$A,">="&DATE(2026,3,1),Détail!$A:$A,"<"&EDATE(DATE(2026,3,1),1)) -> 0
A117: Avril 2026 | B117: =SUMIFS(Détail!$E:$E,Détail!$D:$D,"ISTANBUL 62",Détail!$A:$A,">="&DATE(2026,4,1),Détail!$A:$A,"<"&EDATE(DATE(2026,4,1),1)) -> 0
A118: Mai 2026 | B118: =SUMIFS(Détail!$E:$E,Détail!$D:$D,"ISTANBUL 62",Détail!$A:$A,">="&DATE(2026,5,1),Détail!$A:$A,"<"&EDATE(DATE(2026,5,1),1)) -> 0
A119: Juin 2026 | B119: =SUMIFS(Détail!$E:$E,Détail!$D:$D,"ISTANBUL 62",Détail!$A:$A,">="&DATE(2026,6,1),Détail!$A:$A,"<"&EDATE(DATE(2026,6,1),1)) -> 0
A120: Juillet 2026 | B120: =SUMIFS(Détail!$E:$E,Détail!$D:$D,"ISTANBUL 62",Détail!$A:$A,">="&DATE(2026,7,1),Détail!$A:$A,"<"&EDATE(DATE(2026,7,1),1)) -> 0

Sheet Téléphone-Internet détail
A1: Téléphone / Internet / Logiciels — détail par prestataire (2026)
A3: Orange Sa | C3: =SUMIF(Détail!$D:$D,"ORANGE SA",Détail!$E:$E) -> -3596.25
A4: Mois | B4: Montant
A5: Janvier 2026 | B5: =SUMIFS(Détail!$E:$E,Détail!$D:$D,"ORANGE SA",Détail!$A:$A,">="&DATE(2026,1,1),Détail!$A:$A,"<"&EDATE(DATE(2026,1,1),1)) -> -670.88
A6: Février 2026 | B6: =SUMIFS(Détail!$E:$E,Détail!$D:$D,"ORANGE SA",Détail!$A:$A,">="&DATE(2026,2,1),Détail!$A:$A,"<"&EDATE(DATE(2026,2,1),1)) -> -703.49
A7: Mars 2026 | B7: =SUMIFS(Détail!$E:$E,Détail!$D:$D,"ORANGE SA",Détail!$A:$A,">="&DATE(2026,3,1),Détail!$A:$A,"<"&EDATE(DATE(2026,3,1),1)) -> -518
A8: Avril 2026 | B8: =SUMIFS(Détail!$E:$E,Détail!$D:$D,"ORANGE SA",Détail!$A:$A,">="&DATE(2026,4,1),Détail!$A:$A,"<"&EDATE(DATE(2026,4,1),1)) -> -527.32
A9: Mai 2026 | B9: =SUMIFS(Détail!$E:$E,Détail!$D:$D,"ORANGE SA",Détail!$A:$A,">="&DATE(2026,5,1),Détail!$A:$A,"<"&EDATE(DATE(2026,5,1),1)) -> -642.82
A10: Juin 2026 | B10: =SUMIFS(Détail!$E:$E,Détail!$D:$D,"ORANGE SA",Détail!$A:$A,">="&DATE(2026,6,1),Détail!$A:$A,"<"&EDATE(DATE(2026,6,1),1)) -> -533.74
A11: Juillet 2026 | B11: =SUMIFS(Détail!$E:$E,Détail!$D:$D,"ORANGE SA",Détail!$A:$A,">="&DATE(2026,7,1),Détail!$A:$A,"<"&EDATE(DATE(2026,7,1),1)) -> 0
A14: Apple | C14: =SUMIF(Détail!$D:$D,"APPLE",Détail!$E:$E) -> -1914.69
A15: Mois | B15: Montant
A16: Janvier 2026 | B16: =SUMIFS(Détail!$E:$E,Détail!$D:$D,"APPLE",Détail!$A:$A,">="&DATE(2026,1,1),Détail!$A:$A,"<"&EDATE(DATE(2026,1,1),1)) -> -38.95
A17: Février 2026 | B17: =SUMIFS(Détail!$E:$E,Détail!$D:$D,"APPLE",Détail!$A:$A,">="&DATE(2026,2,1),Détail!$A:$A,"<"&EDATE(DATE(2026,2,1),1)) -> -137.95
A18: Mars 2026 | B18: =SUMIFS(Détail!$E:$E,Détail!$D:$D,"APPLE",Détail!$A:$A,">="&DATE(2026,3,1),Détail!$A:$A,"<"&EDATE(DATE(2026,3,1),1)) -> -38.95
A19: Avril 2026 | B19: =SUMIFS(Détail!$E:$E,Détail!$D:$D,"APPLE",Détail!$A:$A,">="&DATE(2026,4,1),Détail!$A:$A,"<"&EDATE(DATE(2026,4,1),1)) -> -56.93
A20: Mai 2026 | B20: =SUMIFS(Détail!$E:$E,Détail!$D:$D,"APPLE",Détail!$A:$A,">="&DATE(2026,5,1),Détail!$A:$A,"<"&EDATE(DATE(2026,5,1),1)) -> -721.94
A21: Juin 2026 | B21: =SUMIFS(Détail!$E:$E,Détail!$D:$D,"APPLE",Détail!$A:$A,">="&DATE(2026,6,1),Détail!$A:$A,"<"&EDATE(DATE(2026,6,1),1)) -> -905.98
A22: Juillet 2026 | B22: =SUMIFS(Détail!$E:$E,Détail!$D:$D,"APPLE",Détail!$A:$A,">="&DATE(2026,7,1),Détail!$A:$A,"<"&EDATE(DATE(2026,7,1),1)) -> -13.99
A25: Google Workspace | C25: =SUMIF(Détail!$D:$D,"GOOGLE WORKSPACE",Détail!$E:$E) -> -1036.58
A26: Mois | B26: Montant
A27: Janvier 2026 | B27: =SUMIFS(Détail!$E:$E,Détail!$D:$D,"GOOGLE WORKSPACE",Détail!$A:$A,">="&DATE(2026,1,1),Détail!$A:$A,"<"&EDATE(DATE(2026,1,1),1)) -> -145.8
A28: Février 2026 | B28: =SUMIFS(Détail!$E:$E,Détail!$D:$D,"GOOGLE WORKSPACE",Détail!$A:$A,">="&DATE(2026,2,1),Détail!$A:$A,"<"&EDATE(DATE(2026,2,1),1)) -> -145.8
A29: Mars 2026 | B29: =SUMIFS(Détail!$E:$E,Détail!$D:$D,"GOOGLE WORKSPACE",Détail!$A:$A,">="&DATE(2026,3,1),Détail!$A:$A,"<"&EDATE(DATE(2026,3,1),1)) -> -145.8
A30: Avril 2026 | B30: =SUMIFS(Détail!$E:$E,Détail!$D:$D,"GOOGLE WORKSPACE",Détail!$A:$A,">="&DATE(2026,4,1),Détail!$A:$A,"<"&EDATE(DATE(2026,4,1),1)) -> -145.8
A31: Mai 2026 | B31: =SUMIFS(Détail!$E:$E,Détail!$D:$D,"GOOGLE WORKSPACE",Détail!$A:$A,">="&DATE(2026,5,1),Détail!$A:$A,"<"&EDATE(DATE(2026,5,1),1)) -> -145.8
A32: Juin 2026 | B32: =SUMIFS(Détail!$E:$E,Détail!$D:$D,"GOOGLE WORKSPACE",Détail!$A:$A,">="&DATE(2026,6,1),Détail!$A:$A,"<"&EDATE(DATE(2026,6,1),1)) -> -152.06
A33: Juillet 2026 | B33: =SUMIFS(Détail!$E:$E,Détail!$D:$D,"GOOGLE WORKSPACE",Détail!$A:$A,">="&DATE(2026,7,1),Détail!$A:$A,"<"&EDATE(DATE(2026,7,1),1)) -> -155.52
A36: Adobe | C36: =SUMIF(Détail!$D:$D,"ADOBE",Détail!$E:$E) -> -393.24
A37: Mois | B37: Montant
A38: Janvier 2026 | B38: =SUMIFS(Détail!$E:$E,Détail!$D:$D,"ADOBE",Détail!$A:$A,">="&DATE(2026,1,1),Détail!$A:$A,"<"&EDATE(DATE(2026,1,1),1)) -> -65.54
A39: Février 2026 | B39: =SUMIFS(Détail!$E:$E,Détail!$D:$D,"ADOBE",Détail!$A:$A,">="&DATE(2026,2,1),Détail!$A:$A,"<"&EDATE(DATE(2026,2,1),1)) -> 0
A40: Mars 2026 | B40: =SUMIFS(Détail!$E:$E,Détail!$D:$D,"ADOBE",Détail!$A:$A,">="&DATE(2026,3,1),Détail!$A:$A,"<"&EDATE(DATE(2026,3,1),1)) -> -131.08
A41: Avril 2026 | B41: =SUMIFS(Détail!$E:$E,Détail!$D:$D,"ADOBE",Détail!$A:$A,">="&DATE(2026,4,1),Détail!$A:$A,"<"&EDATE(DATE(2026,4,1),1)) -> -65.54
A42: Mai 2026 | B42: =SUMIFS(Détail!$E:$E,Détail!$D:$D,"ADOBE",Détail!$A:$A,">="&DATE(2026,5,1),Détail!$A:$A,"<"&EDATE(DATE(2026,5,1),1)) -> -65.54
A43: Juin 2026 | B43: =SUMIFS(Détail!$E:$E,Détail!$D:$D,"ADOBE",Détail!$A:$A,">="&DATE(2026,6,1),Détail!$A:$A,"<"&EDATE(DATE(2026,6,1),1)) -> -65.54
A44: Juillet 2026 | B44: =SUMIFS(Détail!$E:$E,Détail!$D:$D,"ADOBE",Détail!$A:$A,">="&DATE(2026,7,1),Détail!$A:$A,"<"&EDATE(DATE(2026,7,1),1)) -> 0
A47: Shopify | C47: =SUMIF(Détail!$D:$D,"SHOPIFY",Détail!$E:$E) -> -239.02
A48: Mois | B48: Montant
A49: Janvier 2026 | B49: =SUMIFS(Détail!$E:$E,Détail!$D:$D,"SHOPIFY",Détail!$A:$A,">="&DATE(2026,1,1),Détail!$A:$A,"<"&EDATE(DATE(2026,1,1),1)) -> -33.92
A50: Février 2026 | B50: =SUMIFS(Détail!$E:$E,Détail!$D:$D,"SHOPIFY",Détail!$A:$A,">="&DATE(2026,2,1),Détail!$A:$A,"<"&EDATE(DATE(2026,2,1),1)) -> -33.64
A51: Mars 2026 | B51: =SUMIFS(Détail!$E:$E,Détail!$D:$D,"SHOPIFY",Détail!$A:$A,">="&DATE(2026,3,1),Détail!$A:$A,"<"&EDATE(DATE(2026,3,1),1)) -> -34.28
A52: Avril 2026 | B52: =SUMIFS(Détail!$E:$E,Détail!$D:$D,"SHOPIFY",Détail!$A:$A,">="&DATE(2026,4,1),Détail!$A:$A,"<"&EDATE(DATE(2026,4,1),1)) -> -34.35
A53: Mai 2026 | B53: =SUMIFS(Détail!$E:$E,Détail!$D:$D,"SHOPIFY",Détail!$A:$A,">="&DATE(2026,5,1),Détail!$A:$A,"<"&EDATE(DATE(2026,5,1),1)) -> -33.76
A54: Juin 2026 | B54: =SUMIFS(Détail!$E:$E,Détail!$D:$D,"SHOPIFY",Détail!$A:$A,">="&DATE(2026,6,1),Détail!$A:$A,"<"&EDATE(DATE(2026,6,1),1)) -> -34.37
A55: Juillet 2026 | B55: =SUMIFS(Détail!$E:$E,Détail!$D:$D,"SHOPIFY",Détail!$A:$A,">="&DATE(2026,7,1),Détail!$A:$A,"<"&EDATE(DATE(2026,7,1),1)) -> -34.7
A58: Anthropic / Claude.Ai | C58: =SUMIF(Détail!$D:$D,"ANTHROPIC / CLAUDE.AI",Détail!$E:$E) -> -113.89
A59: Mois | B59: Montant
A60: Janvier 2026 | B60: =SUMIFS(Détail!$E:$E,Détail!$D:$D,"ANTHROPIC / CLAUDE.AI",Détail!$A:$A,">="&DATE(2026,1,1),Détail!$A:$A,"<"&EDATE(DATE(2026,1,1),1)) -> 0
A61: Février 2026 | B61: =SUMIFS(Détail!$E:$E,Détail!$D:$D,"ANTHROPIC / CLAUDE.AI",Détail!$A:$A,">="&DATE(2026,2,1),Détail!$A:$A,"<"&EDATE(DATE(2026,2,1),1)) -> 0
A62: Mars 2026 | B62: =SUMIFS(Détail!$E:$E,Détail!$D:$D,"ANTHROPIC / CLAUDE.AI",Détail!$A:$A,">="&DATE(2026,3,1),Détail!$A:$A,"<"&EDATE(DATE(2026,3,1),1)) -> 0
A63: Avril 2026 | B63: =SUMIFS(Détail!$E:$E,Détail!$D:$D,"ANTHROPIC / CLAUDE.AI",Détail!$A:$A,">="&DATE(2026,4,1),Détail!$A:$A,"<"&EDATE(DATE(2026,4,1),1)) -> -22.22
A64: Mai 2026 | B64: =SUMIFS(Détail!$E:$E,Détail!$D:$D,"ANTHROPIC / CLAUDE.AI",Détail!$A:$A,">="&DATE(2026,5,1),Détail!$A:$A,"<"&EDATE(DATE(2026,5,1),1)) -> -69.45
A65: Juin 2026 | B65: =SUMIFS(Détail!$E:$E,Détail!$D:$D,"ANTHROPIC / CLAUDE.AI",Détail!$A:$A,">="&DATE(2026,6,1),Détail!$A:$A,"<"&EDATE(DATE(2026,6,1),1)) -> -22.22
A66: Juillet 2026 | B66: =SUMIFS(Détail!$E:$E,Détail!$D:$D,"ANTHROPIC / CLAUDE.AI",Détail!$A:$A,">="&DATE(2026,7,1),Détail!$A:$A,"<"&EDATE(DATE(2026,7,1),1)) -> 0
A69: Microsoft | C69: =SUMIF(Détail!$D:$D,"MICROSOFT",Détail!$E:$E) -> -98
A70: Mois | B70: Montant
A71: Janvier 2026 | B71: =SUMIFS(Détail!$E:$E,Détail!$D:$D,"MICROSOFT",Détail!$A:$A,">="&DATE(2026,1,1),Détail!$A:$A,"<"&EDATE(DATE(2026,1,1),1)) -> -13
A72: Février 2026 | B72: =SUMIFS(Détail!$E:$E,Détail!$D:$D,"MICROSOFT",Détail!$A:$A,">="&DATE(2026,2,1),Détail!$A:$A,"<"&EDATE(DATE(2026,2,1),1)) -> 0
A73: Mars 2026 | B73: =SUMIFS(Détail!$E:$E,Détail!$D:$D,"MICROSOFT",Détail!$A:$A,">="&DATE(2026,3,1),Détail!$A:$A,"<"&EDATE(DATE(2026,3,1),1)) -> -26
A74: Avril 2026 | B74: =SUMIFS(Détail!$E:$E,Détail!$D:$D,"MICROSOFT",Détail!$A:$A,">="&DATE(2026,4,1),Détail!$A:$A,"<"&EDATE(DATE(2026,4,1),1)) -> -13
A75: Mai 2026 | B75: =SUMIFS(Détail!$E:$E,Détail!$D:$D,"MICROSOFT",Détail!$A:$A,">="&DATE(2026,5,1),Détail!$A:$A,"<"&EDATE(DATE(2026,5,1),1)) -> -23
A76: Juin 2026 | B76: =SUMIFS(Détail!$E:$E,Détail!$D:$D,"MICROSOFT",Détail!$A:$A,">="&DATE(2026,6,1),Détail!$A:$A,"<"&EDATE(DATE(2026,6,1),1)) -> -23
A77: Juillet 2026 | B77: =SUMIFS(Détail!$E:$E,Détail!$D:$D,"MICROSOFT",Détail!$A:$A,">="&DATE(2026,7,1),Détail!$A:$A,"<"&EDATE(DATE(2026,7,1),1)) -> 0
A80: Fiverr | C80: =SUMIF(Détail!$D:$D,"FIVERR",Détail!$E:$E) -> -80.73
A81: Mois | B81: Montant
A82: Janvier 2026 | B82: =SUMIFS(Détail!$E:$E,Détail!$D:$D,"FIVERR",Détail!$A:$A,">="&DATE(2026,1,1),Détail!$A:$A,"<"&EDATE(DATE(2026,1,1),1)) -> 0
A83: Février 2026 | B83: =SUMIFS(Détail!$E:$E,Détail!$D:$D,"FIVERR",Détail!$A:$A,">="&DATE(2026,2,1),Détail!$A:$A,"<"&EDATE(DATE(2026,2,1),1)) -> 0
A84: Mars 2026 | B84: =SUMIFS(Détail!$E:$E,Détail!$D:$D,"FIVERR",Détail!$A:$A,">="&DATE(2026,3,1),Détail!$A:$A,"<"&EDATE(DATE(2026,3,1),1)) -> 0
A85: Avril 2026 | B85: =SUMIFS(Détail!$E:$E,Détail!$D:$D,"FIVERR",Détail!$A:$A,">="&DATE(2026,4,1),Détail!$A:$A,"<"&EDATE(DATE(2026,4,1),1)) -> 0
A86: Mai 2026 | B86: =SUMIFS(Détail!$E:$E,Détail!$D:$D,"FIVERR",Détail!$A:$A,">="&DATE(2026,5,1),Détail!$A:$A,"<"&EDATE(DATE(2026,5,1),1)) -> 0
A87: Juin 2026 | B87: =SUMIFS(Détail!$E:$E,Détail!$D:$D,"FIVERR",Détail!$A:$A,">="&DATE(2026,6,1),Détail!$A:$A,"<"&EDATE(DATE(2026,6,1),1)) -> -80.73
A88: Juillet 2026 | B88: =SUMIFS(Détail!$E:$E,Détail!$D:$D,"FIVERR",Détail!$A:$A,">="&DATE(2026,7,1),Détail!$A:$A,"<"&EDATE(DATE(2026,7,1),1)) -> 0
A91: Site Web Emmanuellejane.Com | C91: =SUMIF(Détail!$D:$D,"SITE WEB EMMANUELLEJANE.COM",Détail!$E:$E) -> -19.99
A92: Mois | B92: Montant
A93: Janvier 2026 | B93: =SUMIFS(Détail!$E:$E,Détail!$D:$D,"SITE WEB EMMANUELLEJANE.COM",Détail!$A:$A,">="&DATE(2026,1,1),Détail!$A:$A,"<"&EDATE(DATE(2026,1,1),1)) -> 0
A94: Février 2026 | B94: =SUMIFS(Détail!$E:$E,Détail!$D:$D,"SITE WEB EMMANUELLEJANE.COM",Détail!$A:$A,">="&DATE(2026,2,1),Détail!$A:$A,"<"&EDATE(DATE(2026,2,1),1)) -> 0
A95: Mars 2026 | B95: =SUMIFS(Détail!$E:$E,Détail!$D:$D,"SITE WEB EMMANUELLEJANE.COM",Détail!$A:$A,">="&DATE(2026,3,1),Détail!$A:$A,"<"&EDATE(DATE(2026,3,1),1)) -> 0
A96: Avril 2026 | B96: =SUMIFS(Détail!$E:$E,Détail!$D:$D,"SITE WEB EMMANUELLEJANE.COM",Détail!$A:$A,">="&DATE(2026,4,1),Détail!$A:$A,"<"&EDATE(DATE(2026,4,1),1)) -> 0
A97: Mai 2026 | B97: =SUMIFS(Détail!$E:$E,Détail!$D:$D,"SITE WEB EMMANUELLEJANE.COM",Détail!$A:$A,">="&DATE(2026,5,1),Détail!$A:$A,"<"&EDATE(DATE(2026,5,1),1)) -> -19.99
A98: Juin 2026 | B98: =SUMIFS(Détail!$E:$E,Détail!$D:$D,"SITE WEB EMMANUELLEJANE.COM",Détail!$A:$A,">="&DATE(2026,6,1),Détail!$A:$A,"<"&EDATE(DATE(2026,6,1),1)) -> 0
A99: Juillet 2026 | B99: =SUMIFS(Détail!$E:$E,Détail!$D:$D,"SITE WEB EMMANUELLEJANE.COM",Détail!$A:$A,">="&DATE(2026,7,1),Détail!$A:$A,"<"&EDATE(DATE(2026,7,1),1)) -> 0
A102: Nyx*Egfrancesas | C102: =SUMIF(Détail!$D:$D,"NYX*EGFRANCESAS",Détail!$E:$E) -> -13.5
A103: Mois | B103: Montant
A104: Janvier 2026 | B104: =SUMIFS(Détail!$E:$E,Détail!$D:$D,"NYX*EGFRANCESAS",Détail!$A:$A,">="&DATE(2026,1,1),Détail!$A:$A,"<"&EDATE(DATE(2026,1,1),1)) -> -6
A105: Février 2026 | B105: =SUMIFS(Détail!$E:$E,Détail!$D:$D,"NYX*EGFRANCESAS",Détail!$A:$A,">="&DATE(2026,2,1),Détail!$A:$A,"<"&EDATE(DATE(2026,2,1),1)) -> 0
A106: Mars 2026 | B106: =SUMIFS(Détail!$E:$E,Détail!$D:$D,"NYX*EGFRANCESAS",Détail!$A:$A,">="&DATE(2026,3,1),Détail!$A:$A,"<"&EDATE(DATE(2026,3,1),1)) -> 0
A107: Avril 2026 | B107: =SUMIFS(Détail!$E:$E,Détail!$D:$D,"NYX*EGFRANCESAS",Détail!$A:$A,">="&DATE(2026,4,1),Détail!$A:$A,"<"&EDATE(DATE(2026,4,1),1)) -> -3
A108: Mai 2026 | B108: =SUMIFS(Détail!$E:$E,Détail!$D:$D,"NYX*EGFRANCESAS",Détail!$A:$A,">="&DATE(2026,5,1),Détail!$A:$A,"<"&EDATE(DATE(2026,5,1),1)) -> 0
A109: Juin 2026 | B109: =SUMIFS(Détail!$E:$E,Détail!$D:$D,"NYX*EGFRANCESAS",Détail!$A:$A,">="&DATE(2026,6,1),Détail!$A:$A,"<"&EDATE(DATE(2026,6,1),1)) -> -4.5
A110: Juillet 2026 | B110: =SUMIFS(Détail!$E:$E,Détail!$D:$D,"NYX*EGFRANCESAS",Détail!$A:$A,">="&DATE(2026,7,1),Détail!$A:$A,"<"&EDATE(DATE(2026,7,1),1)) -> 0
A113: Ovh Sas | C113: =SUMIF(Détail!$D:$D,"OVH SAS",Détail!$E:$E) -> -2.52
A114: Mois | B114: Montant
A115: Janvier 2026 | B115: =SUMIFS(Détail!$E:$E,Détail!$D:$D,"OVH SAS",Détail!$A:$A,">="&DATE(2026,1,1),Détail!$A:$A,"<"&EDATE(DATE(2026,1,1),1)) -> -0.36
A116: Février 2026 | B116: =SUMIFS(Détail!$E:$E,Détail!$D:$D,"OVH SAS",Détail!$A:$A,">="&DATE(2026,2,1),Détail!$A:$A,"<"&EDATE(DATE(2026,2,1),1)) -> -0.36
A117: Mars 2026 | B117: =SUMIFS(Détail!$E:$E,Détail!$D:$D,"OVH SAS",Détail!$A:$A,">="&DATE(2026,3,1),Détail!$A:$A,"<"&EDATE(DATE(2026,3,1),1)) -> -0.36
A118: Avril 2026 | B118: =SUMIFS(Détail!$E:$E,Détail!$D:$D,"OVH SAS",Détail!$A:$A,">="&DATE(2026,4,1),Détail!$A:$A,"<"&EDATE(DATE(2026,4,1),1)) -> -0.36
A119: Mai 2026 | B119: =SUMIFS(Détail!$E:$E,Détail!$D:$D,"OVH SAS",Détail!$A:$A,">="&DATE(2026,5,1),Détail!$A:$A,"<"&EDATE(DATE(2026,5,1),1)) -> -0.36
A120: Juin 2026 | B120: =SUMIFS(Détail!$E:$E,Détail!$D:$D,"OVH SAS",Détail!$A:$A,">="&DATE(2026,6,1),Détail!$A:$A,"<"&EDATE(DATE(2026,6,1),1)) -> -0.36
A121: Juillet 2026 | B121: =SUMIFS(Détail!$E:$E,Détail!$D:$D,"OVH SAS",Détail!$A:$A,">="&DATE(2026,7,1),Détail!$A:$A,"<"&EDATE(DATE(2026,7,1),1)) -> -0.36

Sheet Frais pro divers détail
A1: Frais professionnels divers — détail par prestataire (2026)
A3: Eaton Technologies Gmbh | C3: =SUMIF(Détail!$D:$D,"EATON TECHNOLOGIES GMBH",Détail!$E:$E) -> -3990
A4: Mois | B4: Montant
A5: Janvier 2026 | B5: =SUMIFS(Détail!$E:$E,Détail!$D:$D,"EATON TECHNOLOGIES GMBH",Détail!$A:$A,">="&DATE(2026,1,1),Détail!$A:$A,"<"&EDATE(DATE(2026,1,1),1)) -> -3990
A6: Février 2026 | B6: =SUMIFS(Détail!$E:$E,Détail!$D:$D,"EATON TECHNOLOGIES GMBH",Détail!$A:$A,">="&DATE(2026,2,1),Détail!$A:$A,"<"&EDATE(DATE(2026,2,1),1)) -> 0
A7: Mars 2026 | B7: =SUMIFS(Détail!$E:$E,Détail!$D:$D,"EATON TECHNOLOGIES GMBH",Détail!$A:$A,">="&DATE(2026,3,1),Détail!$A:$A,"<"&EDATE(DATE(2026,3,1),1)) -> 0
A8: Avril 2026 | B8: =SUMIFS(Détail!$E:$E,Détail!$D:$D,"EATON TECHNOLOGIES GMBH",Détail!$A:$A,">="&DATE(2026,4,1),Détail!$A:$A,"<"&EDATE(DATE(2026,4,1),1)) -> 0
A9: Mai 2026 | B9: =SUMIFS(Détail!$E:$E,Détail!$D:$D,"EATON TECHNOLOGIES GMBH",Détail!$A:$A,">="&DATE(2026,5,1),Détail!$A:$A,"<"&EDATE(DATE(2026,5,1),1)) -> 0
A10: Juin 2026 | B10: =SUMIFS(Détail!$E:$E,Détail!$D:$D,"EATON TECHNOLOGIES GMBH",Détail!$A:$A,">="&DATE(2026,6,1),Détail!$A:$A,"<"&EDATE(DATE(2026,6,1),1)) -> 0
A11: Juillet 2026 | B11: =SUMIFS(Détail!$E:$E,Détail!$D:$D,"EATON TECHNOLOGIES GMBH",Détail!$A:$A,">="&DATE(2026,7,1),Détail!$A:$A,"<"&EDATE(DATE(2026,7,1),1)) -> 0
A14: Sumup *Ultime | C14: =SUMIF(Détail!$D:$D,"SUMUP *ULTIME",Détail!$E:$E) -> -2529
A15: Mois | B15: Montant
A16: Janvier 2026 | B16: =SUMIFS(Détail!$E:$E,Détail!$D:$D,"SUMUP *ULTIME",Détail!$A:$A,">="&DATE(2026,1,1),Détail!$A:$A,"<"&EDATE(DATE(2026,1,1),1)) -> 0
A17: Février 2026 | B17: =SUMIFS(Détail!$E:$E,Détail!$D:$D,"SUMUP *ULTIME",Détail!$A:$A,">="&DATE(2026,2,1),Détail!$A:$A,"<"&EDATE(DATE(2026,2,1),1)) -> 0
A18: Mars 2026 | B18: =SUMIFS(Détail!$E:$E,Détail!$D:$D,"SUMUP *ULTIME",Détail!$A:$A,">="&DATE(2026,3,1),Détail!$A:$A,"<"&EDATE(DATE(2026,3,1),1)) -> 0
A19: Avril 2026 | B19: =SUMIFS(Détail!$E:$E,Détail!$D:$D,"SUMUP *ULTIME",Détail!$A:$A,">="&DATE(2026,4,1),Détail!$A:$A,"<"&EDATE(DATE(2026,4,1),1)) -> 0
A20: Mai 2026 | B20: =SUMIFS(Détail!$E:$E,Détail!$D:$D,"SUMUP *ULTIME",Détail!$A:$A,">="&DATE(2026,5,1),Détail!$A:$A,"<"&EDATE(DATE(2026,5,1),1)) -> -2529
A21: Juin 2026 | B21: =SUMIFS(Détail!$E:$E,Détail!$D:$D,"SUMUP *ULTIME",Détail!$A:$A,">="&DATE(2026,6,1),Détail!$A:$A,"<"&EDATE(DATE(2026,6,1),1)) -> 0
A22: Juillet 2026 | B22: =SUMIFS(Détail!$E:$E,Détail!$D:$D,"SUMUP *ULTIME",Détail!$A:$A,">="&DATE(2026,7,1),Détail!$A:$A,"<"&EDATE(DATE(2026,7,1),1)) -> 0
A25: Tuv Rheinland France Sas | C25: =SUMIF(Détail!$D:$D,"TUV RHEINLAND FRANCE SAS",Détail!$E:$E) -> -1947.77
A26: Mois | B26: Montant
A27: Janvier 2026 | B27: =SUMIFS(Détail!$E:$E,Détail!$D:$D,"TUV RHEINLAND FRANCE SAS",Détail!$A:$A,">="&DATE(2026,1,1),Détail!$A:$A,"<"&EDATE(DATE(2026,1,1),1)) -> -827.87
A28: Février 2026 | B28: =SUMIFS(Détail!$E:$E,Détail!$D:$D,"TUV RHEINLAND FRANCE SAS",Détail!$A:$A,">="&DATE(2026,2,1),Détail!$A:$A,"<"&EDATE(DATE(2026,2,1),1)) -> -1119.9
A29: Mars 2026 | B29: =SUMIFS(Détail!$E:$E,Détail!$D:$D,"TUV RHEINLAND FRANCE SAS",Détail!$A:$A,">="&DATE(2026,3,1),Détail!$A:$A,"<"&EDATE(DATE(2026,3,1),1)) -> 0
A30: Avril 2026 | B30: =SUMIFS(Détail!$E:$E,Détail!$D:$D,"TUV RHEINLAND FRANCE SAS",Détail!$A:$A,">="&DATE(2026,4,1),Détail!$A:$A,"<"&EDATE(DATE(2026,4,1),1)) -> 0
A31: Mai 2026 | B31: =SUMIFS(Détail!$E:$E,Détail!$D:$D,"TUV RHEINLAND FRANCE SAS",Détail!$A:$A,">="&DATE(2026,5,1),Détail!$A:$A,"<"&EDATE(DATE(2026,5,1),1)) -> 0
A32: Juin 2026 | B32: =SUMIFS(Détail!$E:$E,Détail!$D:$D,"TUV RHEINLAND FRANCE SAS",Détail!$A:$A,">="&DATE(2026,6,1),Détail!$A:$A,"<"&EDATE(DATE(2026,6,1),1)) -> 0
A33: Juillet 2026 | B33: =SUMIFS(Détail!$E:$E,Détail!$D:$D,"TUV RHEINLAND FRANCE SAS",Détail!$A:$A,">="&DATE(2026,7,1),Détail!$A:$A,"<"&EDATE(DATE(2026,7,1),1)) -> 0
A36: Gs1 France | C36: =SUMIF(Détail!$D:$D,"GS1 FRANCE",Détail!$E:$E) -> -757.2
A37: Mois | B37: Montant
A38: Janvier 2026 | B38: =SUMIFS(Détail!$E:$E,Détail!$D:$D,"GS1 FRANCE",Détail!$A:$A,">="&DATE(2026,1,1),Détail!$A:$A,"<"&EDATE(DATE(2026,1,1),1)) -> -757.2
A39: Février 2026 | B39: =SUMIFS(Détail!$E:$E,Détail!$D:$D,"GS1 FRANCE",Détail!$A:$A,">="&DATE(2026,2,1),Détail!$A:$A,"<"&EDATE(DATE(2026,2,1),1)) -> 0
A40: Mars 2026 | B40: =SUMIFS(Détail!$E:$E,Détail!$D:$D,"GS1 FRANCE",Détail!$A:$A,">="&DATE(2026,3,1),Détail!$A:$A,"<"&EDATE(DATE(2026,3,1),1)) -> 0
A41: Avril 2026 | B41: =SUMIFS(Détail!$E:$E,Détail!$D:$D,"GS1 FRANCE",Détail!$A:$A,">="&DATE(2026,4,1),Détail!$A:$A,"<"&EDATE(DATE(2026,4,1),1)) -> 0
A42: Mai 2026 | B42: =SUMIFS(Détail!$E:$E,Détail!$D:$D,"GS1 FRANCE",Détail!$A:$A,">="&DATE(2026,5,1),Détail!$A:$A,"<"&EDATE(DATE(2026,5,1),1)) -> 0
A43: Juin 2026 | B43: =SUMIFS(Détail!$E:$E,Détail!$D:$D,"GS1 FRANCE",Détail!$A:$A,">="&DATE(2026,6,1),Détail!$A:$A,"<"&EDATE(DATE(2026,6,1),1)) -> 0
A44: Juillet 2026 | B44: =SUMIFS(Détail!$E:$E,Détail!$D:$D,"GS1 FRANCE",Détail!$A:$A,">="&DATE(2026,7,1),Détail!$A:$A,"<"&EDATE(DATE(2026,7,1),1)) -> 0
A47: Ccip Dfce Gefi | C47: =SUMIF(Détail!$D:$D,"CCIP DFCE GEFI",Détail!$E:$E) -> -716
A48: Mois | B48: Montant
A49: Janvier 2026 | B49: =SUMIFS(Détail!$E:$E,Détail!$D:$D,"CCIP DFCE GEFI",Détail!$A:$A,">="&DATE(2026,1,1),Détail!$A:$A,"<"&EDATE(DATE(2026,1,1),1)) -> -99
A50: Février 2026 | B50: =SUMIFS(Détail!$E:$E,Détail!$D:$D,"CCIP DFCE GEFI",Détail!$A:$A,">="&DATE(2026,2,1),Détail!$A:$A,"<"&EDATE(DATE(2026,2,1),1)) -> -86
A51: Mars 2026 | B51: =SUMIFS(Détail!$E:$E,Détail!$D:$D,"CCIP DFCE GEFI",Détail!$A:$A,">="&DATE(2026,3,1),Détail!$A:$A,"<"&EDATE(DATE(2026,3,1),1)) -> -234
A52: Avril 2026 | B52: =SUMIFS(Détail!$E:$E,Détail!$D:$D,"CCIP DFCE GEFI",Détail!$A:$A,">="&DATE(2026,4,1),Détail!$A:$A,"<"&EDATE(DATE(2026,4,1),1)) -> -84
A53: Mai 2026 | B53: =SUMIFS(Détail!$E:$E,Détail!$D:$D,"CCIP DFCE GEFI",Détail!$A:$A,">="&DATE(2026,5,1),Détail!$A:$A,"<"&EDATE(DATE(2026,5,1),1)) -> -114
A54: Juin 2026 | B54: =SUMIFS(Détail!$E:$E,Détail!$D:$D,"CCIP DFCE GEFI",Détail!$A:$A,">="&DATE(2026,6,1),Détail!$A:$A,"<"&EDATE(DATE(2026,6,1),1)) -> -71
A55: Juillet 2026 | B55: =SUMIFS(Détail!$E:$E,Détail!$D:$D,"CCIP DFCE GEFI",Détail!$A:$A,">="&DATE(2026,7,1),Détail!$A:$A,"<"&EDATE(DATE(2026,7,1),1)) -> -28
A58: Plombier | C58: =SUMIF(Détail!$D:$D,"PLOMBIER",Détail!$E:$E) -> -415
A59: Mois | B59: Montant
A60: Janvier 2026 | B60: =SUMIFS(Détail!$E:$E,Détail!$D:$D,"PLOMBIER",Détail!$A:$A,">="&DATE(2026,1,1),Détail!$A:$A,"<"&EDATE(DATE(2026,1,1),1)) -> 0
A61: Février 2026 | B61: =SUMIFS(Détail!$E:$E,Détail!$D:$D,"PLOMBIER",Détail!$A:$A,">="&DATE(2026,2,1),Détail!$A:$A,"<"&EDATE(DATE(2026,2,1),1)) -> -415
A62: Mars 2026 | B62: =SUMIFS(Détail!$E:$E,Détail!$D:$D,"PLOMBIER",Détail!$A:$A,">="&DATE(2026,3,1),Détail!$A:$A,"<"&EDATE(DATE(2026,3,1),1)) -> 0
A63: Avril 2026 | B63: =SUMIFS(Détail!$E:$E,Détail!$D:$D,"PLOMBIER",Détail!$A:$A,">="&DATE(2026,4,1),Détail!$A:$A,"<"&EDATE(DATE(2026,4,1),1)) -> 0
A64: Mai 2026 | B64: =SUMIFS(Détail!$E:$E,Détail!$D:$D,"PLOMBIER",Détail!$A:$A,">="&DATE(2026,5,1),Détail!$A:$A,"<"&EDATE(DATE(2026,5,1),1)) -> 0
A65: Juin 2026 | B65: =SUMIFS(Détail!$E:$E,Détail!$D:$D,"PLOMBIER",Détail!$A:$A,">="&DATE(2026,6,1),Détail!$A:$A,"<"&EDATE(DATE(2026,6,1),1)) -> 0
A66: Juillet 2026 | B66: =SUMIFS(Détail!$E:$E,Détail!$D:$D,"PLOMBIER",Détail!$A:$A,">="&DATE(2026,7,1),Détail!$A:$A,"<"&EDATE(DATE(2026,7,1),1)) -> 0
A69: Sogesco Sas | C69: =SUMIF(Détail!$D:$D,"SOGESCO SAS",Détail!$E:$E) -> -313.6
A70: Mois | B70: Montant
A71: Janvier 2026 | B71: =SUMIFS(Détail!$E:$E,Détail!$D:$D,"SOGESCO SAS",Détail!$A:$A,">="&DATE(2026,1,1),Détail!$A:$A,"<"&EDATE(DATE(2026,1,1),1)) -> 0
A72: Février 2026 | B72: =SUMIFS(Détail!$E:$E,Détail!$D:$D,"SOGESCO SAS",Détail!$A:$A,">="&DATE(2026,2,1),Détail!$A:$A,"<"&EDATE(DATE(2026,2,1),1)) -> -197.6
A73: Mars 2026 | B73: =SUMIFS(Détail!$E:$E,Détail!$D:$D,"SOGESCO SAS",Détail!$A:$A,">="&DATE(2026,3,1),Détail!$A:$A,"<"&EDATE(DATE(2026,3,1),1)) -> 0
A74: Avril 2026 | B74: =SUMIFS(Détail!$E:$E,Détail!$D:$D,"SOGESCO SAS",Détail!$A:$A,">="&DATE(2026,4,1),Détail!$A:$A,"<"&EDATE(DATE(2026,4,1),1)) -> 0
A75: Mai 2026 | B75: =SUMIFS(Détail!$E:$E,Détail!$D:$D,"SOGESCO SAS",Détail!$A:$A,">="&DATE(2026,5,1),Détail!$A:$A,"<"&EDATE(DATE(2026,5,1),1)) -> -116
A76: Juin 2026 | B76: =SUMIFS(Détail!$E:$E,Détail!$D:$D,"SOGESCO SAS",Détail!$A:$A,">="&DATE(2026,6,1),Détail!$A:$A,"<"&EDATE(DATE(2026,6,1),1)) -> 0
A77: Juillet 2026 | B77: =SUMIFS(Détail!$E:$E,Détail!$D:$D,"SOGESCO SAS",Détail!$A:$A,">="&DATE(2026,7,1),Détail!$A:$A,"<"&EDATE(DATE(2026,7,1),1)) -> 0
A80: Assistance Demarches | C80: =SUMIF(Détail!$D:$D,"ASSISTANCE DEMARCHES",Détail!$E:$E) -> -281.6
A81: Mois | B81: Montant
A82: Janvier 2026 | B82: =SUMIFS(Détail!$E:$E,Détail!$D:$D,"ASSISTANCE DEMARCHES",Détail!$A:$A,">="&DATE(2026,1,1),Détail!$A:$A,"<"&EDATE(DATE(2026,1,1),1)) -> 0
A83: Février 2026 | B83: =SUMIFS(Détail!$E:$E,Détail!$D:$D,"ASSISTANCE DEMARCHES",Détail!$A:$A,">="&DATE(2026,2,1),Détail!$A:$A,"<"&EDATE(DATE(2026,2,1),1)) -> 0
A84: Mars 2026 | B84: =SUMIFS(Détail!$E:$E,Détail!$D:$D,"ASSISTANCE DEMARCHES",Détail!$A:$A,">="&DATE(2026,3,1),Détail!$A:$A,"<"&EDATE(DATE(2026,3,1),1)) -> 0
A85: Avril 2026 | B85: =SUMIFS(Détail!$E:$E,Détail!$D:$D,"ASSISTANCE DEMARCHES",Détail!$A:$A,">="&DATE(2026,4,1),Détail!$A:$A,"<"&EDATE(DATE(2026,4,1),1)) -> 0
A86: Mai 2026 | B86: =SUMIFS(Détail!$E:$E,Détail!$D:$D,"ASSISTANCE DEMARCHES",Détail!$A:$A,">="&DATE(2026,5,1),Détail!$A:$A,"<"&EDATE(DATE(2026,5,1),1)) -> 0
A87: Juin 2026 | B87: =SUMIFS(Détail!$E:$E,Détail!$D:$D,"ASSISTANCE DEMARCHES",Détail!$A:$A,">="&DATE(2026,6,1),Détail!$A:$A,"<"&EDATE(DATE(2026,6,1),1)) -> -281.6
A88: Juillet 2026 | B88: =SUMIFS(Détail!$E:$E,Détail!$D:$D,"ASSISTANCE DEMARCHES",Détail!$A:$A,">="&DATE(2026,7,1),Détail!$A:$A,"<"&EDATE(DATE(2026,7,1),1)) -> 0
A91: Amival | C91: =SUMIF(Détail!$D:$D,"AMIVAL",Détail!$E:$E) -> -252
A92: Mois | B92: Montant
A93: Janvier 2026 | B93: =SUMIFS(Détail!$E:$E,Détail!$D:$D,"AMIVAL",Détail!$A:$A,">="&DATE(2026,1,1),Détail!$A:$A,"<"&EDATE(DATE(2026,1,1),1)) -> 0
A94: Février 2026 | B94: =SUMIFS(Détail!$E:$E,Détail!$D:$D,"AMIVAL",Détail!$A:$A,">="&DATE(2026,2,1),Détail!$A:$A,"<"&EDATE(DATE(2026,2,1),1)) -> 0
A95: Mars 2026 | B95: =SUMIFS(Détail!$E:$E,Détail!$D:$D,"AMIVAL",Détail!$A:$A,">="&DATE(2026,3,1),Détail!$A:$A,"<"&EDATE(DATE(2026,3,1),1)) -> 0
A96: Avril 2026 | B96: =SUMIFS(Détail!$E:$E,Détail!$D:$D,"AMIVAL",Détail!$A:$A,">="&DATE(2026,4,1),Détail!$A:$A,"<"&EDATE(DATE(2026,4,1),1)) -> -252
A97: Mai 2026 | B97: =SUMIFS(Détail!$E:$E,Détail!$D:$D,"AMIVAL",Détail!$A:$A,">="&DATE(2026,5,1),Détail!$A:$A,"<"&EDATE(DATE(2026,5,1),1)) -> 0
A98: Juin 2026 | B98: =SUMIFS(Détail!$E:$E,Détail!$D:$D,"AMIVAL",Détail!$A:$A,">="&DATE(2026,6,1),Détail!$A:$A,"<"&EDATE(DATE(2026,6,1),1)) -> 0
A99: Juillet 2026 | B99: =SUMIFS(Détail!$E:$E,Détail!$D:$D,"AMIVAL",Détail!$A:$A,">="&DATE(2026,7,1),Détail!$A:$A,"<"&EDATE(DATE(2026,7,1),1)) -> 0
A102: Bruneau | C102: =SUMIF(Détail!$D:$D,"BRUNEAU",Détail!$E:$E) -> -245.86
A103: Mois | B103: Montant
A104: Janvier 2026 | B104: =SUMIFS(Détail!$E:$E,Détail!$D:$D,"BRUNEAU",Détail!$A:$A,">="&DATE(2026,1,1),Détail!$A:$A,"<"&EDATE(DATE(2026,1,1),1)) -> -245.86
A105: Février 2026 | B105: =SUMIFS(Détail!$E:$E,Détail!$D:$D,"BRUNEAU",Détail!$A:$A,">="&DATE(2026,2,1),Détail!$A:$A,"<"&EDATE(DATE(2026,2,1),1)) -> 0
A106: Mars 2026 | B106: =SUMIFS(Détail!$E:$E,Détail!$D:$D,"BRUNEAU",Détail!$A:$A,">="&DATE(2026,3,1),Détail!$A:$A,"<"&EDATE(DATE(2026,3,1),1)) -> 0
A107: Avril 2026 | B107: =SUMIFS(Détail!$E:$E,Détail!$D:$D,"BRUNEAU",Détail!$A:$A,">="&DATE(2026,4,1),Détail!$A:$A,"<"&EDATE(DATE(2026,4,1),1)) -> 0
A108: Mai 2026 | B108: =SUMIFS(Détail!$E:$E,Détail!$D:$D,"BRUNEAU",Détail!$A:$A,">="&DATE(2026,5,1),Détail!$A:$A,"<"&EDATE(DATE(2026,5,1),1)) -> 0
A109: Juin 2026 | B109: =SUMIFS(Détail!$E:$E,Détail!$D:$D,"BRUNEAU",Détail!$A:$A,">="&DATE(2026,6,1),Détail!$A:$A,"<"&EDATE(DATE(2026,6,1),1)) -> 0
A110: Juillet 2026 | B110: =SUMIFS(Détail!$E:$E,Détail!$D:$D,"BRUNEAU",Détail!$A:$A,">="&DATE(2026,7,1),Détail!$A:$A,"<"&EDATE(DATE(2026,7,1),1)) -> 0
A113: Sumup *Tns Dep | C113: =SUMIF(Détail!$D:$D,"SUMUP *TNS DEP",Détail!$E:$E) -> -245
A114: Mois | B114: Montant
A115: Janvier 2026 | B115: =SUMIFS(Détail!$E:$E,Détail!$D:$D,"SUMUP *TNS DEP",Détail!$A:$A,">="&DATE(2026,1,1),Détail!$A:$A,"<"&EDATE(DATE(2026,1,1),1)) -> 0
A116: Février 2026 | B116: =SUMIFS(Détail!$E:$E,Détail!$D:$D,"SUMUP *TNS DEP",Détail!$A:$A,">="&DATE(2026,2,1),Détail!$A:$A,"<"&EDATE(DATE(2026,2,1),1)) -> 0
A117: Mars 2026 | B117: =SUMIFS(Détail!$E:$E,Détail!$D:$D,"SUMUP *TNS DEP",Détail!$A:$A,">="&DATE(2026,3,1),Détail!$A:$A,"<"&EDATE(DATE(2026,3,1),1)) -> -135
A118: Avril 2026 | B118: =SUMIFS(Détail!$E:$E,Détail!$D:$D,"SUMUP *TNS DEP",Détail!$A:$A,">="&DATE(2026,4,1),Détail!$A:$A,"<"&EDATE(DATE(2026,4,1),1)) -> -110
A119: Mai 2026 | B119: =SUMIFS(Détail!$E:$E,Détail!$D:$D,"SUMUP *TNS DEP",Détail!$A:$A,">="&DATE(2026,5,1),Détail!$A:$A,"<"&EDATE(DATE(2026,5,1),1)) -> 0
A120: Juin 2026 | B120: =SUMIFS(Détail!$E:$E,Détail!$D:$D,"SUMUP *TNS DEP",Détail!$A:$A,">="&DATE(2026,6,1),Détail!$A:$A,"<"&EDATE(DATE(2026,6,1),1)) -> 0
A121: Juillet 2026 | B121: =SUMIFS(Détail!$E:$E,Détail!$D:$D,"SUMUP *TNS DEP",Détail!$A:$A,">="&DATE(2026,7,1),Détail!$A:$A,"<"&EDATE(DATE(2026,7,1),1)) -> 0
...

Sheet Électricité Gaz détail
A1: Électricité / Gaz — détail mensuel (2026)
A3: Totalenergies Electricite Et Gaz France | C3: =SUMIF(Détail!$D:$D,"TOTALENERGIES ELECTRICITE ET GAZ FRANCE",Détail!$E:$E) -> -5559.55
A4: Mois | B4: Montant
A5: Janvier 2026 | B5: =SUMIFS(Détail!$E:$E,Détail!$D:$D,"TOTALENERGIES ELECTRICITE ET GAZ FRANCE",Détail!$A:$A,">="&DATE(2026,1,1),Détail!$A:$A,"<"&EDATE(DATE(2026,1,1),1)) -> -174.83
A6: Février 2026 | B6: =SUMIFS(Détail!$E:$E,Détail!$D:$D,"TOTALENERGIES ELECTRICITE ET GAZ FRANCE",Détail!$A:$A,">="&DATE(2026,2,1),Détail!$A:$A,"<"&EDATE(DATE(2026,2,1),1)) -> -1320.6
A7: Mars 2026 | B7: =SUMIFS(Détail!$E:$E,Détail!$D:$D,"TOTALENERGIES ELECTRICITE ET GAZ FRANCE",Détail!$A:$A,">="&DATE(2026,3,1),Détail!$A:$A,"<"&EDATE(DATE(2026,3,1),1)) -> -2009.4
A8: Avril 2026 | B8: =SUMIFS(Détail!$E:$E,Détail!$D:$D,"TOTALENERGIES ELECTRICITE ET GAZ FRANCE",Détail!$A:$A,">="&DATE(2026,4,1),Détail!$A:$A,"<"&EDATE(DATE(2026,4,1),1)) -> -160.99
A9: Mai 2026 | B9: =SUMIFS(Détail!$E:$E,Détail!$D:$D,"TOTALENERGIES ELECTRICITE ET GAZ FRANCE",Détail!$A:$A,">="&DATE(2026,5,1),Détail!$A:$A,"<"&EDATE(DATE(2026,5,1),1)) -> -921.54
A10: Juin 2026 | B10: =SUMIFS(Détail!$E:$E,Détail!$D:$D,"TOTALENERGIES ELECTRICITE ET GAZ FRANCE",Détail!$A:$A,">="&DATE(2026,6,1),Détail!$A:$A,"<"&EDATE(DATE(2026,6,1),1)) -> -525.49
A11: Juillet 2026 | B11: =SUMIFS(Détail!$E:$E,Détail!$D:$D,"TOTALENERGIES ELECTRICITE ET GAZ FRANCE",Détail!$A:$A,">="&DATE(2026,7,1),Détail!$A:$A,"<"&EDATE(DATE(2026,7,1),1)) -> -446.7

Sheet Comptabilité détail
A1: Comptabilité / expert-comptable — détail (2026)
A3: Cabinet Sas Daran | C3: =SUMIF(Détail!$D:$D,"CABINET SAS DARAN",Détail!$E:$E) -> -3024
A4: Mois | B4: Montant
A5: Janvier 2026 | B5: =SUMIFS(Détail!$E:$E,Détail!$D:$D,"CABINET SAS DARAN",Détail!$A:$A,">="&DATE(2026,1,1),Détail!$A:$A,"<"&EDATE(DATE(2026,1,1),1)) -> -504
A6: Février 2026 | B6: =SUMIFS(Détail!$E:$E,Détail!$D:$D,"CABINET SAS DARAN",Détail!$A:$A,">="&DATE(2026,2,1),Détail!$A:$A,"<"&EDATE(DATE(2026,2,1),1)) -> -504
A7: Mars 2026 | B7: =SUMIFS(Détail!$E:$E,Détail!$D:$D,"CABINET SAS DARAN",Détail!$A:$A,">="&DATE(2026,3,1),Détail!$A:$A,"<"&EDATE(DATE(2026,3,1),1)) -> -504
A8: Avril 2026 | B8: =SUMIFS(Détail!$E:$E,Détail!$D:$D,"CABINET SAS DARAN",Détail!$A:$A,">="&DATE(2026,4,1),Détail!$A:$A,"<"&EDATE(DATE(2026,4,1),1)) -> -504
A9: Mai 2026 | B9: =SUMIFS(Détail!$E:$E,Détail!$D:$D,"CABINET SAS DARAN",Détail!$A:$A,">="&DATE(2026,5,1),Détail!$A:$A,"<"&EDATE(DATE(2026,5,1),1)) -> -504
A10: Juin 2026 | B10: =SUMIFS(Détail!$E:$E,Détail!$D:$D,"CABINET SAS DARAN",Détail!$A:$A,">="&DATE(2026,6,1),Détail!$A:$A,"<"&EDATE(DATE(2026,6,1),1)) -> -504
A13: Ebp France-E B P Informatique | C13: =SUMIF(Détail!$D:$D,"EBP FRANCE-E B P INFORMATIQUE",Détail!$E:$E) -> -660
A14: Mois | B14: Montant
A15: Janvier 2026 | B15: =SUMIFS(Détail!$E:$E,Détail!$D:$D,"EBP FRANCE-E B P INFORMATIQUE",Détail!$A:$A,">="&DATE(2026,1,1),Détail!$A:$A,"<"&EDATE(DATE(2026,1,1),1)) -> 0
A16: Février 2026 | B16: =SUMIFS(Détail!$E:$E,Détail!$D:$D,"EBP FRANCE-E B P INFORMATIQUE",Détail!$A:$A,">="&DATE(2026,2,1),Détail!$A:$A,"<"&EDATE(DATE(2026,2,1),1)) -> -660
A17: Mars 2026 | B17: =SUMIFS(Détail!$E:$E,Détail!$D:$D,"EBP FRANCE-E B P INFORMATIQUE",Détail!$A:$A,">="&DATE(2026,3,1),Détail!$A:$A,"<"&EDATE(DATE(2026,3,1),1)) -> 0
A18: Avril 2026 | B18: =SUMIFS(Détail!$E:$E,Détail!$D:$D,"EBP FRANCE-E B P INFORMATIQUE",Détail!$A:$A,">="&DATE(2026,4,1),Détail!$A:$A,"<"&EDATE(DATE(2026,4,1),1)) -> 0
A19: Mai 2026 | B19: =SUMIFS(Détail!$E:$E,Détail!$D:$D,"EBP FRANCE-E B P INFORMATIQUE",Détail!$A:$A,">="&DATE(2026,5,1),Détail!$A:$A,"<"&EDATE(DATE(2026,5,1),1)) -> 0
A20: Juin 2026 | B20: =SUMIFS(Détail!$E:$E,Détail!$D:$D,"EBP FRANCE-E B P INFORMATIQUE",Détail!$A:$A,">="&DATE(2026,6,1),Détail!$A:$A,"<"&EDATE(DATE(2026,6,1),1)) -> 0

Sheet Frais bancaires détail
A1: Frais bancaires & financiers — détail par type de frais (2026)
A2: Groupé par type d'opération bancaire (pas de nom de prestataire sur ces lignes).
A4: Interets | C4: =SUMIF(Détail!$C:$C,"INTERETS",Détail!$E:$E) -> -1274.97
A5: Mois | B5: Montant
A6: Janvier 2026 | B6: =SUMIFS(Détail!$E:$E,Détail!$C:$C,"INTERETS",Détail!$A:$A,">="&DATE(2026,1,1),Détail!$A:$A,"<"&EDATE(DATE(2026,1,1),1)) -> -519.86
A7: Février 2026 | B7: =SUMIFS(Détail!$E:$E,Détail!$C:$C,"INTERETS",Détail!$A:$A,">="&DATE(2026,2,1),Détail!$A:$A,"<"&EDATE(DATE(2026,2,1),1)) -> 0
A8: Mars 2026 | B8: =SUMIFS(Détail!$E:$E,Détail!$C:$C,"INTERETS",Détail!$A:$A,">="&DATE(2026,3,1),Détail!$A:$A,"<"&EDATE(DATE(2026,3,1),1)) -> 0
A9: Avril 2026 | B9: =SUMIFS(Détail!$E:$E,Détail!$C:$C,"INTERETS",Détail!$A:$A,">="&DATE(2026,4,1),Détail!$A:$A,"<"&EDATE(DATE(2026,4,1),1)) -> -246.8
A10: Mai 2026 | B10: =SUMIFS(Détail!$E:$E,Détail!$C:$C,"INTERETS",Détail!$A:$A,">="&DATE(2026,5,1),Détail!$A:$A,"<"&EDATE(DATE(2026,5,1),1)) -> 0
A11: Juin 2026 | B11: =SUMIFS(Détail!$E:$E,Détail!$C:$C,"INTERETS",Détail!$A:$A,">="&DATE(2026,6,1),Détail!$A:$A,"<"&EDATE(DATE(2026,6,1),1)) -> 0
A12: Juillet 2026 | B12: =SUMIFS(Détail!$E:$E,Détail!$C:$C,"INTERETS",Détail!$A:$A,">="&DATE(2026,7,1),Détail!$A:$A,"<"&EDATE(DATE(2026,7,1),1)) -> -508.31
A15: Frais De Gestion | C15: =SUMIF(Détail!$C:$C,"FRAIS DE GESTION",Détail!$E:$E) -> -375.49
A16: Mois | B16: Montant
A17: Janvier 2026 | B17: =SUMIFS(Détail!$E:$E,Détail!$C:$C,"FRAIS DE GESTION",Détail!$A:$A,">="&DATE(2026,1,1),Détail!$A:$A,"<"&EDATE(DATE(2026,1,1),1)) -> 0
A18: Février 2026 | B18: =SUMIFS(Détail!$E:$E,Détail!$C:$C,"FRAIS DE GESTION",Détail!$A:$A,">="&DATE(2026,2,1),Détail!$A:$A,"<"&EDATE(DATE(2026,2,1),1)) -> 0
A19: Mars 2026 | B19: =SUMIFS(Détail!$E:$E,Détail!$C:$C,"FRAIS DE GESTION",Détail!$A:$A,">="&DATE(2026,3,1),Détail!$A:$A,"<"&EDATE(DATE(2026,3,1),1)) -> -375.49
A20: Avril 2026 | B20: =SUMIFS(Détail!$E:$E,Détail!$C:$C,"FRAIS DE GESTION",Détail!$A:$A,">="&DATE(2026,4,1),Détail!$A:$A,"<"&EDATE(DATE(2026,4,1),1)) -> 0
A21: Mai 2026 | B21: =SUMIFS(Détail!$E:$E,Détail!$C:$C,"FRAIS DE GESTION",Détail!$A:$A,">="&DATE(2026,5,1),Détail!$A:$A,"<"&EDATE(DATE(2026,5,1),1)) -> 0
A22: Juin 2026 | B22: =SUMIFS(Détail!$E:$E,Détail!$C:$C,"FRAIS DE GESTION",Détail!$A:$A,">="&DATE(2026,6,1),Détail!$A:$A,"<"&EDATE(DATE(2026,6,1),1)) -> 0
A23: Juillet 2026 | B23: =SUMIFS(Détail!$E:$E,Détail!$C:$C,"FRAIS DE GESTION",Détail!$A:$A,">="&DATE(2026,7,1),Détail!$A:$A,"<"&EDATE(DATE(2026,7,1),1)) -> 0
A26: Frais Banque Etrangere | C26: =SUMIF(Détail!$C:$C,"FRAIS BANQUE ETRANGERE",Détail!$E:$E) -> -374.4
A27: Mois | B27: Montant
A28: Janvier 2026 | B28: =SUMIFS(Détail!$E:$E,Détail!$C:$C,"FRAIS BANQUE ETRANGERE",Détail!$A:$A,">="&DATE(2026,1,1),Détail!$A:$A,"<"&EDATE(DATE(2026,1,1),1)) -> -57.6
A29: Février 2026 | B29: =SUMIFS(Détail!$E:$E,Détail!$C:$C,"FRAIS BANQUE ETRANGERE",Détail!$A:$A,">="&DATE(2026,2,1),Détail!$A:$A,"<"&EDATE(DATE(2026,2,1),1)) -> -57.6
A30: Mars 2026 | B30: =SUMIFS(Détail!$E:$E,Détail!$C:$C,"FRAIS BANQUE ETRANGERE",Détail!$A:$A,">="&DATE(2026,3,1),Détail!$A:$A,"<"&EDATE(DATE(2026,3,1),1)) -> -144
A31: Avril 2026 | B31: =SUMIFS(Détail!$E:$E,Détail!$C:$C,"FRAIS BANQUE ETRANGERE",Détail!$A:$A,">="&DATE(2026,4,1),Détail!$A:$A,"<"&EDATE(DATE(2026,4,1),1)) -> -57.6
A32: Mai 2026 | B32: =SUMIFS(Détail!$E:$E,Détail!$C:$C,"FRAIS BANQUE ETRANGERE",Détail!$A:$A,">="&DATE(2026,5,1),Détail!$A:$A,"<"&EDATE(DATE(2026,5,1),1)) -> -28.8
A33: Juin 2026 | B33: =SUMIFS(Détail!$E:$E,Détail!$C:$C,"FRAIS BANQUE ETRANGERE",Détail!$A:$A,">="&DATE(2026,6,1),Détail!$A:$A,"<"&EDATE(DATE(2026,6,1),1)) -> -28.8
A34: Juillet 2026 | B34: =SUMIFS(Détail!$E:$E,Détail!$C:$C,"FRAIS BANQUE ETRANGERE",Détail!$A:$A,">="&DATE(2026,7,1),Détail!$A:$A,"<"&EDATE(DATE(2026,7,1),1)) -> 0
A37: Cotisation | C37: =SUMIF(Détail!$C:$C,"COTISATION",Détail!$E:$E) -> -296.1
A38: Mois | B38: Montant
A39: Janvier 2026 | B39: =SUMIFS(Détail!$E:$E,Détail!$C:$C,"COTISATION",Détail!$A:$A,">="&DATE(2026,1,1),Détail!$A:$A,"<"&EDATE(DATE(2026,1,1),1)) -> -49.35
A40: Février 2026 | B40: =SUMIFS(Détail!$E:$E,Détail!$C:$C,"COTISATION",Détail!$A:$A,">="&DATE(2026,2,1),Détail!$A:$A,"<"&EDATE(DATE(2026,2,1),1)) -> -49.35
A41: Mars 2026 | B41: =SUMIFS(Détail!$E:$E,Détail!$C:$C,"COTISATION",Détail!$A:$A,">="&DATE(2026,3,1),Détail!$A:$A,"<"&EDATE(DATE(2026,3,1),1)) -> -49.35
A42: Avril 2026 | B42: =SUMIFS(Détail!$E:$E,Détail!$C:$C,"COTISATION",Détail!$A:$A,">="&DATE(2026,4,1),Détail!$A:$A,"<"&EDATE(DATE(2026,4,1),1)) -> -49.35
A43: Mai 2026 | B43: =SUMIFS(Détail!$E:$E,Détail!$C:$C,"COTISATION",Détail!$A:$A,">="&DATE(2026,5,1),Détail!$A:$A,"<"&EDATE(DATE(2026,5,1),1)) -> -49.35
A44: Juin 2026 | B44: =SUMIFS(Détail!$E:$E,Détail!$C:$C,"COTISATION",Détail!$A:$A,">="&DATE(2026,6,1),Détail!$A:$A,"<"&EDATE(DATE(2026,6,1),1)) -> -49.35
A45: Juillet 2026 | B45: =SUMIFS(Détail!$E:$E,Détail!$C:$C,"COTISATION",Détail!$A:$A,">="&DATE(2026,7,1),Détail!$A:$A,"<"&EDATE(DATE(2026,7,1),1)) -> 0
A48: Frais De Change | C48: =SUMIF(Détail!$C:$C,"FRAIS DE CHANGE",Détail!$E:$E) -> -230
A49: Mois | B49: Montant
A50: Janvier 2026 | B50: =SUMIFS(Détail!$E:$E,Détail!$C:$C,"FRAIS DE CHANGE",Détail!$A:$A,">="&DATE(2026,1,1),Détail!$A:$A,"<"&EDATE(DATE(2026,1,1),1)) -> -38.5
A51: Février 2026 | B51: =SUMIFS(Détail!$E:$E,Détail!$C:$C,"FRAIS DE CHANGE",Détail!$A:$A,">="&DATE(2026,2,1),Détail!$A:$A,"<"&EDATE(DATE(2026,2,1),1)) -> -38.5
A52: Mars 2026 | B52: =SUMIFS(Détail!$E:$E,Détail!$C:$C,"FRAIS DE CHANGE",Détail!$A:$A,">="&DATE(2026,3,1),Détail!$A:$A,"<"&EDATE(DATE(2026,3,1),1)) -> -85
A53: Avril 2026 | B53: =SUMIFS(Détail!$E:$E,Détail!$C:$C,"FRAIS DE CHANGE",Détail!$A:$A,">="&DATE(2026,4,1),Détail!$A:$A,"<"&EDATE(DATE(2026,4,1),1)) -> -34
A54: Mai 2026 | B54: =SUMIFS(Détail!$E:$E,Détail!$C:$C,"FRAIS DE CHANGE",Détail!$A:$A,">="&DATE(2026,5,1),Détail!$A:$A,"<"&EDATE(DATE(2026,5,1),1)) -> -17
A55: Juin 2026 | B55: =SUMIFS(Détail!$E:$E,Détail!$C:$C,"FRAIS DE CHANGE",Détail!$A:$A,">="&DATE(2026,6,1),Détail!$A:$A,"<"&EDATE(DATE(2026,6,1),1)) -> -17
A56: Juillet 2026 | B56: =SUMIFS(Détail!$E:$E,Détail!$C:$C,"FRAIS DE CHANGE",Détail!$A:$A,">="&DATE(2026,7,1),Détail!$A:$A,"<"&EDATE(DATE(2026,7,1),1)) -> 0
A59: Frais Virement International | C59: =SUMIF(Détail!$C:$C,"FRAIS VIREMENT INTERNATIONAL",Détail!$E:$E) -> -214.8
A60: Mois | B60: Montant
A61: Janvier 2026 | B61: =SUMIFS(Détail!$E:$E,Détail!$C:$C,"FRAIS VIREMENT INTERNATIONAL",Détail!$A:$A,">="&DATE(2026,1,1),Détail!$A:$A,"<"&EDATE(DATE(2026,1,1),1)) -> -37.2
A62: Février 2026 | B62: =SUMIFS(Détail!$E:$E,Détail!$C:$C,"FRAIS VIREMENT INTERNATIONAL",Détail!$A:$A,">="&DATE(2026,2,1),Détail!$A:$A,"<"&EDATE(DATE(2026,2,1),1)) -> -37.2
A63: Mars 2026 | B63: =SUMIFS(Détail!$E:$E,Détail!$C:$C,"FRAIS VIREMENT INTERNATIONAL",Détail!$A:$A,">="&DATE(2026,3,1),Détail!$A:$A,"<"&EDATE(DATE(2026,3,1),1)) -> -78
A64: Avril 2026 | B64: =SUMIFS(Détail!$E:$E,Détail!$C:$C,"FRAIS VIREMENT INTERNATIONAL",Détail!$A:$A,">="&DATE(2026,4,1),Détail!$A:$A,"<"&EDATE(DATE(2026,4,1),1)) -> -31.2
A65: Mai 2026 | B65: =SUMIFS(Détail!$E:$E,Détail!$C:$C,"FRAIS VIREMENT INTERNATIONAL",Détail!$A:$A,">="&DATE(2026,5,1),Détail!$A:$A,"<"&EDATE(DATE(2026,5,1),1)) -> -15.6
A66: Juin 2026 | B66: =SUMIFS(Détail!$E:$E,Détail!$C:$C,"FRAIS VIREMENT INTERNATIONAL",Détail!$A:$A,">="&DATE(2026,6,1),Détail!$A:$A,"<"&EDATE(DATE(2026,6,1),1)) -> -15.6
A67: Juillet 2026 | B67: =SUMIFS(Détail!$E:$E,Détail!$C:$C,"FRAIS VIREMENT INTERNATIONAL",Détail!$A:$A,">="&DATE(2026,7,1),Détail!$A:$A,"<"&EDATE(DATE(2026,7,1),1)) -> 0
A70: Fonds De Garantie | C70: =SUMIF(Détail!$C:$C,"FONDS DE GARANTIE",Détail!$E:$E) -> -187.74
A71: Mois | B71: Montant
A72: Janvier 2026 | B72: =SUMIFS(Détail!$E:$E,Détail!$C:$C,"FONDS DE GARANTIE",Détail!$A:$A,">="&DATE(2026,1,1),Détail!$A:$A,"<"&EDATE(DATE(2026,1,1),1)) -> 0
A73: Février 2026 | B73: =SUMIFS(Détail!$E:$E,Détail!$C:$C,"FONDS DE GARANTIE",Détail!$A:$A,">="&DATE(2026,2,1),Détail!$A:$A,"<"&EDATE(DATE(2026,2,1),1)) -> 0
A74: Mars 2026 | B74: =SUMIFS(Détail!$E:$E,Détail!$C:$C,"FONDS DE GARANTIE",Détail!$A:$A,">="&DATE(2026,3,1),Détail!$A:$A,"<"&EDATE(DATE(2026,3,1),1)) -> -187.74
A75: Avril 2026 | B75: =SUMIFS(Détail!$E:$E,Détail!$C:$C,"FONDS DE GARANTIE",Détail!$A:$A,">="&DATE(2026,4,1),Détail!$A:$A,"<"&EDATE(DATE(2026,4,1),1)) -> 0
A76: Mai 2026 | B76: =SUMIFS(Détail!$E:$E,Détail!$C:$C,"FONDS DE GARANTIE",Détail!$A:$A,">="&DATE(2026,5,1),Détail!$A:$A,"<"&EDATE(DATE(2026,5,1),1)) -> 0
A77: Juin 2026 | B77: =SUMIFS(Détail!$E:$E,Détail!$C:$C,"FONDS DE GARANTIE",Détail!$A:$A,">="&DATE(2026,6,1),Détail!$A:$A,"<"&EDATE(DATE(2026,6,1),1)) -> 0
A78: Juillet 2026 | B78: =SUMIFS(Détail!$E:$E,Détail!$C:$C,"FONDS DE GARANTIE",Détail!$A:$A,">="&DATE(2026,7,1),Détail!$A:$A,"<"&EDATE(DATE(2026,7,1),1)) -> 0
A81: Frais Concours | C81: =SUMIF(Détail!$C:$C,"FRAIS CONCOURS",Détail!$E:$E) -> -187.74
A82: Mois | B82: Montant
A83: Janvier 2026 | B83: =SUMIFS(Détail!$E:$E,Détail!$C:$C,"FRAIS CONCOURS",Détail!$A:$A,">="&DATE(2026,1,1),Détail!$A:$A,"<"&EDATE(DATE(2026,1,1),1)) -> 0
A84: Février 2026 | B84: =SUMIFS(Détail!$E:$E,Détail!$C:$C,"FRAIS CONCOURS",Détail!$A:$A,">="&DATE(2026,2,1),Détail!$A:$A,"<"&EDATE(DATE(2026,2,1),1)) -> 0
A85: Mars 2026 | B85: =SUMIFS(Détail!$E:$E,Détail!$C:$C,"FRAIS CONCOURS",Détail!$A:$A,">="&DATE(2026,3,1),Détail!$A:$A,"<"&EDATE(DATE(2026,3,1),1)) -> -187.74
A86: Avril 2026 | B86: =SUMIFS(Détail!$E:$E,Détail!$C:$C,"FRAIS CONCOURS",Détail!$A:$A,">="&DATE(2026,4,1),Détail!$A:$A,"<"&EDATE(DATE(2026,4,1),1)) -> 0
A87: Mai 2026 | B87: =SUMIFS(Détail!$E:$E,Détail!$C:$C,"FRAIS CONCOURS",Détail!$A:$A,">="&DATE(2026,5,1),Détail!$A:$A,"<"&EDATE(DATE(2026,5,1),1)) -> 0
A88: Juin 2026 | B88: =SUMIFS(Détail!$E:$E,Détail!$C:$C,"FRAIS CONCOURS",Détail!$A:$A,">="&DATE(2026,6,1),Détail!$A:$A,"<"&EDATE(DATE(2026,6,1),1)) -> 0
A89: Juillet 2026 | B89: =SUMIFS(Détail!$E:$E,Détail!$C:$C,"FRAIS CONCOURS",Détail!$A:$A,">="&DATE(2026,7,1),Détail!$A:$A,"<"&EDATE(DATE(2026,7,1),1)) -> 0
A92: Frais Tenue De Compte | C92: =SUMIF(Détail!$C:$C,"FRAIS TENUE DE COMPTE",Détail!$E:$E) -> -148.8
A93: Mois | B93: Montant
A94: Janvier 2026 | B94: =SUMIFS(Détail!$E:$E,Détail!$C:$C,"FRAIS TENUE DE COMPTE",Détail!$A:$A,">="&DATE(2026,1,1),Détail!$A:$A,"<"&EDATE(DATE(2026,1,1),1)) -> 0
A95: Février 2026 | B95: =SUMIFS(Détail!$E:$E,Détail!$C:$C,"FRAIS TENUE DE COMPTE",Détail!$A:$A,">="&DATE(2026,2,1),Détail!$A:$A,"<"&EDATE(DATE(2026,2,1),1)) -> 0
A96: Mars 2026 | B96: =SUMIFS(Détail!$E:$E,Détail!$C:$C,"FRAIS TENUE DE COMPTE",Détail!$A:$A,">="&DATE(2026,3,1),Détail!$A:$A,"<"&EDATE(DATE(2026,3,1),1)) -> -74.4
A97: Avril 2026 | B97: =SUMIFS(Détail!$E:$E,Détail!$C:$C,"FRAIS TENUE DE COMPTE",Détail!$A:$A,">="&DATE(2026,4,1),Détail!$A:$A,"<"&EDATE(DATE(2026,4,1),1)) -> 0
A98: Mai 2026 | B98: =SUMIFS(Détail!$E:$E,Détail!$C:$C,"FRAIS TENUE DE COMPTE",Détail!$A:$A,">="&DATE(2026,5,1),Détail!$A:$A,"<"&EDATE(DATE(2026,5,1),1)) -> 0
A99: Juin 2026 | B99: =SUMIFS(Détail!$E:$E,Détail!$C:$C,"FRAIS TENUE DE COMPTE",Détail!$A:$A,">="&DATE(2026,6,1),Détail!$A:$A,"<"&EDATE(DATE(2026,6,1),1)) -> -74.4
A100: Juillet 2026 | B100: =SUMIFS(Détail!$E:$E,Détail!$C:$C,"FRAIS TENUE DE COMPTE",Détail!$A:$A,">="&DATE(2026,7,1),Détail!$A:$A,"<"&EDATE(DATE(2026,7,1),1)) -> 0
A103: Frais Transaction Carte | C103: =SUMIF(Détail!$C:$C,"FRAIS TRANSACTION CARTE",Détail!$E:$E) -> -87.05
A104: Mois | B104: Montant
A105: Janvier 2026 | B105: =SUMIFS(Détail!$E:$E,Détail!$C:$C,"FRAIS TRANSACTION CARTE",Détail!$A:$A,">="&DATE(2026,1,1),Détail!$A:$A,"<"&EDATE(DATE(2026,1,1),1)) -> -0.5
A106: Février 2026 | B106: =SUMIFS(Détail!$E:$E,Détail!$C:$C,"FRAIS TRANSACTION CARTE",Détail!$A:$A,">="&DATE(2026,2,1),Détail!$A:$A,"<"&EDATE(DATE(2026,2,1),1)) -> -0.49
A107: Mars 2026 | B107: =SUMIFS(Détail!$E:$E,Détail!$C:$C,"FRAIS TRANSACTION CARTE",Détail!$A:$A,">="&DATE(2026,3,1),Détail!$A:$A,"<"&EDATE(DATE(2026,3,1),1)) -> -5.51
A108: Avril 2026 | B108: =SUMIFS(Détail!$E:$E,Détail!$C:$C,"FRAIS TRANSACTION CARTE",Détail!$A:$A,">="&DATE(2026,4,1),Détail!$A:$A,"<"&EDATE(DATE(2026,4,1),1)) -> -10.67
A109: Mai 2026 | B109: =SUMIFS(Détail!$E:$E,Détail!$C:$C,"FRAIS TRANSACTION CARTE",Détail!$A:$A,">="&DATE(2026,5,1),Détail!$A:$A,"<"&EDATE(DATE(2026,5,1),1)) -> -6.66
A110: Juin 2026 | B110: =SUMIFS(Détail!$E:$E,Détail!$C:$C,"FRAIS TRANSACTION CARTE",Détail!$A:$A,">="&DATE(2026,6,1),Détail!$A:$A,"<"&EDATE(DATE(2026,6,1),1)) -> -53.53
A111: Juillet 2026 | B111: =SUMIFS(Détail!$E:$E,Détail!$C:$C,"FRAIS TRANSACTION CARTE",Détail!$A:$A,">="&DATE(2026,7,1),Détail!$A:$A,"<"&EDATE(DATE(2026,7,1),1)) -> -9.69
A114: Frais Virement International Taxable | C114: =SUMIF(Détail!$C:$C,"FRAIS VIREMENT INTERNATIONAL TAXABLE",Détail!$E:$E) -> -58.56
A115: Mois | B115: Montant
A116: Janvier 2026 | B116: =SUMIFS(Détail!$E:$E,Détail!$C:$C,"FRAIS VIREMENT INTERNATIONAL TAXABLE",Détail!$A:$A,">="&DATE(2026,1,1),Détail!$A:$A,"<"&EDATE(DATE(2026,1,1),1)) -> 0
A117: Février 2026 | B117: =SUMIFS(Détail!$E:$E,Détail!$C:$C,"FRAIS VIREMENT INTERNATIONAL TAXABLE",Détail!$A:$A,">="&DATE(2026,2,1),Détail!$A:$A,"<"&EDATE(DATE(2026,2,1),1)) -> -14.64
A118: Mars 2026 | B118: =SUMIFS(Détail!$E:$E,Détail!$C:$C,"FRAIS VIREMENT INTERNATIONAL TAXABLE",Détail!$A:$A,">="&DATE(2026,3,1),Détail!$A:$A,"<"&EDATE(DATE(2026,3,1),1)) -> 0
A119: Avril 2026 | B119: =SUMIFS(Détail!$E:$E,Détail!$C:$C,"FRAIS VIREMENT INTERNATIONAL TAXABLE",Détail!$A:$A,">="&DATE(2026,4,1),Détail!$A:$A,"<"&EDATE(DATE(2026,4,1),1)) -> 0
A120: Mai 2026 | B120: =SUMIFS(Détail!$E:$E,Détail!$C:$C,"FRAIS VIREMENT INTERNATIONAL TAXABLE",Détail!$A:$A,">="&DATE(2026,5,1),Détail!$A:$A,"<"&EDATE(DATE(2026,5,1),1)) -> -29.28
A121: Juin 2026 | B121: =SUMIFS(Détail!$E:$E,Détail!$C:$C,"FRAIS VIREMENT INTERNATIONAL TAXABLE",Détail!$A:$A,">="&DATE(2026,6,1),Détail!$A:$A,"<"&EDATE(DATE(2026,6,1),1)) -> -14.64
...

Sheet Mutuelle détail
A1: Mutuelle / prévoyance salariés — détail par organisme (2026)
A3: Macif Idf Production-Macif | C3: =SUMIF(Détail!$D:$D,"MACIF IDF PRODUCTION-MACIF",Détail!$E:$E) -> -1403.98
A4: Mois | B4: Montant
A5: Janvier 2026 | B5: =SUMIFS(Détail!$E:$E,Détail!$D:$D,"MACIF IDF PRODUCTION-MACIF",Détail!$A:$A,">="&DATE(2026,1,1),Détail!$A:$A,"<"&EDATE(DATE(2026,1,1),1)) -> -130.67
A6: Février 2026 | B6: =SUMIFS(Détail!$E:$E,Détail!$D:$D,"MACIF IDF PRODUCTION-MACIF",Détail!$A:$A,">="&DATE(2026,2,1),Détail!$A:$A,"<"&EDATE(DATE(2026,2,1),1)) -> -130.67
A7: Mars 2026 | B7: =SUMIFS(Détail!$E:$E,Détail!$D:$D,"MACIF IDF PRODUCTION-MACIF",Détail!$A:$A,">="&DATE(2026,3,1),Détail!$A:$A,"<"&EDATE(DATE(2026,3,1),1)) -> -130.67
A8: Avril 2026 | B8: =SUMIFS(Détail!$E:$E,Détail!$D:$D,"MACIF IDF PRODUCTION-MACIF",Détail!$A:$A,">="&DATE(2026,4,1),Détail!$A:$A,"<"&EDATE(DATE(2026,4,1),1)) -> -252.91
A9: Mai 2026 | B9: =SUMIFS(Détail!$E:$E,Détail!$D:$D,"MACIF IDF PRODUCTION-MACIF",Détail!$A:$A,">="&DATE(2026,5,1),Détail!$A:$A,"<"&EDATE(DATE(2026,5,1),1)) -> -253.02
A10: Juin 2026 | B10: =SUMIFS(Détail!$E:$E,Détail!$D:$D,"MACIF IDF PRODUCTION-MACIF",Détail!$A:$A,">="&DATE(2026,6,1),Détail!$A:$A,"<"&EDATE(DATE(2026,6,1),1)) -> -253.02
A11: Juillet 2026 | B11: =SUMIFS(Détail!$E:$E,Détail!$D:$D,"MACIF IDF PRODUCTION-MACIF",Détail!$A:$A,">="&DATE(2026,7,1),Détail!$A:$A,"<"&EDATE(DATE(2026,7,1),1)) -> -253.02
A14: Msp Cot Sante Des Entreprises-Macif Sante Prevoyance | C14: =SUMIF(Détail!$D:$D,"MSP COT SANTE DES ENTREPRISES-MACIF SANTE PREVOYANCE",Détail!$E:$E) -> -862
A15: Mois | B15: Montant
A16: Janvier 2026 | B16: =SUMIFS(Détail!$E:$E,Détail!$D:$D,"MSP COT SANTE DES ENTREPRISES-MACIF SANTE PREVOYANCE",Détail!$A:$A,">="&DATE(2026,1,1),Détail!$A:$A,"<"&EDATE(DATE(2026,1,1),1)) -> 0
A17: Février 2026 | B17: =SUMIFS(Détail!$E:$E,Détail!$D:$D,"MSP COT SANTE DES ENTREPRISES-MACIF SANTE PREVOYANCE",Détail!$A:$A,">="&DATE(2026,2,1),Détail!$A:$A,"<"&EDATE(DATE(2026,2,1),1)) -> 0
A18: Mars 2026 | B18: =SUMIFS(Détail!$E:$E,Détail!$D:$D,"MSP COT SANTE DES ENTREPRISES-MACIF SANTE PREVOYANCE",Détail!$A:$A,">="&DATE(2026,3,1),Détail!$A:$A,"<"&EDATE(DATE(2026,3,1),1)) -> 0
A19: Avril 2026 | B19: =SUMIFS(Détail!$E:$E,Détail!$D:$D,"MSP COT SANTE DES ENTREPRISES-MACIF SANTE PREVOYANCE",Détail!$A:$A,">="&DATE(2026,4,1),Détail!$A:$A,"<"&EDATE(DATE(2026,4,1),1)) -> -215.5
A20: Mai 2026 | B20: =SUMIFS(Détail!$E:$E,Détail!$D:$D,"MSP COT SANTE DES ENTREPRISES-MACIF SANTE PREVOYANCE",Détail!$A:$A,">="&DATE(2026,5,1),Détail!$A:$A,"<"&EDATE(DATE(2026,5,1),1)) -> -215.5
A21: Juin 2026 | B21: =SUMIFS(Détail!$E:$E,Détail!$D:$D,"MSP COT SANTE DES ENTREPRISES-MACIF SANTE PREVOYANCE",Détail!$A:$A,">="&DATE(2026,6,1),Détail!$A:$A,"<"&EDATE(DATE(2026,6,1),1)) -> -215.5
A22: Juillet 2026 | B22: =SUMIFS(Détail!$E:$E,Détail!$D:$D,"MSP COT SANTE DES ENTREPRISES-MACIF SANTE PREVOYANCE",Détail!$A:$A,">="&DATE(2026,7,1),Détail!$A:$A,"<"&EDATE(DATE(2026,7,1),1)) -> -215.5
A25: Amm Cot Sante Des Entreprises-Macif Sante Prevoyance | C25: =SUMIF(Détail!$D:$D,"AMM COT SANTE DES ENTREPRISES-MACIF SANTE PREVOYANCE",Détail!$E:$E) -> -431
A26: Mois | B26: Montant
A27: Janvier 2026 | B27: =SUMIFS(Détail!$E:$E,Détail!$D:$D,"AMM COT SANTE DES ENTREPRISES-MACIF SANTE PREVOYANCE",Détail!$A:$A,">="&DATE(2026,1,1),Détail!$A:$A,"<"&EDATE(DATE(2026,1,1),1)) -> 0
A28: Février 2026 | B28: =SUMIFS(Détail!$E:$E,Détail!$D:$D,"AMM COT SANTE DES ENTREPRISES-MACIF SANTE PREVOYANCE",Détail!$A:$A,">="&DATE(2026,2,1),Détail!$A:$A,"<"&EDATE(DATE(2026,2,1),1)) -> -215.5
A29: Mars 2026 | B29: =SUMIFS(Détail!$E:$E,Détail!$D:$D,"AMM COT SANTE DES ENTREPRISES-MACIF SANTE PREVOYANCE",Détail!$A:$A,">="&DATE(2026,3,1),Détail!$A:$A,"<"&EDATE(DATE(2026,3,1),1)) -> -215.5
A30: Avril 2026 | B30: =SUMIFS(Détail!$E:$E,Détail!$D:$D,"AMM COT SANTE DES ENTREPRISES-MACIF SANTE PREVOYANCE",Détail!$A:$A,">="&DATE(2026,4,1),Détail!$A:$A,"<"&EDATE(DATE(2026,4,1),1)) -> 0
A31: Mai 2026 | B31: =SUMIFS(Détail!$E:$E,Détail!$D:$D,"AMM COT SANTE DES ENTREPRISES-MACIF SANTE PREVOYANCE",Détail!$A:$A,">="&DATE(2026,5,1),Détail!$A:$A,"<"&EDATE(DATE(2026,5,1),1)) -> 0
A32: Juin 2026 | B32: =SUMIFS(Détail!$E:$E,Détail!$D:$D,"AMM COT SANTE DES ENTREPRISES-MACIF SANTE PREVOYANCE",Détail!$A:$A,">="&DATE(2026,6,1),Détail!$A:$A,"<"&EDATE(DATE(2026,6,1),1)) -> 0
A33: Juillet 2026 | B33: =SUMIFS(Détail!$E:$E,Détail!$D:$D,"AMM COT SANTE DES ENTREPRISES-MACIF SANTE PREVOYANCE",Détail!$A:$A,">="&DATE(2026,7,1),Détail!$A:$A,"<"&EDATE(DATE(2026,7,1),1)) -> 0
A36: Cep Treso Sante Prev | C36: =SUMIF(Détail!$D:$D,"CEP TRESO SANTE PREV",Détail!$E:$E) -> -285.83
A37: Mois | B37: Montant
A38: Janvier 2026 | B38: =SUMIFS(Détail!$E:$E,Détail!$D:$D,"CEP TRESO SANTE PREV",Détail!$A:$A,">="&DATE(2026,1,1),Détail!$A:$A,"<"&EDATE(DATE(2026,1,1),1)) -> -144.38
A39: Février 2026 | B39: =SUMIFS(Détail!$E:$E,Détail!$D:$D,"CEP TRESO SANTE PREV",Détail!$A:$A,">="&DATE(2026,2,1),Détail!$A:$A,"<"&EDATE(DATE(2026,2,1),1)) -> 0
A40: Mars 2026 | B40: =SUMIFS(Détail!$E:$E,Détail!$D:$D,"CEP TRESO SANTE PREV",Détail!$A:$A,">="&DATE(2026,3,1),Détail!$A:$A,"<"&EDATE(DATE(2026,3,1),1)) -> 0
A41: Avril 2026 | B41: =SUMIFS(Détail!$E:$E,Détail!$D:$D,"CEP TRESO SANTE PREV",Détail!$A:$A,">="&DATE(2026,4,1),Détail!$A:$A,"<"&EDATE(DATE(2026,4,1),1)) -> -141.45
A42: Mai 2026 | B42: =SUMIFS(Détail!$E:$E,Détail!$D:$D,"CEP TRESO SANTE PREV",Détail!$A:$A,">="&DATE(2026,5,1),Détail!$A:$A,"<"&EDATE(DATE(2026,5,1),1)) -> 0
A43: Juin 2026 | B43: =SUMIFS(Détail!$E:$E,Détail!$D:$D,"CEP TRESO SANTE PREV",Détail!$A:$A,">="&DATE(2026,6,1),Détail!$A:$A,"<"&EDATE(DATE(2026,6,1),1)) -> 0
A44: Juillet 2026 | B44: =SUMIFS(Détail!$E:$E,Détail!$D:$D,"CEP TRESO SANTE PREV",Détail!$A:$A,">="&DATE(2026,7,1),Détail!$A:$A,"<"&EDATE(DATE(2026,7,1),1)) -> 0
A47: Amm Cot Sante Des Entreprises-Apivia Macif Mutuelle | C47: =SUMIF(Détail!$D:$D,"AMM COT SANTE DES ENTREPRISES-APIVIA MACIF MUTUELLE",Détail!$E:$E) -> -211.17
A48: Mois | B48: Montant
A49: Janvier 2026 | B49: =SUMIFS(Détail!$E:$E,Détail!$D:$D,"AMM COT SANTE DES ENTREPRISES-APIVIA MACIF MUTUELLE",Détail!$A:$A,">="&DATE(2026,1,1),Détail!$A:$A,"<"&EDATE(DATE(2026,1,1),1)) -> -211.17
A50: Février 2026 | B50: =SUMIFS(Détail!$E:$E,Détail!$D:$D,"AMM COT SANTE DES ENTREPRISES-APIVIA MACIF MUTUELLE",Détail!$A:$A,">="&DATE(2026,2,1),Détail!$A:$A,"<"&EDATE(DATE(2026,2,1),1)) -> 0
A51: Mars 2026 | B51: =SUMIFS(Détail!$E:$E,Détail!$D:$D,"AMM COT SANTE DES ENTREPRISES-APIVIA MACIF MUTUELLE",Détail!$A:$A,">="&DATE(2026,3,1),Détail!$A:$A,"<"&EDATE(DATE(2026,3,1),1)) -> 0
A52: Avril 2026 | B52: =SUMIFS(Détail!$E:$E,Détail!$D:$D,"AMM COT SANTE DES ENTREPRISES-APIVIA MACIF MUTUELLE",Détail!$A:$A,">="&DATE(2026,4,1),Détail!$A:$A,"<"&EDATE(DATE(2026,4,1),1)) -> 0
A53: Mai 2026 | B53: =SUMIFS(Détail!$E:$E,Détail!$D:$D,"AMM COT SANTE DES ENTREPRISES-APIVIA MACIF MUTUELLE",Détail!$A:$A,">="&DATE(2026,5,1),Détail!$A:$A,"<"&EDATE(DATE(2026,5,1),1)) -> 0
A54: Juin 2026 | B54: =SUMIFS(Détail!$E:$E,Détail!$D:$D,"AMM COT SANTE DES ENTREPRISES-APIVIA MACIF MUTUELLE",Détail!$A:$A,">="&DATE(2026,6,1),Détail!$A:$A,"<"&EDATE(DATE(2026,6,1),1)) -> 0
A55: Juillet 2026 | B55: =SUMIFS(Détail!$E:$E,Détail!$D:$D,"AMM COT SANTE DES ENTREPRISES-APIVIA MACIF MUTUELLE",Détail!$A:$A,">="&DATE(2026,7,1),Détail!$A:$A,"<"&EDATE(DATE(2026,7,1),1)) -> 0

Sheet Fournitures bureau détail
A1: Fournitures bureau / colis / achats en ligne — détail par prestataire (2026)
A3: Amazon Payments | C3: =SUMIF(Détail!$D:$D,"AMAZON PAYMENTS",Détail!$E:$E) -> -1755.79
A4: Mois | B4: Montant
A5: Février 2026 | B5: =SUMIFS(Détail!$E:$E,Détail!$D:$D,"AMAZON PAYMENTS",Détail!$A:$A,">="&DATE(2026,2,1),Détail!$A:$A,"<"&EDATE(DATE(2026,2,1),1)) -> -144.47
A6: Mars 2026 | B6: =SUMIFS(Détail!$E:$E,Détail!$D:$D,"AMAZON PAYMENTS",Détail!$A:$A,">="&DATE(2026,3,1),Détail!$A:$A,"<"&EDATE(DATE(2026,3,1),1)) -> -723.92
A7: Avril 2026 | B7: =SUMIFS(Détail!$E:$E,Détail!$D:$D,"AMAZON PAYMENTS",Détail!$A:$A,">="&DATE(2026,4,1),Détail!$A:$A,"<"&EDATE(DATE(2026,4,1),1)) -> -174.07
A8: Mai 2026 | B8: =SUMIFS(Détail!$E:$E,Détail!$D:$D,"AMAZON PAYMENTS",Détail!$A:$A,">="&DATE(2026,5,1),Détail!$A:$A,"<"&EDATE(DATE(2026,5,1),1)) -> -232.26
A9: Juin 2026 | B9: =SUMIFS(Détail!$E:$E,Détail!$D:$D,"AMAZON PAYMENTS",Détail!$A:$A,">="&DATE(2026,6,1),Détail!$A:$A,"<"&EDATE(DATE(2026,6,1),1)) -> -479.08
A10: Juillet 2026 | B10: =SUMIFS(Détail!$E:$E,Détail!$D:$D,"AMAZON PAYMENTS",Détail!$A:$A,">="&DATE(2026,7,1),Détail!$A:$A,"<"&EDATE(DATE(2026,7,1),1)) -> -1.99
A13: Boulanger | C13: =SUMIF(Détail!$D:$D,"BOULANGER",Détail!$E:$E) -> -698.98
A14: Mois | B14: Montant
A15: Février 2026 | B15: =SUMIFS(Détail!$E:$E,Détail!$D:$D,"BOULANGER",Détail!$A:$A,">="&DATE(2026,2,1),Détail!$A:$A,"<"&EDATE(DATE(2026,2,1),1)) -> 0
A16: Mars 2026 | B16: =SUMIFS(Détail!$E:$E,Détail!$D:$D,"BOULANGER",Détail!$A:$A,">="&DATE(2026,3,1),Détail!$A:$A,"<"&EDATE(DATE(2026,3,1),1)) -> 0
A17: Avril 2026 | B17: =SUMIFS(Détail!$E:$E,Détail!$D:$D,"BOULANGER",Détail!$A:$A,">="&DATE(2026,4,1),Détail!$A:$A,"<"&EDATE(DATE(2026,4,1),1)) -> 0
A18: Mai 2026 | B18: =SUMIFS(Détail!$E:$E,Détail!$D:$D,"BOULANGER",Détail!$A:$A,">="&DATE(2026,5,1),Détail!$A:$A,"<"&EDATE(DATE(2026,5,1),1)) -> -698.98
A19: Juin 2026 | B19: =SUMIFS(Détail!$E:$E,Détail!$D:$D,"BOULANGER",Détail!$A:$A,">="&DATE(2026,6,1),Détail!$A:$A,"<"&EDATE(DATE(2026,6,1),1)) -> 0
A20: Juillet 2026 | B20: =SUMIFS(Détail!$E:$E,Détail!$D:$D,"BOULANGER",Détail!$A:$A,">="&DATE(2026,7,1),Détail!$A:$A,"<"&EDATE(DATE(2026,7,1),1)) -> 0
A23: Office Depot | C23: =SUMIF(Détail!$D:$D,"OFFICE DEPOT",Détail!$E:$E) -> -476.45
A24: Mois | B24: Montant
A25: Février 2026 | B25: =SUMIFS(Détail!$E:$E,Détail!$D:$D,"OFFICE DEPOT",Détail!$A:$A,">="&DATE(2026,2,1),Détail!$A:$A,"<"&EDATE(DATE(2026,2,1),1)) -> 0
A26: Mars 2026 | B26: =SUMIFS(Détail!$E:$E,Détail!$D:$D,"OFFICE DEPOT",Détail!$A:$A,">="&DATE(2026,3,1),Détail!$A:$A,"<"&EDATE(DATE(2026,3,1),1)) -> 0
A27: Avril 2026 | B27: =SUMIFS(Détail!$E:$E,Détail!$D:$D,"OFFICE DEPOT",Détail!$A:$A,">="&DATE(2026,4,1),Détail!$A:$A,"<"&EDATE(DATE(2026,4,1),1)) -> 0
A28: Mai 2026 | B28: =SUMIFS(Détail!$E:$E,Détail!$D:$D,"OFFICE DEPOT",Détail!$A:$A,">="&DATE(2026,5,1),Détail!$A:$A,"<"&EDATE(DATE(2026,5,1),1)) -> 0
A29: Juin 2026 | B29: =SUMIFS(Détail!$E:$E,Détail!$D:$D,"OFFICE DEPOT",Détail!$A:$A,">="&DATE(2026,6,1),Détail!$A:$A,"<"&EDATE(DATE(2026,6,1),1)) -> -280.49
A30: Juillet 2026 | B30: =SUMIFS(Détail!$E:$E,Détail!$D:$D,"OFFICE DEPOT",Détail!$A:$A,">="&DATE(2026,7,1),Détail!$A:$A,"<"&EDATE(DATE(2026,7,1),1)) -> -195.96
A33: Aliexpress | C33: =SUMIF(Détail!$D:$D,"ALIEXPRESS",Détail!$E:$E) -> -440.23
A34: Mois | B34: Montant
A35: Février 2026 | B35: =SUMIFS(Détail!$E:$E,Détail!$D:$D,"ALIEXPRESS",Détail!$A:$A,">="&DATE(2026,2,1),Détail!$A:$A,"<"&EDATE(DATE(2026,2,1),1)) -> 0
A36: Mars 2026 | B36: =SUMIFS(Détail!$E:$E,Détail!$D:$D,"ALIEXPRESS",Détail!$A:$A,">="&DATE(2026,3,1),Détail!$A:$A,"<"&EDATE(DATE(2026,3,1),1)) -> 0
A37: Avril 2026 | B37: =SUMIFS(Détail!$E:$E,Détail!$D:$D,"ALIEXPRESS",Détail!$A:$A,">="&DATE(2026,4,1),Détail!$A:$A,"<"&EDATE(DATE(2026,4,1),1)) -> 0
A38: Mai 2026 | B38: =SUMIFS(Détail!$E:$E,Détail!$D:$D,"ALIEXPRESS",Détail!$A:$A,">="&DATE(2026,5,1),Détail!$A:$A,"<"&EDATE(DATE(2026,5,1),1)) -> 0
A39: Juin 2026 | B39: =SUMIFS(Détail!$E:$E,Détail!$D:$D,"ALIEXPRESS",Détail!$A:$A,">="&DATE(2026,6,1),Détail!$A:$A,"<"&EDATE(DATE(2026,6,1),1)) -> -440.23
A40: Juillet 2026 | B40: =SUMIFS(Détail!$E:$E,Détail!$D:$D,"ALIEXPRESS",Détail!$A:$A,">="&DATE(2026,7,1),Détail!$A:$A,"<"&EDATE(DATE(2026,7,1),1)) -> 0
A43: Aramex Emirates | C43: =SUMIF(Détail!$D:$D,"ARAMEX EMIRATES",Détail!$E:$E) -> -132.6
A44: Mois | B44: Montant
A45: Février 2026 | B45: =SUMIFS(Détail!$E:$E,Détail!$D:$D,"ARAMEX EMIRATES",Détail!$A:$A,">="&DATE(2026,2,1),Détail!$A:$A,"<"&EDATE(DATE(2026,2,1),1)) -> 0
A46: Mars 2026 | B46: =SUMIFS(Détail!$E:$E,Détail!$D:$D,"ARAMEX EMIRATES",Détail!$A:$A,">="&DATE(2026,3,1),Détail!$A:$A,"<"&EDATE(DATE(2026,3,1),1)) -> 0
A47: Avril 2026 | B47: =SUMIFS(Détail!$E:$E,Détail!$D:$D,"ARAMEX EMIRATES",Détail!$A:$A,">="&DATE(2026,4,1),Détail!$A:$A,"<"&EDATE(DATE(2026,4,1),1)) -> 0
A48: Mai 2026 | B48: =SUMIFS(Détail!$E:$E,Détail!$D:$D,"ARAMEX EMIRATES",Détail!$A:$A,">="&DATE(2026,5,1),Détail!$A:$A,"<"&EDATE(DATE(2026,5,1),1)) -> -132.6
A49: Juin 2026 | B49: =SUMIFS(Détail!$E:$E,Détail!$D:$D,"ARAMEX EMIRATES",Détail!$A:$A,">="&DATE(2026,6,1),Détail!$A:$A,"<"&EDATE(DATE(2026,6,1),1)) -> 0
A50: Juillet 2026 | B50: =SUMIFS(Détail!$E:$E,Détail!$D:$D,"ARAMEX EMIRATES",Détail!$A:$A,">="&DATE(2026,7,1),Détail!$A:$A,"<"&EDATE(DATE(2026,7,1),1)) -> 0
A53: Pk Novedad Onli | C53: =SUMIF(Détail!$D:$D,"PK NOVEDAD ONLI",Détail!$E:$E) -> -82.8
A54: Mois | B54: Montant
A55: Février 2026 | B55: =SUMIFS(Détail!$E:$E,Détail!$D:$D,"PK NOVEDAD ONLI",Détail!$A:$A,">="&DATE(2026,2,1),Détail!$A:$A,"<"&EDATE(DATE(2026,2,1),1)) -> 0
A56: Mars 2026 | B56: =SUMIFS(Détail!$E:$E,Détail!$D:$D,"PK NOVEDAD ONLI",Détail!$A:$A,">="&DATE(2026,3,1),Détail!$A:$A,"<"&EDATE(DATE(2026,3,1),1)) -> 0
A57: Avril 2026 | B57: =SUMIFS(Détail!$E:$E,Détail!$D:$D,"PK NOVEDAD ONLI",Détail!$A:$A,">="&DATE(2026,4,1),Détail!$A:$A,"<"&EDATE(DATE(2026,4,1),1)) -> -82.8
A58: Mai 2026 | B58: =SUMIFS(Détail!$E:$E,Détail!$D:$D,"PK NOVEDAD ONLI",Détail!$A:$A,">="&DATE(2026,5,1),Détail!$A:$A,"<"&EDATE(DATE(2026,5,1),1)) -> 0
A59: Juin 2026 | B59: =SUMIFS(Détail!$E:$E,Détail!$D:$D,"PK NOVEDAD ONLI",Détail!$A:$A,">="&DATE(2026,6,1),Détail!$A:$A,"<"&EDATE(DATE(2026,6,1),1)) -> 0
A60: Juillet 2026 | B60: =SUMIFS(Détail!$E:$E,Détail!$D:$D,"PK NOVEDAD ONLI",Détail!$A:$A,">="&DATE(2026,7,1),Détail!$A:$A,"<"&EDATE(DATE(2026,7,1),1)) -> 0
A63: Action 4632 | C63: =SUMIF(Détail!$D:$D,"ACTION 4632",Détail!$E:$E) -> -40.33
A64: Mois | B64: Montant
A65: Février 2026 | B65: =SUMIFS(Détail!$E:$E,Détail!$D:$D,"ACTION 4632",Détail!$A:$A,">="&DATE(2026,2,1),Détail!$A:$A,"<"&EDATE(DATE(2026,2,1),1)) -> 0
A66: Mars 2026 | B66: =SUMIFS(Détail!$E:$E,Détail!$D:$D,"ACTION 4632",Détail!$A:$A,">="&DATE(2026,3,1),Détail!$A:$A,"<"&EDATE(DATE(2026,3,1),1)) -> 0
A67: Avril 2026 | B67: =SUMIFS(Détail!$E:$E,Détail!$D:$D,"ACTION 4632",Détail!$A:$A,">="&DATE(2026,4,1),Détail!$A:$A,"<"&EDATE(DATE(2026,4,1),1)) -> 0
A68: Mai 2026 | B68: =SUMIFS(Détail!$E:$E,Détail!$D:$D,"ACTION 4632",Détail!$A:$A,">="&DATE(2026,5,1),Détail!$A:$A,"<"&EDATE(DATE(2026,5,1),1)) -> 0
A69: Juin 2026 | B69: =SUMIFS(Détail!$E:$E,Détail!$D:$D,"ACTION 4632",Détail!$A:$A,">="&DATE(2026,6,1),Détail!$A:$A,"<"&EDATE(DATE(2026,6,1),1)) -> 0
A70: Juillet 2026 | B70: =SUMIFS(Détail!$E:$E,Détail!$D:$D,"ACTION 4632",Détail!$A:$A,">="&DATE(2026,7,1),Détail!$A:$A,"<"&EDATE(DATE(2026,7,1),1)) -> -40.33
A73: Fnac - Nfc | C73: =SUMIF(Détail!$D:$D,"FNAC - NFC",Détail!$E:$E) -> -40.28
A74: Mois | B74: Montant
A75: Février 2026 | B75: =SUMIFS(Détail!$E:$E,Détail!$D:$D,"FNAC - NFC",Détail!$A:$A,">="&DATE(2026,2,1),Détail!$A:$A,"<"&EDATE(DATE(2026,2,1),1)) -> -40.28
A76: Mars 2026 | B76: =SUMIFS(Détail!$E:$E,Détail!$D:$D,"FNAC - NFC",Détail!$A:$A,">="&DATE(2026,3,1),Détail!$A:$A,"<"&EDATE(DATE(2026,3,1),1)) -> 0
A77: Avril 2026 | B77: =SUMIFS(Détail!$E:$E,Détail!$D:$D,"FNAC - NFC",Détail!$A:$A,">="&DATE(2026,4,1),Détail!$A:$A,"<"&EDATE(DATE(2026,4,1),1)) -> 0
A78: Mai 2026 | B78: =SUMIFS(Détail!$E:$E,Détail!$D:$D,"FNAC - NFC",Détail!$A:$A,">="&DATE(2026,5,1),Détail!$A:$A,"<"&EDATE(DATE(2026,5,1),1)) -> 0
A79: Juin 2026 | B79: =SUMIFS(Détail!$E:$E,Détail!$D:$D,"FNAC - NFC",Détail!$A:$A,">="&DATE(2026,6,1),Détail!$A:$A,"<"&EDATE(DATE(2026,6,1),1)) -> 0
A80: Juillet 2026 | B80: =SUMIFS(Détail!$E:$E,Détail!$D:$D,"FNAC - NFC",Détail!$A:$A,">="&DATE(2026,7,1),Détail!$A:$A,"<"&EDATE(DATE(2026,7,1),1)) -> 0
A83: Bricorama | C83: =SUMIF(Détail!$D:$D,"BRICORAMA",Détail!$E:$E) -> -6.99
A84: Mois | B84: Montant
A85: Février 2026 | B85: =SUMIFS(Détail!$E:$E,Détail!$D:$D,"BRICORAMA",Détail!$A:$A,">="&DATE(2026,2,1),Détail!$A:$A,"<"&EDATE(DATE(2026,2,1),1)) -> -6.99
A86: Mars 2026 | B86: =SUMIFS(Détail!$E:$E,Détail!$D:$D,"BRICORAMA",Détail!$A:$A,">="&DATE(2026,3,1),Détail!$A:$A,"<"&EDATE(DATE(2026,3,1),1)) -> 0
A87: Avril 2026 | B87: =SUMIFS(Détail!$E:$E,Détail!$D:$D,"BRICORAMA",Détail!$A:$A,">="&DATE(2026,4,1),Détail!$A:$A,"<"&EDATE(DATE(2026,4,1),1)) -> 0
A88: Mai 2026 | B88: =SUMIFS(Détail!$E:$E,Détail!$D:$D,"BRICORAMA",Détail!$A:$A,">="&DATE(2026,5,1),Détail!$A:$A,"<"&EDATE(DATE(2026,5,1),1)) -> 0
A89: Juin 2026 | B89: =SUMIFS(Détail!$E:$E,Détail!$D:$D,"BRICORAMA",Détail!$A:$A,">="&DATE(2026,6,1),Détail!$A:$A,"<"&EDATE(DATE(2026,6,1),1)) -> 0
A90: Juillet 2026 | B90: =SUMIFS(Détail!$E:$E,Détail!$D:$D,"BRICORAMA",Détail!$A:$A,">="&DATE(2026,7,1),Détail!$A:$A,"<"&EDATE(DATE(2026,7,1),1)) -> 0

Sheet Transport livraison détail
A1: Transport / livraison (colis, courrier) — détail par prestataire (2026)
A3: Ifs | C3: =SUMIF(Détail!$D:$D,"IFS",Détail!$E:$E) -> -40894.81
A4: Mois | B4: Montant
A5: Janvier 2026 | B5: =SUMIFS(Détail!$E:$E,Détail!$D:$D,"IFS",Détail!$A:$A,">="&DATE(2026,1,1),Détail!$A:$A,"<"&EDATE(DATE(2026,1,1),1)) -> -6343.1
A6: Février 2026 | B6: =SUMIFS(Détail!$E:$E,Détail!$D:$D,"IFS",Détail!$A:$A,">="&DATE(2026,2,1),Détail!$A:$A,"<"&EDATE(DATE(2026,2,1),1)) -> -5951.2
A7: Mars 2026 | B7: =SUMIFS(Détail!$E:$E,Détail!$D:$D,"IFS",Détail!$A:$A,">="&DATE(2026,3,1),Détail!$A:$A,"<"&EDATE(DATE(2026,3,1),1)) -> 0
A8: Avril 2026 | B8: =SUMIFS(Détail!$E:$E,Détail!$D:$D,"IFS",Détail!$A:$A,">="&DATE(2026,4,1),Détail!$A:$A,"<"&EDATE(DATE(2026,4,1),1)) -> -9975.2
A9: Mai 2026 | B9: =SUMIFS(Détail!$E:$E,Détail!$D:$D,"IFS",Détail!$A:$A,">="&DATE(2026,5,1),Détail!$A:$A,"<"&EDATE(DATE(2026,5,1),1)) -> -7826.85
A10: Juin 2026 | B10: =SUMIFS(Détail!$E:$E,Détail!$D:$D,"IFS",Détail!$A:$A,">="&DATE(2026,6,1),Détail!$A:$A,"<"&EDATE(DATE(2026,6,1),1)) -> -10798.46
A11: Juillet 2026 | B11: =SUMIFS(Détail!$E:$E,Détail!$D:$D,"IFS",Détail!$A:$A,">="&DATE(2026,7,1),Détail!$A:$A,"<"&EDATE(DATE(2026,7,1),1)) -> 0
A14: La Poste.Fr | C14: =SUMIF(Détail!$D:$D,"LA POSTE.FR",Détail!$E:$E) -> -1125.82
A15: Mois | B15: Montant
A16: Janvier 2026 | B16: =SUMIFS(Détail!$E:$E,Détail!$D:$D,"LA POSTE.FR",Détail!$A:$A,">="&DATE(2026,1,1),Détail!$A:$A,"<"&EDATE(DATE(2026,1,1),1)) -> -109.36
A17: Février 2026 | B17: =SUMIFS(Détail!$E:$E,Détail!$D:$D,"LA POSTE.FR",Détail!$A:$A,">="&DATE(2026,2,1),Détail!$A:$A,"<"&EDATE(DATE(2026,2,1),1)) -> -36.27
A18: Mars 2026 | B18: =SUMIFS(Détail!$E:$E,Détail!$D:$D,"LA POSTE.FR",Détail!$A:$A,">="&DATE(2026,3,1),Détail!$A:$A,"<"&EDATE(DATE(2026,3,1),1)) -> -143.13
A19: Avril 2026 | B19: =SUMIFS(Détail!$E:$E,Détail!$D:$D,"LA POSTE.FR",Détail!$A:$A,">="&DATE(2026,4,1),Détail!$A:$A,"<"&EDATE(DATE(2026,4,1),1)) -> -457.25
A20: Mai 2026 | B20: =SUMIFS(Détail!$E:$E,Détail!$D:$D,"LA POSTE.FR",Détail!$A:$A,">="&DATE(2026,5,1),Détail!$A:$A,"<"&EDATE(DATE(2026,5,1),1)) -> -100.22
A21: Juin 2026 | B21: =SUMIFS(Détail!$E:$E,Détail!$D:$D,"LA POSTE.FR",Détail!$A:$A,">="&DATE(2026,6,1),Détail!$A:$A,"<"&EDATE(DATE(2026,6,1),1)) -> -243.72
A22: Juillet 2026 | B22: =SUMIFS(Détail!$E:$E,Détail!$D:$D,"LA POSTE.FR",Détail!$A:$A,">="&DATE(2026,7,1),Détail!$A:$A,"<"&EDATE(DATE(2026,7,1),1)) -> -35.87
A25: Dhl Internat. Exp France | C25: =SUMIF(Détail!$D:$D,"DHL INTERNAT. EXP FRANCE",Détail!$E:$E) -> -894.27
A26: Mois | B26: Montant
A27: Janvier 2026 | B27: =SUMIFS(Détail!$E:$E,Détail!$D:$D,"DHL INTERNAT. EXP FRANCE",Détail!$A:$A,">="&DATE(2026,1,1),Détail!$A:$A,"<"&EDATE(DATE(2026,1,1),1)) -> 0
A28: Février 2026 | B28: =SUMIFS(Détail!$E:$E,Détail!$D:$D,"DHL INTERNAT. EXP FRANCE",Détail!$A:$A,">="&DATE(2026,2,1),Détail!$A:$A,"<"&EDATE(DATE(2026,2,1),1)) -> -54.76
A29: Mars 2026 | B29: =SUMIFS(Détail!$E:$E,Détail!$D:$D,"DHL INTERNAT. EXP FRANCE",Détail!$A:$A,">="&DATE(2026,3,1),Détail!$A:$A,"<"&EDATE(DATE(2026,3,1),1)) -> -348.76
A30: Avril 2026 | B30: =SUMIFS(Détail!$E:$E,Détail!$D:$D,"DHL INTERNAT. EXP FRANCE",Détail!$A:$A,">="&DATE(2026,4,1),Détail!$A:$A,"<"&EDATE(DATE(2026,4,1),1)) -> -63.05
A31: Mai 2026 | B31: =SUMIFS(Détail!$E:$E,Détail!$D:$D,"DHL INTERNAT. EXP FRANCE",Détail!$A:$A,">="&DATE(2026,5,1),Détail!$A:$A,"<"&EDATE(DATE(2026,5,1),1)) -> -196.21
A32: Juin 2026 | B32: =SUMIFS(Détail!$E:$E,Détail!$D:$D,"DHL INTERNAT. EXP FRANCE",Détail!$A:$A,">="&DATE(2026,6,1),Détail!$A:$A,"<"&EDATE(DATE(2026,6,1),1)) -> -231.49
A33: Juillet 2026 | B33: =SUMIFS(Détail!$E:$E,Détail!$D:$D,"DHL INTERNAT. EXP FRANCE",Détail!$A:$A,">="&DATE(2026,7,1),Détail!$A:$A,"<"&EDATE(DATE(2026,7,1),1)) -> 0

Sheet Prêt détail
A1: Prêt professionnel — détail (2026)
A3: Pret Professionnel Equipement (N°07113890) | C3: =SUMIF(Détail!$D:$D,"PRET PROFESSIONNEL EQUIPEMENT (N°07113890)",Détail!$E:$E) -> -2232.96
A4: Mois | B4: Montant
A5: Avril 2026 | B5: =SUMIFS(Détail!$E:$E,Détail!$D:$D,"PRET PROFESSIONNEL EQUIPEMENT (N°07113890)",Détail!$A:$A,">="&DATE(2026,4,1),Détail!$A:$A,"<"&EDATE(DATE(2026,4,1),1)) -> -558.24
A6: Mai 2026 | B6: =SUMIFS(Détail!$E:$E,Détail!$D:$D,"PRET PROFESSIONNEL EQUIPEMENT (N°07113890)",Détail!$A:$A,">="&DATE(2026,5,1),Détail!$A:$A,"<"&EDATE(DATE(2026,5,1),1)) -> -558.24
A7: Juin 2026 | B7: =SUMIFS(Détail!$E:$E,Détail!$D:$D,"PRET PROFESSIONNEL EQUIPEMENT (N°07113890)",Détail!$A:$A,">="&DATE(2026,6,1),Détail!$A:$A,"<"&EDATE(DATE(2026,6,1),1)) -> -558.24
A8: Juillet 2026 | B8: =SUMIFS(Détail!$E:$E,Détail!$D:$D,"PRET PROFESSIONNEL EQUIPEMENT (N°07113890)",Détail!$A:$A,">="&DATE(2026,7,1),Détail!$A:$A,"<"&EDATE(DATE(2026,7,1),1)) -> -558.24

Sheet Saisie détail
A1: Saisie administrative — détail (2026)
A3: Reglement Saisie (Amende) | C3: =SUMIF(Détail!$D:$D,"REGLEMENT SAISIE (AMENDE)",Détail!$E:$E) -> -1875
A4: Mois | B4: Montant
A5: Mai 2026 | B5: =SUMIFS(Détail!$E:$E,Détail!$D:$D,"REGLEMENT SAISIE (AMENDE)",Détail!$A:$A,">="&DATE(2026,5,1),Détail!$A:$A,"<"&EDATE(DATE(2026,5,1),1)) -> 0
A6: Juin 2026 | B6: =SUMIFS(Détail!$E:$E,Détail!$D:$D,"REGLEMENT SAISIE (AMENDE)",Détail!$A:$A,">="&DATE(2026,6,1),Détail!$A:$A,"<"&EDATE(DATE(2026,6,1),1)) -> -1875
A9: Frais Bancaires Saisie | C9: =SUMIF(Détail!$D:$D,"FRAIS BANCAIRES SAISIE",Détail!$E:$E) -> -100
A10: Mois | B10: Montant
A11: Mai 2026 | B11: =SUMIFS(Détail!$E:$E,Détail!$D:$D,"FRAIS BANCAIRES SAISIE",Détail!$A:$A,">="&DATE(2026,5,1),Détail!$A:$A,"<"&EDATE(DATE(2026,5,1),1)) -> -100
A12: Juin 2026 | B12: =SUMIFS(Détail!$E:$E,Détail!$D:$D,"FRAIS BANCAIRES SAISIE",Détail!$A:$A,">="&DATE(2026,6,1),Détail!$A:$A,"<"&EDATE(DATE(2026,6,1),1)) -> 0

Sheet Alimentation détail
A1: Alimentation / supermarché — détail par enseigne (2026)
A3: Supermarche L' | C3: =SUMIF(Détail!$D:$D,"SUPERMARCHE L'",Détail!$E:$E) -> -561.38
A4: Mois | B4: Montant
A5: Janvier 2026 | B5: =SUMIFS(Détail!$E:$E,Détail!$D:$D,"SUPERMARCHE L'",Détail!$A:$A,">="&DATE(2026,1,1),Détail!$A:$A,"<"&EDATE(DATE(2026,1,1),1)) -> -15.53
A6: Février 2026 | B6: =SUMIFS(Détail!$E:$E,Détail!$D:$D,"SUPERMARCHE L'",Détail!$A:$A,">="&DATE(2026,2,1),Détail!$A:$A,"<"&EDATE(DATE(2026,2,1),1)) -> -77.16
A7: Mars 2026 | B7: =SUMIFS(Détail!$E:$E,Détail!$D:$D,"SUPERMARCHE L'",Détail!$A:$A,">="&DATE(2026,3,1),Détail!$A:$A,"<"&EDATE(DATE(2026,3,1),1)) -> -68.46
A8: Avril 2026 | B8: =SUMIFS(Détail!$E:$E,Détail!$D:$D,"SUPERMARCHE L'",Détail!$A:$A,">="&DATE(2026,4,1),Détail!$A:$A,"<"&EDATE(DATE(2026,4,1),1)) -> -69.43
A9: Mai 2026 | B9: =SUMIFS(Détail!$E:$E,Détail!$D:$D,"SUPERMARCHE L'",Détail!$A:$A,">="&DATE(2026,5,1),Détail!$A:$A,"<"&EDATE(DATE(2026,5,1),1)) -> -86.2
A10: Juin 2026 | B10: =SUMIFS(Détail!$E:$E,Détail!$D:$D,"SUPERMARCHE L'",Détail!$A:$A,">="&DATE(2026,6,1),Détail!$A:$A,"<"&EDATE(DATE(2026,6,1),1)) -> -158.48
A11: Juillet 2026 | B11: =SUMIFS(Détail!$E:$E,Détail!$D:$D,"SUPERMARCHE L'",Détail!$A:$A,">="&DATE(2026,7,1),Détail!$A:$A,"<"&EDATE(DATE(2026,7,1),1)) -> -86.12
A14: Carrefour Dac V | C14: =SUMIF(Détail!$D:$D,"CARREFOUR DAC V",Détail!$E:$E) -> -79.47
A15: Mois | B15: Montant
A16: Janvier 2026 | B16: =SUMIFS(Détail!$E:$E,Détail!$D:$D,"CARREFOUR DAC V",Détail!$A:$A,">="&DATE(2026,1,1),Détail!$A:$A,"<"&EDATE(DATE(2026,1,1),1)) -> 0
A17: Février 2026 | B17: =SUMIFS(Détail!$E:$E,Détail!$D:$D,"CARREFOUR DAC V",Détail!$A:$A,">="&DATE(2026,2,1),Détail!$A:$A,"<"&EDATE(DATE(2026,2,1),1)) -> 0
A18: Mars 2026 | B18: =SUMIFS(Détail!$E:$E,Détail!$D:$D,"CARREFOUR DAC V",Détail!$A:$A,">="&DATE(2026,3,1),Détail!$A:$A,"<"&EDATE(DATE(2026,3,1),1)) -> 0
A19: Avril 2026 | B19: =SUMIFS(Détail!$E:$E,Détail!$D:$D,"CARREFOUR DAC V",Détail!$A:$A,">="&DATE(2026,4,1),Détail!$A:$A,"<"&EDATE(DATE(2026,4,1),1)) -> 0
A20: Mai 2026 | B20: =SUMIFS(Détail!$E:$E,Détail!$D:$D,"CARREFOUR DAC V",Détail!$A:$A,">="&DATE(2026,5,1),Détail!$A:$A,"<"&EDATE(DATE(2026,5,1),1)) -> -79.47
A21: Juin 2026 | B21: =SUMIFS(Détail!$E:$E,Détail!$D:$D,"CARREFOUR DAC V",Détail!$A:$A,">="&DATE(2026,6,1),Détail!$A:$A,"<"&EDATE(DATE(2026,6,1),1)) -> 0
A22: Juillet 2026 | B22: =SUMIFS(Détail!$E:$E,Détail!$D:$D,"CARREFOUR DAC V",Détail!$A:$A,">="&DATE(2026,7,1),Détail!$A:$A,"<"&EDATE(DATE(2026,7,1),1)) -> 0
A25: E.Leclerc | C25: =SUMIF(Détail!$D:$D,"E.LECLERC",Détail!$E:$E) -> -20.4
A26: Mois | B26: Montant
A27: Janvier 2026 | B27: =SUMIFS(Détail!$E:$E,Détail!$D:$D,"E.LECLERC",Détail!$A:$A,">="&DATE(2026,1,1),Détail!$A:$A,"<"&EDATE(DATE(2026,1,1),1)) -> 0
A28: Février 2026 | B28: =SUMIFS(Détail!$E:$E,Détail!$D:$D,"E.LECLERC",Détail!$A:$A,">="&DATE(2026,2,1),Détail!$A:$A,"<"&EDATE(DATE(2026,2,1),1)) -> 0
A29: Mars 2026 | B29: =SUMIFS(Détail!$E:$E,Détail!$D:$D,"E.LECLERC",Détail!$A:$A,">="&DATE(2026,3,1),Détail!$A:$A,"<"&EDATE(DATE(2026,3,1),1)) -> 0
A30: Avril 2026 | B30: =SUMIFS(Détail!$E:$E,Détail!$D:$D,"E.LECLERC",Détail!$A:$A,">="&DATE(2026,4,1),Détail!$A:$A,"<"&EDATE(DATE(2026,4,1),1)) -> 0
A31: Mai 2026 | B31: =SUMIFS(Détail!$E:$E,Détail!$D:$D,"E.LECLERC",Détail!$A:$A,">="&DATE(2026,5,1),Détail!$A:$A,"<"&EDATE(DATE(2026,5,1),1)) -> -20.4
A32: Juin 2026 | B32: =SUMIFS(Détail!$E:$E,Détail!$D:$D,"E.LECLERC",Détail!$A:$A,">="&DATE(2026,6,1),Détail!$A:$A,"<"&EDATE(DATE(2026,6,1),1)) -> 0
A33: Juillet 2026 | B33: =SUMIFS(Détail!$E:$E,Détail!$D:$D,"E.LECLERC",Détail!$A:$A,">="&DATE(2026,7,1),Détail!$A:$A,"<"&EDATE(DATE(2026,7,1),1)) -> 0
A36: Intermarche Cha | C36: =SUMIF(Détail!$D:$D,"INTERMARCHE CHA",Détail!$E:$E) -> -12.08
A37: Mois | B37: Montant
A38: Janvier 2026 | B38: =SUMIFS(Détail!$E:$E,Détail!$D:$D,"INTERMARCHE CHA",Détail!$A:$A,">="&DATE(2026,1,1),Détail!$A:$A,"<"&EDATE(DATE(2026,1,1),1)) -> 0
A39: Février 2026 | B39: =SUMIFS(Détail!$E:$E,Détail!$D:$D,"INTERMARCHE CHA",Détail!$A:$A,">="&DATE(2026,2,1),Détail!$A:$A,"<"&EDATE(DATE(2026,2,1),1)) -> 0
A40: Mars 2026 | B40: =SUMIFS(Détail!$E:$E,Détail!$D:$D,"INTERMARCHE CHA",Détail!$A:$A,">="&DATE(2026,3,1),Détail!$A:$A,"<"&EDATE(DATE(2026,3,1),1)) -> 0
A41: Avril 2026 | B41: =SUMIFS(Détail!$E:$E,Détail!$D:$D,"INTERMARCHE CHA",Détail!$A:$A,">="&DATE(2026,4,1),Détail!$A:$A,"<"&EDATE(DATE(2026,4,1),1)) -> 0
A42: Mai 2026 | B42: =SUMIFS(Détail!$E:$E,Détail!$D:$D,"INTERMARCHE CHA",Détail!$A:$A,">="&DATE(2026,5,1),Détail!$A:$A,"<"&EDATE(DATE(2026,5,1),1)) -> -12.08
A43: Juin 2026 | B43: =SUMIFS(Détail!$E:$E,Détail!$D:$D,"INTERMARCHE CHA",Détail!$A:$A,">="&DATE(2026,6,1),Détail!$A:$A,"<"&EDATE(DATE(2026,6,1),1)) -> 0
A44: Juillet 2026 | B44: =SUMIFS(Détail!$E:$E,Détail!$D:$D,"INTERMARCHE CHA",Détail!$A:$A,">="&DATE(2026,7,1),Détail!$A:$A,"<"&EDATE(DATE(2026,7,1),1)) -> 0

Sheet Assurances détail
A1: Assurances — détail (2026)
A3: Swisslife Assurance De Biens | C3: =SUMIF(Détail!$D:$D,"SWISSLIFE ASSURANCE DE BIENS",Détail!$E:$E) -> -549.22
A4: Mois | B4: Montant
A5: Janvier 2026 | B5: =SUMIFS(Détail!$E:$E,Détail!$D:$D,"SWISSLIFE ASSURANCE DE BIENS",Détail!$A:$A,">="&DATE(2026,1,1),Détail!$A:$A,"<"&EDATE(DATE(2026,1,1),1)) -> -78.46
A6: Février 2026 | B6: =SUMIFS(Détail!$E:$E,Détail!$D:$D,"SWISSLIFE ASSURANCE DE BIENS",Détail!$A:$A,">="&DATE(2026,2,1),Détail!$A:$A,"<"&EDATE(DATE(2026,2,1),1)) -> -78.46
A7: Mars 2026 | B7: =SUMIFS(Détail!$E:$E,Détail!$D:$D,"SWISSLIFE ASSURANCE DE BIENS",Détail!$A:$A,">="&DATE(2026,3,1),Détail!$A:$A,"<"&EDATE(DATE(2026,3,1),1)) -> -78.46
A8: Avril 2026 | B8: =SUMIFS(Détail!$E:$E,Détail!$D:$D,"SWISSLIFE ASSURANCE DE BIENS",Détail!$A:$A,">="&DATE(2026,4,1),Détail!$A:$A,"<"&EDATE(DATE(2026,4,1),1)) -> -78.46
A9: Mai 2026 | B9: =SUMIFS(Détail!$E:$E,Détail!$D:$D,"SWISSLIFE ASSURANCE DE BIENS",Détail!$A:$A,">="&DATE(2026,5,1),Détail!$A:$A,"<"&EDATE(DATE(2026,5,1),1)) -> -78.46
A10: Juin 2026 | B10: =SUMIFS(Détail!$E:$E,Détail!$D:$D,"SWISSLIFE ASSURANCE DE BIENS",Détail!$A:$A,">="&DATE(2026,6,1),Détail!$A:$A,"<"&EDATE(DATE(2026,6,1),1)) -> -78.46
A11: Juillet 2026 | B11: =SUMIFS(Détail!$E:$E,Détail!$D:$D,"SWISSLIFE ASSURANCE DE BIENS",Détail!$A:$A,">="&DATE(2026,7,1),Détail!$A:$A,"<"&EDATE(DATE(2026,7,1),1)) -> -78.46

Sheet Carburant péages parking détail
A1: Carburant, péages, parking, leasing — détail par poste (2026)
A2: Regroupe carburant (par enseigne), péages, abonnements télépéage, parking et le crédit/leasing véhicule (VW Bank).
A4: Leasing / crédit véhicule (VW Bank) | C4: =SUMIF(Détail!$D:$D,"VW BANK FRANCE",Détail!$E:$E) -> -6108.69
A5: Mois | B5: Montant
A6: Janvier 2026 | B6: =SUMIFS(Détail!$E:$E,Détail!$D:$D,"VW BANK FRANCE",Détail!$A:$A,">="&DATE(2026,1,1),Détail!$A:$A,"<"&EDATE(DATE(2026,1,1),1)) -> -872.67
A7: Février 2026 | B7: =SUMIFS(Détail!$E:$E,Détail!$D:$D,"VW BANK FRANCE",Détail!$A:$A,">="&DATE(2026,2,1),Détail!$A:$A,"<"&EDATE(DATE(2026,2,1),1)) -> -872.67
A8: Mars 2026 | B8: =SUMIFS(Détail!$E:$E,Détail!$D:$D,"VW BANK FRANCE",Détail!$A:$A,">="&DATE(2026,3,1),Détail!$A:$A,"<"&EDATE(DATE(2026,3,1),1)) -> -872.67
A9: Avril 2026 | B9: =SUMIFS(Détail!$E:$E,Détail!$D:$D,"VW BANK FRANCE",Détail!$A:$A,">="&DATE(2026,4,1),Détail!$A:$A,"<"&EDATE(DATE(2026,4,1),1)) -> -872.67
A10: Mai 2026 | B10: =SUMIFS(Détail!$E:$E,Détail!$D:$D,"VW BANK FRANCE",Détail!$A:$A,">="&DATE(2026,5,1),Détail!$A:$A,"<"&EDATE(DATE(2026,5,1),1)) -> -872.67
A11: Juin 2026 | B11: =SUMIFS(Détail!$E:$E,Détail!$D:$D,"VW BANK FRANCE",Détail!$A:$A,">="&DATE(2026,6,1),Détail!$A:$A,"<"&EDATE(DATE(2026,6,1),1)) -> -872.67
A12: Juillet 2026 | B12: =SUMIFS(Détail!$E:$E,Détail!$D:$D,"VW BANK FRANCE",Détail!$A:$A,">="&DATE(2026,7,1),Détail!$A:$A,"<"&EDATE(DATE(2026,7,1),1)) -> -872.67
A14: Carburant — Total | C14: =SUMIF(Détail!$D:$D,"TOTAL",Détail!$E:$E)+SUMIF(Détail!$D:$D,"TOTAL NB000698",Détail!$E:$E) -> -3139.8
A15: Mois | B15: Montant
A16: Janvier 2026 | B16: =SUMIFS(Détail!$E:$E,Détail!$D:$D,"TOTAL",Détail!$A:$A,">="&DATE(2026,1,1),Détail!$A:$A,"<"&EDATE(DATE(2026,1,1),1))+SUMIFS(Détail!$E:$E,Détail!$D:$D,"TOTAL NB000698",Détail!$A:$A,">="&DATE(2026,1,1),Détail!$A:$A,"<"&EDATE(DATE(2026,1,1),1)) -> -538.12
A17: Février 2026 | B17: =SUMIFS(Détail!$E:$E,Détail!$D:$D,"TOTAL",Détail!$A:$A,">="&DATE(2026,2,1),Détail!$A:$A,"<"&EDATE(DATE(2026,2,1),1))+SUMIFS(Détail!$E:$E,Détail!$D:$D,"TOTAL NB000698",Détail!$A:$A,">="&DATE(2026,2,1),Détail!$A:$A,"<"&EDATE(DATE(2026,2,1),1)) -> -291.67
A18: Mars 2026 | B18: =SUMIFS(Détail!$E:$E,Détail!$D:$D,"TOTAL",Détail!$A:$A,">="&DATE(2026,3,1),Détail!$A:$A,"<"&EDATE(DATE(2026,3,1),1))+SUMIFS(Détail!$E:$E,Détail!$D:$D,"TOTAL NB000698",Détail!$A:$A,">="&DATE(2026,3,1),Détail!$A:$A,"<"&EDATE(DATE(2026,3,1),1)) -> -509.85
A19: Avril 2026 | B19: =SUMIFS(Détail!$E:$E,Détail!$D:$D,"TOTAL",Détail!$A:$A,">="&DATE(2026,4,1),Détail!$A:$A,"<"&EDATE(DATE(2026,4,1),1))+SUMIFS(Détail!$E:$E,Détail!$D:$D,"TOTAL NB000698",Détail!$A:$A,">="&DATE(2026,4,1),Détail!$A:$A,"<"&EDATE(DATE(2026,4,1),1)) -> -824
A20: Mai 2026 | B20: =SUMIFS(Détail!$E:$E,Détail!$D:$D,"TOTAL",Détail!$A:$A,">="&DATE(2026,5,1),Détail!$A:$A,"<"&EDATE(DATE(2026,5,1),1))+SUMIFS(Détail!$E:$E,Détail!$D:$D,"TOTAL NB000698",Détail!$A:$A,">="&DATE(2026,5,1),Détail!$A:$A,"<"&EDATE(DATE(2026,5,1),1)) -> -460.21
A21: Juin 2026 | B21: =SUMIFS(Détail!$E:$E,Détail!$D:$D,"TOTAL",Détail!$A:$A,">="&DATE(2026,6,1),Détail!$A:$A,"<"&EDATE(DATE(2026,6,1),1))+SUMIFS(Détail!$E:$E,Détail!$D:$D,"TOTAL NB000698",Détail!$A:$A,">="&DATE(2026,6,1),Détail!$A:$A,"<"&EDATE(DATE(2026,6,1),1)) -> -309.73
A22: Juillet 2026 | B22: =SUMIFS(Détail!$E:$E,Détail!$D:$D,"TOTAL",Détail!$A:$A,">="&DATE(2026,7,1),Détail!$A:$A,"<"&EDATE(DATE(2026,7,1),1))+SUMIFS(Détail!$E:$E,Détail!$D:$D,"TOTAL NB000698",Détail!$A:$A,">="&DATE(2026,7,1),Détail!$A:$A,"<"&EDATE(DATE(2026,7,1),1)) -> -206.22
A23: Prestataires : | B23: Total, Total Nb000698
A25: Carburant — Esso | C25: =SUMIF(Détail!$D:$D,"ESSO CHAMPIGNY",Détail!$E:$E)+SUMIF(Détail!$D:$D,"ESSO ST THIBAUL",Détail!$E:$E)+SUMIF(Détail!$D:$D,"ESSO VALFONTENA",Détail!$E:$E)+SUMIF(Détail!$D:$D,"ESSO ERAGNYBELL",Détail!$E:$E)+SUMIF(Détail!$D:$D,"ESSO CHAMPILAVA",Détail!$E:$E)+SUMIF(Détail!$D:$D,"ESSO ATTAINVILL",Détail!$E:$E)+SUMIF(Détail!$D:$D,"ESSO JOINVILLE",Détail!$E:$E)+SUMIF(Détail!$D:$D,"ESSO RDAM STADH",Détail!$E:$E)+SUMIF(Détail!$D:$D,"ESSO ASSEVILLER",Détail!$E:$E)+SUMIF(Détail!$D:$D,"ESSO DAC VERDUN",Détail!$E:$E)+SUMIF(Détail!$D:$D,"ESSO VIRONVAYSU",Détail!$E:$E) -> -2541.23
A26: Mois | B26: Montant
A27: Janvier 2026 | B27: =SUMIFS(Détail!$E:$E,Détail!$D:$D,"ESSO CHAMPIGNY",Détail!$A:$A,">="&DATE(2026,1,1),Détail!$A:$A,"<"&EDATE(DATE(2026,1,1),1))+SUMIFS(Détail!$E:$E,Détail!$D:$D,"ESSO ST THIBAUL",Détail!$A:$A,">="&DATE(2026,1,1),Détail!$A:$A,"<"&EDATE(DATE(2026,1,1),1))+SUMIFS(Détail!$E:$E,Détail!$D:$D,"ESSO VALFONTENA",Détail!$A:$A,">="&DATE(2026,1,1),Détail!$A:$A,"<"&EDATE(DATE(2026,1,1),1))+SUMIFS(Détail!$E:$E,Détail!$D:$D,"ESSO ERAGNYBELL",Détail!$A:$A,">="&DATE(2026,1,1),Détail!$A:$A,"<"&EDATE(DATE(2026,1,1),1))+SUMIFS(Détail!$E:$E,Détail!$D:$D,"ESSO CHAMPILAVA",Détail!$A:$A,">="&DATE(2026,1,1),Détail!$A:$A,"<"&EDATE(DATE(2026,1,1),1))+SUMIFS(Détail!$E:$E,Détail!$D:$D,"ESSO ATTAINVILL",Détail!$A:$A,">="&DATE(2026,1,1),Détail!$A:$A,"<"&EDATE(DATE(2026,1,1),1))+SUMIFS(Détail!$E:$E,Détail!$D:$D,"ESSO JOINVILLE",Détail!$A:$A,">="&DATE(2026,1,1),Détail!$A:$A,"<"&EDATE(DATE(2026,1,1),1))+SUMIFS(Détail!$E:$E,Détail!$D:$D,"ESSO RDAM STADH",Détail!$A:$A,">="&DATE(2026,1,1),Détail!$A:$A,"<"&EDATE(DATE(2026,1,1),1))+SUMIFS(Détail!$E:$E,Détail!$D:$D,"ESSO ASSEVILLER",Détail!$A:$A,">="&DATE(2026,1,1),Détail!$A:$A,"<"&EDATE(DATE(2026,1,1),1))+SUMIFS(Détail!$E:$E,Détail!$D:$D,"ESSO DAC VERDUN",Détail!$A:$A,">="&DATE(2026,1,1),Détail!$A:$A,"<"&EDATE(DATE(2026,1,1),1))+SUMIFS(Détail!$E:$E,Détail!$D:$D,"ESSO VIRONVAYSU",Détail!$A:$A,">="&DATE(2026,1,1),Détail!$A:$A,"<"&EDATE(DATE(2026,1,1),1)) -> -316.69
A28: Février 2026 | B28: =SUMIFS(Détail!$E:$E,Détail!$D:$D,"ESSO CHAMPIGNY",Détail!$A:$A,">="&DATE(2026,2,1),Détail!$A:$A,"<"&EDATE(DATE(2026,2,1),1))+SUMIFS(Détail!$E:$E,Détail!$D:$D,"ESSO ST THIBAUL",Détail!$A:$A,">="&DATE(2026,2,1),Détail!$A:$A,"<"&EDATE(DATE(2026,2,1),1))+SUMIFS(Détail!$E:$E,Détail!$D:$D,"ESSO VALFONTENA",Détail!$A:$A,">="&DATE(2026,2,1),Détail!$A:$A,"<"&EDATE(DATE(2026,2,1),1))+SUMIFS(Détail!$E:$E,Détail!$D:$D,"ESSO ERAGNYBELL",Détail!$A:$A,">="&DATE(2026,2,1),Détail!$A:$A,"<"&EDATE(DATE(2026,2,1),1))+SUMIFS(Détail!$E:$E,Détail!$D:$D,"ESSO CHAMPILAVA",Détail!$A:$A,">="&DATE(2026,2,1),Détail!$A:$A,"<"&EDATE(DATE(2026,2,1),1))+SUMIFS(Détail!$E:$E,Détail!$D:$D,"ESSO ATTAINVILL",Détail!$A:$A,">="&DATE(2026,2,1),Détail!$A:$A,"<"&EDATE(DATE(2026,2,1),1))+SUMIFS(Détail!$E:$E,Détail!$D:$D,"ESSO JOINVILLE",Détail!$A:$A,">="&DATE(2026,2,1),Détail!$A:$A,"<"&EDATE(DATE(2026,2,1),1))+SUMIFS(Détail!$E:$E,Détail!$D:$D,"ESSO RDAM STADH",Détail!$A:$A,">="&DATE(2026,2,1),Détail!$A:$A,"<"&EDATE(DATE(2026,2,1),1))+SUMIFS(Détail!$E:$E,Détail!$D:$D,"ESSO ASSEVILLER",Détail!$A:$A,">="&DATE(2026,2,1),Détail!$A:$A,"<"&EDATE(DATE(2026,2,1),1))+SUMIFS(Détail!$E:$E,Détail!$D:$D,"ESSO DAC VERDUN",Détail!$A:$A,">="&DATE(2026,2,1),Détail!$A:$A,"<"&EDATE(DATE(2026,2,1),1))+SUMIFS(Détail!$E:$E,Détail!$D:$D,"ESSO VIRONVAYSU",Détail!$A:$A,">="&DATE(2026,2,1),Détail!$A:$A,"<"&EDATE(DATE(2026,2,1),1)) -> -303.73
A29: Mars 2026 | B29: =SUMIFS(Détail!$E:$E,Détail!$D:$D,"ESSO CHAMPIGNY",Détail!$A:$A,">="&DATE(2026,3,1),Détail!$A:$A,"<"&EDATE(DATE(2026,3,1),1))+SUMIFS(Détail!$E:$E,Détail!$D:$D,"ESSO ST THIBAUL",Détail!$A:$A,">="&DATE(2026,3,1),Détail!$A:$A,"<"&EDATE(DATE(2026,3,1),1))+SUMIFS(Détail!$E:$E,Détail!$D:$D,"ESSO VALFONTENA",Détail!$A:$A,">="&DATE(2026,3,1),Détail!$A:$A,"<"&EDATE(DATE(2026,3,1),1))+SUMIFS(Détail!$E:$E,Détail!$D:$D,"ESSO ERAGNYBELL",Détail!$A:$A,">="&DATE(2026,3,1),Détail!$A:$A,"<"&EDATE(DATE(2026,3,1),1))+SUMIFS(Détail!$E:$E,Détail!$D:$D,"ESSO CHAMPILAVA",Détail!$A:$A,">="&DATE(2026,3,1),Détail!$A:$A,"<"&EDATE(DATE(2026,3,1),1))+SUMIFS(Détail!$E:$E,Détail!$D:$D,"ESSO ATTAINVILL",Détail!$A:$A,">="&DATE(2026,3,1),Détail!$A:$A,"<"&EDATE(DATE(2026,3,1),1))+SUMIFS(Détail!$E:$E,Détail!$D:$D,"ESSO JOINVILLE",Détail!$A:$A,">="&DATE(2026,3,1),Détail!$A:$A,"<"&EDATE(DATE(2026,3,1),1))+SUMIFS(Détail!$E:$E,Détail!$D:$D,"ESSO RDAM STADH",Détail!$A:$A,">="&DATE(2026,3,1),Détail!$A:$A,"<"&EDATE(DATE(2026,3,1),1))+SUMIFS(Détail!$E:$E,Détail!$D:$D,"ESSO ASSEVILLER",Détail!$A:$A,">="&DATE(2026,3,1),Détail!$A:$A,"<"&EDATE(DATE(2026,3,1),1))+SUMIFS(Détail!$E:$E,Détail!$D:$D,"ESSO DAC VERDUN",Détail!$A:$A,">="&DATE(2026,3,1),Détail!$A:$A,"<"&EDATE(DATE(2026,3,1),1))+SUMIFS(Détail!$E:$E,Détail!$D:$D,"ESSO VIRONVAYSU",Détail!$A:$A,">="&DATE(2026,3,1),Détail!$A:$A,"<"&EDATE(DATE(2026,3,1),1)) -> -403.18
A30: Avril 2026 | B30: =SUMIFS(Détail!$E:$E,Détail!$D:$D,"ESSO CHAMPIGNY",Détail!$A:$A,">="&DATE(2026,4,1),Détail!$A:$A,"<"&EDATE(DATE(2026,4,1),1))+SUMIFS(Détail!$E:$E,Détail!$D:$D,"ESSO ST THIBAUL",Détail!$A:$A,">="&DATE(2026,4,1),Détail!$A:$A,"<"&EDATE(DATE(2026,4,1),1))+SUMIFS(Détail!$E:$E,Détail!$D:$D,"ESSO VALFONTENA",Détail!$A:$A,">="&DATE(2026,4,1),Détail!$A:$A,"<"&EDATE(DATE(2026,4,1),1))+SUMIFS(Détail!$E:$E,Détail!$D:$D,"ESSO ERAGNYBELL",Détail!$A:$A,">="&DATE(2026,4,1),Détail!$A:$A,"<"&EDATE(DATE(2026,4,1),1))+SUMIFS(Détail!$E:$E,Détail!$D:$D,"ESSO CHAMPILAVA",Détail!$A:$A,">="&DATE(2026,4,1),Détail!$A:$A,"<"&EDATE(DATE(2026,4,1),1))+SUMIFS(Détail!$E:$E,Détail!$D:$D,"ESSO ATTAINVILL",Détail!$A:$A,">="&DATE(2026,4,1),Détail!$A:$A,"<"&EDATE(DATE(2026,4,1),1))+SUMIFS(Détail!$E:$E,Détail!$D:$D,"ESSO JOINVILLE",Détail!$A:$A,">="&DATE(2026,4,1),Détail!$A:$A,"<"&EDATE(DATE(2026,4,1),1))+SUMIFS(Détail!$E:$E,Détail!$D:$D,"ESSO RDAM STADH",Détail!$A:$A,">="&DATE(2026,4,1),Détail!$A:$A,"<"&EDATE(DATE(2026,4,1),1))+SUMIFS(Détail!$E:$E,Détail!$D:$D,"ESSO ASSEVILLER",Détail!$A:$A,">="&DATE(2026,4,1),Détail!$A:$A,"<"&EDATE(DATE(2026,4,1),1))+SUMIFS(Détail!$E:$E,Détail!$D:$D,"ESSO DAC VERDUN",Détail!$A:$A,">="&DATE(2026,4,1),Détail!$A:$A,"<"&EDATE(DATE(2026,4,1),1))+SUMIFS(Détail!$E:$E,Détail!$D:$D,"ESSO VIRONVAYSU",Détail!$A:$A,">="&DATE(2026,4,1),Détail!$A:$A,"<"&EDATE(DATE(2026,4,1),1)) -> -610.71
A31: Mai 2026 | B31: =SUMIFS(Détail!$E:$E,Détail!$D:$D,"ESSO CHAMPIGNY",Détail!$A:$A,">="&DATE(2026,5,1),Détail!$A:$A,"<"&EDATE(DATE(2026,5,1),1))+SUMIFS(Détail!$E:$E,Détail!$D:$D,"ESSO ST THIBAUL",Détail!$A:$A,">="&DATE(2026,5,1),Détail!$A:$A,"<"&EDATE(DATE(2026,5,1),1))+SUMIFS(Détail!$E:$E,Détail!$D:$D,"ESSO VALFONTENA",Détail!$A:$A,">="&DATE(2026,5,1),Détail!$A:$A,"<"&EDATE(DATE(2026,5,1),1))+SUMIFS(Détail!$E:$E,Détail!$D:$D,"ESSO ERAGNYBELL",Détail!$A:$A,">="&DATE(2026,5,1),Détail!$A:$A,"<"&EDATE(DATE(2026,5,1),1))+SUMIFS(Détail!$E:$E,Détail!$D:$D,"ESSO CHAMPILAVA",Détail!$A:$A,">="&DATE(2026,5,1),Détail!$A:$A,"<"&EDATE(DATE(2026,5,1),1))+SUMIFS(Détail!$E:$E,Détail!$D:$D,"ESSO ATTAINVILL",Détail!$A:$A,">="&DATE(2026,5,1),Détail!$A:$A,"<"&EDATE(DATE(2026,5,1),1))+SUMIFS(Détail!$E:$E,Détail!$D:$D,"ESSO JOINVILLE",Détail!$A:$A,">="&DATE(2026,5,1),Détail!$A:$A,"<"&EDATE(DATE(2026,5,1),1))+SUMIFS(Détail!$E:$E,Détail!$D:$D,"ESSO RDAM STADH",Détail!$A:$A,">="&DATE(2026,5,1),Détail!$A:$A,"<"&EDATE(DATE(2026,5,1),1))+SUMIFS(Détail!$E:$E,Détail!$D:$D,"ESSO ASSEVILLER",Détail!$A:$A,">="&DATE(2026,5,1),Détail!$A:$A,"<"&EDATE(DATE(2026,5,1),1))+SUMIFS(Détail!$E:$E,Détail!$D:$D,"ESSO DAC VERDUN",Détail!$A:$A,">="&DATE(2026,5,1),Détail!$A:$A,"<"&EDATE(DATE(2026,5,1),1))+SUMIFS(Détail!$E:$E,Détail!$D:$D,"ESSO VIRONVAYSU",Détail!$A:$A,">="&DATE(2026,5,1),Détail!$A:$A,"<"&EDATE(DATE(2026,5,1),1)) -> -379.94
A32: Juin 2026 | B32: =SUMIFS(Détail!$E:$E,Détail!$D:$D,"ESSO CHAMPIGNY",Détail!$A:$A,">="&DATE(2026,6,1),Détail!$A:$A,"<"&EDATE(DATE(2026,6,1),1))+SUMIFS(Détail!$E:$E,Détail!$D:$D,"ESSO ST THIBAUL",Détail!$A:$A,">="&DATE(2026,6,1),Détail!$A:$A,"<"&EDATE(DATE(2026,6,1),1))+SUMIFS(Détail!$E:$E,Détail!$D:$D,"ESSO VALFONTENA",Détail!$A:$A,">="&DATE(2026,6,1),Détail!$A:$A,"<"&EDATE(DATE(2026,6,1),1))+SUMIFS(Détail!$E:$E,Détail!$D:$D,"ESSO ERAGNYBELL",Détail!$A:$A,">="&DATE(2026,6,1),Détail!$A:$A,"<"&EDATE(DATE(2026,6,1),1))+SUMIFS(Détail!$E:$E,Détail!$D:$D,"ESSO CHAMPILAVA",Détail!$A:$A,">="&DATE(2026,6,1),Détail!$A:$A,"<"&EDATE(DATE(2026,6,1),1))+SUMIFS(Détail!$E:$E,Détail!$D:$D,"ESSO ATTAINVILL",Détail!$A:$A,">="&DATE(2026,6,1),Détail!$A:$A,"<"&EDATE(DATE(2026,6,1),1))+SUMIFS(Détail!$E:$E,Détail!$D:$D,"ESSO JOINVILLE",Détail!$A:$A,">="&DATE(2026,6,1),Détail!$A:$A,"<"&EDATE(DATE(2026,6,1),1))+SUMIFS(Détail!$E:$E,Détail!$D:$D,"ESSO RDAM STADH",Détail!$A:$A,">="&DATE(2026,6,1),Détail!$A:$A,"<"&EDATE(DATE(2026,6,1),1))+SUMIFS(Détail!$E:$E,Détail!$D:$D,"ESSO ASSEVILLER",Détail!$A:$A,">="&DATE(2026,6,1),Détail!$A:$A,"<"&EDATE(DATE(2026,6,1),1))+SUMIFS(Détail!$E:$E,Détail!$D:$D,"ESSO DAC VERDUN",Détail!$A:$A,">="&DATE(2026,6,1),Détail!$A:$A,"<"&EDATE(DATE(2026,6,1),1))+SUMIFS(Détail!$E:$E,Détail!$D:$D,"ESSO VIRONVAYSU",Détail!$A:$A,">="&DATE(2026,6,1),Détail!$A:$A,"<"&EDATE(DATE(2026,6,1),1)) -> -456.84
A33: Juillet 2026 | B33: =SUMIFS(Détail!$E:$E,Détail!$D:$D,"ESSO CHAMPIGNY",Détail!$A:$A,">="&DATE(2026,7,1),Détail!$A:$A,"<"&EDATE(DATE(2026,7,1),1))+SUMIFS(Détail!$E:$E,Détail!$D:$D,"ESSO ST THIBAUL",Détail!$A:$A,">="&DATE(2026,7,1),Détail!$A:$A,"<"&EDATE(DATE(2026,7,1),1))+SUMIFS(Détail!$E:$E,Détail!$D:$D,"ESSO VALFONTENA",Détail!$A:$A,">="&DATE(2026,7,1),Détail!$A:$A,"<"&EDATE(DATE(2026,7,1),1))+SUMIFS(Détail!$E:$E,Détail!$D:$D,"ESSO ERAGNYBELL",Détail!$A:$A,">="&DATE(2026,7,1),Détail!$A:$A,"<"&EDATE(DATE(2026,7,1),1))+SUMIFS(Détail!$E:$E,Détail!$D:$D,"ESSO CHAMPILAVA",Détail!$A:$A,">="&DATE(2026,7,1),Détail!$A:$A,"<"&EDATE(DATE(2026,7,1),1))+SUMIFS(Détail!$E:$E,Détail!$D:$D,"ESSO ATTAINVILL",Détail!$A:$A,">="&DATE(2026,7,1),Détail!$A:$A,"<"&EDATE(DATE(2026,7,1),1))+SUMIFS(Détail!$E:$E,Détail!$D:$D,"ESSO JOINVILLE",Détail!$A:$A,">="&DATE(2026,7,1),Détail!$A:$A,"<"&EDATE(DATE(2026,7,1),1))+SUMIFS(Détail!$E:$E,Détail!$D:$D,"ESSO RDAM STADH",Détail!$A:$A,">="&DATE(2026,7,1),Détail!$A:$A,"<"&EDATE(DATE(2026,7,1),1))+SUMIFS(Détail!$E:$E,Détail!$D:$D,"ESSO ASSEVILLER",Détail!$A:$A,">="&DATE(2026,7,1),Détail!$A:$A,"<"&EDATE(DATE(2026,7,1),1))+SUMIFS(Détail!$E:$E,Détail!$D:$D,"ESSO DAC VERDUN",Détail!$A:$A,">="&DATE(2026,7,1),Détail!$A:$A,"<"&EDATE(DATE(2026,7,1),1))+SUMIFS(Détail!$E:$E,Détail!$D:$D,"ESSO VIRONVAYSU",Détail!$A:$A,">="&DATE(2026,7,1),Détail!$A:$A,"<"&EDATE(DATE(2026,7,1),1)) -> -70.14
A34: Prestataires : | B34: Esso Champigny, Esso St Thibaul, Esso Valfontena, Esso Eragnybell, Esso Champilava, Esso Attainvill, Esso Joinville, Esso Rdam Stadh, Esso Asseviller, Esso Dac Verdun, Esso Vironvaysu
A36: Carburant — Avia | C36: =SUMIF(Détail!$D:$D,"STATION AVIA",Détail!$E:$E) -> -271.36
A37: Mois | B37: Montant
A38: Janvier 2026 | B38: =SUMIFS(Détail!$E:$E,Détail!$D:$D,"STATION AVIA",Détail!$A:$A,">="&DATE(2026,1,1),Détail!$A:$A,"<"&EDATE(DATE(2026,1,1),1)) -> 0
A39: Février 2026 | B39: =SUMIFS(Détail!$E:$E,Détail!$D:$D,"STATION AVIA",Détail!$A:$A,">="&DATE(2026,2,1),Détail!$A:$A,"<"&EDATE(DATE(2026,2,1),1)) -> 0
A40: Mars 2026 | B40: =SUMIFS(Détail!$E:$E,Détail!$D:$D,"STATION AVIA",Détail!$A:$A,">="&DATE(2026,3,1),Détail!$A:$A,"<"&EDATE(DATE(2026,3,1),1)) -> 0
A41: Avril 2026 | B41: =SUMIFS(Détail!$E:$E,Détail!$D:$D,"STATION AVIA",Détail!$A:$A,">="&DATE(2026,4,1),Détail!$A:$A,"<"&EDATE(DATE(2026,4,1),1)) -> -271.36
A42: Mai 2026 | B42: =SUMIFS(Détail!$E:$E,Détail!$D:$D,"STATION AVIA",Détail!$A:$A,">="&DATE(2026,5,1),Détail!$A:$A,"<"&EDATE(DATE(2026,5,1),1)) -> 0
A43: Juin 2026 | B43: =SUMIFS(Détail!$E:$E,Détail!$D:$D,"STATION AVIA",Détail!$A:$A,">="&DATE(2026,6,1),Détail!$A:$A,"<"&EDATE(DATE(2026,6,1),1)) -> 0
A44: Juillet 2026 | B44: =SUMIFS(Détail!$E:$E,Détail!$D:$D,"STATION AVIA",Détail!$A:$A,">="&DATE(2026,7,1),Détail!$A:$A,"<"&EDATE(DATE(2026,7,1),1)) -> 0
A46: Carburant — Shell | C46: =SUMIF(Détail!$D:$D,"SHELL DAC",Détail!$E:$E) -> -69.38
A47: Mois | B47: Montant
A48: Janvier 2026 | B48: =SUMIFS(Détail!$E:$E,Détail!$D:$D,"SHELL DAC",Détail!$A:$A,">="&DATE(2026,1,1),Détail!$A:$A,"<"&EDATE(DATE(2026,1,1),1)) -> 0
A49: Février 2026 | B49: =SUMIFS(Détail!$E:$E,Détail!$D:$D,"SHELL DAC",Détail!$A:$A,">="&DATE(2026,2,1),Détail!$A:$A,"<"&EDATE(DATE(2026,2,1),1)) -> 0
A50: Mars 2026 | B50: =SUMIFS(Détail!$E:$E,Détail!$D:$D,"SHELL DAC",Détail!$A:$A,">="&DATE(2026,3,1),Détail!$A:$A,"<"&EDATE(DATE(2026,3,1),1)) -> -69.38
A51: Avril 2026 | B51: =SUMIFS(Détail!$E:$E,Détail!$D:$D,"SHELL DAC",Détail!$A:$A,">="&DATE(2026,4,1),Détail!$A:$A,"<"&EDATE(DATE(2026,4,1),1)) -> 0
A52: Mai 2026 | B52: =SUMIFS(Détail!$E:$E,Détail!$D:$D,"SHELL DAC",Détail!$A:$A,">="&DATE(2026,5,1),Détail!$A:$A,"<"&EDATE(DATE(2026,5,1),1)) -> 0
A53: Juin 2026 | B53: =SUMIFS(Détail!$E:$E,Détail!$D:$D,"SHELL DAC",Détail!$A:$A,">="&DATE(2026,6,1),Détail!$A:$A,"<"&EDATE(DATE(2026,6,1),1)) -> 0
A54: Juillet 2026 | B54: =SUMIFS(Détail!$E:$E,Détail!$D:$D,"SHELL DAC",Détail!$A:$A,">="&DATE(2026,7,1),Détail!$A:$A,"<"&EDATE(DATE(2026,7,1),1)) -> 0
A56: Carburant — Certas | C56: =SUMIF(Détail!$D:$D,"CERTAS ESSOF241",Détail!$E:$E) -> -56.29
A57: Mois | B57: Montant
A58: Janvier 2026 | B58: =SUMIFS(Détail!$E:$E,Détail!$D:$D,"CERTAS ESSOF241",Détail!$A:$A,">="&DATE(2026,1,1),Détail!$A:$A,"<"&EDATE(DATE(2026,1,1),1)) -> 0
A59: Février 2026 | B59: =SUMIFS(Détail!$E:$E,Détail!$D:$D,"CERTAS ESSOF241",Détail!$A:$A,">="&DATE(2026,2,1),Détail!$A:$A,"<"&EDATE(DATE(2026,2,1),1)) -> 0
A60: Mars 2026 | B60: =SUMIFS(Détail!$E:$E,Détail!$D:$D,"CERTAS ESSOF241",Détail!$A:$A,">="&DATE(2026,3,1),Détail!$A:$A,"<"&EDATE(DATE(2026,3,1),1)) -> 0
A61: Avril 2026 | B61: =SUMIFS(Détail!$E:$E,Détail!$D:$D,"CERTAS ESSOF241",Détail!$A:$A,">="&DATE(2026,4,1),Détail!$A:$A,"<"&EDATE(DATE(2026,4,1),1)) -> 0
A62: Mai 2026 | B62: =SUMIFS(Détail!$E:$E,Détail!$D:$D,"CERTAS ESSOF241",Détail!$A:$A,">="&DATE(2026,5,1),Détail!$A:$A,"<"&EDATE(DATE(2026,5,1),1)) -> 0
A63: Juin 2026 | B63: =SUMIFS(Détail!$E:$E,Détail!$D:$D,"CERTAS ESSOF241",Détail!$A:$A,">="&DATE(2026,6,1),Détail!$A:$A,"<"&EDATE(DATE(2026,6,1),1)) -> -56.29
A64: Juillet 2026 | B64: =SUMIFS(Détail!$E:$E,Détail!$D:$D,"CERTAS ESSOF241",Détail!$A:$A,">="&DATE(2026,7,1),Détail!$A:$A,"<"&EDATE(DATE(2026,7,1),1)) -> 0
A66: Péages | C66: =SUMIF(Détail!$D:$D,"SANEF AUTOROUTE",Détail!$E:$E)+SUMIF(Détail!$D:$D,"SANEF",Détail!$E:$E)+SUMIF(Détail!$D:$D,"COFIROUTE",Détail!$E:$E)+SUMIF(Détail!$D:$D,"APRR",Détail!$E:$E)+SUMIF(Détail!$D:$D,"APRR NFC",Détail!$E:$E)+SUMIF(Détail!$D:$D,"AUTOROUTES DU S",Détail!$E:$E)+SUMIF(Détail!$D:$D,"SAPN",Détail!$E:$E)+SUMIF(Détail!$D:$D,"ROCADIS",Détail!$E:$E) -> -521.8
A67: Mois | B67: Montant
A68: Janvier 2026 | B68: =SUMIFS(Détail!$E:$E,Détail!$D:$D,"SANEF AUTOROUTE",Détail!$A:$A,">="&DATE(2026,1,1),Détail!$A:$A,"<"&EDATE(DATE(2026,1,1),1))+SUMIFS(Détail!$E:$E,Détail!$D:$D,"SANEF",Détail!$A:$A,">="&DATE(2026,1,1),Détail!$A:$A,"<"&EDATE(DATE(2026,1,1),1))+SUMIFS(Détail!$E:$E,Détail!$D:$D,"COFIROUTE",Détail!$A:$A,">="&DATE(2026,1,1),Détail!$A:$A,"<"&EDATE(DATE(2026,1,1),1))+SUMIFS(Détail!$E:$E,Détail!$D:$D,"APRR",Détail!$A:$A,">="&DATE(2026,1,1),Détail!$A:$A,"<"&EDATE(DATE(2026,1,1),1))+SUMIFS(Détail!$E:$E,Détail!$D:$D,"APRR NFC",Détail!$A:$A,">="&DATE(2026,1,1),Détail!$A:$A,"<"&EDATE(DATE(2026,1,1),1))+SUMIFS(Détail!$E:$E,Détail!$D:$D,"AUTOROUTES DU S",Détail!$A:$A,">="&DATE(2026,1,1),Détail!$A:$A,"<"&EDATE(DATE(2026,1,1),1))+SUMIFS(Détail!$E:$E,Détail!$D:$D,"SAPN",Détail!$A:$A,">="&DATE(2026,1,1),Détail!$A:$A,"<"&EDATE(DATE(2026,1,1),1))+SUMIFS(Détail!$E:$E,Détail!$D:$D,"ROCADIS",Détail!$A:$A,">="&DATE(2026,1,1),Détail!$A:$A,"<"&EDATE(DATE(2026,1,1),1)) -> -94.9
A69: Février 2026 | B69: =SUMIFS(Détail!$E:$E,Détail!$D:$D,"SANEF AUTOROUTE",Détail!$A:$A,">="&DATE(2026,2,1),Détail!$A:$A,"<"&EDATE(DATE(2026,2,1),1))+SUMIFS(Détail!$E:$E,Détail!$D:$D,"SANEF",Détail!$A:$A,">="&DATE(2026,2,1),Détail!$A:$A,"<"&EDATE(DATE(2026,2,1),1))+SUMIFS(Détail!$E:$E,Détail!$D:$D,"COFIROUTE",Détail!$A:$A,">="&DATE(2026,2,1),Détail!$A:$A,"<"&EDATE(DATE(2026,2,1),1))+SUMIFS(Détail!$E:$E,Détail!$D:$D,"APRR",Détail!$A:$A,">="&DATE(2026,2,1),Détail!$A:$A,"<"&EDATE(DATE(2026,2,1),1))+SUMIFS(Détail!$E:$E,Détail!$D:$D,"APRR NFC",Détail!$A:$A,">="&DATE(2026,2,1),Détail!$A:$A,"<"&EDATE(DATE(2026,2,1),1))+SUMIFS(Détail!$E:$E,Détail!$D:$D,"AUTOROUTES DU S",Détail!$A:$A,">="&DATE(2026,2,1),Détail!$A:$A,"<"&EDATE(DATE(2026,2,1),1))+SUMIFS(Détail!$E:$E,Détail!$D:$D,"SAPN",Détail!$A:$A,">="&DATE(2026,2,1),Détail!$A:$A,"<"&EDATE(DATE(2026,2,1),1))+SUMIFS(Détail!$E:$E,Détail!$D:$D,"ROCADIS",Détail!$A:$A,">="&DATE(2026,2,1),Détail!$A:$A,"<"&EDATE(DATE(2026,2,1),1)) -> -64.5
A70: Mars 2026 | B70: =SUMIFS(Détail!$E:$E,Détail!$D:$D,"SANEF AUTOROUTE",Détail!$A:$A,">="&DATE(2026,3,1),Détail!$A:$A,"<"&EDATE(DATE(2026,3,1),1))+SUMIFS(Détail!$E:$E,Détail!$D:$D,"SANEF",Détail!$A:$A,">="&DATE(2026,3,1),Détail!$A:$A,"<"&EDATE(DATE(2026,3,1),1))+SUMIFS(Détail!$E:$E,Détail!$D:$D,"COFIROUTE",Détail!$A:$A,">="&DATE(2026,3,1),Détail!$A:$A,"<"&EDATE(DATE(2026,3,1),1))+SUMIFS(Détail!$E:$E,Détail!$D:$D,"APRR",Détail!$A:$A,">="&DATE(2026,3,1),Détail!$A:$A,"<"&EDATE(DATE(2026,3,1),1))+SUMIFS(Détail!$E:$E,Détail!$D:$D,"APRR NFC",Détail!$A:$A,">="&DATE(2026,3,1),Détail!$A:$A,"<"&EDATE(DATE(2026,3,1),1))+SUMIFS(Détail!$E:$E,Détail!$D:$D,"AUTOROUTES DU S",Détail!$A:$A,">="&DATE(2026,3,1),Détail!$A:$A,"<"&EDATE(DATE(2026,3,1),1))+SUMIFS(Détail!$E:$E,Détail!$D:$D,"SAPN",Détail!$A:$A,">="&DATE(2026,3,1),Détail!$A:$A,"<"&EDATE(DATE(2026,3,1),1))+SUMIFS(Détail!$E:$E,Détail!$D:$D,"ROCADIS",Détail!$A:$A,">="&DATE(2026,3,1),Détail!$A:$A,"<"&EDATE(DATE(2026,3,1),1)) -> -101
A71: Avril 2026 | B71: =SUMIFS(Détail!$E:$E,Détail!$D:$D,"SANEF AUTOROUTE",Détail!$A:$A,">="&DATE(2026,4,1),Détail!$A:$A,"<"&EDATE(DATE(2026,4,1),1))+SUMIFS(Détail!$E:$E,Détail!$D:$D,"SANEF",Détail!$A:$A,">="&DATE(2026,4,1),Détail!$A:$A,"<"&EDATE(DATE(2026,4,1),1))+SUMIFS(Détail!$E:$E,Détail!$D:$D,"COFIROUTE",Détail!$A:$A,">="&DATE(2026,4,1),Détail!$A:$A,"<"&EDATE(DATE(2026,4,1),1))+SUMIFS(Détail!$E:$E,Détail!$D:$D,"APRR",Détail!$A:$A,">="&DATE(2026,4,1),Détail!$A:$A,"<"&EDATE(DATE(2026,4,1),1))+SUMIFS(Détail!$E:$E,Détail!$D:$D,"APRR NFC",Détail!$A:$A,">="&DATE(2026,4,1),Détail!$A:$A,"<"&EDATE(DATE(2026,4,1),1))+SUMIFS(Détail!$E:$E,Détail!$D:$D,"AUTOROUTES DU S",Détail!$A:$A,">="&DATE(2026,4,1),Détail!$A:$A,"<"&EDATE(DATE(2026,4,1),1))+SUMIFS(Détail!$E:$E,Détail!$D:$D,"SAPN",Détail!$A:$A,">="&DATE(2026,4,1),Détail!$A:$A,"<"&EDATE(DATE(2026,4,1),1))+SUMIFS(Détail!$E:$E,Détail!$D:$D,"ROCADIS",Détail!$A:$A,">="&DATE(2026,4,1),Détail!$A:$A,"<"&EDATE(DATE(2026,4,1),1)) -> -261.4
A72: Mai 2026 | B72: =SUMIFS(Détail!$E:$E,Détail!$D:$D,"SANEF AUTOROUTE",Détail!$A:$A,">="&DATE(2026,5,1),Détail!$A:$A,"<"&EDATE(DATE(2026,5,1),1))+SUMIFS(Détail!$E:$E,Détail!$D:$D,"SANEF",Détail!$A:$A,">="&DATE(2026,5,1),Détail!$A:$A,"<"&EDATE(DATE(2026,5,1),1))+SUMIFS(Détail!$E:$E,Détail!$D:$D,"COFIROUTE",Détail!$A:$A,">="&DATE(2026,5,1),Détail!$A:$A,"<"&EDATE(DATE(2026,5,1),1))+SUMIFS(Détail!$E:$E,Détail!$D:$D,"APRR",Détail!$A:$A,">="&DATE(2026,5,1),Détail!$A:$A,"<"&EDATE(DATE(2026,5,1),1))+SUMIFS(Détail!$E:$E,Détail!$D:$D,"APRR NFC",Détail!$A:$A,">="&DATE(2026,5,1),Détail!$A:$A,"<"&EDATE(DATE(2026,5,1),1))+SUMIFS(Détail!$E:$E,Détail!$D:$D,"AUTOROUTES DU S",Détail!$A:$A,">="&DATE(2026,5,1),Détail!$A:$A,"<"&EDATE(DATE(2026,5,1),1))+SUMIFS(Détail!$E:$E,Détail!$D:$D,"SAPN",Détail!$A:$A,">="&DATE(2026,5,1),Détail!$A:$A,"<"&EDATE(DATE(2026,5,1),1))+SUMIFS(Détail!$E:$E,Détail!$D:$D,"ROCADIS",Détail!$A:$A,">="&DATE(2026,5,1),Détail!$A:$A,"<"&EDATE(DATE(2026,5,1),1)) -> 0
A73: Juin 2026 | B73: =SUMIFS(Détail!$E:$E,Détail!$D:$D,"SANEF AUTOROUTE",Détail!$A:$A,">="&DATE(2026,6,1),Détail!$A:$A,"<"&EDATE(DATE(2026,6,1),1))+SUMIFS(Détail!$E:$E,Détail!$D:$D,"SANEF",Détail!$A:$A,">="&DATE(2026,6,1),Détail!$A:$A,"<"&EDATE(DATE(2026,6,1),1))+SUMIFS(Détail!$E:$E,Détail!$D:$D,"COFIROUTE",Détail!$A:$A,">="&DATE(2026,6,1),Détail!$A:$A,"<"&EDATE(DATE(2026,6,1),1))+SUMIFS(Détail!$E:$E,Détail!$D:$D,"APRR",Détail!$A:$A,">="&DATE(2026,6,1),Détail!$A:$A,"<"&EDATE(DATE(2026,6,1),1))+SUMIFS(Détail!$E:$E,Détail!$D:$D,"APRR NFC",Détail!$A:$A,">="&DATE(2026,6,1),Détail!$A:$A,"<"&EDATE(DATE(2026,6,1),1))+SUMIFS(Détail!$E:$E,Détail!$D:$D,"AUTOROUTES DU S",Détail!$A:$A,">="&DATE(2026,6,1),Détail!$A:$A,"<"&EDATE(DATE(2026,6,1),1))+SUMIFS(Détail!$E:$E,Détail!$D:$D,"SAPN",Détail!$A:$A,">="&DATE(2026,6,1),Détail!$A:$A,"<"&EDATE(DATE(2026,6,1),1))+SUMIFS(Détail!$E:$E,Détail!$D:$D,"ROCADIS",Détail!$A:$A,">="&DATE(2026,6,1),Détail!$A:$A,"<"&EDATE(DATE(2026,6,1),1)) -> 0
A74: Juillet 2026 | B74: =SUMIFS(Détail!$E:$E,Détail!$D:$D,"SANEF AUTOROUTE",Détail!$A:$A,">="&DATE(2026,7,1),Détail!$A:$A,"<"&EDATE(DATE(2026,7,1),1))+SUMIFS(Détail!$E:$E,Détail!$D:$D,"SANEF",Détail!$A:$A,">="&DATE(2026,7,1),Détail!$A:$A,"<"&EDATE(DATE(2026,7,1),1))+SUMIFS(Détail!$E:$E,Détail!$D:$D,"COFIROUTE",Détail!$A:$A,">="&DATE(2026,7,1),Détail!$A:$A,"<"&EDATE(DATE(2026,7,1),1))+SUMIFS(Détail!$E:$E,Détail!$D:$D,"APRR",Détail!$A:$A,">="&DATE(2026,7,1),Détail!$A:$A,"<"&EDATE(DATE(2026,7,1),1))+SUMIFS(Détail!$E:$E,Détail!$D:$D,"APRR NFC",Détail!$A:$A,">="&DATE(2026,7,1),Détail!$A:$A,"<"&EDATE(DATE(2026,7,1),1))+SUMIFS(Détail!$E:$E,Détail!$D:$D,"AUTOROUTES DU S",Détail!$A:$A,">="&DATE(2026,7,1),Détail!$A:$A,"<"&EDATE(DATE(2026,7,1),1))+SUMIFS(Détail!$E:$E,Détail!$D:$D,"SAPN",Détail!$A:$A,">="&DATE(2026,7,1),Détail!$A:$A,"<"&EDATE(DATE(2026,7,1),1))+SUMIFS(Détail!$E:$E,Détail!$D:$D,"ROCADIS",Détail!$A:$A,">="&DATE(2026,7,1),Détail!$A:$A,"<"&EDATE(DATE(2026,7,1),1)) -> 0
A75: Prestataires : | B75: Sanef Autoroute, Sanef, Cofiroute, Aprr, Aprr Nfc, Autoroutes Du S, Sapn, Rocadis
A77: Abonnements télépéage | C77: =SUMIF(Détail!$D:$D,"BIPANDGO",Détail!$E:$E)+SUMIF(Détail!$D:$D,"BIPANDGO-BIP GO",Détail!$E:$E)+SUMIF(Détail!$D:$D,"ROOLE-IDENTICAR-IDENTICAR",Détail!$E:$E) -> -376.9
A78: Mois | B78: Montant
A79: Janvier 2026 | B79: =SUMIFS(Détail!$E:$E,Détail!$D:$D,"BIPANDGO",Détail!$A:$A,">="&DATE(2026,1,1),Détail!$A:$A,"<"&EDATE(DATE(2026,1,1),1))+SUMIFS(Détail!$E:$E,Détail!$D:$D,"BIPANDGO-BIP GO",Détail!$A:$A,">="&DATE(2026,1,1),Détail!$A:$A,"<"&EDATE(DATE(2026,1,1),1))+SUMIFS(Détail!$E:$E,Détail!$D:$D,"ROOLE-IDENTICAR-IDENTICAR",Détail!$A:$A,">="&DATE(2026,1,1),Détail!$A:$A,"<"&EDATE(DATE(2026,1,1),1)) -> -15.95
A80: Février 2026 | B80: =SUMIFS(Détail!$E:$E,Détail!$D:$D,"BIPANDGO",Détail!$A:$A,">="&DATE(2026,2,1),Détail!$A:$A,"<"&EDATE(DATE(2026,2,1),1))+SUMIFS(Détail!$E:$E,Détail!$D:$D,"BIPANDGO-BIP GO",Détail!$A:$A,">="&DATE(2026,2,1),Détail!$A:$A,"<"&EDATE(DATE(2026,2,1),1))+SUMIFS(Détail!$E:$E,Détail!$D:$D,"ROOLE-IDENTICAR-IDENTICAR",Détail!$A:$A,">="&DATE(2026,2,1),Détail!$A:$A,"<"&EDATE(DATE(2026,2,1),1)) -> -15.95
A81: Mars 2026 | B81: =SUMIFS(Détail!$E:$E,Détail!$D:$D,"BIPANDGO",Détail!$A:$A,">="&DATE(2026,3,1),Détail!$A:$A,"<"&EDATE(DATE(2026,3,1),1))+SUMIFS(Détail!$E:$E,Détail!$D:$D,"BIPANDGO-BIP GO",Détail!$A:$A,">="&DATE(2026,3,1),Détail!$A:$A,"<"&EDATE(DATE(2026,3,1),1))+SUMIFS(Détail!$E:$E,Détail!$D:$D,"ROOLE-IDENTICAR-IDENTICAR",Détail!$A:$A,">="&DATE(2026,3,1),Détail!$A:$A,"<"&EDATE(DATE(2026,3,1),1)) -> -15.95
A82: Avril 2026 | B82: =SUMIFS(Détail!$E:$E,Détail!$D:$D,"BIPANDGO",Détail!$A:$A,">="&DATE(2026,4,1),Détail!$A:$A,"<"&EDATE(DATE(2026,4,1),1))+SUMIFS(Détail!$E:$E,Détail!$D:$D,"BIPANDGO-BIP GO",Détail!$A:$A,">="&DATE(2026,4,1),Détail!$A:$A,"<"&EDATE(DATE(2026,4,1),1))+SUMIFS(Détail!$E:$E,Détail!$D:$D,"ROOLE-IDENTICAR-IDENTICAR",Détail!$A:$A,">="&DATE(2026,4,1),Détail!$A:$A,"<"&EDATE(DATE(2026,4,1),1)) -> -45.95
A83: Mai 2026 | B83: =SUMIFS(Détail!$E:$E,Détail!$D:$D,"BIPANDGO",Détail!$A:$A,">="&DATE(2026,5,1),Détail!$A:$A,"<"&EDATE(DATE(2026,5,1),1))+SUMIFS(Détail!$E:$E,Détail!$D:$D,"BIPANDGO-BIP GO",Détail!$A:$A,">="&DATE(2026,5,1),Détail!$A:$A,"<"&EDATE(DATE(2026,5,1),1))+SUMIFS(Détail!$E:$E,Détail!$D:$D,"ROOLE-IDENTICAR-IDENTICAR",Détail!$A:$A,">="&DATE(2026,5,1),Détail!$A:$A,"<"&EDATE(DATE(2026,5,1),1)) -> -160.05
A84: Juin 2026 | B84: =SUMIFS(Détail!$E:$E,Détail!$D:$D,"BIPANDGO",Détail!$A:$A,">="&DATE(2026,6,1),Détail!$A:$A,"<"&EDATE(DATE(2026,6,1),1))+SUMIFS(Détail!$E:$E,Détail!$D:$D,"BIPANDGO-BIP GO",Détail!$A:$A,">="&DATE(2026,6,1),Détail!$A:$A,"<"&EDATE(DATE(2026,6,1),1))+SUMIFS(Détail!$E:$E,Détail!$D:$D,"ROOLE-IDENTICAR-IDENTICAR",Détail!$A:$A,">="&DATE(2026,6,1),Détail!$A:$A,"<"&EDATE(DATE(2026,6,1),1)) -> -123.05
A85: Juillet 2026 | B85: =SUMIFS(Détail!$E:$E,Détail!$D:$D,"BIPANDGO",Détail!$A:$A,">="&DATE(2026,7,1),Détail!$A:$A,"<"&EDATE(DATE(2026,7,1),1))+SUMIFS(Détail!$E:$E,Détail!$D:$D,"BIPANDGO-BIP GO",Détail!$A:$A,">="&DATE(2026,7,1),Détail!$A:$A,"<"&EDATE(DATE(2026,7,1),1))+SUMIFS(Détail!$E:$E,Détail!$D:$D,"ROOLE-IDENTICAR-IDENTICAR",Détail!$A:$A,">="&DATE(2026,7,1),Détail!$A:$A,"<"&EDATE(DATE(2026,7,1),1)) -> 0
A86: Prestataires : | B86: Bipandgo, Bipandgo-Bip Go, Roole-Identicar-Identicar
A88: Parking | C88: =SUMIF(Détail!$D:$D,"PARK CASINO ROS",Détail!$E:$E)+SUMIF(Détail!$D:$D,"VIPARIS PDV PKG",Détail!$E:$E)+SUMIF(Détail!$D:$D,"BSM AP MARINA P",Détail!$E:$E)+SUMIF(Détail!$D:$D,"INDIGO 941401",Détail!$E:$E)+SUMIF(Détail!$D:$D,"INDIGO 750108",Détail!$E:$E)+SUMIF(Détail!$D:$D,"INDIGO 940006",Détail!$E:$E)+SUMIF(Détail!$D:$D,"PARK PTE VERSAI",Détail!$E:$E)+SUMIF(Détail!$D:$D,"ADP ORY P3 CBBS",Détail!$E:$E)+SUMIF(Détail!$D:$D,"ADP ROISSY PEF",Détail!$E:$E)+SUMIF(Détail!$D:$D,"EFFIA PARK",Détail!$E:$E)+SUMIF(Détail!$D:$D,"H P P E",Détail!$E:$E) -> -160.5
A89: Mois | B89: Montant
A90: Janvier 2026 | B90: =SUMIFS(Détail!$E:$E,Détail!$D:$D,"PARK CASINO ROS",Détail!$A:$A,">="&DATE(2026,1,1),Détail!$A:$A,"<"&EDATE(DATE(2026,1,1),1))+SUMIFS(Détail!$E:$E,Détail!$D:$D,"VIPARIS PDV PKG",Détail!$A:$A,">="&DATE(2026,1,1),Détail!$A:$A,"<"&EDATE(DATE(2026,1,1),1))+SUMIFS(Détail!$E:$E,Détail!$D:$D,"BSM AP MARINA P",Détail!$A:$A,">="&DATE(2026,1,1),Détail!$A:$A,"<"&EDATE(DATE(2026,1,1),1))+SUMIFS(Détail!$E:$E,Détail!$D:$D,"INDIGO 941401",Détail!$A:$A,">="&DATE(2026,1,1),Détail!$A:$A,"<"&EDATE(DATE(2026,1,1),1))+SUMIFS(Détail!$E:$E,Détail!$D:$D,"INDIGO 750108",Détail!$A:$A,">="&DATE(2026,1,1),Détail!$A:$A,"<"&EDATE(DATE(2026,1,1),1))+SUMIFS(Détail!$E:$E,Détail!$D:$D,"INDIGO 940006",Détail!$A:$A,">="&DATE(2026,1,1),Détail!$A:$A,"<"&EDATE(DATE(2026,1,1),1))+SUMIFS(Détail!$E:$E,Détail!$D:$D,"PARK PTE VERSAI",Détail!$A:$A,">="&DATE(2026,1,1),Détail!$A:$A,"<"&EDATE(DATE(2026,1,1),1))+SUMIFS(Détail!$E:$E,Détail!$D:$D,"ADP ORY P3 CBBS",Détail!$A:$A,">="&DATE(2026,1,1),Détail!$A:$A,"<"&EDATE(DATE(2026,1,1),1))+SUMIFS(Détail!$E:$E,Détail!$D:$D,"ADP ROISSY PEF",Détail!$A:$A,">="&DATE(2026,1,1),Détail!$A:$A,"<"&EDATE(DATE(2026,1,1),1))+SUMIFS(Détail!$E:$E,Détail!$D:$D,"EFFIA PARK",Détail!$A:$A,">="&DATE(2026,1,1),Détail!$A:$A,"<"&EDATE(DATE(2026,1,1),1))+SUMIFS(Détail!$E:$E,Détail!$D:$D,"H P P E",Détail!$A:$A,">="&DATE(2026,1,1),Détail!$A:$A,"<"&EDATE(DATE(2026,1,1),1)) -> -51.7
A91: Février 2026 | B91: =SUMIFS(Détail!$E:$E,Détail!$D:$D,"PARK CASINO ROS",Détail!$A:$A,">="&DATE(2026,2,1),Détail!$A:$A,"<"&EDATE(DATE(2026,2,1),1))+SUMIFS(Détail!$E:$E,Détail!$D:$D,"VIPARIS PDV PKG",Détail!$A:$A,">="&DATE(2026,2,1),Détail!$A:$A,"<"&EDATE(DATE(2026,2,1),1))+SUMIFS(Détail!$E:$E,Détail!$D:$D,"BSM AP MARINA P",Détail!$A:$A,">="&DATE(2026,2,1),Détail!$A:$A,"<"&EDATE(DATE(2026,2,1),1))+SUMIFS(Détail!$E:$E,Détail!$D:$D,"INDIGO 941401",Détail!$A:$A,">="&DATE(2026,2,1),Détail!$A:$A,"<"&EDATE(DATE(2026,2,1),1))+SUMIFS(Détail!$E:$E,Détail!$D:$D,"INDIGO 750108",Détail!$A:$A,">="&DATE(2026,2,1),Détail!$A:$A,"<"&EDATE(DATE(2026,2,1),1))+SUMIFS(Détail!$E:$E,Détail!$D:$D,"INDIGO 940006",Détail!$A:$A,">="&DATE(2026,2,1),Détail!$A:$A,"<"&EDATE(DATE(2026,2,1),1))+SUMIFS(Détail!$E:$E,Détail!$D:$D,"PARK PTE VERSAI",Détail!$A:$A,">="&DATE(2026,2,1),Détail!$A:$A,"<"&EDATE(DATE(2026,2,1),1))+SUMIFS(Détail!$E:$E,Détail!$D:$D,"ADP ORY P3 CBBS",Détail!$A:$A,">="&DATE(2026,2,1),Détail!$A:$A,"<"&EDATE(DATE(2026,2,1),1))+SUMIFS(Détail!$E:$E,Détail!$D:$D,"ADP ROISSY PEF",Détail!$A:$A,">="&DATE(2026,2,1),Détail!$A:$A,"<"&EDATE(DATE(2026,2,1),1))+SUMIFS(Détail!$E:$E,Détail!$D:$D,"EFFIA PARK",Détail!$A:$A,">="&DATE(2026,2,1),Détail!$A:$A,"<"&EDATE(DATE(2026,2,1),1))+SUMIFS(Détail!$E:$E,Détail!$D:$D,"H P P E",Détail!$A:$A,">="&DATE(2026,2,1),Détail!$A:$A,"<"&EDATE(DATE(2026,2,1),1)) -> -20.4
A92: Mars 2026 | B92: =SUMIFS(Détail!$E:$E,Détail!$D:$D,"PARK CASINO ROS",Détail!$A:$A,">="&DATE(2026,3,1),Détail!$A:$A,"<"&EDATE(DATE(2026,3,1),1))+SUMIFS(Détail!$E:$E,Détail!$D:$D,"VIPARIS PDV PKG",Détail!$A:$A,">="&DATE(2026,3,1),Détail!$A:$A,"<"&EDATE(DATE(2026,3,1),1))+SUMIFS(Détail!$E:$E,Détail!$D:$D,"BSM AP MARINA P",Détail!$A:$A,">="&DATE(2026,3,1),Détail!$A:$A,"<"&EDATE(DATE(2026,3,1),1))+SUMIFS(Détail!$E:$E,Détail!$D:$D,"INDIGO 941401",Détail!$A:$A,">="&DATE(2026,3,1),Détail!$A:$A,"<"&EDATE(DATE(2026,3,1),1))+SUMIFS(Détail!$E:$E,Détail!$D:$D,"INDIGO 750108",Détail!$A:$A,">="&DATE(2026,3,1),Détail!$A:$A,"<"&EDATE(DATE(2026,3,1),1))+SUMIFS(Détail!$E:$E,Détail!$D:$D,"INDIGO 940006",Détail!$A:$A,">="&DATE(2026,3,1),Détail!$A:$A,"<"&EDATE(DATE(2026,3,1),1))+SUMIFS(Détail!$E:$E,Détail!$D:$D,"PARK PTE VERSAI",Détail!$A:$A,">="&DATE(2026,3,1),Détail!$A:$A,"<"&EDATE(DATE(2026,3,1),1))+SUMIFS(Détail!$E:$E,Détail!$D:$D,"ADP ORY P3 CBBS",Détail!$A:$A,">="&DATE(2026,3,1),Détail!$A:$A,"<"&EDATE(DATE(2026,3,1),1))+SUMIFS(Détail!$E:$E,Détail!$D:$D,"ADP ROISSY PEF",Détail!$A:$A,">="&DATE(2026,3,1),Détail!$A:$A,"<"&EDATE(DATE(2026,3,1),1))+SUMIFS(Détail!$E:$E,Détail!$D:$D,"EFFIA PARK",Détail!$A:$A,">="&DATE(2026,3,1),Détail!$A:$A,"<"&EDATE(DATE(2026,3,1),1))+SUMIFS(Détail!$E:$E,Détail!$D:$D,"H P P E",Détail!$A:$A,">="&DATE(2026,3,1),Détail!$A:$A,"<"&EDATE(DATE(2026,3,1),1)) -> -6.2
A93: Avril 2026 | B93: =SUMIFS(Détail!$E:$E,Détail!$D:$D,"PARK CASINO ROS",Détail!$A:$A,">="&DATE(2026,4,1),Détail!$A:$A,"<"&EDATE(DATE(2026,4,1),1))+SUMIFS(Détail!$E:$E,Détail!$D:$D,"VIPARIS PDV PKG",Détail!$A:$A,">="&DATE(2026,4,1),Détail!$A:$A,"<"&EDATE(DATE(2026,4,1),1))+SUMIFS(Détail!$E:$E,Détail!$D:$D,"BSM AP MARINA P",Détail!$A:$A,">="&DATE(2026,4,1),Détail!$A:$A,"<"&EDATE(DATE(2026,4,1),1))+SUMIFS(Détail!$E:$E,Détail!$D:$D,"INDIGO 941401",Détail!$A:$A,">="&DATE(2026,4,1),Détail!$A:$A,"<"&EDATE(DATE(2026,4,1),1))+SUMIFS(Détail!$E:$E,Détail!$D:$D,"INDIGO 750108",Détail!$A:$A,">="&DATE(2026,4,1),Détail!$A:$A,"<"&EDATE(DATE(2026,4,1),1))+SUMIFS(Détail!$E:$E,Détail!$D:$D,"INDIGO 940006",Détail!$A:$A,">="&DATE(2026,4,1),Détail!$A:$A,"<"&EDATE(DATE(2026,4,1),1))+SUMIFS(Détail!$E:$E,Détail!$D:$D,"PARK PTE VERSAI",Détail!$A:$A,">="&DATE(2026,4,1),Détail!$A:$A,"<"&EDATE(DATE(2026,4,1),1))+SUMIFS(Détail!$E:$E,Détail!$D:$D,"ADP ORY P3 CBBS",Détail!$A:$A,">="&DATE(2026,4,1),Détail!$A:$A,"<"&EDATE(DATE(2026,4,1),1))+SUMIFS(Détail!$E:$E,Détail!$D:$D,"ADP ROISSY PEF",Détail!$A:$A,">="&DATE(2026,4,1),Détail!$A:$A,"<"&EDATE(DATE(2026,4,1),1))+SUMIFS(Détail!$E:$E,Détail!$D:$D,"EFFIA PARK",Détail!$A:$A,">="&DATE(2026,4,1),Détail!$A:$A,"<"&EDATE(DATE(2026,4,1),1))+SUMIFS(Détail!$E:$E,Détail!$D:$D,"H P P E",Détail!$A:$A,">="&DATE(2026,4,1),Détail!$A:$A,"<"&EDATE(DATE(2026,4,1),1)) -> -61
A94: Mai 2026 | B94: =SUMIFS(Détail!$E:$E,Détail!$D:$D,"PARK CASINO ROS",Détail!$A:$A,">="&DATE(2026,5,1),Détail!$A:$A,"<"&EDATE(DATE(2026,5,1),1))+SUMIFS(Détail!$E:$E,Détail!$D:$D,"VIPARIS PDV PKG",Détail!$A:$A,">="&DATE(2026,5,1),Détail!$A:$A,"<"&EDATE(DATE(2026,5,1),1))+SUMIFS(Détail!$E:$E,Détail!$D:$D,"BSM AP MARINA P",Détail!$A:$A,">="&DATE(2026,5,1),Détail!$A:$A,"<"&EDATE(DATE(2026,5,1),1))+SUMIFS(Détail!$E:$E,Détail!$D:$D,"INDIGO 941401",Détail!$A:$A,">="&DATE(2026,5,1),Détail!$A:$A,"<"&EDATE(DATE(2026,5,1),1))+SUMIFS(Détail!$E:$E,Détail!$D:$D,"INDIGO 750108",Détail!$A:$A,">="&DATE(2026,5,1),Détail!$A:$A,"<"&EDATE(DATE(2026,5,1),1))+SUMIFS(Détail!$E:$E,Détail!$D:$D,"INDIGO 940006",Détail!$A:$A,">="&DATE(2026,5,1),Détail!$A:$A,"<"&EDATE(DATE(2026,5,1),1))+SUMIFS(Détail!$E:$E,Détail!$D:$D,"PARK PTE VERSAI",Détail!$A:$A,">="&DATE(2026,5,1),Détail!$A:$A,"<"&EDATE(DATE(2026,5,1),1))+SUMIFS(Détail!$E:$E,Détail!$D:$D,"ADP ORY P3 CBBS",Détail!$A:$A,">="&DATE(2026,5,1),Détail!$A:$A,"<"&EDATE(DATE(2026,5,1),1))+SUMIFS(Détail!$E:$E,Détail!$D:$D,"ADP ROISSY PEF",Détail!$A:$A,">="&DATE(2026,5,1),Détail!$A:$A,"<"&EDATE(DATE(2026,5,1),1))+SUMIFS(Détail!$E:$E,Détail!$D:$D,"EFFIA PARK",Détail!$A:$A,">="&DATE(2026,5,1),Détail!$A:$A,"<"&EDATE(DATE(2026,5,1),1))+SUMIFS(Détail!$E:$E,Détail!$D:$D,"H P P E",Détail!$A:$A,">="&DATE(2026,5,1),Détail!$A:$A,"<"&EDATE(DATE(2026,5,1),1)) -> -5.35
A95: Juin 2026 | B95: =SUMIFS(Détail!$E:$E,Détail!$D:$D,"PARK CASINO ROS",Détail!$A:$A,">="&DATE(2026,6,1),Détail!$A:$A,"<"&EDATE(DATE(2026,6,1),1))+SUMIFS(Détail!$E:$E,Détail!$D:$D,"VIPARIS PDV PKG",Détail!$A:$A,">="&DATE(2026,6,1),Détail!$A:$A,"<"&EDATE(DATE(2026,6,1),1))+SUMIFS(Détail!$E:$E,Détail!$D:$D,"BSM AP MARINA P",Détail!$A:$A,">="&DATE(2026,6,1),Détail!$A:$A,"<"&EDATE(DATE(2026,6,1),1))+SUMIFS(Détail!$E:$E,Détail!$D:$D,"INDIGO 941401",Détail!$A:$A,">="&DATE(2026,6,1),Détail!$A:$A,"<"&EDATE(DATE(2026,6,1),1))+SUMIFS(Détail!$E:$E,Détail!$D:$D,"INDIGO 750108",Détail!$A:$A,">="&DATE(2026,6,1),Détail!$A:$A,"<"&EDATE(DATE(2026,6,1),1))+SUMIFS(Détail!$E:$E,Détail!$D:$D,"INDIGO 940006",Détail!$A:$A,">="&DATE(2026,6,1),Détail!$A:$A,"<"&EDATE(DATE(2026,6,1),1))+SUMIFS(Détail!$E:$E,Détail!$D:$D,"PARK PTE VERSAI",Détail!$A:$A,">="&DATE(2026,6,1),Détail!$A:$A,"<"&EDATE(DATE(2026,6,1),1))+SUMIFS(Détail!$E:$E,Détail!$D:$D,"ADP ORY P3 CBBS",Détail!$A:$A,">="&DATE(2026,6,1),Détail!$A:$A,"<"&EDATE(DATE(2026,6,1),1))+SUMIFS(Détail!$E:$E,Détail!$D:$D,"ADP ROISSY PEF",Détail!$A:$A,">="&DATE(2026,6,1),Détail!$A:$A,"<"&EDATE(DATE(2026,6,1),1))+SUMIFS(Détail!$E:$E,Détail!$D:$D,"EFFIA PARK",Détail!$A:$A,">="&DATE(2026,6,1),Détail!$A:$A,"<"&EDATE(DATE(2026,6,1),1))+SUMIFS(Détail!$E:$E,Détail!$D:$D,"H P P E",Détail!$A:$A,">="&DATE(2026,6,1),Détail!$A:$A,"<"&EDATE(DATE(2026,6,1),1)) -> -7.35
A96: Juillet 2026 | B96: =SUMIFS(Détail!$E:$E,Détail!$D:$D,"PARK CASINO ROS",Détail!$A:$A,">="&DATE(2026,7,1),Détail!$A:$A,"<"&EDATE(DATE(2026,7,1),1))+SUMIFS(Détail!$E:$E,Détail!$D:$D,"VIPARIS PDV PKG",Détail!$A:$A,">="&DATE(2026,7,1),Détail!$A:$A,"<"&EDATE(DATE(2026,7,1),1))+SUMIFS(Détail!$E:$E,Détail!$D:$D,"BSM AP MARINA P",Détail!$A:$A,">="&DATE(2026,7,1),Détail!$A:$A,"<"&EDATE(DATE(2026,7,1),1))+SUMIFS(Détail!$E:$E,Détail!$D:$D,"INDIGO 941401",Détail!$A:$A,">="&DATE(2026,7,1),Détail!$A:$A,"<"&EDATE(DATE(2026,7,1),1))+SUMIFS(Détail!$E:$E,Détail!$D:$D,"INDIGO 750108",Détail!$A:$A,">="&DATE(2026,7,1),Détail!$A:$A,"<"&EDATE(DATE(2026,7,1),1))+SUMIFS(Détail!$E:$E,Détail!$D:$D,"INDIGO 940006",Détail!$A:$A,">="&DATE(2026,7,1),Détail!$A:$A,"<"&EDATE(DATE(2026,7,1),1))+SUMIFS(Détail!$E:$E,Détail!$D:$D,"PARK PTE VERSAI",Détail!$A:$A,">="&DATE(2026,7,1),Détail!$A:$A,"<"&EDATE(DATE(2026,7,1),1))+SUMIFS(Détail!$E:$E,Détail!$D:$D,"ADP ORY P3 CBBS",Détail!$A:$A,">="&DATE(2026,7,1),Détail!$A:$A,"<"&EDATE(DATE(2026,7,1),1))+SUMIFS(Détail!$E:$E,Détail!$D:$D,"ADP ROISSY PEF",Détail!$A:$A,">="&DATE(2026,7,1),Détail!$A:$A,"<"&EDATE(DATE(2026,7,1),1))+SUMIFS(Détail!$E:$E,Détail!$D:$D,"EFFIA PARK",Détail!$A:$A,">="&DATE(2026,7,1),Détail!$A:$A,"<"&EDATE(DATE(2026,7,1),1))+SUMIFS(Détail!$E:$E,Détail!$D:$D,"H P P E",Détail!$A:$A,">="&DATE(2026,7,1),Détail!$A:$A,"<"&EDATE(DATE(2026,7,1),1)) -> -8.5
A97: Prestataires : | B97: Park Casino Ros, Viparis Pdv Pkg, Bsm Ap Marina P, Indigo 941401, Indigo 750108, Indigo 940006, Park Pte Versai, Adp Ory P3 Cbbs, Adp Roissy Pef, Effia Park, H P P E

Sheet Frais véhicule détail
A1: Frais de véhicule (entretien, réparation) — détail par prestataire (2026)
A3: Jfc By Mary Automobiles | C3: =SUMIF(Détail!$D:$D,"JFC BY MARY AUTOMOBILES",Détail!$E:$E) -> -3754.96
A4: Mois | B4: Montant
A5: Janvier 2026 | B5: =SUMIFS(Détail!$E:$E,Détail!$D:$D,"JFC BY MARY AUTOMOBILES",Détail!$A:$A,">="&DATE(2026,1,1),Détail!$A:$A,"<"&EDATE(DATE(2026,1,1),1)) -> 0
A6: Mars 2026 | B6: =SUMIFS(Détail!$E:$E,Détail!$D:$D,"JFC BY MARY AUTOMOBILES",Détail!$A:$A,">="&DATE(2026,3,1),Détail!$A:$A,"<"&EDATE(DATE(2026,3,1),1)) -> -3754.96
A7: Avril 2026 | B7: =SUMIFS(Détail!$E:$E,Détail!$D:$D,"JFC BY MARY AUTOMOBILES",Détail!$A:$A,">="&DATE(2026,4,1),Détail!$A:$A,"<"&EDATE(DATE(2026,4,1),1)) -> 0
A8: Mai 2026 | B8: =SUMIFS(Détail!$E:$E,Détail!$D:$D,"JFC BY MARY AUTOMOBILES",Détail!$A:$A,">="&DATE(2026,5,1),Détail!$A:$A,"<"&EDATE(DATE(2026,5,1),1)) -> 0
A9: Juin 2026 | B9: =SUMIFS(Détail!$E:$E,Détail!$D:$D,"JFC BY MARY AUTOMOBILES",Détail!$A:$A,">="&DATE(2026,6,1),Détail!$A:$A,"<"&EDATE(DATE(2026,6,1),1)) -> 0
A12: Easy Pneus | C12: =SUMIF(Détail!$D:$D,"EASY PNEUS",Détail!$E:$E) -> -285.08
A13: Mois | B13: Montant
A14: Janvier 2026 | B14: =SUMIFS(Détail!$E:$E,Détail!$D:$D,"EASY PNEUS",Détail!$A:$A,">="&DATE(2026,1,1),Détail!$A:$A,"<"&EDATE(DATE(2026,1,1),1)) -> 0
A15: Mars 2026 | B15: =SUMIFS(Détail!$E:$E,Détail!$D:$D,"EASY PNEUS",Détail!$A:$A,">="&DATE(2026,3,1),Détail!$A:$A,"<"&EDATE(DATE(2026,3,1),1)) -> 0
A16: Avril 2026 | B16: =SUMIFS(Détail!$E:$E,Détail!$D:$D,"EASY PNEUS",Détail!$A:$A,">="&DATE(2026,4,1),Détail!$A:$A,"<"&EDATE(DATE(2026,4,1),1)) -> 0
A17: Mai 2026 | B17: =SUMIFS(Détail!$E:$E,Détail!$D:$D,"EASY PNEUS",Détail!$A:$A,">="&DATE(2026,5,1),Détail!$A:$A,"<"&EDATE(DATE(2026,5,1),1)) -> -285.08
A18: Juin 2026 | B18: =SUMIFS(Détail!$E:$E,Détail!$D:$D,"EASY PNEUS",Détail!$A:$A,">="&DATE(2026,6,1),Détail!$A:$A,"<"&EDATE(DATE(2026,6,1),1)) -> 0
A21: Speedy Champign | C21: =SUMIF(Détail!$D:$D,"SPEEDY CHAMPIGN",Détail!$E:$E) -> -147
A22: Mois | B22: Montant
A23: Janvier 2026 | B23: =SUMIFS(Détail!$E:$E,Détail!$D:$D,"SPEEDY CHAMPIGN",Détail!$A:$A,">="&DATE(2026,1,1),Détail!$A:$A,"<"&EDATE(DATE(2026,1,1),1)) -> -147
A24: Mars 2026 | B24: =SUMIFS(Détail!$E:$E,Détail!$D:$D,"SPEEDY CHAMPIGN",Détail!$A:$A,">="&DATE(2026,3,1),Détail!$A:$A,"<"&EDATE(DATE(2026,3,1),1)) -> 0
A25: Avril 2026 | B25: =SUMIFS(Détail!$E:$E,Détail!$D:$D,"SPEEDY CHAMPIGN",Détail!$A:$A,">="&DATE(2026,4,1),Détail!$A:$A,"<"&EDATE(DATE(2026,4,1),1)) -> 0
A26: Mai 2026 | B26: =SUMIFS(Détail!$E:$E,Détail!$D:$D,"SPEEDY CHAMPIGN",Détail!$A:$A,">="&DATE(2026,5,1),Détail!$A:$A,"<"&EDATE(DATE(2026,5,1),1)) -> 0
A27: Juin 2026 | B27: =SUMIFS(Détail!$E:$E,Détail!$D:$D,"SPEEDY CHAMPIGN",Détail!$A:$A,">="&DATE(2026,6,1),Détail!$A:$A,"<"&EDATE(DATE(2026,6,1),1)) -> 0
A30: Lm Auto Parts | C30: =SUMIF(Détail!$D:$D,"LM AUTO PARTS",Détail!$E:$E) -> -142
A31: Mois | B31: Montant
A32: Janvier 2026 | B32: =SUMIFS(Détail!$E:$E,Détail!$D:$D,"LM AUTO PARTS",Détail!$A:$A,">="&DATE(2026,1,1),Détail!$A:$A,"<"&EDATE(DATE(2026,1,1),1)) -> 0
A33: Mars 2026 | B33: =SUMIFS(Détail!$E:$E,Détail!$D:$D,"LM AUTO PARTS",Détail!$A:$A,">="&DATE(2026,3,1),Détail!$A:$A,"<"&EDATE(DATE(2026,3,1),1)) -> 0
A34: Avril 2026 | B34: =SUMIFS(Détail!$E:$E,Détail!$D:$D,"LM AUTO PARTS",Détail!$A:$A,">="&DATE(2026,4,1),Détail!$A:$A,"<"&EDATE(DATE(2026,4,1),1)) -> 0
A35: Mai 2026 | B35: =SUMIFS(Détail!$E:$E,Détail!$D:$D,"LM AUTO PARTS",Détail!$A:$A,">="&DATE(2026,5,1),Détail!$A:$A,"<"&EDATE(DATE(2026,5,1),1)) -> 0
A36: Juin 2026 | B36: =SUMIFS(Détail!$E:$E,Détail!$D:$D,"LM AUTO PARTS",Détail!$A:$A,">="&DATE(2026,6,1),Détail!$A:$A,"<"&EDATE(DATE(2026,6,1),1)) -> -142
A39: Autolook Rapid | C39: =SUMIF(Détail!$D:$D,"AUTOLOOK RAPID",Détail!$E:$E) -> -60
A40: Mois | B40: Montant
A41: Janvier 2026 | B41: =SUMIFS(Détail!$E:$E,Détail!$D:$D,"AUTOLOOK RAPID",Détail!$A:$A,">="&DATE(2026,1,1),Détail!$A:$A,"<"&EDATE(DATE(2026,1,1),1)) -> 0
A42: Mars 2026 | B42: =SUMIFS(Détail!$E:$E,Détail!$D:$D,"AUTOLOOK RAPID",Détail!$A:$A,">="&DATE(2026,3,1),Détail!$A:$A,"<"&EDATE(DATE(2026,3,1),1)) -> 0
A43: Avril 2026 | B43: =SUMIFS(Détail!$E:$E,Détail!$D:$D,"AUTOLOOK RAPID",Détail!$A:$A,">="&DATE(2026,4,1),Détail!$A:$A,"<"&EDATE(DATE(2026,4,1),1)) -> -60
A44: Mai 2026 | B44: =SUMIFS(Détail!$E:$E,Détail!$D:$D,"AUTOLOOK RAPID",Détail!$A:$A,">="&DATE(2026,5,1),Détail!$A:$A,"<"&EDATE(DATE(2026,5,1),1)) -> 0
A45: Juin 2026 | B45: =SUMIFS(Détail!$E:$E,Détail!$D:$D,"AUTOLOOK RAPID",Détail!$A:$A,">="&DATE(2026,6,1),Détail!$A:$A,"<"&EDATE(DATE(2026,6,1),1)) -> 0
A48: Lavage Auto | C48: =SUMIF(Détail!$D:$D,"LAVAGE AUTO",Détail!$E:$E) -> -20
A49: Mois | B49: Montant
A50: Janvier 2026 | B50: =SUMIFS(Détail!$E:$E,Détail!$D:$D,"LAVAGE AUTO",Détail!$A:$A,">="&DATE(2026,1,1),Détail!$A:$A,"<"&EDATE(DATE(2026,1,1),1)) -> 0
A51: Mars 2026 | B51: =SUMIFS(Détail!$E:$E,Détail!$D:$D,"LAVAGE AUTO",Détail!$A:$A,">="&DATE(2026,3,1),Détail!$A:$A,"<"&EDATE(DATE(2026,3,1),1)) -> 0
A52: Avril 2026 | B52: =SUMIFS(Détail!$E:$E,Détail!$D:$D,"LAVAGE AUTO",Détail!$A:$A,">="&DATE(2026,4,1),Détail!$A:$A,"<"&EDATE(DATE(2026,4,1),1)) -> -20
A53: Mai 2026 | B53: =SUMIFS(Détail!$E:$E,Détail!$D:$D,"LAVAGE AUTO",Détail!$A:$A,">="&DATE(2026,5,1),Détail!$A:$A,"<"&EDATE(DATE(2026,5,1),1)) -> 0
A54: Juin 2026 | B54: =SUMIFS(Détail!$E:$E,Détail!$D:$D,"LAVAGE AUTO",Détail!$A:$A,">="&DATE(2026,6,1),Détail!$A:$A,"<"&EDATE(DATE(2026,6,1),1)) -> 0
A57: Jet Servicio | C57: =SUMIF(Détail!$D:$D,"JET SERVICIO",Détail!$E:$E) -> -17.12
A58: Mois | B58: Montant
A59: Janvier 2026 | B59: =SUMIFS(Détail!$E:$E,Détail!$D:$D,"JET SERVICIO",Détail!$A:$A,">="&DATE(2026,1,1),Détail!$A:$A,"<"&EDATE(DATE(2026,1,1),1)) -> 0
A60: Mars 2026 | B60: =SUMIFS(Détail!$E:$E,Détail!$D:$D,"JET SERVICIO",Détail!$A:$A,">="&DATE(2026,3,1),Détail!$A:$A,"<"&EDATE(DATE(2026,3,1),1)) -> 0
A61: Avril 2026 | B61: =SUMIFS(Détail!$E:$E,Détail!$D:$D,"JET SERVICIO",Détail!$A:$A,">="&DATE(2026,4,1),Détail!$A:$A,"<"&EDATE(DATE(2026,4,1),1)) -> -17.12
A62: Mai 2026 | B62: =SUMIFS(Détail!$E:$E,Détail!$D:$D,"JET SERVICIO",Détail!$A:$A,">="&DATE(2026,5,1),Détail!$A:$A,"<"&EDATE(DATE(2026,5,1),1)) -> 0
A63: Juin 2026 | B63: =SUMIFS(Détail!$E:$E,Détail!$D:$D,"JET SERVICIO",Détail!$A:$A,">="&DATE(2026,6,1),Détail!$A:$A,"<"&EDATE(DATE(2026,6,1),1)) -> 0

Sheet Restauration détail
A1: Restauration — détail par enseigne (2026)
A3: Mcdonald'S | C3: =SUMIF(Détail!$D:$D,"MCDONALD'S",Détail!$E:$E) -> -161.38
A4: Mois | B4: Montant
A5: Janvier 2026 | B5: =SUMIFS(Détail!$E:$E,Détail!$D:$D,"MCDONALD'S",Détail!$A:$A,">="&DATE(2026,1,1),Détail!$A:$A,"<"&EDATE(DATE(2026,1,1),1)) -> -27.49
A6: Mars 2026 | B6: =SUMIFS(Détail!$E:$E,Détail!$D:$D,"MCDONALD'S",Détail!$A:$A,">="&DATE(2026,3,1),Détail!$A:$A,"<"&EDATE(DATE(2026,3,1),1)) -> -36.45
A7: Avril 2026 | B7: =SUMIFS(Détail!$E:$E,Détail!$D:$D,"MCDONALD'S",Détail!$A:$A,">="&DATE(2026,4,1),Détail!$A:$A,"<"&EDATE(DATE(2026,4,1),1)) -> -82.75
A8: Mai 2026 | B8: =SUMIFS(Détail!$E:$E,Détail!$D:$D,"MCDONALD'S",Détail!$A:$A,">="&DATE(2026,5,1),Détail!$A:$A,"<"&EDATE(DATE(2026,5,1),1)) -> 0
A9: Juin 2026 | B9: =SUMIFS(Détail!$E:$E,Détail!$D:$D,"MCDONALD'S",Détail!$A:$A,">="&DATE(2026,6,1),Détail!$A:$A,"<"&EDATE(DATE(2026,6,1),1)) -> -14.69
A12: Subway | C12: =SUMIF(Détail!$D:$D,"SUBWAY",Détail!$E:$E) -> -75.4
A13: Mois | B13: Montant
A14: Janvier 2026 | B14: =SUMIFS(Détail!$E:$E,Détail!$D:$D,"SUBWAY",Détail!$A:$A,">="&DATE(2026,1,1),Détail!$A:$A,"<"&EDATE(DATE(2026,1,1),1)) -> 0
A15: Mars 2026 | B15: =SUMIFS(Détail!$E:$E,Détail!$D:$D,"SUBWAY",Détail!$A:$A,">="&DATE(2026,3,1),Détail!$A:$A,"<"&EDATE(DATE(2026,3,1),1)) -> -75.4
A16: Avril 2026 | B16: =SUMIFS(Détail!$E:$E,Détail!$D:$D,"SUBWAY",Détail!$A:$A,">="&DATE(2026,4,1),Détail!$A:$A,"<"&EDATE(DATE(2026,4,1),1)) -> 0
A17: Mai 2026 | B17: =SUMIFS(Détail!$E:$E,Détail!$D:$D,"SUBWAY",Détail!$A:$A,">="&DATE(2026,5,1),Détail!$A:$A,"<"&EDATE(DATE(2026,5,1),1)) -> 0
A18: Juin 2026 | B18: =SUMIFS(Détail!$E:$E,Détail!$D:$D,"SUBWAY",Détail!$A:$A,">="&DATE(2026,6,1),Détail!$A:$A,"<"&EDATE(DATE(2026,6,1),1)) -> 0
A21: Andrea Pappada' | C21: =SUMIF(Détail!$D:$D,"ANDREA PAPPADA'",Détail!$E:$E) -> -44.7
A22: Mois | B22: Montant
A23: Janvier 2026 | B23: =SUMIFS(Détail!$E:$E,Détail!$D:$D,"ANDREA PAPPADA'",Détail!$A:$A,">="&DATE(2026,1,1),Détail!$A:$A,"<"&EDATE(DATE(2026,1,1),1)) -> 0
A24: Mars 2026 | B24: =SUMIFS(Détail!$E:$E,Détail!$D:$D,"ANDREA PAPPADA'",Détail!$A:$A,">="&DATE(2026,3,1),Détail!$A:$A,"<"&EDATE(DATE(2026,3,1),1)) -> 0
A25: Avril 2026 | B25: =SUMIFS(Détail!$E:$E,Détail!$D:$D,"ANDREA PAPPADA'",Détail!$A:$A,">="&DATE(2026,4,1),Détail!$A:$A,"<"&EDATE(DATE(2026,4,1),1)) -> 0
A26: Mai 2026 | B26: =SUMIFS(Détail!$E:$E,Détail!$D:$D,"ANDREA PAPPADA'",Détail!$A:$A,">="&DATE(2026,5,1),Détail!$A:$A,"<"&EDATE(DATE(2026,5,1),1)) -> 0
A27: Juin 2026 | B27: =SUMIFS(Détail!$E:$E,Détail!$D:$D,"ANDREA PAPPADA'",Détail!$A:$A,">="&DATE(2026,6,1),Détail!$A:$A,"<"&EDATE(DATE(2026,6,1),1)) -> -44.7
A30: Horeto Paris | C30: =SUMIF(Détail!$D:$D,"HORETO PARIS",Détail!$E:$E) -> -26.5
A31: Mois | B31: Montant
A32: Janvier 2026 | B32: =SUMIFS(Détail!$E:$E,Détail!$D:$D,"HORETO PARIS",Détail!$A:$A,">="&DATE(2026,1,1),Détail!$A:$A,"<"&EDATE(DATE(2026,1,1),1)) -> 0
A33: Mars 2026 | B33: =SUMIFS(Détail!$E:$E,Détail!$D:$D,"HORETO PARIS",Détail!$A:$A,">="&DATE(2026,3,1),Détail!$A:$A,"<"&EDATE(DATE(2026,3,1),1)) -> 0
A34: Avril 2026 | B34: =SUMIFS(Détail!$E:$E,Détail!$D:$D,"HORETO PARIS",Détail!$A:$A,">="&DATE(2026,4,1),Détail!$A:$A,"<"&EDATE(DATE(2026,4,1),1)) -> -26.5
A35: Mai 2026 | B35: =SUMIFS(Détail!$E:$E,Détail!$D:$D,"HORETO PARIS",Détail!$A:$A,">="&DATE(2026,5,1),Détail!$A:$A,"<"&EDATE(DATE(2026,5,1),1)) -> 0
A36: Juin 2026 | B36: =SUMIFS(Détail!$E:$E,Détail!$D:$D,"HORETO PARIS",Détail!$A:$A,">="&DATE(2026,6,1),Détail!$A:$A,"<"&EDATE(DATE(2026,6,1),1)) -> 0
A39: Deliveroo | C39: =SUMIF(Détail!$D:$D,"DELIVEROO",Détail!$E:$E) -> -26.11
A40: Mois | B40: Montant
A41: Janvier 2026 | B41: =SUMIFS(Détail!$E:$E,Détail!$D:$D,"DELIVEROO",Détail!$A:$A,">="&DATE(2026,1,1),Détail!$A:$A,"<"&EDATE(DATE(2026,1,1),1)) -> 0
A42: Mars 2026 | B42: =SUMIFS(Détail!$E:$E,Détail!$D:$D,"DELIVEROO",Détail!$A:$A,">="&DATE(2026,3,1),Détail!$A:$A,"<"&EDATE(DATE(2026,3,1),1)) -> 0
A43: Avril 2026 | B43: =SUMIFS(Détail!$E:$E,Détail!$D:$D,"DELIVEROO",Détail!$A:$A,">="&DATE(2026,4,1),Détail!$A:$A,"<"&EDATE(DATE(2026,4,1),1)) -> 0
A44: Mai 2026 | B44: =SUMIFS(Détail!$E:$E,Détail!$D:$D,"DELIVEROO",Détail!$A:$A,">="&DATE(2026,5,1),Détail!$A:$A,"<"&EDATE(DATE(2026,5,1),1)) -> 0
A45: Juin 2026 | B45: =SUMIFS(Détail!$E:$E,Détail!$D:$D,"DELIVEROO",Détail!$A:$A,">="&DATE(2026,6,1),Détail!$A:$A,"<"&EDATE(DATE(2026,6,1),1)) -> -26.11
A48: Ravi Rs | C48: =SUMIF(Détail!$D:$D,"RAVI RS",Détail!$E:$E) -> -19.8
A49: Mois | B49: Montant
A50: Janvier 2026 | B50: =SUMIFS(Détail!$E:$E,Détail!$D:$D,"RAVI RS",Détail!$A:$A,">="&DATE(2026,1,1),Détail!$A:$A,"<"&EDATE(DATE(2026,1,1),1)) -> 0
A51: Mars 2026 | B51: =SUMIFS(Détail!$E:$E,Détail!$D:$D,"RAVI RS",Détail!$A:$A,">="&DATE(2026,3,1),Détail!$A:$A,"<"&EDATE(DATE(2026,3,1),1)) -> 0
A52: Avril 2026 | B52: =SUMIFS(Détail!$E:$E,Détail!$D:$D,"RAVI RS",Détail!$A:$A,">="&DATE(2026,4,1),Détail!$A:$A,"<"&EDATE(DATE(2026,4,1),1)) -> -19.8
A53: Mai 2026 | B53: =SUMIFS(Détail!$E:$E,Détail!$D:$D,"RAVI RS",Détail!$A:$A,">="&DATE(2026,5,1),Détail!$A:$A,"<"&EDATE(DATE(2026,5,1),1)) -> 0
A54: Juin 2026 | B54: =SUMIFS(Détail!$E:$E,Détail!$D:$D,"RAVI RS",Détail!$A:$A,">="&DATE(2026,6,1),Détail!$A:$A,"<"&EDATE(DATE(2026,6,1),1)) -> 0
A57: Chicken Et Comp | C57: =SUMIF(Détail!$D:$D,"CHICKEN ET COMP",Détail!$E:$E) -> -18
A58: Mois | B58: Montant
A59: Janvier 2026 | B59: =SUMIFS(Détail!$E:$E,Détail!$D:$D,"CHICKEN ET COMP",Détail!$A:$A,">="&DATE(2026,1,1),Détail!$A:$A,"<"&EDATE(DATE(2026,1,1),1)) -> -18
A60: Mars 2026 | B60: =SUMIFS(Détail!$E:$E,Détail!$D:$D,"CHICKEN ET COMP",Détail!$A:$A,">="&DATE(2026,3,1),Détail!$A:$A,"<"&EDATE(DATE(2026,3,1),1)) -> 0
A61: Avril 2026 | B61: =SUMIFS(Détail!$E:$E,Détail!$D:$D,"CHICKEN ET COMP",Détail!$A:$A,">="&DATE(2026,4,1),Détail!$A:$A,"<"&EDATE(DATE(2026,4,1),1)) -> 0
A62: Mai 2026 | B62: =SUMIFS(Détail!$E:$E,Détail!$D:$D,"CHICKEN ET COMP",Détail!$A:$A,">="&DATE(2026,5,1),Détail!$A:$A,"<"&EDATE(DATE(2026,5,1),1)) -> 0
A63: Juin 2026 | B63: =SUMIFS(Détail!$E:$E,Détail!$D:$D,"CHICKEN ET COMP",Détail!$A:$A,">="&DATE(2026,6,1),Détail!$A:$A,"<"&EDATE(DATE(2026,6,1),1)) -> 0
A66: G La Dalle Cham | C66: =SUMIF(Détail!$D:$D,"G LA DALLE CHAM",Détail!$E:$E) -> -16.3
A67: Mois | B67: Montant
A68: Janvier 2026 | B68: =SUMIFS(Détail!$E:$E,Détail!$D:$D,"G LA DALLE CHAM",Détail!$A:$A,">="&DATE(2026,1,1),Détail!$A:$A,"<"&EDATE(DATE(2026,1,1),1)) -> 0
A69: Mars 2026 | B69: =SUMIFS(Détail!$E:$E,Détail!$D:$D,"G LA DALLE CHAM",Détail!$A:$A,">="&DATE(2026,3,1),Détail!$A:$A,"<"&EDATE(DATE(2026,3,1),1)) -> 0
A70: Avril 2026 | B70: =SUMIFS(Détail!$E:$E,Détail!$D:$D,"G LA DALLE CHAM",Détail!$A:$A,">="&DATE(2026,4,1),Détail!$A:$A,"<"&EDATE(DATE(2026,4,1),1)) -> 0
A71: Mai 2026 | B71: =SUMIFS(Détail!$E:$E,Détail!$D:$D,"G LA DALLE CHAM",Détail!$A:$A,">="&DATE(2026,5,1),Détail!$A:$A,"<"&EDATE(DATE(2026,5,1),1)) -> -16.3
A72: Juin 2026 | B72: =SUMIFS(Détail!$E:$E,Détail!$D:$D,"G LA DALLE CHAM",Détail!$A:$A,">="&DATE(2026,6,1),Détail!$A:$A,"<"&EDATE(DATE(2026,6,1),1)) -> 0
A75: Alice Pizza Neg | C75: =SUMIF(Détail!$D:$D,"ALICE PIZZA NEG",Détail!$E:$E) -> -13.7
A76: Mois | B76: Montant
A77: Janvier 2026 | B77: =SUMIFS(Détail!$E:$E,Détail!$D:$D,"ALICE PIZZA NEG",Détail!$A:$A,">="&DATE(2026,1,1),Détail!$A:$A,"<"&EDATE(DATE(2026,1,1),1)) -> 0
A78: Mars 2026 | B78: =SUMIFS(Détail!$E:$E,Détail!$D:$D,"ALICE PIZZA NEG",Détail!$A:$A,">="&DATE(2026,3,1),Détail!$A:$A,"<"&EDATE(DATE(2026,3,1),1)) -> 0
A79: Avril 2026 | B79: =SUMIFS(Détail!$E:$E,Détail!$D:$D,"ALICE PIZZA NEG",Détail!$A:$A,">="&DATE(2026,4,1),Détail!$A:$A,"<"&EDATE(DATE(2026,4,1),1)) -> 0
A80: Mai 2026 | B80: =SUMIFS(Détail!$E:$E,Détail!$D:$D,"ALICE PIZZA NEG",Détail!$A:$A,">="&DATE(2026,5,1),Détail!$A:$A,"<"&EDATE(DATE(2026,5,1),1)) -> 0
A81: Juin 2026 | B81: =SUMIFS(Détail!$E:$E,Détail!$D:$D,"ALICE PIZZA NEG",Détail!$A:$A,">="&DATE(2026,6,1),Détail!$A:$A,"<"&EDATE(DATE(2026,6,1),1)) -> -13.7
A84: Maison Pradier | C84: =SUMIF(Détail!$D:$D,"MAISON PRADIER",Détail!$E:$E) -> -5.9
A85: Mois | B85: Montant
A86: Janvier 2026 | B86: =SUMIFS(Détail!$E:$E,Détail!$D:$D,"MAISON PRADIER",Détail!$A:$A,">="&DATE(2026,1,1),Détail!$A:$A,"<"&EDATE(DATE(2026,1,1),1)) -> 0
A87: Mars 2026 | B87: =SUMIFS(Détail!$E:$E,Détail!$D:$D,"MAISON PRADIER",Détail!$A:$A,">="&DATE(2026,3,1),Détail!$A:$A,"<"&EDATE(DATE(2026,3,1),1)) -> 0
A88: Avril 2026 | B88: =SUMIFS(Détail!$E:$E,Détail!$D:$D,"MAISON PRADIER",Détail!$A:$A,">="&DATE(2026,4,1),Détail!$A:$A,"<"&EDATE(DATE(2026,4,1),1)) -> 0
A89: Mai 2026 | B89: =SUMIFS(Détail!$E:$E,Détail!$D:$D,"MAISON PRADIER",Détail!$A:$A,">="&DATE(2026,5,1),Détail!$A:$A,"<"&EDATE(DATE(2026,5,1),1)) -> 0
A90: Juin 2026 | B90: =SUMIFS(Détail!$E:$E,Détail!$D:$D,"MAISON PRADIER",Détail!$A:$A,">="&DATE(2026,6,1),Détail!$A:$A,"<"&EDATE(DATE(2026,6,1),1)) -> -5.9
A93: Au Sourire De P | C93: =SUMIF(Détail!$D:$D,"AU SOURIRE DE P",Détail!$E:$E) -> -3
A94: Mois | B94: Montant
A95: Janvier 2026 | B95: =SUMIFS(Détail!$E:$E,Détail!$D:$D,"AU SOURIRE DE P",Détail!$A:$A,">="&DATE(2026,1,1),Détail!$A:$A,"<"&EDATE(DATE(2026,1,1),1)) -> 0
A96: Mars 2026 | B96: =SUMIFS(Détail!$E:$E,Détail!$D:$D,"AU SOURIRE DE P",Détail!$A:$A,">="&DATE(2026,3,1),Détail!$A:$A,"<"&EDATE(DATE(2026,3,1),1)) -> 0
A97: Avril 2026 | B97: =SUMIFS(Détail!$E:$E,Détail!$D:$D,"AU SOURIRE DE P",Détail!$A:$A,">="&DATE(2026,4,1),Détail!$A:$A,"<"&EDATE(DATE(2026,4,1),1)) -> 0
A98: Mai 2026 | B98: =SUMIFS(Détail!$E:$E,Détail!$D:$D,"AU SOURIRE DE P",Détail!$A:$A,">="&DATE(2026,5,1),Détail!$A:$A,"<"&EDATE(DATE(2026,5,1),1)) -> 0
A99: Juin 2026 | B99: =SUMIFS(Détail!$E:$E,Détail!$D:$D,"AU SOURIRE DE P",Détail!$A:$A,">="&DATE(2026,6,1),Détail!$A:$A,"<"&EDATE(DATE(2026,6,1),1)) -> -3

Sheet Détail
A1: Date | B1: Référence | C1: Type d'opération | D1: Fournisseur / Libellé | E1: Montant (€) | F1: Catégorie
A2: 46024 | B2: 0000935 | C2: CARTE | D2: GOOGLE WORKSPACE | E2: -145.8 | F2: Téléphone / Internet / Logiciels
A3: 46024 | B3: 2835991 | C3: PRELEVEMENT SEPA | D3: VW BANK FRANCE | E3: -872.67 | F3: Carburant, péages, parking, leasing
A4: 46024 | B4: 2837774 | C4: VIREMENT SEPA RECU | D4: STRIPE | E4: 154.97 | F4: Encaissement (hors périmètre charges)
A5: 46024 | B5: 2005520 | C5: CARTE | D5: TOTAL | E5: -60.96 | F5: Carburant, péages, parking, leasing
A6: 46027 | B6: 2837770 | C6: PRELEVEMENT SEPA | D6: AMM COT SANTE DES ENTREPRISES-APIVIA MACIF MUTUELLE | E6: -79 | F6: Mutuelle / prévoyance salariés
A7: 46027 | B7: 1518638 | C7: VIREMENT INTERNATIONAL RECU | D7: SARL JADE CREATION SALGDZALXXX | E7: 1382.36 | F7: Encaissement (hors périmètre charges)
A8: 46027 | B8: 9001928 | C8: VIREMENT SEPA EMIS | D8: MR BOUDJADA SAID | E8: -3000 | F8: Rémunération gérant
A9: 46027 | B9: 2837771 | C9: PRELEVEMENT SEPA | D9: TOTALENERGIES ELECTRICITE ET GAZ FRANCE | E9: -174.83 | F9: Électricité / Gaz
A10: 46027 | B10: 2838249 | C10: PRELEVEMENT SEPA | D10: OVH SAS | E10: -0.36 | F10: Téléphone / Internet / Logiciels
A11: 46028 | B11: 2304611 | C11: CARTE | D11: CCIP DFCE GEFI | E11: -28 | F11: Frais professionnels divers
A12: 46028 | B12: 2304621 | C12: CARTE | D12: CCIP DFCE GEFI | E12: -43 | F12: Frais professionnels divers
A13: 46028 | B13: 2839970 | C13: VIREMENT SEPA RECU | D13: STRIPE | E13: 115.84 | F13: Encaissement (hors périmètre charges)
... A24: 46034 | B24: 3801940 | C24: VIREMENT INTERNATIONAL RECU | D24: ALMUFTAH MARKETING | E24: 21555.14 | F24: Encaissement (hors périmètre charges)
A25: 46034 | B25: 2037013 | C25: INTERETS | E25: -519.86 | F25: Frais bancaires & financiers
A26: 46034 | B26: 3801940 | C26: FRAIS AVIS D'OPERE | D26: (DONT HORS TAXE E.1,00 TVA TAUX 20,00 % E.0,20) | E26: -1.2 | F26: Frais bancaires & financiers
A27: 46034 | B27: 2843139 | C27: PRELEVEMENT SEPA | D27: AMM COT SANTE DES ENTREPRISES-APIVIA MACIF MUTUELLE | E27: -132.17 | F27: Mutuelle / prévoyance salariés
A28: 46034 | B28: 3801944 | C28: VIREMENT INTERNATIONAL RECU | D28: NB EVOLUTION FZCO | E28: 35100 | F28: Encaissement (hors périmètre charges)
A29: 46034 | B29: 3009049 | C29: CARTE | D29: ESSO CHAMPIGNY | E29: -38.43 | F29: Carburant, péages, parking, leasing
A30: 46034 | B30: 3801950 | C30: FRAIS AVIS D'OPERE | D30: (DONT HORS TAXE E.1,00 TVA TAUX 20,00 % E.0,20) | E30: -1.2 | F30: Frais bancaires & financiers
A31: 46034 | B31: 2839273 | C31: PRELEVEMENT SEPA | D31: SWISSLIFE ASSURANCE DE BIENS | E31: -78.46 | F31: Assurances
A32: 46034 | B32: 3801944 | C32: FRAIS AVIS D'OPERE | D32: (DONT HORS TAXE E.1,00 TVA TAUX 20,00 % E.0,20) | E32: -1.2 | F32: Frais bancaires & financiers
A33: 46035 | B33: 1970096 | C33: FRAIS VIREMENT INTERNATIONAL | D33: (DONT HORS TAXE E.13,00 TVA TAUX 20,00 % E.2,60) | E33: -15.6 | F33: Frais bancaires & financiers
A34: 46035 | B34: 2035140 | C34: CARTE | D34: COFIROUTE | E34: -1.7 | F34: Carburant, péages, parking, leasing
A35: 46035 | B35: 9003848 | C35: VIREMENT SEPA EMIS | D35: GS1 FRANCE | E35: -757.2 | F35: Frais professionnels divers
A36: 46035 | B36: 9003811 | C36: VIREMENT SEPA EMIS | D36: FRANCE CONDITIONNEMENT PARFUM | E36: -9350.99 | F36: Usine de conditionnement et macération
A37: 46035 | B37: 1970096 | C37: FRAIS AVIS D'OPERE | D37: (DONT HORS TAXE E.1,00 TVA TAUX 20,00 % E.0,20) | E37: -1.2 | F37: Frais bancaires & financiers
... A44: 46035 | B44: 9003740 | C44: VIREMENT SEPA EMIS | D44: CARTONNAGES DU VAL D ORGE | E44: -1828.8 | F44: Fournisseurs matières premières & emballage (France)
A45: 46035 | B45: 1970096 | C45: FRAIS DE CHANGE | E45: -17 | F45: Frais bancaires & financiers
A46: 46035 | B46: 2033230 | C46: CARTE | D46: COFIROUTE | E46: -1.7 | F46: Carburant, péages, parking, leasing
A47: 46035 | B47: 9003951 | C47: VIREMENT SEPA EMIS | D47: TUV RHEINLAND FRANCE SAS | E47: -827.87 | F47: Frais professionnels divers
A48: 46036 | B48: 0510702 | C48: CARTE | D48: ISTANBUL 62 | E48: -10 | F48: Voyages / déplacements
A49: 46036 | B49: 2065191 | C49: CARTE | D49: TOTAL | E49: -81.08 | F49: Carburant, péages, parking, leasing
A50: 46036 | B50: 3012604 | C50: CARTE | D50: MCDONALD'S | E50: -14.6 | F50: Restauration
A51: 46036 | B51: 2013580 | C51: CARTE | D51: PARK CASINO ROS | E51: -8.8 | F51: Carburant, péages, parking, leasing
A52: 46036 | B52: 2845280 | C52: VIREMENT SEPA RECU | D52: SIE MARNE ET BOIS | E52: 6230 | F52: Encaissement (hors périmètre charges)
A53: 46036 | B53: 0002198 | C53: COTISATION | D53: COTISATION BREDACCES PRO | E53: -49.35 | F53: Frais bancaires & financiers
A54: 46036 | B54: 2844724 | C54: PRELEVEMENT SEPA | D54: CABINET SAS DARAN | E54: -504 | F54: Comptabilité / expert-comptable
A55: 46036 | B55: 1020984 | C55: CARTE | D55: APPLE | E55: -3.99 | F55: Téléphone / Internet / Logiciels
A56: 46037 | B56: 2844470 | C56: PRELEVEMENT SEPA | D56: ORANGE SA | E56: -248.34 | F56: Téléphone / Internet / Logiciels
A57: 46037 | B57: 6015218 | C57: CARTE | D57: MCDONALD'S | E57: -12.89 | F57: Restauration
A58: 46037 | B58: 2083600 | C58: CARTE | D58: TOTAL | E58: -76.23 | F58: Carburant, péages, parking, leasing
A59: 46037 | B59: 2037013 | C59: COTISATION BRED GARANTIE HOMME CLE | E59: -7.69 | F59: Frais bancaires & financiers
A60: 46038 | B60: 2847589 | C60: VIREMENT SEPA RECU | D60: STRIPE | E60: 19.44 | F60: Encaissement (hors périmètre charges)
A61: 46038 | B61: 9003285 | C61: VIREMENT SEPA EMIS | D61: FRANCE CONDITIONNEMENT PARFUM | E61: -13243.6 | F61: Usine de conditionnement et macération
A62: 46038 | B62: 2848080 | C62: VIREMENT SEPA RECU | D62: UZDAROJI AKCINE BENDROVE "VILARTINA" | E62: 6186 | F62: Encaissement (hors périmètre charges)
A63: 46038 | B63: 0066143 | C63: CARTE | D63: CHICKEN ET COMP | E63: -18 | F63: Restauration
A64: 46038 | B64: 1040836 | C64: CARTE | D64: APPLE | E64: -22.99 | F64: Téléphone / Internet / Logiciels
A65: 46038 | B65: 2069870 | C65: CARTE | D65: SANEF | E65: -10.7 | F65: Carburant, péages, parking, leasing
A66: 46038 | B66: 2846911 | C66: PRELEVEMENT SEPA | D66: URSSAF D'ILE DE FRANCE | E66: -4947 | F66: Charges sociales & cotisations
A67: 46038 | B67: 1042875 | C67: FACTURE CB CREDIT | D67: APPLE | E67: 7.99 | F67: Téléphone / Internet / Logiciels
A68: 46038 | B68: 2069880 | C68: CARTE | D68: SANEF | E68: -10.7 | F68: Carburant, péages, parking, leasing
A69: 46038 | B69: 1040836 | C69: CARTE | D69: APPLE | E69: -7.99 | F69: Téléphone / Internet / Logiciels
A70: 46041 | B70: 2099451 | C70: CARTE | D70: COFIROUTE | E70: -19 | F70: Carburant, péages, parking, leasing
A71: 46041 | B71: 2019543 | C71: CARTE | D71: PARK CASINO ROS | E71: -4.4 | F71: Carburant, péages, parking, leasing
... A127: 46052 | B127: 9100040 | C127: FACTURE CB CREDIT | D127: EMIRATES | E127: 796.93 | F127: Voyages / déplacements
A128: 46052 | B128: 1975630 | C128: FRAIS DE CHANGE | E128: -21.5 | F128: Frais bancaires & financiers
A129: 46052 | B129: 9006537 | C129: VIREMENT SEPA EMIS | D129: MR BOUDJADA MOUNIR | E129: -1233.82 | F129: Salaires (salariés)
A130: 46052 | B130: 9006560 | C130: VIREMENT SEPA EMIS | D130: MME MACHADO NATALI | E130: -1287.51 | F130: Salaires (salariés)
A131: 46052 | B131: 1975630 | C131: FRAIS BANQUE ETRANGERE | D131: (DONT HORS TAXE E.24,00 TVA TAUX 20,00 % E.4,80) | E131: -28.8 | F131: Frais bancaires & financiers
A132: 46052 | B132: 3490961 | C132: CARTE | D132: GRAINE DU SUD | E132: -25.5 | F132: Frais professionnels divers
A133: 46052 | B133: 1975630 | C133: FRAIS VIREMENT INTERNATIONAL | D133: (DONT HORS TAXE E.18,00 TVA TAUX 20,00 % E.3,60) | E133: -21.6 | F133: Frais bancaires & financiers
A134: 46052 | B134: 9006520 | C134: VIREMENT SEPA EMIS | D134: MR BOUDAJA NASSIM | E134: -2465.38 | F134: Salaires (salariés)
A135: 46055 | B135: 2856494 | C135: PRELEVEMENT SEPA | D135: TOTALENERGIES ELECTRICITE ET GAZ FRANCE | E135: -1082.33 | F135: Électricité / Gaz
