Workbook

Sheet Résumé
A1: Récapitulatif des charges — Compte BRED EJ 2025
A2: Période couverte : 02/01/2025 au 31/12/2025 — 1396 opérations (année complète)
A4: Total encaissements | B4: =SUMIF(Détail!F:F,"Encaissement*",Détail!E:E) -> 1518357.5
A5: Total charges (hors encaissements, hors chèques/non classé à vérifier) | B5: =SUMIFS(Détail!E:E,Détail!F:F,"<>Encaissement (hors périmètre charges)",Détail!F:F,"<>Paiement par chèque (à vérifier)",Détail!F:F,"<>Non classé / à vérifier",Détail!F:F,"<>Saisie administrative") -> -1498281.5
A6: Solde net (encaissements + charges + à vérifier) | B6: =SUMIF(Détail!F:F,"<>",Détail!E:E) -> 20075.96
A8: Détail par catégorie de charge
A9: Catégorie | B9: Nb opérations | C9: Montant total (€) | D9: % du total charges
A10: Fournisseurs matières premières & emballage (France) | B10: =COUNTIF(Détail!F:F,A10) -> 40 | C10: =SUMIF(Détail!F:F,A10,Détail!E:E) -> -509820.77 | D10: =C10/$B$5 -> 0.34027035
A11: Usine de conditionnement et macération | B11: =COUNTIF(Détail!F:F,A11) -> 26 | C11: =SUMIF(Détail!F:F,A11,Détail!E:E) -> -317174.39 | D11: =C11/$B$5 -> 0.21169212
A12: Fournisseurs internationaux (Chine/Import) | B12: =COUNTIF(Détail!F:F,A12) -> 24 | C12: =SUMIF(Détail!F:F,A12,Détail!E:E) -> -297383.41 | D12: =C12/$B$5 -> 0.198483
A13: Transport / livraison (colis, courrier) | B13: =COUNTIF(Détail!F:F,A13) -> 52 | C13: =SUMIF(Détail!F:F,A13,Détail!E:E) -> -81550.38 | D13: =C13/$B$5 -> 0.054429277
A14: Salaires (salariés) | B14: =COUNTIF(Détail!F:F,A14) -> 47 | C14: =SUMIF(Détail!F:F,A14,Détail!E:E) -> -74079.75 | D14: =C14/$B$5 -> 0.049443145
A15: Charges sociales & cotisations | B15: =COUNTIF(Détail!F:F,A15) -> 51 | C15: =SUMIF(Détail!F:F,A15,Détail!E:E) -> -44915.46 | D15: =C15/$B$5 -> 0.029977984
A16: Rémunération gérant | B16: =COUNTIF(Détail!F:F,A16) -> 13 | C16: =SUMIF(Détail!F:F,A16,Détail!E:E) -> -48500 | D16: =C16/$B$5 -> 0.032370419
A17: Frais professionnels divers | B17: =COUNTIF(Détail!F:F,A17) -> 88 | C17: =SUMIF(Détail!F:F,A17,Détail!E:E) -> -29712.26 | D17: =C17/$B$5 -> 0.019830893
A18: Voyages / déplacements | B18: =COUNTIF(Détail!F:F,A18) -> 67 | C18: =SUMIF(Détail!F:F,A18,Détail!E:E) -> -20990.53 | D18: =C18/$B$5 -> 0.014009737
A19: Carburant, péages, parking, leasing | B19: =COUNTIF(Détail!F:F,A19) -> 308 | C19: =SUMIF(Détail!F:F,A19,Détail!E:E) -> -20090.51 | D19: =C19/$B$5 -> 0.013409035
A20: Téléphone / Internet / Logiciels | B20: =COUNTIF(Détail!F:F,A20) -> 112 | C20: =SUMIF(Détail!F:F,A20,Détail!E:E) -> -11539.97 | D20: =C20/$B$5 -> 0.0077021373
A21: Commission vendeur | B21: =COUNTIF(Détail!F:F,A21) -> 1 | C21: =SUMIF(Détail!F:F,A21,Détail!E:E) -> -9359.1 | D21: =C21/$B$5 -> 0.0062465564
... A32: Prêt professionnel | B32: =COUNTIF(Détail!F:F,A32) -> 8 | C32: =SUMIF(Détail!F:F,A32,Détail!E:E) -> -230.88 | D32: =C32/$B$5 -> 0.00015409654
A33: TOTAL | B33: =SUM(B10:B32) -> 1307 | C33: =SUM(C10:C32) -> -1498281.5
A35: 🟠 En orange : catégories pas encore validées avec Mounir (à vérifier)

Sheet Revenus
A1: Revenus — Compte BRED EJ 2025
A2: Période couverte : 08/01/2025 au 30/12/2025 — 89 encaissements
A4: Total encaissements | B4: =SUM('Détail Revenus'!E:E) -> 1518357.5
A6: Détail par source de revenu
A7: Source | B7: Nb opérations | C7: Montant total (€) | D7: % du total
A8: NB Evolution FZCO (factures NB...) | B8: =COUNTIF('Détail Revenus'!F:F,A8) -> 24 | C8: =SUMIF('Détail Revenus'!F:F,A8,'Détail Revenus'!E:E) -> 741899.27 | D8: =C8/$B$4 -> 0.48861963
A9: Usine Algérie (Jade Création — sans marge) | B9: =COUNTIF('Détail Revenus'!F:F,A9) -> 5 | C9: =SUMIF('Détail Revenus'!F:F,A9,'Détail Revenus'!E:E) -> 350326.07 | D9: =C9/$B$4 -> 0.230727
A10: Encaissements non identifiés | B10: =COUNTIF('Détail Revenus'!F:F,A10) -> 0 | C10: =SUMIF('Détail Revenus'!F:F,A10,'Détail Revenus'!E:E) -> 0 | D10: =C10/$B$4 -> 0
A11: Arzum Group Mmc | B11: =COUNTIF('Détail Revenus'!F:F,A11) -> 6 | C11: =SUMIF('Détail Revenus'!F:F,A11,'Détail Revenus'!E:E) -> 88829 | D11: =C11/$B$4 -> 0.058503351
A12: Al Muftah | B12: =COUNTIF('Détail Revenus'!F:F,A12) -> 4 | C12: =SUMIF('Détail Revenus'!F:F,A12,'Détail Revenus'!E:E) -> 67324.2 | D12: =C12/$B$4 -> 0.044340151
A13: Al Fawanis Company | B13: =COUNTIF('Détail Revenus'!F:F,A13) -> 2 | C13: =SUMIF('Détail Revenus'!F:F,A13,'Détail Revenus'!E:E) -> 45195.4 | D13: =C13/$B$4 -> 0.029765981
A14: Chaloub Trading | B14: =COUNTIF('Détail Revenus'!F:F,A14) -> 4 | C14: =SUMIF('Détail Revenus'!F:F,A14,'Détail Revenus'!E:E) -> 21372 | D14: =C14/$B$4 -> 0.014075737
A15: Dv Menswear | B15: =COUNTIF('Détail Revenus'!F:F,A15) -> 3 | C15: =SUMIF('Détail Revenus'!F:F,A15,'Détail Revenus'!E:E) -> 14076.41 | D15: =C15/$B$4 -> 0.0092708141
A16: Khiyat Cospara | B16: =COUNTIF('Détail Revenus'!F:F,A16) -> 1 | C16: =SUMIF('Détail Revenus'!F:F,A16,'Détail Revenus'!E:E) -> 6460.8 | D16: =C16/$B$4 -> 0.0042551244
A17: Cielomed | B17: =COUNTIF('Détail Revenus'!F:F,A17) -> 1 | C17: =SUMIF('Détail Revenus'!F:F,A17,'Détail Revenus'!E:E) -> 6254 | D17: =C17/$B$4 -> 0.0041189246
A18: Passion Parfum | B18: =COUNTIF('Détail Revenus'!F:F,A18) -> 2 | C18: =SUMIF('Détail Revenus'!F:F,A18,'Détail Revenus'!E:E) -> 6224 | D18: =C18/$B$4 -> 0.0040991664
A19: Davidson Distributors Llc | B19: =COUNTIF('Détail Revenus'!F:F,A19) -> 2 | C19: =SUMIF('Détail Revenus'!F:F,A19,'Détail Revenus'!E:E) -> 3943 | D19: =C19/$B$4 -> 0.0025968852
... A28: Créance 2024 encaissée en 2025 (Usine Algérie) | B28: =COUNTIF('Détail Revenus'!F:F,A28) -> 1 | C28: =SUMIF('Détail Revenus'!F:F,A28,'Détail Revenus'!E:E) -> 95044 | D28: =C28/$B$4 -> 0.06259659
A29: TOTAL | B29: =SUM(B8:B28) -> 89 | C29: =SUM(C8:C28) -> 1518357.5
A31: 🟠 En orange : sources pas encore confirmées avec Mounir

Sheet Revenus détail
A1: Revenus — détail par source et par mois (2025)
A3: NB Evolution FZCO (factures NB...) | C3: =SUMIF('Détail Revenus'!$F:$F,"NB Evolution FZCO (factures NB...)",'Détail Revenus'!$E:$E) -> 741899.27
A4: Mois | B4: Montant
A5: Janvier 2025 | B5: =SUMIFS('Détail Revenus'!$E:$E,'Détail Revenus'!$F:$F,"NB Evolution FZCO (factures NB...)",'Détail Revenus'!$A:$A,">="&DATE(2025,1,1),'Détail Revenus'!$A:$A,"<"&EDATE(DATE(2025,1,1),1)) -> 44118.93
A6: Février 2025 | B6: =SUMIFS('Détail Revenus'!$E:$E,'Détail Revenus'!$F:$F,"NB Evolution FZCO (factures NB...)",'Détail Revenus'!$A:$A,">="&DATE(2025,2,1),'Détail Revenus'!$A:$A,"<"&EDATE(DATE(2025,2,1),1)) -> 35000
A7: Mars 2025 | B7: =SUMIFS('Détail Revenus'!$E:$E,'Détail Revenus'!$F:$F,"NB Evolution FZCO (factures NB...)",'Détail Revenus'!$A:$A,">="&DATE(2025,3,1),'Détail Revenus'!$A:$A,"<"&EDATE(DATE(2025,3,1),1)) -> 60000
A8: Avril 2025 | B8: =SUMIFS('Détail Revenus'!$E:$E,'Détail Revenus'!$F:$F,"NB Evolution FZCO (factures NB...)",'Détail Revenus'!$A:$A,">="&DATE(2025,4,1),'Détail Revenus'!$A:$A,"<"&EDATE(DATE(2025,4,1),1)) -> 88852
A9: Mai 2025 | B9: =SUMIFS('Détail Revenus'!$E:$E,'Détail Revenus'!$F:$F,"NB Evolution FZCO (factures NB...)",'Détail Revenus'!$A:$A,">="&DATE(2025,5,1),'Détail Revenus'!$A:$A,"<"&EDATE(DATE(2025,5,1),1)) -> 101000
A10: Juin 2025 | B10: =SUMIFS('Détail Revenus'!$E:$E,'Détail Revenus'!$F:$F,"NB Evolution FZCO (factures NB...)",'Détail Revenus'!$A:$A,">="&DATE(2025,6,1),'Détail Revenus'!$A:$A,"<"&EDATE(DATE(2025,6,1),1)) -> 89169.04
A11: Juillet 2025 | B11: =SUMIFS('Détail Revenus'!$E:$E,'Détail Revenus'!$F:$F,"NB Evolution FZCO (factures NB...)",'Détail Revenus'!$A:$A,">="&DATE(2025,7,1),'Détail Revenus'!$A:$A,"<"&EDATE(DATE(2025,7,1),1)) -> 98080
A12: Août 2025 | B12: =SUMIFS('Détail Revenus'!$E:$E,'Détail Revenus'!$F:$F,"NB Evolution FZCO (factures NB...)",'Détail Revenus'!$A:$A,">="&DATE(2025,8,1),'Détail Revenus'!$A:$A,"<"&EDATE(DATE(2025,8,1),1)) -> 0
A13: Septembre 2025 | B13: =SUMIFS('Détail Revenus'!$E:$E,'Détail Revenus'!$F:$F,"NB Evolution FZCO (factures NB...)",'Détail Revenus'!$A:$A,">="&DATE(2025,9,1),'Détail Revenus'!$A:$A,"<"&EDATE(DATE(2025,9,1),1)) -> 0
A14: Octobre 2025 | B14: =SUMIFS('Détail Revenus'!$E:$E,'Détail Revenus'!$F:$F,"NB Evolution FZCO (factures NB...)",'Détail Revenus'!$A:$A,">="&DATE(2025,10,1),'Détail Revenus'!$A:$A,"<"&EDATE(DATE(2025,10,1),1)) -> 76279.3
A15: Novembre 2025 | B15: =SUMIFS('Détail Revenus'!$E:$E,'Détail Revenus'!$F:$F,"NB Evolution FZCO (factures NB...)",'Détail Revenus'!$A:$A,">="&DATE(2025,11,1),'Détail Revenus'!$A:$A,"<"&EDATE(DATE(2025,11,1),1)) -> 0
A16: Décembre 2025 | B16: =SUMIFS('Détail Revenus'!$E:$E,'Détail Revenus'!$F:$F,"NB Evolution FZCO (factures NB...)",'Détail Revenus'!$A:$A,">="&DATE(2025,12,1),'Détail Revenus'!$A:$A,"<"&EDATE(DATE(2025,12,1),1)) -> 149400
A19: Usine Algérie (Jade Création — sans marge) | C19: =SUMIF('Détail Revenus'!$F:$F,"Usine Algérie (Jade Création — sans marge)",'Détail Revenus'!$E:$E) -> 350326.07
A20: Noms bancaires d'origine : | B20: SARL JADE CREATION SALGDZALXXX, SARL JADE CREATION SALGDZALXXX SALGDZALXXX
A21: Mois | B21: Montant
A22: Janvier 2025 | B22: =SUMIFS('Détail Revenus'!$E:$E,'Détail Revenus'!$F:$F,"Usine Algérie (Jade Création — sans marge)",'Détail Revenus'!$A:$A,">="&DATE(2025,1,1),'Détail Revenus'!$A:$A,"<"&EDATE(DATE(2025,1,1),1)) -> 0
A23: Février 2025 | B23: =SUMIFS('Détail Revenus'!$E:$E,'Détail Revenus'!$F:$F,"Usine Algérie (Jade Création — sans marge)",'Détail Revenus'!$A:$A,">="&DATE(2025,2,1),'Détail Revenus'!$A:$A,"<"&EDATE(DATE(2025,2,1),1)) -> 0
A24: Mars 2025 | B24: =SUMIFS('Détail Revenus'!$E:$E,'Détail Revenus'!$F:$F,"Usine Algérie (Jade Création — sans marge)",'Détail Revenus'!$A:$A,">="&DATE(2025,3,1),'Détail Revenus'!$A:$A,"<"&EDATE(DATE(2025,3,1),1)) -> 0
A25: Avril 2025 | B25: =SUMIFS('Détail Revenus'!$E:$E,'Détail Revenus'!$F:$F,"Usine Algérie (Jade Création — sans marge)",'Détail Revenus'!$A:$A,">="&DATE(2025,4,1),'Détail Revenus'!$A:$A,"<"&EDATE(DATE(2025,4,1),1)) -> 27129.32
A26: Mai 2025 | B26: =SUMIFS('Détail Revenus'!$E:$E,'Détail Revenus'!$F:$F,"Usine Algérie (Jade Création — sans marge)",'Détail Revenus'!$A:$A,">="&DATE(2025,5,1),'Détail Revenus'!$A:$A,"<"&EDATE(DATE(2025,5,1),1)) -> 0
A27: Juin 2025 | B27: =SUMIFS('Détail Revenus'!$E:$E,'Détail Revenus'!$F:$F,"Usine Algérie (Jade Création — sans marge)",'Détail Revenus'!$A:$A,">="&DATE(2025,6,1),'Détail Revenus'!$A:$A,"<"&EDATE(DATE(2025,6,1),1)) -> 0
A28: Juillet 2025 | B28: =SUMIFS('Détail Revenus'!$E:$E,'Détail Revenus'!$F:$F,"Usine Algérie (Jade Création — sans marge)",'Détail Revenus'!$A:$A,">="&DATE(2025,7,1),'Détail Revenus'!$A:$A,"<"&EDATE(DATE(2025,7,1),1)) -> 57046
A29: Août 2025 | B29: =SUMIFS('Détail Revenus'!$E:$E,'Détail Revenus'!$F:$F,"Usine Algérie (Jade Création — sans marge)",'Détail Revenus'!$A:$A,">="&DATE(2025,8,1),'Détail Revenus'!$A:$A,"<"&EDATE(DATE(2025,8,1),1)) -> 120449.68
A30: Septembre 2025 | B30: =SUMIFS('Détail Revenus'!$E:$E,'Détail Revenus'!$F:$F,"Usine Algérie (Jade Création — sans marge)",'Détail Revenus'!$A:$A,">="&DATE(2025,9,1),'Détail Revenus'!$A:$A,"<"&EDATE(DATE(2025,9,1),1)) -> 0
A31: Octobre 2025 | B31: =SUMIFS('Détail Revenus'!$E:$E,'Détail Revenus'!$F:$F,"Usine Algérie (Jade Création — sans marge)",'Détail Revenus'!$A:$A,">="&DATE(2025,10,1),'Détail Revenus'!$A:$A,"<"&EDATE(DATE(2025,10,1),1)) -> 132807.4
A32: Novembre 2025 | B32: =SUMIFS('Détail Revenus'!$E:$E,'Détail Revenus'!$F:$F,"Usine Algérie (Jade Création — sans marge)",'Détail Revenus'!$A:$A,">="&DATE(2025,11,1),'Détail Revenus'!$A:$A,"<"&EDATE(DATE(2025,11,1),1)) -> 12893.67
A33: Décembre 2025 | B33: =SUMIFS('Détail Revenus'!$E:$E,'Détail Revenus'!$F:$F,"Usine Algérie (Jade Création — sans marge)",'Détail Revenus'!$A:$A,">="&DATE(2025,12,1),'Détail Revenus'!$A:$A,"<"&EDATE(DATE(2025,12,1),1)) -> 0
A36: Encaissements non identifiés | C36: =SUMIF('Détail Revenus'!$F:$F,"Encaissements non identifiés",'Détail Revenus'!$E:$E) -> 0
A37: Noms bancaires d'origine : | B37: SIE MARNE ET BOIS, (sans libellé), PERFUMEPARADISE APS, ASOL ALDEAR CO, AKKONA SPOLKA Z OGRANICZONA ODPOWIEDZIALNOSCIA, SMART UK BRANDS LTD 167-169 5TH FLO, RAS TRANSPORT
A38: Mois | B38: Montant
A39: Janvier 2025 | B39: =SUMIFS('Détail Revenus'!$E:$E,'Détail Revenus'!$F:$F,"Encaissements non identifiés",'Détail Revenus'!$A:$A,">="&DATE(2025,1,1),'Détail Revenus'!$A:$A,"<"&EDATE(DATE(2025,1,1),1)) -> 0
A40: Février 2025 | B40: =SUMIFS('Détail Revenus'!$E:$E,'Détail Revenus'!$F:$F,"Encaissements non identifiés",'Détail Revenus'!$A:$A,">="&DATE(2025,2,1),'Détail Revenus'!$A:$A,"<"&EDATE(DATE(2025,2,1),1)) -> 0
A41: Mars 2025 | B41: =SUMIFS('Détail Revenus'!$E:$E,'Détail Revenus'!$F:$F,"Encaissements non identifiés",'Détail Revenus'!$A:$A,">="&DATE(2025,3,1),'Détail Revenus'!$A:$A,"<"&EDATE(DATE(2025,3,1),1)) -> 0
A42: Avril 2025 | B42: =SUMIFS('Détail Revenus'!$E:$E,'Détail Revenus'!$F:$F,"Encaissements non identifiés",'Détail Revenus'!$A:$A,">="&DATE(2025,4,1),'Détail Revenus'!$A:$A,"<"&EDATE(DATE(2025,4,1),1)) -> 0
A43: Mai 2025 | B43: =SUMIFS('Détail Revenus'!$E:$E,'Détail Revenus'!$F:$F,"Encaissements non identifiés",'Détail Revenus'!$A:$A,">="&DATE(2025,5,1),'Détail Revenus'!$A:$A,"<"&EDATE(DATE(2025,5,1),1)) -> 0
A44: Juin 2025 | B44: =SUMIFS('Détail Revenus'!$E:$E,'Détail Revenus'!$F:$F,"Encaissements non identifiés",'Détail Revenus'!$A:$A,">="&DATE(2025,6,1),'Détail Revenus'!$A:$A,"<"&EDATE(DATE(2025,6,1),1)) -> 0
A45: Juillet 2025 | B45: =SUMIFS('Détail Revenus'!$E:$E,'Détail Revenus'!$F:$F,"Encaissements non identifiés",'Détail Revenus'!$A:$A,">="&DATE(2025,7,1),'Détail Revenus'!$A:$A,"<"&EDATE(DATE(2025,7,1),1)) -> 0
A46: Août 2025 | B46: =SUMIFS('Détail Revenus'!$E:$E,'Détail Revenus'!$F:$F,"Encaissements non identifiés",'Détail Revenus'!$A:$A,">="&DATE(2025,8,1),'Détail Revenus'!$A:$A,"<"&EDATE(DATE(2025,8,1),1)) -> 0
A47: Septembre 2025 | B47: =SUMIFS('Détail Revenus'!$E:$E,'Détail Revenus'!$F:$F,"Encaissements non identifiés",'Détail Revenus'!$A:$A,">="&DATE(2025,9,1),'Détail Revenus'!$A:$A,"<"&EDATE(DATE(2025,9,1),1)) -> 0
A48: Octobre 2025 | B48: =SUMIFS('Détail Revenus'!$E:$E,'Détail Revenus'!$F:$F,"Encaissements non identifiés",'Détail Revenus'!$A:$A,">="&DATE(2025,10,1),'Détail Revenus'!$A:$A,"<"&EDATE(DATE(2025,10,1),1)) -> 0
A49: Novembre 2025 | B49: =SUMIFS('Détail Revenus'!$E:$E,'Détail Revenus'!$F:$F,"Encaissements non identifiés",'Détail Revenus'!$A:$A,">="&DATE(2025,11,1),'Détail Revenus'!$A:$A,"<"&EDATE(DATE(2025,11,1),1)) -> 0
A50: Décembre 2025 | B50: =SUMIFS('Détail Revenus'!$E:$E,'Détail Revenus'!$F:$F,"Encaissements non identifiés",'Détail Revenus'!$A:$A,">="&DATE(2025,12,1),'Détail Revenus'!$A:$A,"<"&EDATE(DATE(2025,12,1),1)) -> 0
A53: Arzum Group Mmc | C53: =SUMIF('Détail Revenus'!$F:$F,"Arzum Group Mmc",'Détail Revenus'!$E:$E) -> 88829
A54: Noms bancaires d'origine : | B54: ARZUM GROUP, ARZUM GROUP MMC, TAX ID 2007973391 ARZUM GROUP MMC
A55: Mois | B55: Montant
A56: Janvier 2025 | B56: =SUMIFS('Détail Revenus'!$E:$E,'Détail Revenus'!$F:$F,"Arzum Group Mmc",'Détail Revenus'!$A:$A,">="&DATE(2025,1,1),'Détail Revenus'!$A:$A,"<"&EDATE(DATE(2025,1,1),1)) -> 23001
A57: Février 2025 | B57: =SUMIFS('Détail Revenus'!$E:$E,'Détail Revenus'!$F:$F,"Arzum Group Mmc",'Détail Revenus'!$A:$A,">="&DATE(2025,2,1),'Détail Revenus'!$A:$A,"<"&EDATE(DATE(2025,2,1),1)) -> 0
A58: Mars 2025 | B58: =SUMIFS('Détail Revenus'!$E:$E,'Détail Revenus'!$F:$F,"Arzum Group Mmc",'Détail Revenus'!$A:$A,">="&DATE(2025,3,1),'Détail Revenus'!$A:$A,"<"&EDATE(DATE(2025,3,1),1)) -> 20590
A59: Avril 2025 | B59: =SUMIFS('Détail Revenus'!$E:$E,'Détail Revenus'!$F:$F,"Arzum Group Mmc",'Détail Revenus'!$A:$A,">="&DATE(2025,4,1),'Détail Revenus'!$A:$A,"<"&EDATE(DATE(2025,4,1),1)) -> 0
A60: Mai 2025 | B60: =SUMIFS('Détail Revenus'!$E:$E,'Détail Revenus'!$F:$F,"Arzum Group Mmc",'Détail Revenus'!$A:$A,">="&DATE(2025,5,1),'Détail Revenus'!$A:$A,"<"&EDATE(DATE(2025,5,1),1)) -> 0
A61: Juin 2025 | B61: =SUMIFS('Détail Revenus'!$E:$E,'Détail Revenus'!$F:$F,"Arzum Group Mmc",'Détail Revenus'!$A:$A,">="&DATE(2025,6,1),'Détail Revenus'!$A:$A,"<"&EDATE(DATE(2025,6,1),1)) -> 0
A62: Juillet 2025 | B62: =SUMIFS('Détail Revenus'!$E:$E,'Détail Revenus'!$F:$F,"Arzum Group Mmc",'Détail Revenus'!$A:$A,">="&DATE(2025,7,1),'Détail Revenus'!$A:$A,"<"&EDATE(DATE(2025,7,1),1)) -> 15303
A63: Août 2025 | B63: =SUMIFS('Détail Revenus'!$E:$E,'Détail Revenus'!$F:$F,"Arzum Group Mmc",'Détail Revenus'!$A:$A,">="&DATE(2025,8,1),'Détail Revenus'!$A:$A,"<"&EDATE(DATE(2025,8,1),1)) -> 0
A64: Septembre 2025 | B64: =SUMIFS('Détail Revenus'!$E:$E,'Détail Revenus'!$F:$F,"Arzum Group Mmc",'Détail Revenus'!$A:$A,">="&DATE(2025,9,1),'Détail Revenus'!$A:$A,"<"&EDATE(DATE(2025,9,1),1)) -> 0
A65: Octobre 2025 | B65: =SUMIFS('Détail Revenus'!$E:$E,'Détail Revenus'!$F:$F,"Arzum Group Mmc",'Détail Revenus'!$A:$A,">="&DATE(2025,10,1),'Détail Revenus'!$A:$A,"<"&EDATE(DATE(2025,10,1),1)) -> 0
A66: Novembre 2025 | B66: =SUMIFS('Détail Revenus'!$E:$E,'Détail Revenus'!$F:$F,"Arzum Group Mmc",'Détail Revenus'!$A:$A,">="&DATE(2025,11,1),'Détail Revenus'!$A:$A,"<"&EDATE(DATE(2025,11,1),1)) -> 10000
A67: Décembre 2025 | B67: =SUMIFS('Détail Revenus'!$E:$E,'Détail Revenus'!$F:$F,"Arzum Group Mmc",'Détail Revenus'!$A:$A,">="&DATE(2025,12,1),'Détail Revenus'!$A:$A,"<"&EDATE(DATE(2025,12,1),1)) -> 19935
A70: Al Muftah | C70: =SUMIF('Détail Revenus'!$F:$F,"Al Muftah",'Détail Revenus'!$E:$E) -> 67324.2
A71: Noms bancaires d'origine : | B71: ALMUFTAH MARKETING, ALMUFTAH TRADING AND CONTRACTING
A72: Mois | B72: Montant
A73: Janvier 2025 | B73: =SUMIFS('Détail Revenus'!$E:$E,'Détail Revenus'!$F:$F,"Al Muftah",'Détail Revenus'!$A:$A,">="&DATE(2025,1,1),'Détail Revenus'!$A:$A,"<"&EDATE(DATE(2025,1,1),1)) -> 0
A74: Février 2025 | B74: =SUMIFS('Détail Revenus'!$E:$E,'Détail Revenus'!$F:$F,"Al Muftah",'Détail Revenus'!$A:$A,">="&DATE(2025,2,1),'Détail Revenus'!$A:$A,"<"&EDATE(DATE(2025,2,1),1)) -> 0
A75: Mars 2025 | B75: =SUMIFS('Détail Revenus'!$E:$E,'Détail Revenus'!$F:$F,"Al Muftah",'Détail Revenus'!$A:$A,">="&DATE(2025,3,1),'Détail Revenus'!$A:$A,"<"&EDATE(DATE(2025,3,1),1)) -> 19024.3
A76: Avril 2025 | B76: =SUMIFS('Détail Revenus'!$E:$E,'Détail Revenus'!$F:$F,"Al Muftah",'Détail Revenus'!$A:$A,">="&DATE(2025,4,1),'Détail Revenus'!$A:$A,"<"&EDATE(DATE(2025,4,1),1)) -> 0
A77: Mai 2025 | B77: =SUMIFS('Détail Revenus'!$E:$E,'Détail Revenus'!$F:$F,"Al Muftah",'Détail Revenus'!$A:$A,">="&DATE(2025,5,1),'Détail Revenus'!$A:$A,"<"&EDATE(DATE(2025,5,1),1)) -> 0
A78: Juin 2025 | B78: =SUMIFS('Détail Revenus'!$E:$E,'Détail Revenus'!$F:$F,"Al Muftah",'Détail Revenus'!$A:$A,">="&DATE(2025,6,1),'Détail Revenus'!$A:$A,"<"&EDATE(DATE(2025,6,1),1)) -> 25918.15
A79: Juillet 2025 | B79: =SUMIFS('Détail Revenus'!$E:$E,'Détail Revenus'!$F:$F,"Al Muftah",'Détail Revenus'!$A:$A,">="&DATE(2025,7,1),'Détail Revenus'!$A:$A,"<"&EDATE(DATE(2025,7,1),1)) -> 0
A80: Août 2025 | B80: =SUMIFS('Détail Revenus'!$E:$E,'Détail Revenus'!$F:$F,"Al Muftah",'Détail Revenus'!$A:$A,">="&DATE(2025,8,1),'Détail Revenus'!$A:$A,"<"&EDATE(DATE(2025,8,1),1)) -> 0
A81: Septembre 2025 | B81: =SUMIFS('Détail Revenus'!$E:$E,'Détail Revenus'!$F:$F,"Al Muftah",'Détail Revenus'!$A:$A,">="&DATE(2025,9,1),'Détail Revenus'!$A:$A,"<"&EDATE(DATE(2025,9,1),1)) -> 22381.75
A82: Octobre 2025 | B82: =SUMIFS('Détail Revenus'!$E:$E,'Détail Revenus'!$F:$F,"Al Muftah",'Détail Revenus'!$A:$A,">="&DATE(2025,10,1),'Détail Revenus'!$A:$A,"<"&EDATE(DATE(2025,10,1),1)) -> 0
A83: Novembre 2025 | B83: =SUMIFS('Détail Revenus'!$E:$E,'Détail Revenus'!$F:$F,"Al Muftah",'Détail Revenus'!$A:$A,">="&DATE(2025,11,1),'Détail Revenus'!$A:$A,"<"&EDATE(DATE(2025,11,1),1)) -> 0
A84: Décembre 2025 | B84: =SUMIFS('Détail Revenus'!$E:$E,'Détail Revenus'!$F:$F,"Al Muftah",'Détail Revenus'!$A:$A,">="&DATE(2025,12,1),'Détail Revenus'!$A:$A,"<"&EDATE(DATE(2025,12,1),1)) -> 0
A87: Al Fawanis Company | C87: =SUMIF('Détail Revenus'!$F:$F,"Al Fawanis Company",'Détail Revenus'!$E:$E) -> 45195.4
A88: Mois | B88: Montant
A89: Janvier 2025 | B89: =SUMIFS('Détail Revenus'!$E:$E,'Détail Revenus'!$F:$F,"Al Fawanis Company",'Détail Revenus'!$A:$A,">="&DATE(2025,1,1),'Détail Revenus'!$A:$A,"<"&EDATE(DATE(2025,1,1),1)) -> 0
A90: Février 2025 | B90: =SUMIFS('Détail Revenus'!$E:$E,'Détail Revenus'!$F:$F,"Al Fawanis Company",'Détail Revenus'!$A:$A,">="&DATE(2025,2,1),'Détail Revenus'!$A:$A,"<"&EDATE(DATE(2025,2,1),1)) -> 0
A91: Mars 2025 | B91: =SUMIFS('Détail Revenus'!$E:$E,'Détail Revenus'!$F:$F,"Al Fawanis Company",'Détail Revenus'!$A:$A,">="&DATE(2025,3,1),'Détail Revenus'!$A:$A,"<"&EDATE(DATE(2025,3,1),1)) -> 0
A92: Avril 2025 | B92: =SUMIFS('Détail Revenus'!$E:$E,'Détail Revenus'!$F:$F,"Al Fawanis Company",'Détail Revenus'!$A:$A,">="&DATE(2025,4,1),'Détail Revenus'!$A:$A,"<"&EDATE(DATE(2025,4,1),1)) -> 0
A93: Mai 2025 | B93: =SUMIFS('Détail Revenus'!$E:$E,'Détail Revenus'!$F:$F,"Al Fawanis Company",'Détail Revenus'!$A:$A,">="&DATE(2025,5,1),'Détail Revenus'!$A:$A,"<"&EDATE(DATE(2025,5,1),1)) -> 0
A94: Juin 2025 | B94: =SUMIFS('Détail Revenus'!$E:$E,'Détail Revenus'!$F:$F,"Al Fawanis Company",'Détail Revenus'!$A:$A,">="&DATE(2025,6,1),'Détail Revenus'!$A:$A,"<"&EDATE(DATE(2025,6,1),1)) -> 0
A95: Juillet 2025 | B95: =SUMIFS('Détail Revenus'!$E:$E,'Détail Revenus'!$F:$F,"Al Fawanis Company",'Détail Revenus'!$A:$A,">="&DATE(2025,7,1),'Détail Revenus'!$A:$A,"<"&EDATE(DATE(2025,7,1),1)) -> 0
A96: Août 2025 | B96: =SUMIFS('Détail Revenus'!$E:$E,'Détail Revenus'!$F:$F,"Al Fawanis Company",'Détail Revenus'!$A:$A,">="&DATE(2025,8,1),'Détail Revenus'!$A:$A,"<"&EDATE(DATE(2025,8,1),1)) -> 0
A97: Septembre 2025 | B97: =SUMIFS('Détail Revenus'!$E:$E,'Détail Revenus'!$F:$F,"Al Fawanis Company",'Détail Revenus'!$A:$A,">="&DATE(2025,9,1),'Détail Revenus'!$A:$A,"<"&EDATE(DATE(2025,9,1),1)) -> 22991
A98: Octobre 2025 | B98: =SUMIFS('Détail Revenus'!$E:$E,'Détail Revenus'!$F:$F,"Al Fawanis Company",'Détail Revenus'!$A:$A,">="&DATE(2025,10,1),'Détail Revenus'!$A:$A,"<"&EDATE(DATE(2025,10,1),1)) -> 22204.4
A99: Novembre 2025 | B99: =SUMIFS('Détail Revenus'!$E:$E,'Détail Revenus'!$F:$F,"Al Fawanis Company",'Détail Revenus'!$A:$A,">="&DATE(2025,11,1),'Détail Revenus'!$A:$A,"<"&EDATE(DATE(2025,11,1),1)) -> 0
A100: Décembre 2025 | B100: =SUMIFS('Détail Revenus'!$E:$E,'Détail Revenus'!$F:$F,"Al Fawanis Company",'Détail Revenus'!$A:$A,">="&DATE(2025,12,1),'Détail Revenus'!$A:$A,"<"&EDATE(DATE(2025,12,1),1)) -> 0
A103: Chaloub Trading | C103: =SUMIF('Détail Revenus'!$F:$F,"Chaloub Trading",'Détail Revenus'!$E:$E) -> 21372
A104: Noms bancaires d'origine : | B104: 1/CHALHOUB COMPANY FOR GENERAL TRA, CHALHOUB FOR GENERAL TRADING SARL
A105: Mois | B105: Montant
A106: Janvier 2025 | B106: =SUMIFS('Détail Revenus'!$E:$E,'Détail Revenus'!$F:$F,"Chaloub Trading",'Détail Revenus'!$A:$A,">="&DATE(2025,1,1),'Détail Revenus'!$A:$A,"<"&EDATE(DATE(2025,1,1),1)) -> 0
A107: Février 2025 | B107: =SUMIFS('Détail Revenus'!$E:$E,'Détail Revenus'!$F:$F,"Chaloub Trading",'Détail Revenus'!$A:$A,">="&DATE(2025,2,1),'Détail Revenus'!$A:$A,"<"&EDATE(DATE(2025,2,1),1)) -> 0
A108: Mars 2025 | B108: =SUMIFS('Détail Revenus'!$E:$E,'Détail Revenus'!$F:$F,"Chaloub Trading",'Détail Revenus'!$A:$A,">="&DATE(2025,3,1),'Détail Revenus'!$A:$A,"<"&EDATE(DATE(2025,3,1),1)) -> 5918
A109: Avril 2025 | B109: =SUMIFS('Détail Revenus'!$E:$E,'Détail Revenus'!$F:$F,"Chaloub Trading",'Détail Revenus'!$A:$A,">="&DATE(2025,4,1),'Détail Revenus'!$A:$A,"<"&EDATE(DATE(2025,4,1),1)) -> 0
A110: Mai 2025 | B110: =SUMIFS('Détail Revenus'!$E:$E,'Détail Revenus'!$F:$F,"Chaloub Trading",'Détail Revenus'!$A:$A,">="&DATE(2025,5,1),'Détail Revenus'!$A:$A,"<"&EDATE(DATE(2025,5,1),1)) -> 0
A111: Juin 2025 | B111: =SUMIFS('Détail Revenus'!$E:$E,'Détail Revenus'!$F:$F,"Chaloub Trading",'Détail Revenus'!$A:$A,">="&DATE(2025,6,1),'Détail Revenus'!$A:$A,"<"&EDATE(DATE(2025,6,1),1)) -> 0
A112: Juillet 2025 | B112: =SUMIFS('Détail Revenus'!$E:$E,'Détail Revenus'!$F:$F,"Chaloub Trading",'Détail Revenus'!$A:$A,">="&DATE(2025,7,1),'Détail Revenus'!$A:$A,"<"&EDATE(DATE(2025,7,1),1)) -> 9022
A113: Août 2025 | B113: =SUMIFS('Détail Revenus'!$E:$E,'Détail Revenus'!$F:$F,"Chaloub Trading",'Détail Revenus'!$A:$A,">="&DATE(2025,8,1),'Détail Revenus'!$A:$A,"<"&EDATE(DATE(2025,8,1),1)) -> 2558
...

Sheet Salaires détail
A1: Salaires & rémunération gérant — détail par personne (2025)
A3: Mr Boudjada Said (Gérant — rémunération libre) | C3: =SUMIF(Détail!$D:$D,"MR BOUDJADA SAID",Détail!$E:$E) -> -48500
A4: Mois | B4: Montant
A5: Janvier 2025 | B5: =SUMIFS(Détail!$E:$E,Détail!$D:$D,"MR BOUDJADA SAID",Détail!$A:$A,">="&DATE(2025,1,1),Détail!$A:$A,"<"&EDATE(DATE(2025,1,1),1)) -> -5000
A6: Février 2025 | B6: =SUMIFS(Détail!$E:$E,Détail!$D:$D,"MR BOUDJADA SAID",Détail!$A:$A,">="&DATE(2025,2,1),Détail!$A:$A,"<"&EDATE(DATE(2025,2,1),1)) -> -4000
A7: Mars 2025 | B7: =SUMIFS(Détail!$E:$E,Détail!$D:$D,"MR BOUDJADA SAID",Détail!$A:$A,">="&DATE(2025,3,1),Détail!$A:$A,"<"&EDATE(DATE(2025,3,1),1)) -> -6000
A8: Avril 2025 | B8: =SUMIFS(Détail!$E:$E,Détail!$D:$D,"MR BOUDJADA SAID",Détail!$A:$A,">="&DATE(2025,4,1),Détail!$A:$A,"<"&EDATE(DATE(2025,4,1),1)) -> -6000
A9: Mai 2025 | B9: =SUMIFS(Détail!$E:$E,Détail!$D:$D,"MR BOUDJADA SAID",Détail!$A:$A,">="&DATE(2025,5,1),Détail!$A:$A,"<"&EDATE(DATE(2025,5,1),1)) -> 0
A10: Juin 2025 | B10: =SUMIFS(Détail!$E:$E,Détail!$D:$D,"MR BOUDJADA SAID",Détail!$A:$A,">="&DATE(2025,6,1),Détail!$A:$A,"<"&EDATE(DATE(2025,6,1),1)) -> 0
A11: Juillet 2025 | B11: =SUMIFS(Détail!$E:$E,Détail!$D:$D,"MR BOUDJADA SAID",Détail!$A:$A,">="&DATE(2025,7,1),Détail!$A:$A,"<"&EDATE(DATE(2025,7,1),1)) -> -8500
A12: Août 2025 | B12: =SUMIFS(Détail!$E:$E,Détail!$D:$D,"MR BOUDJADA SAID",Détail!$A:$A,">="&DATE(2025,8,1),Détail!$A:$A,"<"&EDATE(DATE(2025,8,1),1)) -> -5000
A13: Septembre 2025 | B13: =SUMIFS(Détail!$E:$E,Détail!$D:$D,"MR BOUDJADA SAID",Détail!$A:$A,">="&DATE(2025,9,1),Détail!$A:$A,"<"&EDATE(DATE(2025,9,1),1)) -> -6000
A14: Octobre 2025 | B14: =SUMIFS(Détail!$E:$E,Détail!$D:$D,"MR BOUDJADA SAID",Détail!$A:$A,">="&DATE(2025,10,1),Détail!$A:$A,"<"&EDATE(DATE(2025,10,1),1)) -> -5000
A15: Novembre 2025 | B15: =SUMIFS(Détail!$E:$E,Détail!$D:$D,"MR BOUDJADA SAID",Détail!$A:$A,">="&DATE(2025,11,1),Détail!$A:$A,"<"&EDATE(DATE(2025,11,1),1)) -> -3000
A16: Décembre 2025 | B16: =SUMIFS(Détail!$E:$E,Détail!$D:$D,"MR BOUDJADA SAID",Détail!$A:$A,">="&DATE(2025,12,1),Détail!$A:$A,"<"&EDATE(DATE(2025,12,1),1)) -> 0
A19: Mr Boudaja Nassim (Salarié) | C19: =SUMIF(Détail!$D:$D,"MR BOUDAJA NASSIM",Détail!$E:$E) -> -29984.91
A20: Mois | B20: Montant
A21: Janvier 2025 | B21: =SUMIFS(Détail!$E:$E,Détail!$D:$D,"MR BOUDAJA NASSIM",Détail!$A:$A,">="&DATE(2025,1,1),Détail!$A:$A,"<"&EDATE(DATE(2025,1,1),1)) -> 0
A22: Février 2025 | B22: =SUMIFS(Détail!$E:$E,Détail!$D:$D,"MR BOUDAJA NASSIM",Détail!$A:$A,">="&DATE(2025,2,1),Détail!$A:$A,"<"&EDATE(DATE(2025,2,1),1)) -> -4720.82
A23: Mars 2025 | B23: =SUMIFS(Détail!$E:$E,Détail!$D:$D,"MR BOUDAJA NASSIM",Détail!$A:$A,">="&DATE(2025,3,1),Détail!$A:$A,"<"&EDATE(DATE(2025,3,1),1)) -> -1984.55
A24: Avril 2025 | B24: =SUMIFS(Détail!$E:$E,Détail!$D:$D,"MR BOUDAJA NASSIM",Détail!$A:$A,">="&DATE(2025,4,1),Détail!$A:$A,"<"&EDATE(DATE(2025,4,1),1)) -> -1984.55
A25: Mai 2025 | B25: =SUMIFS(Détail!$E:$E,Détail!$D:$D,"MR BOUDAJA NASSIM",Détail!$A:$A,">="&DATE(2025,5,1),Détail!$A:$A,"<"&EDATE(DATE(2025,5,1),1)) -> -1984.55
A26: Juin 2025 | B26: =SUMIFS(Détail!$E:$E,Détail!$D:$D,"MR BOUDAJA NASSIM",Détail!$A:$A,">="&DATE(2025,6,1),Détail!$A:$A,"<"&EDATE(DATE(2025,6,1),1)) -> -2484.55
A27: Juillet 2025 | B27: =SUMIFS(Détail!$E:$E,Détail!$D:$D,"MR BOUDAJA NASSIM",Détail!$A:$A,">="&DATE(2025,7,1),Détail!$A:$A,"<"&EDATE(DATE(2025,7,1),1)) -> -2466.15
A28: Août 2025 | B28: =SUMIFS(Détail!$E:$E,Détail!$D:$D,"MR BOUDAJA NASSIM",Détail!$A:$A,">="&DATE(2025,8,1),Détail!$A:$A,"<"&EDATE(DATE(2025,8,1),1)) -> -2481.8
A29: Septembre 2025 | B29: =SUMIFS(Détail!$E:$E,Détail!$D:$D,"MR BOUDAJA NASSIM",Détail!$A:$A,">="&DATE(2025,9,1),Détail!$A:$A,"<"&EDATE(DATE(2025,9,1),1)) -> -2481.8
A30: Octobre 2025 | B30: =SUMIFS(Détail!$E:$E,Détail!$D:$D,"MR BOUDAJA NASSIM",Détail!$A:$A,">="&DATE(2025,10,1),Détail!$A:$A,"<"&EDATE(DATE(2025,10,1),1)) -> -2465.38
A31: Novembre 2025 | B31: =SUMIFS(Détail!$E:$E,Détail!$D:$D,"MR BOUDAJA NASSIM",Détail!$A:$A,">="&DATE(2025,11,1),Détail!$A:$A,"<"&EDATE(DATE(2025,11,1),1)) -> -2465.38
A32: Décembre 2025 | B32: =SUMIFS(Détail!$E:$E,Détail!$D:$D,"MR BOUDAJA NASSIM",Détail!$A:$A,">="&DATE(2025,12,1),Détail!$A:$A,"<"&EDATE(DATE(2025,12,1),1)) -> -4465.38
A35: Mr Boudjada Mounir (Salarié) | C35: =SUMIF(Détail!$D:$D,"MR BOUDJADA MOUNIR",Détail!$E:$E) -> -20959.29
A36: Mois | B36: Montant
A37: Janvier 2025 | B37: =SUMIFS(Détail!$E:$E,Détail!$D:$D,"MR BOUDJADA MOUNIR",Détail!$A:$A,">="&DATE(2025,1,1),Détail!$A:$A,"<"&EDATE(DATE(2025,1,1),1)) -> -1449.27
A38: Février 2025 | B38: =SUMIFS(Détail!$E:$E,Détail!$D:$D,"MR BOUDJADA MOUNIR",Détail!$A:$A,">="&DATE(2025,2,1),Détail!$A:$A,"<"&EDATE(DATE(2025,2,1),1)) -> -1449.27
A39: Mars 2025 | B39: =SUMIFS(Détail!$E:$E,Détail!$D:$D,"MR BOUDJADA MOUNIR",Détail!$A:$A,">="&DATE(2025,3,1),Détail!$A:$A,"<"&EDATE(DATE(2025,3,1),1)) -> -1449.27
A40: Avril 2025 | B40: =SUMIFS(Détail!$E:$E,Détail!$D:$D,"MR BOUDJADA MOUNIR",Détail!$A:$A,">="&DATE(2025,4,1),Détail!$A:$A,"<"&EDATE(DATE(2025,4,1),1)) -> -1473.11
A41: Mai 2025 | B41: =SUMIFS(Détail!$E:$E,Détail!$D:$D,"MR BOUDJADA MOUNIR",Détail!$A:$A,">="&DATE(2025,5,1),Détail!$A:$A,"<"&EDATE(DATE(2025,5,1),1)) -> -4040.11
A42: Juin 2025 | B42: =SUMIFS(Détail!$E:$E,Détail!$D:$D,"MR BOUDJADA MOUNIR",Détail!$A:$A,">="&DATE(2025,6,1),Détail!$A:$A,"<"&EDATE(DATE(2025,6,1),1)) -> -1240.11
A43: Juillet 2025 | B43: =SUMIFS(Détail!$E:$E,Détail!$D:$D,"MR BOUDJADA MOUNIR",Détail!$A:$A,">="&DATE(2025,7,1),Détail!$A:$A,"<"&EDATE(DATE(2025,7,1),1)) -> -1228.51
A44: Août 2025 | B44: =SUMIFS(Détail!$E:$E,Détail!$D:$D,"MR BOUDJADA MOUNIR",Détail!$A:$A,">="&DATE(2025,8,1),Détail!$A:$A,"<"&EDATE(DATE(2025,8,1),1)) -> -1273.69
A45: Septembre 2025 | B45: =SUMIFS(Détail!$E:$E,Détail!$D:$D,"MR BOUDJADA MOUNIR",Détail!$A:$A,">="&DATE(2025,9,1),Détail!$A:$A,"<"&EDATE(DATE(2025,9,1),1)) -> -1218.1
A46: Octobre 2025 | B46: =SUMIFS(Détail!$E:$E,Détail!$D:$D,"MR BOUDJADA MOUNIR",Détail!$A:$A,">="&DATE(2025,10,1),Détail!$A:$A,"<"&EDATE(DATE(2025,10,1),1)) -> -1236.18
A47: Novembre 2025 | B47: =SUMIFS(Détail!$E:$E,Détail!$D:$D,"MR BOUDJADA MOUNIR",Détail!$A:$A,">="&DATE(2025,11,1),Détail!$A:$A,"<"&EDATE(DATE(2025,11,1),1)) -> -1303.84
A48: Décembre 2025 | B48: =SUMIFS(Détail!$E:$E,Détail!$D:$D,"MR BOUDJADA MOUNIR",Détail!$A:$A,">="&DATE(2025,12,1),Détail!$A:$A,"<"&EDATE(DATE(2025,12,1),1)) -> -3597.83
A51: Mme Machado Natali (Salarié) | C51: =SUMIF(Détail!$D:$D,"MME MACHADO NATALI",Détail!$E:$E) -> -20135.55
A52: Mois | B52: Montant
A53: Janvier 2025 | B53: =SUMIFS(Détail!$E:$E,Détail!$D:$D,"MME MACHADO NATALI",Détail!$A:$A,">="&DATE(2025,1,1),Détail!$A:$A,"<"&EDATE(DATE(2025,1,1),1)) -> -1000
A54: Février 2025 | B54: =SUMIFS(Détail!$E:$E,Détail!$D:$D,"MME MACHADO NATALI",Détail!$A:$A,">="&DATE(2025,2,1),Détail!$A:$A,"<"&EDATE(DATE(2025,2,1),1)) -> -1636.46
A55: Mars 2025 | B55: =SUMIFS(Détail!$E:$E,Détail!$D:$D,"MME MACHADO NATALI",Détail!$A:$A,">="&DATE(2025,3,1),Détail!$A:$A,"<"&EDATE(DATE(2025,3,1),1)) -> -1271.06
A56: Avril 2025 | B56: =SUMIFS(Détail!$E:$E,Détail!$D:$D,"MME MACHADO NATALI",Détail!$A:$A,">="&DATE(2025,4,1),Détail!$A:$A,"<"&EDATE(DATE(2025,4,1),1)) -> -1000
A57: Mai 2025 | B57: =SUMIFS(Détail!$E:$E,Détail!$D:$D,"MME MACHADO NATALI",Détail!$A:$A,">="&DATE(2025,5,1),Détail!$A:$A,"<"&EDATE(DATE(2025,5,1),1)) -> -1314.24
A58: Juin 2025 | B58: =SUMIFS(Détail!$E:$E,Détail!$D:$D,"MME MACHADO NATALI",Détail!$A:$A,">="&DATE(2025,6,1),Détail!$A:$A,"<"&EDATE(DATE(2025,6,1),1)) -> -2581.16
A59: Juillet 2025 | B59: =SUMIFS(Détail!$E:$E,Détail!$D:$D,"MME MACHADO NATALI",Détail!$A:$A,">="&DATE(2025,7,1),Détail!$A:$A,"<"&EDATE(DATE(2025,7,1),1)) -> -1300.24
A60: Août 2025 | B60: =SUMIFS(Détail!$E:$E,Détail!$D:$D,"MME MACHADO NATALI",Détail!$A:$A,">="&DATE(2025,8,1),Détail!$A:$A,"<"&EDATE(DATE(2025,8,1),1)) -> -1356.37
A61: Septembre 2025 | B61: =SUMIFS(Détail!$E:$E,Détail!$D:$D,"MME MACHADO NATALI",Détail!$A:$A,">="&DATE(2025,9,1),Détail!$A:$A,"<"&EDATE(DATE(2025,9,1),1)) -> -800
A62: Octobre 2025 | B62: =SUMIFS(Détail!$E:$E,Détail!$D:$D,"MME MACHADO NATALI",Détail!$A:$A,">="&DATE(2025,10,1),Détail!$A:$A,"<"&EDATE(DATE(2025,10,1),1)) -> -2793.12
A63: Novembre 2025 | B63: =SUMIFS(Détail!$E:$E,Détail!$D:$D,"MME MACHADO NATALI",Détail!$A:$A,">="&DATE(2025,11,1),Détail!$A:$A,"<"&EDATE(DATE(2025,11,1),1)) -> -1782.23
A64: Décembre 2025 | B64: =SUMIFS(Détail!$E:$E,Détail!$D:$D,"MME MACHADO NATALI",Détail!$A:$A,">="&DATE(2025,12,1),Détail!$A:$A,"<"&EDATE(DATE(2025,12,1),1)) -> -3300.67
A67: Mme Machado Natali (Avance Sur Salaire) | C67: =SUMIF(Détail!$D:$D,"MME MACHADO NATALI (avance sur salaire)",Détail!$E:$E) -> -3000
A68: Mois | B68: Montant
A69: Janvier 2025 | B69: =SUMIFS(Détail!$E:$E,Détail!$D:$D,"MME MACHADO NATALI (avance sur salaire)",Détail!$A:$A,">="&DATE(2025,1,1),Détail!$A:$A,"<"&EDATE(DATE(2025,1,1),1)) -> 0
A70: Février 2025 | B70: =SUMIFS(Détail!$E:$E,Détail!$D:$D,"MME MACHADO NATALI (avance sur salaire)",Détail!$A:$A,">="&DATE(2025,2,1),Détail!$A:$A,"<"&EDATE(DATE(2025,2,1),1)) -> 0
A71: Mars 2025 | B71: =SUMIFS(Détail!$E:$E,Détail!$D:$D,"MME MACHADO NATALI (avance sur salaire)",Détail!$A:$A,">="&DATE(2025,3,1),Détail!$A:$A,"<"&EDATE(DATE(2025,3,1),1)) -> 0
A72: Avril 2025 | B72: =SUMIFS(Détail!$E:$E,Détail!$D:$D,"MME MACHADO NATALI (avance sur salaire)",Détail!$A:$A,">="&DATE(2025,4,1),Détail!$A:$A,"<"&EDATE(DATE(2025,4,1),1)) -> 0
A73: Mai 2025 | B73: =SUMIFS(Détail!$E:$E,Détail!$D:$D,"MME MACHADO NATALI (avance sur salaire)",Détail!$A:$A,">="&DATE(2025,5,1),Détail!$A:$A,"<"&EDATE(DATE(2025,5,1),1)) -> 0
A74: Juin 2025 | B74: =SUMIFS(Détail!$E:$E,Détail!$D:$D,"MME MACHADO NATALI (avance sur salaire)",Détail!$A:$A,">="&DATE(2025,6,1),Détail!$A:$A,"<"&EDATE(DATE(2025,6,1),1)) -> 0
A75: Juillet 2025 | B75: =SUMIFS(Détail!$E:$E,Détail!$D:$D,"MME MACHADO NATALI (avance sur salaire)",Détail!$A:$A,">="&DATE(2025,7,1),Détail!$A:$A,"<"&EDATE(DATE(2025,7,1),1)) -> 0
A76: Août 2025 | B76: =SUMIFS(Détail!$E:$E,Détail!$D:$D,"MME MACHADO NATALI (avance sur salaire)",Détail!$A:$A,">="&DATE(2025,8,1),Détail!$A:$A,"<"&EDATE(DATE(2025,8,1),1)) -> 0
A77: Septembre 2025 | B77: =SUMIFS(Détail!$E:$E,Détail!$D:$D,"MME MACHADO NATALI (avance sur salaire)",Détail!$A:$A,">="&DATE(2025,9,1),Détail!$A:$A,"<"&EDATE(DATE(2025,9,1),1)) -> 0
A78: Octobre 2025 | B78: =SUMIFS(Détail!$E:$E,Détail!$D:$D,"MME MACHADO NATALI (avance sur salaire)",Détail!$A:$A,">="&DATE(2025,10,1),Détail!$A:$A,"<"&EDATE(DATE(2025,10,1),1)) -> 0
A79: Novembre 2025 | B79: =SUMIFS(Détail!$E:$E,Détail!$D:$D,"MME MACHADO NATALI (avance sur salaire)",Détail!$A:$A,">="&DATE(2025,11,1),Détail!$A:$A,"<"&EDATE(DATE(2025,11,1),1)) -> -3000
A80: Décembre 2025 | B80: =SUMIFS(Détail!$E:$E,Détail!$D:$D,"MME MACHADO NATALI (avance sur salaire)",Détail!$A:$A,">="&DATE(2025,12,1),Détail!$A:$A,"<"&EDATE(DATE(2025,12,1),1)) -> 0

Sheet Fournisseurs France détail
A1: Fournisseurs matières premières & emballage (France) — détail par fournisseur (2025)
A3: Firmenich | C3: =SUMIF(Détail!$D:$D,"FIRMENICH",Détail!$E:$E) -> -227485.55
A4: Mois | B4: Montant
A5: Janvier 2025 | B5: =SUMIFS(Détail!$E:$E,Détail!$D:$D,"FIRMENICH",Détail!$A:$A,">="&DATE(2025,1,1),Détail!$A:$A,"<"&EDATE(DATE(2025,1,1),1)) -> 0
A6: Février 2025 | B6: =SUMIFS(Détail!$E:$E,Détail!$D:$D,"FIRMENICH",Détail!$A:$A,">="&DATE(2025,2,1),Détail!$A:$A,"<"&EDATE(DATE(2025,2,1),1)) -> 0
A7: Mars 2025 | B7: =SUMIFS(Détail!$E:$E,Détail!$D:$D,"FIRMENICH",Détail!$A:$A,">="&DATE(2025,3,1),Détail!$A:$A,"<"&EDATE(DATE(2025,3,1),1)) -> -26530.22
A8: Avril 2025 | B8: =SUMIFS(Détail!$E:$E,Détail!$D:$D,"FIRMENICH",Détail!$A:$A,">="&DATE(2025,4,1),Détail!$A:$A,"<"&EDATE(DATE(2025,4,1),1)) -> 0
A9: Mai 2025 | B9: =SUMIFS(Détail!$E:$E,Détail!$D:$D,"FIRMENICH",Détail!$A:$A,">="&DATE(2025,5,1),Détail!$A:$A,"<"&EDATE(DATE(2025,5,1),1)) -> 0
A10: Juin 2025 | B10: =SUMIFS(Détail!$E:$E,Détail!$D:$D,"FIRMENICH",Détail!$A:$A,">="&DATE(2025,6,1),Détail!$A:$A,"<"&EDATE(DATE(2025,6,1),1)) -> 0
A11: Juillet 2025 | B11: =SUMIFS(Détail!$E:$E,Détail!$D:$D,"FIRMENICH",Détail!$A:$A,">="&DATE(2025,7,1),Détail!$A:$A,"<"&EDATE(DATE(2025,7,1),1)) -> -88850.73
A12: Août 2025 | B12: =SUMIFS(Détail!$E:$E,Détail!$D:$D,"FIRMENICH",Détail!$A:$A,">="&DATE(2025,8,1),Détail!$A:$A,"<"&EDATE(DATE(2025,8,1),1)) -> -101001.5
A13: Septembre 2025 | B13: =SUMIFS(Détail!$E:$E,Détail!$D:$D,"FIRMENICH",Détail!$A:$A,">="&DATE(2025,9,1),Détail!$A:$A,"<"&EDATE(DATE(2025,9,1),1)) -> 0
A14: Octobre 2025 | B14: =SUMIFS(Détail!$E:$E,Détail!$D:$D,"FIRMENICH",Détail!$A:$A,">="&DATE(2025,10,1),Détail!$A:$A,"<"&EDATE(DATE(2025,10,1),1)) -> 0
A15: Décembre 2025 | B15: =SUMIFS(Détail!$E:$E,Détail!$D:$D,"FIRMENICH",Détail!$A:$A,">="&DATE(2025,12,1),Détail!$A:$A,"<"&EDATE(DATE(2025,12,1),1)) -> -11103.1
A18: Aromascent | C18: =SUMIF(Détail!$D:$D,"AROMASCENT",Détail!$E:$E) -> -95058
A19: Mois | B19: Montant
A20: Janvier 2025 | B20: =SUMIFS(Détail!$E:$E,Détail!$D:$D,"AROMASCENT",Détail!$A:$A,">="&DATE(2025,1,1),Détail!$A:$A,"<"&EDATE(DATE(2025,1,1),1)) -> 0
A21: Février 2025 | B21: =SUMIFS(Détail!$E:$E,Détail!$D:$D,"AROMASCENT",Détail!$A:$A,">="&DATE(2025,2,1),Détail!$A:$A,"<"&EDATE(DATE(2025,2,1),1)) -> 0
A22: Mars 2025 | B22: =SUMIFS(Détail!$E:$E,Détail!$D:$D,"AROMASCENT",Détail!$A:$A,">="&DATE(2025,3,1),Détail!$A:$A,"<"&EDATE(DATE(2025,3,1),1)) -> -86184
A23: Avril 2025 | B23: =SUMIFS(Détail!$E:$E,Détail!$D:$D,"AROMASCENT",Détail!$A:$A,">="&DATE(2025,4,1),Détail!$A:$A,"<"&EDATE(DATE(2025,4,1),1)) -> 0
A24: Mai 2025 | B24: =SUMIFS(Détail!$E:$E,Détail!$D:$D,"AROMASCENT",Détail!$A:$A,">="&DATE(2025,5,1),Détail!$A:$A,"<"&EDATE(DATE(2025,5,1),1)) -> 0
A25: Juin 2025 | B25: =SUMIFS(Détail!$E:$E,Détail!$D:$D,"AROMASCENT",Détail!$A:$A,">="&DATE(2025,6,1),Détail!$A:$A,"<"&EDATE(DATE(2025,6,1),1)) -> 0
A26: Juillet 2025 | B26: =SUMIFS(Détail!$E:$E,Détail!$D:$D,"AROMASCENT",Détail!$A:$A,">="&DATE(2025,7,1),Détail!$A:$A,"<"&EDATE(DATE(2025,7,1),1)) -> 0
A27: Août 2025 | B27: =SUMIFS(Détail!$E:$E,Détail!$D:$D,"AROMASCENT",Détail!$A:$A,">="&DATE(2025,8,1),Détail!$A:$A,"<"&EDATE(DATE(2025,8,1),1)) -> 0
A28: Septembre 2025 | B28: =SUMIFS(Détail!$E:$E,Détail!$D:$D,"AROMASCENT",Détail!$A:$A,">="&DATE(2025,9,1),Détail!$A:$A,"<"&EDATE(DATE(2025,9,1),1)) -> 0
A29: Octobre 2025 | B29: =SUMIFS(Détail!$E:$E,Détail!$D:$D,"AROMASCENT",Détail!$A:$A,">="&DATE(2025,10,1),Détail!$A:$A,"<"&EDATE(DATE(2025,10,1),1)) -> -5916
A30: Décembre 2025 | B30: =SUMIFS(Détail!$E:$E,Détail!$D:$D,"AROMASCENT",Détail!$A:$A,">="&DATE(2025,12,1),Détail!$A:$A,"<"&EDATE(DATE(2025,12,1),1)) -> -2958
A33: Cpl Aromas France | C33: =SUMIF(Détail!$D:$D,"CPL AROMAS FRANCE",Détail!$E:$E) -> -75040
A34: Mois | B34: Montant
A35: Janvier 2025 | B35: =SUMIFS(Détail!$E:$E,Détail!$D:$D,"CPL AROMAS FRANCE",Détail!$A:$A,">="&DATE(2025,1,1),Détail!$A:$A,"<"&EDATE(DATE(2025,1,1),1)) -> -5075
A36: Février 2025 | B36: =SUMIFS(Détail!$E:$E,Détail!$D:$D,"CPL AROMAS FRANCE",Détail!$A:$A,">="&DATE(2025,2,1),Détail!$A:$A,"<"&EDATE(DATE(2025,2,1),1)) -> -13125
A37: Mars 2025 | B37: =SUMIFS(Détail!$E:$E,Détail!$D:$D,"CPL AROMAS FRANCE",Détail!$A:$A,">="&DATE(2025,3,1),Détail!$A:$A,"<"&EDATE(DATE(2025,3,1),1)) -> -18250
A38: Avril 2025 | B38: =SUMIFS(Détail!$E:$E,Détail!$D:$D,"CPL AROMAS FRANCE",Détail!$A:$A,">="&DATE(2025,4,1),Détail!$A:$A,"<"&EDATE(DATE(2025,4,1),1)) -> 0
A39: Mai 2025 | B39: =SUMIFS(Détail!$E:$E,Détail!$D:$D,"CPL AROMAS FRANCE",Détail!$A:$A,">="&DATE(2025,5,1),Détail!$A:$A,"<"&EDATE(DATE(2025,5,1),1)) -> -6686
A40: Juin 2025 | B40: =SUMIFS(Détail!$E:$E,Détail!$D:$D,"CPL AROMAS FRANCE",Détail!$A:$A,">="&DATE(2025,6,1),Détail!$A:$A,"<"&EDATE(DATE(2025,6,1),1)) -> 0
A41: Juillet 2025 | B41: =SUMIFS(Détail!$E:$E,Détail!$D:$D,"CPL AROMAS FRANCE",Détail!$A:$A,">="&DATE(2025,7,1),Détail!$A:$A,"<"&EDATE(DATE(2025,7,1),1)) -> 0
A42: Août 2025 | B42: =SUMIFS(Détail!$E:$E,Détail!$D:$D,"CPL AROMAS FRANCE",Détail!$A:$A,">="&DATE(2025,8,1),Détail!$A:$A,"<"&EDATE(DATE(2025,8,1),1)) -> 0
A43: Septembre 2025 | B43: =SUMIFS(Détail!$E:$E,Détail!$D:$D,"CPL AROMAS FRANCE",Détail!$A:$A,">="&DATE(2025,9,1),Détail!$A:$A,"<"&EDATE(DATE(2025,9,1),1)) -> -4670
A44: Octobre 2025 | B44: =SUMIFS(Détail!$E:$E,Détail!$D:$D,"CPL AROMAS FRANCE",Détail!$A:$A,">="&DATE(2025,10,1),Détail!$A:$A,"<"&EDATE(DATE(2025,10,1),1)) -> -26418
A45: Décembre 2025 | B45: =SUMIFS(Détail!$E:$E,Détail!$D:$D,"CPL AROMAS FRANCE",Détail!$A:$A,">="&DATE(2025,12,1),Détail!$A:$A,"<"&EDATE(DATE(2025,12,1),1)) -> -816
A48: Envases | C48: =SUMIF(Détail!$D:$D,"ENVASES",Détail!$E:$E) -> -46448.1
A49: Mois | B49: Montant
A50: Janvier 2025 | B50: =SUMIFS(Détail!$E:$E,Détail!$D:$D,"ENVASES",Détail!$A:$A,">="&DATE(2025,1,1),Détail!$A:$A,"<"&EDATE(DATE(2025,1,1),1)) -> 0
A51: Février 2025 | B51: =SUMIFS(Détail!$E:$E,Détail!$D:$D,"ENVASES",Détail!$A:$A,">="&DATE(2025,2,1),Détail!$A:$A,"<"&EDATE(DATE(2025,2,1),1)) -> 0
A52: Mars 2025 | B52: =SUMIFS(Détail!$E:$E,Détail!$D:$D,"ENVASES",Détail!$A:$A,">="&DATE(2025,3,1),Détail!$A:$A,"<"&EDATE(DATE(2025,3,1),1)) -> 0
A53: Avril 2025 | B53: =SUMIFS(Détail!$E:$E,Détail!$D:$D,"ENVASES",Détail!$A:$A,">="&DATE(2025,4,1),Détail!$A:$A,"<"&EDATE(DATE(2025,4,1),1)) -> 0
A54: Mai 2025 | B54: =SUMIFS(Détail!$E:$E,Détail!$D:$D,"ENVASES",Détail!$A:$A,">="&DATE(2025,5,1),Détail!$A:$A,"<"&EDATE(DATE(2025,5,1),1)) -> 0
A55: Juin 2025 | B55: =SUMIFS(Détail!$E:$E,Détail!$D:$D,"ENVASES",Détail!$A:$A,">="&DATE(2025,6,1),Détail!$A:$A,"<"&EDATE(DATE(2025,6,1),1)) -> 0
A56: Juillet 2025 | B56: =SUMIFS(Détail!$E:$E,Détail!$D:$D,"ENVASES",Détail!$A:$A,">="&DATE(2025,7,1),Détail!$A:$A,"<"&EDATE(DATE(2025,7,1),1)) -> -42938.1
A57: Août 2025 | B57: =SUMIFS(Détail!$E:$E,Détail!$D:$D,"ENVASES",Détail!$A:$A,">="&DATE(2025,8,1),Détail!$A:$A,"<"&EDATE(DATE(2025,8,1),1)) -> 0
A58: Septembre 2025 | B58: =SUMIFS(Détail!$E:$E,Détail!$D:$D,"ENVASES",Détail!$A:$A,">="&DATE(2025,9,1),Détail!$A:$A,"<"&EDATE(DATE(2025,9,1),1)) -> 0
A59: Octobre 2025 | B59: =SUMIFS(Détail!$E:$E,Détail!$D:$D,"ENVASES",Détail!$A:$A,">="&DATE(2025,10,1),Détail!$A:$A,"<"&EDATE(DATE(2025,10,1),1)) -> -3510
A60: Décembre 2025 | B60: =SUMIFS(Détail!$E:$E,Détail!$D:$D,"ENVASES",Détail!$A:$A,">="&DATE(2025,12,1),Détail!$A:$A,"<"&EDATE(DATE(2025,12,1),1)) -> 0
A63: Neroli France | C63: =SUMIF(Détail!$D:$D,"NEROLI FRANCE",Détail!$E:$E) -> -25792
A64: Mois | B64: Montant
A65: Janvier 2025 | B65: =SUMIFS(Détail!$E:$E,Détail!$D:$D,"NEROLI FRANCE",Détail!$A:$A,">="&DATE(2025,1,1),Détail!$A:$A,"<"&EDATE(DATE(2025,1,1),1)) -> 0
A66: Février 2025 | B66: =SUMIFS(Détail!$E:$E,Détail!$D:$D,"NEROLI FRANCE",Détail!$A:$A,">="&DATE(2025,2,1),Détail!$A:$A,"<"&EDATE(DATE(2025,2,1),1)) -> -660
A67: Mars 2025 | B67: =SUMIFS(Détail!$E:$E,Détail!$D:$D,"NEROLI FRANCE",Détail!$A:$A,">="&DATE(2025,3,1),Détail!$A:$A,"<"&EDATE(DATE(2025,3,1),1)) -> 0
A68: Avril 2025 | B68: =SUMIFS(Détail!$E:$E,Détail!$D:$D,"NEROLI FRANCE",Détail!$A:$A,">="&DATE(2025,4,1),Détail!$A:$A,"<"&EDATE(DATE(2025,4,1),1)) -> -6100
A69: Mai 2025 | B69: =SUMIFS(Détail!$E:$E,Détail!$D:$D,"NEROLI FRANCE",Détail!$A:$A,">="&DATE(2025,5,1),Détail!$A:$A,"<"&EDATE(DATE(2025,5,1),1)) -> -8137
A70: Juin 2025 | B70: =SUMIFS(Détail!$E:$E,Détail!$D:$D,"NEROLI FRANCE",Détail!$A:$A,">="&DATE(2025,6,1),Détail!$A:$A,"<"&EDATE(DATE(2025,6,1),1)) -> 0
A71: Juillet 2025 | B71: =SUMIFS(Détail!$E:$E,Détail!$D:$D,"NEROLI FRANCE",Détail!$A:$A,">="&DATE(2025,7,1),Détail!$A:$A,"<"&EDATE(DATE(2025,7,1),1)) -> 0
A72: Août 2025 | B72: =SUMIFS(Détail!$E:$E,Détail!$D:$D,"NEROLI FRANCE",Détail!$A:$A,">="&DATE(2025,8,1),Détail!$A:$A,"<"&EDATE(DATE(2025,8,1),1)) -> 0
A73: Septembre 2025 | B73: =SUMIFS(Détail!$E:$E,Détail!$D:$D,"NEROLI FRANCE",Détail!$A:$A,">="&DATE(2025,9,1),Détail!$A:$A,"<"&EDATE(DATE(2025,9,1),1)) -> -6510
A74: Octobre 2025 | B74: =SUMIFS(Détail!$E:$E,Détail!$D:$D,"NEROLI FRANCE",Détail!$A:$A,">="&DATE(2025,10,1),Détail!$A:$A,"<"&EDATE(DATE(2025,10,1),1)) -> 0
A75: Décembre 2025 | B75: =SUMIFS(Détail!$E:$E,Détail!$D:$D,"NEROLI FRANCE",Détail!$A:$A,">="&DATE(2025,12,1),Détail!$A:$A,"<"&EDATE(DATE(2025,12,1),1)) -> -4385
A78: Cartonnages Du Val D Orge | C78: =SUMIF(Détail!$D:$D,"CARTONNAGES DU VAL D ORGE",Détail!$E:$E) -> -16276.62
A79: Mois | B79: Montant
A80: Janvier 2025 | B80: =SUMIFS(Détail!$E:$E,Détail!$D:$D,"CARTONNAGES DU VAL D ORGE",Détail!$A:$A,">="&DATE(2025,1,1),Détail!$A:$A,"<"&EDATE(DATE(2025,1,1),1)) -> -2251.2
A81: Février 2025 | B81: =SUMIFS(Détail!$E:$E,Détail!$D:$D,"CARTONNAGES DU VAL D ORGE",Détail!$A:$A,">="&DATE(2025,2,1),Détail!$A:$A,"<"&EDATE(DATE(2025,2,1),1)) -> 0
A82: Mars 2025 | B82: =SUMIFS(Détail!$E:$E,Détail!$D:$D,"CARTONNAGES DU VAL D ORGE",Détail!$A:$A,">="&DATE(2025,3,1),Détail!$A:$A,"<"&EDATE(DATE(2025,3,1),1)) -> 0
A83: Avril 2025 | B83: =SUMIFS(Détail!$E:$E,Détail!$D:$D,"CARTONNAGES DU VAL D ORGE",Détail!$A:$A,">="&DATE(2025,4,1),Détail!$A:$A,"<"&EDATE(DATE(2025,4,1),1)) -> 0
A84: Mai 2025 | B84: =SUMIFS(Détail!$E:$E,Détail!$D:$D,"CARTONNAGES DU VAL D ORGE",Détail!$A:$A,">="&DATE(2025,5,1),Détail!$A:$A,"<"&EDATE(DATE(2025,5,1),1)) -> 0
A85: Juin 2025 | B85: =SUMIFS(Détail!$E:$E,Détail!$D:$D,"CARTONNAGES DU VAL D ORGE",Détail!$A:$A,">="&DATE(2025,6,1),Détail!$A:$A,"<"&EDATE(DATE(2025,6,1),1)) -> -7534.5
A86: Juillet 2025 | B86: =SUMIFS(Détail!$E:$E,Détail!$D:$D,"CARTONNAGES DU VAL D ORGE",Détail!$A:$A,">="&DATE(2025,7,1),Détail!$A:$A,"<"&EDATE(DATE(2025,7,1),1)) -> -2785
A87: Août 2025 | B87: =SUMIFS(Détail!$E:$E,Détail!$D:$D,"CARTONNAGES DU VAL D ORGE",Détail!$A:$A,">="&DATE(2025,8,1),Détail!$A:$A,"<"&EDATE(DATE(2025,8,1),1)) -> 0
A88: Septembre 2025 | B88: =SUMIFS(Détail!$E:$E,Détail!$D:$D,"CARTONNAGES DU VAL D ORGE",Détail!$A:$A,">="&DATE(2025,9,1),Détail!$A:$A,"<"&EDATE(DATE(2025,9,1),1)) -> -3705.92
A89: Octobre 2025 | B89: =SUMIFS(Détail!$E:$E,Détail!$D:$D,"CARTONNAGES DU VAL D ORGE",Détail!$A:$A,">="&DATE(2025,10,1),Détail!$A:$A,"<"&EDATE(DATE(2025,10,1),1)) -> 0
A90: Décembre 2025 | B90: =SUMIFS(Détail!$E:$E,Détail!$D:$D,"CARTONNAGES DU VAL D ORGE",Détail!$A:$A,">="&DATE(2025,12,1),Détail!$A:$A,"<"&EDATE(DATE(2025,12,1),1)) -> 0
A93: Sleeve Concept | C93: =SUMIF(Détail!$D:$D,"SLEEVE CONCEPT",Détail!$E:$E) -> -14760.5
A94: Mois | B94: Montant
A95: Janvier 2025 | B95: =SUMIFS(Détail!$E:$E,Détail!$D:$D,"SLEEVE CONCEPT",Détail!$A:$A,">="&DATE(2025,1,1),Détail!$A:$A,"<"&EDATE(DATE(2025,1,1),1)) -> 0
A96: Février 2025 | B96: =SUMIFS(Détail!$E:$E,Détail!$D:$D,"SLEEVE CONCEPT",Détail!$A:$A,">="&DATE(2025,2,1),Détail!$A:$A,"<"&EDATE(DATE(2025,2,1),1)) -> 0
A97: Mars 2025 | B97: =SUMIFS(Détail!$E:$E,Détail!$D:$D,"SLEEVE CONCEPT",Détail!$A:$A,">="&DATE(2025,3,1),Détail!$A:$A,"<"&EDATE(DATE(2025,3,1),1)) -> 0
A98: Avril 2025 | B98: =SUMIFS(Détail!$E:$E,Détail!$D:$D,"SLEEVE CONCEPT",Détail!$A:$A,">="&DATE(2025,4,1),Détail!$A:$A,"<"&EDATE(DATE(2025,4,1),1)) -> -10738.2
A99: Mai 2025 | B99: =SUMIFS(Détail!$E:$E,Détail!$D:$D,"SLEEVE CONCEPT",Détail!$A:$A,">="&DATE(2025,5,1),Détail!$A:$A,"<"&EDATE(DATE(2025,5,1),1)) -> 0
A100: Juin 2025 | B100: =SUMIFS(Détail!$E:$E,Détail!$D:$D,"SLEEVE CONCEPT",Détail!$A:$A,">="&DATE(2025,6,1),Détail!$A:$A,"<"&EDATE(DATE(2025,6,1),1)) -> 0
A101: Juillet 2025 | B101: =SUMIFS(Détail!$E:$E,Détail!$D:$D,"SLEEVE CONCEPT",Détail!$A:$A,">="&DATE(2025,7,1),Détail!$A:$A,"<"&EDATE(DATE(2025,7,1),1)) -> -2284.9
A102: Août 2025 | B102: =SUMIFS(Détail!$E:$E,Détail!$D:$D,"SLEEVE CONCEPT",Détail!$A:$A,">="&DATE(2025,8,1),Détail!$A:$A,"<"&EDATE(DATE(2025,8,1),1)) -> 0
A103: Septembre 2025 | B103: =SUMIFS(Détail!$E:$E,Détail!$D:$D,"SLEEVE CONCEPT",Détail!$A:$A,">="&DATE(2025,9,1),Détail!$A:$A,"<"&EDATE(DATE(2025,9,1),1)) -> 0
A104: Octobre 2025 | B104: =SUMIFS(Détail!$E:$E,Détail!$D:$D,"SLEEVE CONCEPT",Détail!$A:$A,">="&DATE(2025,10,1),Détail!$A:$A,"<"&EDATE(DATE(2025,10,1),1)) -> 0
A105: Décembre 2025 | B105: =SUMIFS(Détail!$E:$E,Détail!$D:$D,"SLEEVE CONCEPT",Détail!$A:$A,">="&DATE(2025,12,1),Détail!$A:$A,"<"&EDATE(DATE(2025,12,1),1)) -> -1737.4
A108: Nasmir Europe Fragrances | C108: =SUMIF(Détail!$D:$D,"NASMIR EUROPE FRAGRANCES",Détail!$E:$E) -> -6010
A109: Mois | B109: Montant
A110: Janvier 2025 | B110: =SUMIFS(Détail!$E:$E,Détail!$D:$D,"NASMIR EUROPE FRAGRANCES",Détail!$A:$A,">="&DATE(2025,1,1),Détail!$A:$A,"<"&EDATE(DATE(2025,1,1),1)) -> 0
A111: Février 2025 | B111: =SUMIFS(Détail!$E:$E,Détail!$D:$D,"NASMIR EUROPE FRAGRANCES",Détail!$A:$A,">="&DATE(2025,2,1),Détail!$A:$A,"<"&EDATE(DATE(2025,2,1),1)) -> 0
A112: Mars 2025 | B112: =SUMIFS(Détail!$E:$E,Détail!$D:$D,"NASMIR EUROPE FRAGRANCES",Détail!$A:$A,">="&DATE(2025,3,1),Détail!$A:$A,"<"&EDATE(DATE(2025,3,1),1)) -> 0
A113: Avril 2025 | B113: =SUMIFS(Détail!$E:$E,Détail!$D:$D,"NASMIR EUROPE FRAGRANCES",Détail!$A:$A,">="&DATE(2025,4,1),Détail!$A:$A,"<"&EDATE(DATE(2025,4,1),1)) -> 0
A114: Mai 2025 | B114: =SUMIFS(Détail!$E:$E,Détail!$D:$D,"NASMIR EUROPE FRAGRANCES",Détail!$A:$A,">="&DATE(2025,5,1),Détail!$A:$A,"<"&EDATE(DATE(2025,5,1),1)) -> 0
A115: Juin 2025 | B115: =SUMIFS(Détail!$E:$E,Détail!$D:$D,"NASMIR EUROPE FRAGRANCES",Détail!$A:$A,">="&DATE(2025,6,1),Détail!$A:$A,"<"&EDATE(DATE(2025,6,1),1)) -> 0
...

Sheet Usine conditionnement détail
A1: Usine de conditionnement et macération — détail (2025)
A3: France Conditionnement Parfum | C3: =SUMIF(Détail!$D:$D,"FRANCE CONDITIONNEMENT PARFUM",Détail!$E:$E) -> -282990.43
A4: Mois | B4: Montant
A5: Janvier 2025 | B5: =SUMIFS(Détail!$E:$E,Détail!$D:$D,"FRANCE CONDITIONNEMENT PARFUM",Détail!$A:$A,">="&DATE(2025,1,1),Détail!$A:$A,"<"&EDATE(DATE(2025,1,1),1)) -> -33630.81
A6: Mars 2025 | B6: =SUMIFS(Détail!$E:$E,Détail!$D:$D,"FRANCE CONDITIONNEMENT PARFUM",Détail!$A:$A,">="&DATE(2025,3,1),Détail!$A:$A,"<"&EDATE(DATE(2025,3,1),1)) -> -9896.52
A7: Avril 2025 | B7: =SUMIFS(Détail!$E:$E,Détail!$D:$D,"FRANCE CONDITIONNEMENT PARFUM",Détail!$A:$A,">="&DATE(2025,4,1),Détail!$A:$A,"<"&EDATE(DATE(2025,4,1),1)) -> -21066.05
A8: Mai 2025 | B8: =SUMIFS(Détail!$E:$E,Détail!$D:$D,"FRANCE CONDITIONNEMENT PARFUM",Détail!$A:$A,">="&DATE(2025,5,1),Détail!$A:$A,"<"&EDATE(DATE(2025,5,1),1)) -> -48375.39
A9: Juin 2025 | B9: =SUMIFS(Détail!$E:$E,Détail!$D:$D,"FRANCE CONDITIONNEMENT PARFUM",Détail!$A:$A,">="&DATE(2025,6,1),Détail!$A:$A,"<"&EDATE(DATE(2025,6,1),1)) -> -3496.58
A10: Juillet 2025 | B10: =SUMIFS(Détail!$E:$E,Détail!$D:$D,"FRANCE CONDITIONNEMENT PARFUM",Détail!$A:$A,">="&DATE(2025,7,1),Détail!$A:$A,"<"&EDATE(DATE(2025,7,1),1)) -> -57951.62
A11: Septembre 2025 | B11: =SUMIFS(Détail!$E:$E,Détail!$D:$D,"FRANCE CONDITIONNEMENT PARFUM",Détail!$A:$A,">="&DATE(2025,9,1),Détail!$A:$A,"<"&EDATE(DATE(2025,9,1),1)) -> -12593.08
A12: Octobre 2025 | B12: =SUMIFS(Détail!$E:$E,Détail!$D:$D,"FRANCE CONDITIONNEMENT PARFUM",Détail!$A:$A,">="&DATE(2025,10,1),Détail!$A:$A,"<"&EDATE(DATE(2025,10,1),1)) -> -73181.32
A13: Novembre 2025 | B13: =SUMIFS(Détail!$E:$E,Détail!$D:$D,"FRANCE CONDITIONNEMENT PARFUM",Détail!$A:$A,">="&DATE(2025,11,1),Détail!$A:$A,"<"&EDATE(DATE(2025,11,1),1)) -> -11848.95
A14: Décembre 2025 | B14: =SUMIFS(Détail!$E:$E,Détail!$D:$D,"FRANCE CONDITIONNEMENT PARFUM",Détail!$A:$A,">="&DATE(2025,12,1),Détail!$A:$A,"<"&EDATE(DATE(2025,12,1),1)) -> -10916.11
A17: Amival | C17: =SUMIF(Détail!$D:$D,"AMIVAL",Détail!$E:$E) -> -34183.96
A18: Mois | B18: Montant
A19: Janvier 2025 | B19: =SUMIFS(Détail!$E:$E,Détail!$D:$D,"AMIVAL",Détail!$A:$A,">="&DATE(2025,1,1),Détail!$A:$A,"<"&EDATE(DATE(2025,1,1),1)) -> 0
A20: Mars 2025 | B20: =SUMIFS(Détail!$E:$E,Détail!$D:$D,"AMIVAL",Détail!$A:$A,">="&DATE(2025,3,1),Détail!$A:$A,"<"&EDATE(DATE(2025,3,1),1)) -> 0
A21: Avril 2025 | B21: =SUMIFS(Détail!$E:$E,Détail!$D:$D,"AMIVAL",Détail!$A:$A,">="&DATE(2025,4,1),Détail!$A:$A,"<"&EDATE(DATE(2025,4,1),1)) -> 0
A22: Mai 2025 | B22: =SUMIFS(Détail!$E:$E,Détail!$D:$D,"AMIVAL",Détail!$A:$A,">="&DATE(2025,5,1),Détail!$A:$A,"<"&EDATE(DATE(2025,5,1),1)) -> 0
A23: Juin 2025 | B23: =SUMIFS(Détail!$E:$E,Détail!$D:$D,"AMIVAL",Détail!$A:$A,">="&DATE(2025,6,1),Détail!$A:$A,"<"&EDATE(DATE(2025,6,1),1)) -> -10000
A24: Juillet 2025 | B24: =SUMIFS(Détail!$E:$E,Détail!$D:$D,"AMIVAL",Détail!$A:$A,">="&DATE(2025,7,1),Détail!$A:$A,"<"&EDATE(DATE(2025,7,1),1)) -> -24183.96
A25: Septembre 2025 | B25: =SUMIFS(Détail!$E:$E,Détail!$D:$D,"AMIVAL",Détail!$A:$A,">="&DATE(2025,9,1),Détail!$A:$A,"<"&EDATE(DATE(2025,9,1),1)) -> 0
A26: Octobre 2025 | B26: =SUMIFS(Détail!$E:$E,Détail!$D:$D,"AMIVAL",Détail!$A:$A,">="&DATE(2025,10,1),Détail!$A:$A,"<"&EDATE(DATE(2025,10,1),1)) -> 0
A27: Novembre 2025 | B27: =SUMIFS(Détail!$E:$E,Détail!$D:$D,"AMIVAL",Détail!$A:$A,">="&DATE(2025,11,1),Détail!$A:$A,"<"&EDATE(DATE(2025,11,1),1)) -> 0
A28: Décembre 2025 | B28: =SUMIFS(Détail!$E:$E,Détail!$D:$D,"AMIVAL",Détail!$A:$A,">="&DATE(2025,12,1),Détail!$A:$A,"<"&EDATE(DATE(2025,12,1),1)) -> 0

Sheet Fournisseurs intl détail
A1: Fournisseurs internationaux (Chine/Import) — détail par fournisseur (2025)
A3: Zhejiang Bi Industrial Co Ltd | C3: =SUMIF(Détail!$D:$D,"ZHEJIANG BI INDUSTRIAL CO LTD",Détail!$E:$E) -> -245581.16
A4: Mois | B4: Montant
A5: Janvier 2025 | B5: =SUMIFS(Détail!$E:$E,Détail!$D:$D,"ZHEJIANG BI INDUSTRIAL CO LTD",Détail!$A:$A,">="&DATE(2025,1,1),Détail!$A:$A,"<"&EDATE(DATE(2025,1,1),1)) -> 0
A6: Mars 2025 | B6: =SUMIFS(Détail!$E:$E,Détail!$D:$D,"ZHEJIANG BI INDUSTRIAL CO LTD",Détail!$A:$A,">="&DATE(2025,3,1),Détail!$A:$A,"<"&EDATE(DATE(2025,3,1),1)) -> -25738.1
A7: Avril 2025 | B7: =SUMIFS(Détail!$E:$E,Détail!$D:$D,"ZHEJIANG BI INDUSTRIAL CO LTD",Détail!$A:$A,">="&DATE(2025,4,1),Détail!$A:$A,"<"&EDATE(DATE(2025,4,1),1)) -> 0
A8: Mai 2025 | B8: =SUMIFS(Détail!$E:$E,Détail!$D:$D,"ZHEJIANG BI INDUSTRIAL CO LTD",Détail!$A:$A,">="&DATE(2025,5,1),Détail!$A:$A,"<"&EDATE(DATE(2025,5,1),1)) -> -11187.07
A9: Juin 2025 | B9: =SUMIFS(Détail!$E:$E,Détail!$D:$D,"ZHEJIANG BI INDUSTRIAL CO LTD",Détail!$A:$A,">="&DATE(2025,6,1),Détail!$A:$A,"<"&EDATE(DATE(2025,6,1),1)) -> -74407.99
A10: Septembre 2025 | B10: =SUMIFS(Détail!$E:$E,Détail!$D:$D,"ZHEJIANG BI INDUSTRIAL CO LTD",Détail!$A:$A,">="&DATE(2025,9,1),Détail!$A:$A,"<"&EDATE(DATE(2025,9,1),1)) -> 0
A11: Octobre 2025 | B11: =SUMIFS(Détail!$E:$E,Détail!$D:$D,"ZHEJIANG BI INDUSTRIAL CO LTD",Détail!$A:$A,">="&DATE(2025,10,1),Détail!$A:$A,"<"&EDATE(DATE(2025,10,1),1)) -> 0
A12: Novembre 2025 | B12: =SUMIFS(Détail!$E:$E,Détail!$D:$D,"ZHEJIANG BI INDUSTRIAL CO LTD",Détail!$A:$A,">="&DATE(2025,11,1),Détail!$A:$A,"<"&EDATE(DATE(2025,11,1),1)) -> -7264.03
A13: Décembre 2025 | B13: =SUMIFS(Détail!$E:$E,Détail!$D:$D,"ZHEJIANG BI INDUSTRIAL CO LTD",Détail!$A:$A,">="&DATE(2025,12,1),Détail!$A:$A,"<"&EDATE(DATE(2025,12,1),1)) -> -126983.97
A16: Leaders Hardware Plastic Co Limited | C16: =SUMIF(Détail!$D:$D,"LEADERS HARDWARE PLASTIC CO LIMITED",Détail!$E:$E) -> -19669.88
A17: Mois | B17: Montant
A18: Janvier 2025 | B18: =SUMIFS(Détail!$E:$E,Détail!$D:$D,"LEADERS HARDWARE PLASTIC CO LIMITED",Détail!$A:$A,">="&DATE(2025,1,1),Détail!$A:$A,"<"&EDATE(DATE(2025,1,1),1)) -> -5727.66
A19: Mars 2025 | B19: =SUMIFS(Détail!$E:$E,Détail!$D:$D,"LEADERS HARDWARE PLASTIC CO LIMITED",Détail!$A:$A,">="&DATE(2025,3,1),Détail!$A:$A,"<"&EDATE(DATE(2025,3,1),1)) -> 0
A20: Avril 2025 | B20: =SUMIFS(Détail!$E:$E,Détail!$D:$D,"LEADERS HARDWARE PLASTIC CO LIMITED",Détail!$A:$A,">="&DATE(2025,4,1),Détail!$A:$A,"<"&EDATE(DATE(2025,4,1),1)) -> -5189
A21: Mai 2025 | B21: =SUMIFS(Détail!$E:$E,Détail!$D:$D,"LEADERS HARDWARE PLASTIC CO LIMITED",Détail!$A:$A,">="&DATE(2025,5,1),Détail!$A:$A,"<"&EDATE(DATE(2025,5,1),1)) -> -1752.85
A22: Juin 2025 | B22: =SUMIFS(Détail!$E:$E,Détail!$D:$D,"LEADERS HARDWARE PLASTIC CO LIMITED",Détail!$A:$A,">="&DATE(2025,6,1),Détail!$A:$A,"<"&EDATE(DATE(2025,6,1),1)) -> -3332.97
A23: Septembre 2025 | B23: =SUMIFS(Détail!$E:$E,Détail!$D:$D,"LEADERS HARDWARE PLASTIC CO LIMITED",Détail!$A:$A,">="&DATE(2025,9,1),Détail!$A:$A,"<"&EDATE(DATE(2025,9,1),1)) -> -798.78
A24: Octobre 2025 | B24: =SUMIFS(Détail!$E:$E,Détail!$D:$D,"LEADERS HARDWARE PLASTIC CO LIMITED",Détail!$A:$A,">="&DATE(2025,10,1),Détail!$A:$A,"<"&EDATE(DATE(2025,10,1),1)) -> -2868.62
A25: Novembre 2025 | B25: =SUMIFS(Détail!$E:$E,Détail!$D:$D,"LEADERS HARDWARE PLASTIC CO LIMITED",Détail!$A:$A,">="&DATE(2025,11,1),Détail!$A:$A,"<"&EDATE(DATE(2025,11,1),1)) -> 0
A26: Décembre 2025 | B26: =SUMIFS(Détail!$E:$E,Détail!$D:$D,"LEADERS HARDWARE PLASTIC CO LIMITED",Détail!$A:$A,">="&DATE(2025,12,1),Détail!$A:$A,"<"&EDATE(DATE(2025,12,1),1)) -> 0
A29: Shenzhen Fortress Industry Co | C29: =SUMIF(Détail!$D:$D,"SHENZHEN FORTRESS INDUSTRY CO",Détail!$E:$E) -> -13150.78
A30: Mois | B30: Montant
A31: Janvier 2025 | B31: =SUMIFS(Détail!$E:$E,Détail!$D:$D,"SHENZHEN FORTRESS INDUSTRY CO",Détail!$A:$A,">="&DATE(2025,1,1),Détail!$A:$A,"<"&EDATE(DATE(2025,1,1),1)) -> 0
A32: Mars 2025 | B32: =SUMIFS(Détail!$E:$E,Détail!$D:$D,"SHENZHEN FORTRESS INDUSTRY CO",Détail!$A:$A,">="&DATE(2025,3,1),Détail!$A:$A,"<"&EDATE(DATE(2025,3,1),1)) -> 0
A33: Avril 2025 | B33: =SUMIFS(Détail!$E:$E,Détail!$D:$D,"SHENZHEN FORTRESS INDUSTRY CO",Détail!$A:$A,">="&DATE(2025,4,1),Détail!$A:$A,"<"&EDATE(DATE(2025,4,1),1)) -> 0
A34: Mai 2025 | B34: =SUMIFS(Détail!$E:$E,Détail!$D:$D,"SHENZHEN FORTRESS INDUSTRY CO",Détail!$A:$A,">="&DATE(2025,5,1),Détail!$A:$A,"<"&EDATE(DATE(2025,5,1),1)) -> 0
A35: Juin 2025 | B35: =SUMIFS(Détail!$E:$E,Détail!$D:$D,"SHENZHEN FORTRESS INDUSTRY CO",Détail!$A:$A,">="&DATE(2025,6,1),Détail!$A:$A,"<"&EDATE(DATE(2025,6,1),1)) -> 0
A36: Septembre 2025 | B36: =SUMIFS(Détail!$E:$E,Détail!$D:$D,"SHENZHEN FORTRESS INDUSTRY CO",Détail!$A:$A,">="&DATE(2025,9,1),Détail!$A:$A,"<"&EDATE(DATE(2025,9,1),1)) -> 0
A37: Octobre 2025 | B37: =SUMIFS(Détail!$E:$E,Détail!$D:$D,"SHENZHEN FORTRESS INDUSTRY CO",Détail!$A:$A,">="&DATE(2025,10,1),Détail!$A:$A,"<"&EDATE(DATE(2025,10,1),1)) -> -13150.78
A38: Novembre 2025 | B38: =SUMIFS(Détail!$E:$E,Détail!$D:$D,"SHENZHEN FORTRESS INDUSTRY CO",Détail!$A:$A,">="&DATE(2025,11,1),Détail!$A:$A,"<"&EDATE(DATE(2025,11,1),1)) -> 0
A39: Décembre 2025 | B39: =SUMIFS(Détail!$E:$E,Détail!$D:$D,"SHENZHEN FORTRESS INDUSTRY CO",Détail!$A:$A,">="&DATE(2025,12,1),Détail!$A:$A,"<"&EDATE(DATE(2025,12,1),1)) -> 0
A42: Luxe Perfumes Fzc | C42: =SUMIF(Détail!$D:$D,"LUXE PERFUMES FZC",Détail!$E:$E) -> -10208
A43: Mois | B43: Montant
A44: Janvier 2025 | B44: =SUMIFS(Détail!$E:$E,Détail!$D:$D,"LUXE PERFUMES FZC",Détail!$A:$A,">="&DATE(2025,1,1),Détail!$A:$A,"<"&EDATE(DATE(2025,1,1),1)) -> 0
A45: Mars 2025 | B45: =SUMIFS(Détail!$E:$E,Détail!$D:$D,"LUXE PERFUMES FZC",Détail!$A:$A,">="&DATE(2025,3,1),Détail!$A:$A,"<"&EDATE(DATE(2025,3,1),1)) -> 0
A46: Avril 2025 | B46: =SUMIFS(Détail!$E:$E,Détail!$D:$D,"LUXE PERFUMES FZC",Détail!$A:$A,">="&DATE(2025,4,1),Détail!$A:$A,"<"&EDATE(DATE(2025,4,1),1)) -> -10208
A47: Mai 2025 | B47: =SUMIFS(Détail!$E:$E,Détail!$D:$D,"LUXE PERFUMES FZC",Détail!$A:$A,">="&DATE(2025,5,1),Détail!$A:$A,"<"&EDATE(DATE(2025,5,1),1)) -> 0
A48: Juin 2025 | B48: =SUMIFS(Détail!$E:$E,Détail!$D:$D,"LUXE PERFUMES FZC",Détail!$A:$A,">="&DATE(2025,6,1),Détail!$A:$A,"<"&EDATE(DATE(2025,6,1),1)) -> 0
A49: Septembre 2025 | B49: =SUMIFS(Détail!$E:$E,Détail!$D:$D,"LUXE PERFUMES FZC",Détail!$A:$A,">="&DATE(2025,9,1),Détail!$A:$A,"<"&EDATE(DATE(2025,9,1),1)) -> 0
A50: Octobre 2025 | B50: =SUMIFS(Détail!$E:$E,Détail!$D:$D,"LUXE PERFUMES FZC",Détail!$A:$A,">="&DATE(2025,10,1),Détail!$A:$A,"<"&EDATE(DATE(2025,10,1),1)) -> 0
A51: Novembre 2025 | B51: =SUMIFS(Détail!$E:$E,Détail!$D:$D,"LUXE PERFUMES FZC",Détail!$A:$A,">="&DATE(2025,11,1),Détail!$A:$A,"<"&EDATE(DATE(2025,11,1),1)) -> 0
A52: Décembre 2025 | B52: =SUMIFS(Détail!$E:$E,Détail!$D:$D,"LUXE PERFUMES FZC",Détail!$A:$A,">="&DATE(2025,12,1),Détail!$A:$A,"<"&EDATE(DATE(2025,12,1),1)) -> 0
A55: Gold Rock Company Limited | C55: =SUMIF(Détail!$D:$D,"GOLD ROCK COMPANY LIMITED",Détail!$E:$E) -> -7217.25
A56: Mois | B56: Montant
A57: Janvier 2025 | B57: =SUMIFS(Détail!$E:$E,Détail!$D:$D,"GOLD ROCK COMPANY LIMITED",Détail!$A:$A,">="&DATE(2025,1,1),Détail!$A:$A,"<"&EDATE(DATE(2025,1,1),1)) -> 0
A58: Mars 2025 | B58: =SUMIFS(Détail!$E:$E,Détail!$D:$D,"GOLD ROCK COMPANY LIMITED",Détail!$A:$A,">="&DATE(2025,3,1),Détail!$A:$A,"<"&EDATE(DATE(2025,3,1),1)) -> -4290.8
A59: Avril 2025 | B59: =SUMIFS(Détail!$E:$E,Détail!$D:$D,"GOLD ROCK COMPANY LIMITED",Détail!$A:$A,">="&DATE(2025,4,1),Détail!$A:$A,"<"&EDATE(DATE(2025,4,1),1)) -> 0
A60: Mai 2025 | B60: =SUMIFS(Détail!$E:$E,Détail!$D:$D,"GOLD ROCK COMPANY LIMITED",Détail!$A:$A,">="&DATE(2025,5,1),Détail!$A:$A,"<"&EDATE(DATE(2025,5,1),1)) -> 0
A61: Juin 2025 | B61: =SUMIFS(Détail!$E:$E,Détail!$D:$D,"GOLD ROCK COMPANY LIMITED",Détail!$A:$A,">="&DATE(2025,6,1),Détail!$A:$A,"<"&EDATE(DATE(2025,6,1),1)) -> 0
A62: Septembre 2025 | B62: =SUMIFS(Détail!$E:$E,Détail!$D:$D,"GOLD ROCK COMPANY LIMITED",Détail!$A:$A,">="&DATE(2025,9,1),Détail!$A:$A,"<"&EDATE(DATE(2025,9,1),1)) -> 0
A63: Octobre 2025 | B63: =SUMIFS(Détail!$E:$E,Détail!$D:$D,"GOLD ROCK COMPANY LIMITED",Détail!$A:$A,">="&DATE(2025,10,1),Détail!$A:$A,"<"&EDATE(DATE(2025,10,1),1)) -> 0
A64: Novembre 2025 | B64: =SUMIFS(Détail!$E:$E,Détail!$D:$D,"GOLD ROCK COMPANY LIMITED",Détail!$A:$A,">="&DATE(2025,11,1),Détail!$A:$A,"<"&EDATE(DATE(2025,11,1),1)) -> 0
A65: Décembre 2025 | B65: =SUMIFS(Détail!$E:$E,Détail!$D:$D,"GOLD ROCK COMPANY LIMITED",Détail!$A:$A,">="&DATE(2025,12,1),Détail!$A:$A,"<"&EDATE(DATE(2025,12,1),1)) -> -2926.45
A68: Alibaba.Com Sin | C68: =SUMIF(Détail!$D:$D,"ALIBABA.COM SIN",Détail!$E:$E) -> -1601.47
A69: Mois | B69: Montant
A70: Janvier 2025 | B70: =SUMIFS(Détail!$E:$E,Détail!$D:$D,"ALIBABA.COM SIN",Détail!$A:$A,">="&DATE(2025,1,1),Détail!$A:$A,"<"&EDATE(DATE(2025,1,1),1)) -> 0
A71: Mars 2025 | B71: =SUMIFS(Détail!$E:$E,Détail!$D:$D,"ALIBABA.COM SIN",Détail!$A:$A,">="&DATE(2025,3,1),Détail!$A:$A,"<"&EDATE(DATE(2025,3,1),1)) -> 0
A72: Avril 2025 | B72: =SUMIFS(Détail!$E:$E,Détail!$D:$D,"ALIBABA.COM SIN",Détail!$A:$A,">="&DATE(2025,4,1),Détail!$A:$A,"<"&EDATE(DATE(2025,4,1),1)) -> 0
A73: Mai 2025 | B73: =SUMIFS(Détail!$E:$E,Détail!$D:$D,"ALIBABA.COM SIN",Détail!$A:$A,">="&DATE(2025,5,1),Détail!$A:$A,"<"&EDATE(DATE(2025,5,1),1)) -> 0
A74: Juin 2025 | B74: =SUMIFS(Détail!$E:$E,Détail!$D:$D,"ALIBABA.COM SIN",Détail!$A:$A,">="&DATE(2025,6,1),Détail!$A:$A,"<"&EDATE(DATE(2025,6,1),1)) -> 0
A75: Septembre 2025 | B75: =SUMIFS(Détail!$E:$E,Détail!$D:$D,"ALIBABA.COM SIN",Détail!$A:$A,">="&DATE(2025,9,1),Détail!$A:$A,"<"&EDATE(DATE(2025,9,1),1)) -> -1601.47
A76: Octobre 2025 | B76: =SUMIFS(Détail!$E:$E,Détail!$D:$D,"ALIBABA.COM SIN",Détail!$A:$A,">="&DATE(2025,10,1),Détail!$A:$A,"<"&EDATE(DATE(2025,10,1),1)) -> 0
A77: Novembre 2025 | B77: =SUMIFS(Détail!$E:$E,Détail!$D:$D,"ALIBABA.COM SIN",Détail!$A:$A,">="&DATE(2025,11,1),Détail!$A:$A,"<"&EDATE(DATE(2025,11,1),1)) -> 0
A78: Décembre 2025 | B78: =SUMIFS(Détail!$E:$E,Détail!$D:$D,"ALIBABA.COM SIN",Détail!$A:$A,">="&DATE(2025,12,1),Détail!$A:$A,"<"&EDATE(DATE(2025,12,1),1)) -> 0

Sheet Charges sociales détail
A1: Charges sociales & cotisations — détail par organisme (2025)
A3: Urssaf D'Ile De France | C3: =SUMIF(Détail!$D:$D,"URSSAF D'ILE DE FRANCE",Détail!$E:$E) -> -33018
A4: Mois | B4: Montant
A5: Janvier 2025 | B5: =SUMIFS(Détail!$E:$E,Détail!$D:$D,"URSSAF D'ILE DE FRANCE",Détail!$A:$A,">="&DATE(2025,1,1),Détail!$A:$A,"<"&EDATE(DATE(2025,1,1),1)) -> -1341
A6: Février 2025 | B6: =SUMIFS(Détail!$E:$E,Détail!$D:$D,"URSSAF D'ILE DE FRANCE",Détail!$A:$A,">="&DATE(2025,2,1),Détail!$A:$A,"<"&EDATE(DATE(2025,2,1),1)) -> -2405
A7: Mars 2025 | B7: =SUMIFS(Détail!$E:$E,Détail!$D:$D,"URSSAF D'ILE DE FRANCE",Détail!$A:$A,">="&DATE(2025,3,1),Détail!$A:$A,"<"&EDATE(DATE(2025,3,1),1)) -> -2860
A8: Avril 2025 | B8: =SUMIFS(Détail!$E:$E,Détail!$D:$D,"URSSAF D'ILE DE FRANCE",Détail!$A:$A,">="&DATE(2025,4,1),Détail!$A:$A,"<"&EDATE(DATE(2025,4,1),1)) -> -2839
A9: Mai 2025 | B9: =SUMIFS(Détail!$E:$E,Détail!$D:$D,"URSSAF D'ILE DE FRANCE",Détail!$A:$A,">="&DATE(2025,5,1),Détail!$A:$A,"<"&EDATE(DATE(2025,5,1),1)) -> -2887
A10: Juin 2025 | B10: =SUMIFS(Détail!$E:$E,Détail!$D:$D,"URSSAF D'ILE DE FRANCE",Détail!$A:$A,">="&DATE(2025,6,1),Détail!$A:$A,"<"&EDATE(DATE(2025,6,1),1)) -> -2927
A11: Juillet 2025 | B11: =SUMIFS(Détail!$E:$E,Détail!$D:$D,"URSSAF D'ILE DE FRANCE",Détail!$A:$A,">="&DATE(2025,7,1),Détail!$A:$A,"<"&EDATE(DATE(2025,7,1),1)) -> -2924
A12: Août 2025 | B12: =SUMIFS(Détail!$E:$E,Détail!$D:$D,"URSSAF D'ILE DE FRANCE",Détail!$A:$A,">="&DATE(2025,8,1),Détail!$A:$A,"<"&EDATE(DATE(2025,8,1),1)) -> -2930
A13: Septembre 2025 | B13: =SUMIFS(Détail!$E:$E,Détail!$D:$D,"URSSAF D'ILE DE FRANCE",Détail!$A:$A,">="&DATE(2025,9,1),Détail!$A:$A,"<"&EDATE(DATE(2025,9,1),1)) -> -3015
A14: Octobre 2025 | B14: =SUMIFS(Détail!$E:$E,Détail!$D:$D,"URSSAF D'ILE DE FRANCE",Détail!$A:$A,">="&DATE(2025,10,1),Détail!$A:$A,"<"&EDATE(DATE(2025,10,1),1)) -> -2927
A15: Novembre 2025 | B15: =SUMIFS(Détail!$E:$E,Détail!$D:$D,"URSSAF D'ILE DE FRANCE",Détail!$A:$A,">="&DATE(2025,11,1),Détail!$A:$A,"<"&EDATE(DATE(2025,11,1),1)) -> -3041
A16: Décembre 2025 | B16: =SUMIFS(Détail!$E:$E,Détail!$D:$D,"URSSAF D'ILE DE FRANCE",Détail!$A:$A,">="&DATE(2025,12,1),Détail!$A:$A,"<"&EDATE(DATE(2025,12,1),1)) -> -2922
A19: Ag2R Reunica | C19: =SUMIF(Détail!$D:$D,"AG2R REUNICA",Détail!$E:$E) -> -6882.84
A20: Mois | B20: Montant
A21: Janvier 2025 | B21: =SUMIFS(Détail!$E:$E,Détail!$D:$D,"AG2R REUNICA",Détail!$A:$A,">="&DATE(2025,1,1),Détail!$A:$A,"<"&EDATE(DATE(2025,1,1),1)) -> -268.42
A22: Février 2025 | B22: =SUMIFS(Détail!$E:$E,Détail!$D:$D,"AG2R REUNICA",Détail!$A:$A,">="&DATE(2025,2,1),Détail!$A:$A,"<"&EDATE(DATE(2025,2,1),1)) -> -503.88
A23: Mars 2025 | B23: =SUMIFS(Détail!$E:$E,Détail!$D:$D,"AG2R REUNICA",Détail!$A:$A,">="&DATE(2025,3,1),Détail!$A:$A,"<"&EDATE(DATE(2025,3,1),1)) -> -604.33
A24: Avril 2025 | B24: =SUMIFS(Détail!$E:$E,Détail!$D:$D,"AG2R REUNICA",Détail!$A:$A,">="&DATE(2025,4,1),Détail!$A:$A,"<"&EDATE(DATE(2025,4,1),1)) -> -600.22
A25: Mai 2025 | B25: =SUMIFS(Détail!$E:$E,Détail!$D:$D,"AG2R REUNICA",Détail!$A:$A,">="&DATE(2025,5,1),Détail!$A:$A,"<"&EDATE(DATE(2025,5,1),1)) -> -610.81
A26: Juin 2025 | B26: =SUMIFS(Détail!$E:$E,Détail!$D:$D,"AG2R REUNICA",Détail!$A:$A,">="&DATE(2025,6,1),Détail!$A:$A,"<"&EDATE(DATE(2025,6,1),1)) -> -611.37
A27: Juillet 2025 | B27: =SUMIFS(Détail!$E:$E,Détail!$D:$D,"AG2R REUNICA",Détail!$A:$A,">="&DATE(2025,7,1),Détail!$A:$A,"<"&EDATE(DATE(2025,7,1),1)) -> -610.75
A28: Août 2025 | B28: =SUMIFS(Détail!$E:$E,Détail!$D:$D,"AG2R REUNICA",Détail!$A:$A,">="&DATE(2025,8,1),Détail!$A:$A,"<"&EDATE(DATE(2025,8,1),1)) -> -610.68
A29: Septembre 2025 | B29: =SUMIFS(Détail!$E:$E,Détail!$D:$D,"AG2R REUNICA",Détail!$A:$A,">="&DATE(2025,9,1),Détail!$A:$A,"<"&EDATE(DATE(2025,9,1),1)) -> -631.06
A30: Octobre 2025 | B30: =SUMIFS(Détail!$E:$E,Détail!$D:$D,"AG2R REUNICA",Détail!$A:$A,">="&DATE(2025,10,1),Détail!$A:$A,"<"&EDATE(DATE(2025,10,1),1)) -> -610.48
A31: Novembre 2025 | B31: =SUMIFS(Détail!$E:$E,Détail!$D:$D,"AG2R REUNICA",Détail!$A:$A,">="&DATE(2025,11,1),Détail!$A:$A,"<"&EDATE(DATE(2025,11,1),1)) -> -610.23
A32: Décembre 2025 | B32: =SUMIFS(Détail!$E:$E,Détail!$D:$D,"AG2R REUNICA",Détail!$A:$A,">="&DATE(2025,12,1),Détail!$A:$A,"<"&EDATE(DATE(2025,12,1),1)) -> -610.61
A35: Direction Generale Des Finances Publiques (Dgfip) | C35: =SUMIF(Détail!$D:$D,"DIRECTION GENERALE DES FINANCES PUBLIQUES (DGFIP)",Détail!$E:$E) -> -4795
A36: Mois | B36: Montant
A37: Janvier 2025 | B37: =SUMIFS(Détail!$E:$E,Détail!$D:$D,"DIRECTION GENERALE DES FINANCES PUBLIQUES (DGFIP)",Détail!$A:$A,">="&DATE(2025,1,1),Détail!$A:$A,"<"&EDATE(DATE(2025,1,1),1)) -> -33
A38: Février 2025 | B38: =SUMIFS(Détail!$E:$E,Détail!$D:$D,"DIRECTION GENERALE DES FINANCES PUBLIQUES (DGFIP)",Détail!$A:$A,">="&DATE(2025,2,1),Détail!$A:$A,"<"&EDATE(DATE(2025,2,1),1)) -> -143
A39: Mars 2025 | B39: =SUMIFS(Détail!$E:$E,Détail!$D:$D,"DIRECTION GENERALE DES FINANCES PUBLIQUES (DGFIP)",Détail!$A:$A,">="&DATE(2025,3,1),Détail!$A:$A,"<"&EDATE(DATE(2025,3,1),1)) -> -191
A40: Avril 2025 | B40: =SUMIFS(Détail!$E:$E,Détail!$D:$D,"DIRECTION GENERALE DES FINANCES PUBLIQUES (DGFIP)",Détail!$A:$A,">="&DATE(2025,4,1),Détail!$A:$A,"<"&EDATE(DATE(2025,4,1),1)) -> -191
A41: Mai 2025 | B41: =SUMIFS(Détail!$E:$E,Détail!$D:$D,"DIRECTION GENERALE DES FINANCES PUBLIQUES (DGFIP)",Détail!$A:$A,">="&DATE(2025,5,1),Détail!$A:$A,"<"&EDATE(DATE(2025,5,1),1)) -> -191
A42: Juin 2025 | B42: =SUMIFS(Détail!$E:$E,Détail!$D:$D,"DIRECTION GENERALE DES FINANCES PUBLIQUES (DGFIP)",Détail!$A:$A,">="&DATE(2025,6,1),Détail!$A:$A,"<"&EDATE(DATE(2025,6,1),1)) -> -191
A43: Juillet 2025 | B43: =SUMIFS(Détail!$E:$E,Détail!$D:$D,"DIRECTION GENERALE DES FINANCES PUBLIQUES (DGFIP)",Détail!$A:$A,">="&DATE(2025,7,1),Détail!$A:$A,"<"&EDATE(DATE(2025,7,1),1)) -> -191
A44: Août 2025 | B44: =SUMIFS(Détail!$E:$E,Détail!$D:$D,"DIRECTION GENERALE DES FINANCES PUBLIQUES (DGFIP)",Détail!$A:$A,">="&DATE(2025,8,1),Détail!$A:$A,"<"&EDATE(DATE(2025,8,1),1)) -> -190
A45: Septembre 2025 | B45: =SUMIFS(Détail!$E:$E,Détail!$D:$D,"DIRECTION GENERALE DES FINANCES PUBLIQUES (DGFIP)",Détail!$A:$A,">="&DATE(2025,9,1),Détail!$A:$A,"<"&EDATE(DATE(2025,9,1),1)) -> -192
A46: Octobre 2025 | B46: =SUMIFS(Détail!$E:$E,Détail!$D:$D,"DIRECTION GENERALE DES FINANCES PUBLIQUES (DGFIP)",Détail!$A:$A,">="&DATE(2025,10,1),Détail!$A:$A,"<"&EDATE(DATE(2025,10,1),1)) -> -191
A47: Novembre 2025 | B47: =SUMIFS(Détail!$E:$E,Détail!$D:$D,"DIRECTION GENERALE DES FINANCES PUBLIQUES (DGFIP)",Détail!$A:$A,">="&DATE(2025,11,1),Détail!$A:$A,"<"&EDATE(DATE(2025,11,1),1)) -> -236
A48: Décembre 2025 | B48: =SUMIFS(Détail!$E:$E,Détail!$D:$D,"DIRECTION GENERALE DES FINANCES PUBLIQUES (DGFIP)",Détail!$A:$A,">="&DATE(2025,12,1),Détail!$A:$A,"<"&EDATE(DATE(2025,12,1),1)) -> -2855
A51: Ag2R La Mondiale | C51: =SUMIF(Détail!$D:$D,"AG2R LA MONDIALE",Détail!$E:$E) -> -69.62
A52: Mois | B52: Montant
A53: Janvier 2025 | B53: =SUMIFS(Détail!$E:$E,Détail!$D:$D,"AG2R LA MONDIALE",Détail!$A:$A,">="&DATE(2025,1,1),Détail!$A:$A,"<"&EDATE(DATE(2025,1,1),1)) -> 0
A54: Février 2025 | B54: =SUMIFS(Détail!$E:$E,Détail!$D:$D,"AG2R LA MONDIALE",Détail!$A:$A,">="&DATE(2025,2,1),Détail!$A:$A,"<"&EDATE(DATE(2025,2,1),1)) -> 0
A55: Mars 2025 | B55: =SUMIFS(Détail!$E:$E,Détail!$D:$D,"AG2R LA MONDIALE",Détail!$A:$A,">="&DATE(2025,3,1),Détail!$A:$A,"<"&EDATE(DATE(2025,3,1),1)) -> 0
A56: Avril 2025 | B56: =SUMIFS(Détail!$E:$E,Détail!$D:$D,"AG2R LA MONDIALE",Détail!$A:$A,">="&DATE(2025,4,1),Détail!$A:$A,"<"&EDATE(DATE(2025,4,1),1)) -> 0
A57: Mai 2025 | B57: =SUMIFS(Détail!$E:$E,Détail!$D:$D,"AG2R LA MONDIALE",Détail!$A:$A,">="&DATE(2025,5,1),Détail!$A:$A,"<"&EDATE(DATE(2025,5,1),1)) -> 0
A58: Juin 2025 | B58: =SUMIFS(Détail!$E:$E,Détail!$D:$D,"AG2R LA MONDIALE",Détail!$A:$A,">="&DATE(2025,6,1),Détail!$A:$A,"<"&EDATE(DATE(2025,6,1),1)) -> 0
A59: Juillet 2025 | B59: =SUMIFS(Détail!$E:$E,Détail!$D:$D,"AG2R LA MONDIALE",Détail!$A:$A,">="&DATE(2025,7,1),Détail!$A:$A,"<"&EDATE(DATE(2025,7,1),1)) -> -69.62
A60: Août 2025 | B60: =SUMIFS(Détail!$E:$E,Détail!$D:$D,"AG2R LA MONDIALE",Détail!$A:$A,">="&DATE(2025,8,1),Détail!$A:$A,"<"&EDATE(DATE(2025,8,1),1)) -> 0
A61: Septembre 2025 | B61: =SUMIFS(Détail!$E:$E,Détail!$D:$D,"AG2R LA MONDIALE",Détail!$A:$A,">="&DATE(2025,9,1),Détail!$A:$A,"<"&EDATE(DATE(2025,9,1),1)) -> 0
A62: Octobre 2025 | B62: =SUMIFS(Détail!$E:$E,Détail!$D:$D,"AG2R LA MONDIALE",Détail!$A:$A,">="&DATE(2025,10,1),Détail!$A:$A,"<"&EDATE(DATE(2025,10,1),1)) -> 0
A63: Novembre 2025 | B63: =SUMIFS(Détail!$E:$E,Détail!$D:$D,"AG2R LA MONDIALE",Détail!$A:$A,">="&DATE(2025,11,1),Détail!$A:$A,"<"&EDATE(DATE(2025,11,1),1)) -> 0
A64: Décembre 2025 | B64: =SUMIFS(Détail!$E:$E,Détail!$D:$D,"AG2R LA MONDIALE",Détail!$A:$A,">="&DATE(2025,12,1),Détail!$A:$A,"<"&EDATE(DATE(2025,12,1),1)) -> 0
A67: Akto | C67: =SUMIF(Détail!$D:$D,"AKTO",Détail!$E:E) -> -150
A68: Mois | B68: Montant
A69: Janvier 2025 | B69: =SUMIFS(Détail!$E:$E,Détail!$D:$D,"AKTO",Détail!$A:$A,">="&DATE(2025,1,1),Détail!$A:$A,"<"&EDATE(DATE(2025,1,1),1)) -> 0
A70: Février 2025 | B70: =SUMIFS(Détail!$E:$E,Détail!$D:$D,"AKTO",Détail!$A:$A,">="&DATE(2025,2,1),Détail!$A:$A,"<"&EDATE(DATE(2025,2,1),1)) -> 0
A71: Mars 2025 | B71: =SUMIFS(Détail!$E:$E,Détail!$D:$D,"AKTO",Détail!$A:$A,">="&DATE(2025,3,1),Détail!$A:$A,"<"&EDATE(DATE(2025,3,1),1)) -> -150
A72: Avril 2025 | B72: =SUMIFS(Détail!$E:$E,Détail!$D:$D,"AKTO",Détail!$A:$A,">="&DATE(2025,4,1),Détail!$A:$A,"<"&EDATE(DATE(2025,4,1),1)) -> 0
A73: Mai 2025 | B73: =SUMIFS(Détail!$E:$E,Détail!$D:$D,"AKTO",Détail!$A:$A,">="&DATE(2025,5,1),Détail!$A:$A,"<"&EDATE(DATE(2025,5,1),1)) -> 0
A74: Juin 2025 | B74: =SUMIFS(Détail!$E:$E,Détail!$D:$D,"AKTO",Détail!$A:$A,">="&DATE(2025,6,1),Détail!$A:$A,"<"&EDATE(DATE(2025,6,1),1)) -> 0
A75: Juillet 2025 | B75: =SUMIFS(Détail!$E:$E,Détail!$D:$D,"AKTO",Détail!$A:$A,">="&DATE(2025,7,1),Détail!$A:$A,"<"&EDATE(DATE(2025,7,1),1)) -> 0
A76: Août 2025 | B76: =SUMIFS(Détail!$E:$E,Détail!$D:$D,"AKTO",Détail!$A:$A,">="&DATE(2025,8,1),Détail!$A:$A,"<"&EDATE(DATE(2025,8,1),1)) -> 0
A77: Septembre 2025 | B77: =SUMIFS(Détail!$E:$E,Détail!$D:$D,"AKTO",Détail!$A:$A,">="&DATE(2025,9,1),Détail!$A:$A,"<"&EDATE(DATE(2025,9,1),1)) -> 0
A78: Octobre 2025 | B78: =SUMIFS(Détail!$E:$E,Détail!$D:$D,"AKTO",Détail!$A:$A,">="&DATE(2025,10,1),Détail!$A:$A,"<"&EDATE(DATE(2025,10,1),1)) -> 0
A79: Novembre 2025 | B79: =SUMIFS(Détail!$E:$E,Détail!$D:$D,"AKTO",Détail!$A:$A,">="&DATE(2025,11,1),Détail!$A:$A,"<"&EDATE(DATE(2025,11,1),1)) -> 0
A80: Décembre 2025 | B80: =SUMIFS(Détail!$E:$E,Détail!$D:$D,"AKTO",Détail!$A:$A,">="&DATE(2025,12,1),Détail!$A:$A,"<"&EDATE(DATE(2025,12,1),1)) -> 0

Sheet Voyages détail
A1: Voyages / déplacements — détail par prestataire (2025)
A3: Emirates | C3: =SUMIF(Détail!$D:$D,"EMIRATES",Détail!$E:$E) -> -10638.18
A4: Mois | B4: Montant
A5: Janvier 2025 | B5: =SUMIFS(Détail!$E:$E,Détail!$D:$D,"EMIRATES",Détail!$A:$A,">="&DATE(2025,1,1),Détail!$A:$A,"<"&EDATE(DATE(2025,1,1),1)) -> 0
A6: Février 2025 | B6: =SUMIFS(Détail!$E:$E,Détail!$D:$D,"EMIRATES",Détail!$A:$A,">="&DATE(2025,2,1),Détail!$A:$A,"<"&EDATE(DATE(2025,2,1),1)) -> 0
A7: Mars 2025 | B7: =SUMIFS(Détail!$E:$E,Détail!$D:$D,"EMIRATES",Détail!$A:$A,">="&DATE(2025,3,1),Détail!$A:$A,"<"&EDATE(DATE(2025,3,1),1)) -> 0
A8: Avril 2025 | B8: =SUMIFS(Détail!$E:$E,Détail!$D:$D,"EMIRATES",Détail!$A:$A,">="&DATE(2025,4,1),Détail!$A:$A,"<"&EDATE(DATE(2025,4,1),1)) -> -2378.04
A9: Mai 2025 | B9: =SUMIFS(Détail!$E:$E,Détail!$D:$D,"EMIRATES",Détail!$A:$A,">="&DATE(2025,5,1),Détail!$A:$A,"<"&EDATE(DATE(2025,5,1),1)) -> -856.32
A10: Juin 2025 | B10: =SUMIFS(Détail!$E:$E,Détail!$D:$D,"EMIRATES",Détail!$A:$A,">="&DATE(2025,6,1),Détail!$A:$A,"<"&EDATE(DATE(2025,6,1),1)) -> -916.64
A11: Juillet 2025 | B11: =SUMIFS(Détail!$E:$E,Détail!$D:$D,"EMIRATES",Détail!$A:$A,">="&DATE(2025,7,1),Détail!$A:$A,"<"&EDATE(DATE(2025,7,1),1)) -> -1910.9
A12: Août 2025 | B12: =SUMIFS(Détail!$E:$E,Détail!$D:$D,"EMIRATES",Détail!$A:$A,">="&DATE(2025,8,1),Détail!$A:$A,"<"&EDATE(DATE(2025,8,1),1)) -> 0
A13: Septembre 2025 | B13: =SUMIFS(Détail!$E:$E,Détail!$D:$D,"EMIRATES",Détail!$A:$A,">="&DATE(2025,9,1),Détail!$A:$A,"<"&EDATE(DATE(2025,9,1),1)) -> -3176.88
A14: Octobre 2025 | B14: =SUMIFS(Détail!$E:$E,Détail!$D:$D,"EMIRATES",Détail!$A:$A,">="&DATE(2025,10,1),Détail!$A:$A,"<"&EDATE(DATE(2025,10,1),1)) -> -1324.8
A15: Novembre 2025 | B15: =SUMIFS(Détail!$E:$E,Détail!$D:$D,"EMIRATES",Détail!$A:$A,">="&DATE(2025,11,1),Détail!$A:$A,"<"&EDATE(DATE(2025,11,1),1)) -> -74.6
A16: Décembre 2025 | B16: =SUMIFS(Détail!$E:$E,Détail!$D:$D,"EMIRATES",Détail!$A:$A,">="&DATE(2025,12,1),Détail!$A:$A,"<"&EDATE(DATE(2025,12,1),1)) -> 0
A19: Air France | C19: =SUMIF(Détail!$D:$D,"AIR FRANCE",Détail!$E:$E) -> -2218.54
A20: Mois | B20: Montant
A21: Janvier 2025 | B21: =SUMIFS(Détail!$E:$E,Détail!$D:$D,"AIR FRANCE",Détail!$A:$A,">="&DATE(2025,1,1),Détail!$A:$A,"<"&EDATE(DATE(2025,1,1),1)) -> -198.15
A22: Février 2025 | B22: =SUMIFS(Détail!$E:$E,Détail!$D:$D,"AIR FRANCE",Détail!$A:$A,">="&DATE(2025,2,1),Détail!$A:$A,"<"&EDATE(DATE(2025,2,1),1)) -> 0
A23: Mars 2025 | B23: =SUMIFS(Détail!$E:$E,Détail!$D:$D,"AIR FRANCE",Détail!$A:$A,">="&DATE(2025,3,1),Détail!$A:$A,"<"&EDATE(DATE(2025,3,1),1)) -> -350.21
A24: Avril 2025 | B24: =SUMIFS(Détail!$E:$E,Détail!$D:$D,"AIR FRANCE",Détail!$A:$A,">="&DATE(2025,4,1),Détail!$A:$A,"<"&EDATE(DATE(2025,4,1),1)) -> 0
A25: Mai 2025 | B25: =SUMIFS(Détail!$E:$E,Détail!$D:$D,"AIR FRANCE",Détail!$A:$A,">="&DATE(2025,5,1),Détail!$A:$A,"<"&EDATE(DATE(2025,5,1),1)) -> -199.6
A26: Juin 2025 | B26: =SUMIFS(Détail!$E:$E,Détail!$D:$D,"AIR FRANCE",Détail!$A:$A,">="&DATE(2025,6,1),Détail!$A:$A,"<"&EDATE(DATE(2025,6,1),1)) -> 0
A27: Juillet 2025 | B27: =SUMIFS(Détail!$E:$E,Détail!$D:$D,"AIR FRANCE",Détail!$A:$A,">="&DATE(2025,7,1),Détail!$A:$A,"<"&EDATE(DATE(2025,7,1),1)) -> 0
A28: Août 2025 | B28: =SUMIFS(Détail!$E:$E,Détail!$D:$D,"AIR FRANCE",Détail!$A:$A,">="&DATE(2025,8,1),Détail!$A:$A,"<"&EDATE(DATE(2025,8,1),1)) -> -831.75
A29: Septembre 2025 | B29: =SUMIFS(Détail!$E:$E,Détail!$D:$D,"AIR FRANCE",Détail!$A:$A,">="&DATE(2025,9,1),Détail!$A:$A,"<"&EDATE(DATE(2025,9,1),1)) -> 0
A30: Octobre 2025 | B30: =SUMIFS(Détail!$E:$E,Détail!$D:$D,"AIR FRANCE",Détail!$A:$A,">="&DATE(2025,10,1),Détail!$A:$A,"<"&EDATE(DATE(2025,10,1),1)) -> 0
A31: Novembre 2025 | B31: =SUMIFS(Détail!$E:$E,Détail!$D:$D,"AIR FRANCE",Détail!$A:$A,">="&DATE(2025,11,1),Détail!$A:$A,"<"&EDATE(DATE(2025,11,1),1)) -> -267.08
A32: Décembre 2025 | B32: =SUMIFS(Détail!$E:$E,Détail!$D:$D,"AIR FRANCE",Détail!$A:$A,">="&DATE(2025,12,1),Détail!$A:$A,"<"&EDATE(DATE(2025,12,1),1)) -> -371.75
A35: Sonder.Com | C35: =SUMIF(Détail!$D:$D,"SONDER.COM",Détail!$E:$E) -> -1586.9
A36: Mois | B36: Montant
A37: Janvier 2025 | B37: =SUMIFS(Détail!$E:$E,Détail!$D:$D,"SONDER.COM",Détail!$A:$A,">="&DATE(2025,1,1),Détail!$A:$A,"<"&EDATE(DATE(2025,1,1),1)) -> 0
A38: Février 2025 | B38: =SUMIFS(Détail!$E:$E,Détail!$D:$D,"SONDER.COM",Détail!$A:$A,">="&DATE(2025,2,1),Détail!$A:$A,"<"&EDATE(DATE(2025,2,1),1)) -> 0
A39: Mars 2025 | B39: =SUMIFS(Détail!$E:$E,Détail!$D:$D,"SONDER.COM",Détail!$A:$A,">="&DATE(2025,3,1),Détail!$A:$A,"<"&EDATE(DATE(2025,3,1),1)) -> 0
A40: Avril 2025 | B40: =SUMIFS(Détail!$E:$E,Détail!$D:$D,"SONDER.COM",Détail!$A:$A,">="&DATE(2025,4,1),Détail!$A:$A,"<"&EDATE(DATE(2025,4,1),1)) -> 0
A41: Mai 2025 | B41: =SUMIFS(Détail!$E:$E,Détail!$D:$D,"SONDER.COM",Détail!$A:$A,">="&DATE(2025,5,1),Détail!$A:$A,"<"&EDATE(DATE(2025,5,1),1)) -> 0
A42: Juin 2025 | B42: =SUMIFS(Détail!$E:$E,Détail!$D:$D,"SONDER.COM",Détail!$A:$A,">="&DATE(2025,6,1),Détail!$A:$A,"<"&EDATE(DATE(2025,6,1),1)) -> 0
A43: Juillet 2025 | B43: =SUMIFS(Détail!$E:$E,Détail!$D:$D,"SONDER.COM",Détail!$A:$A,">="&DATE(2025,7,1),Détail!$A:$A,"<"&EDATE(DATE(2025,7,1),1)) -> 0
A44: Août 2025 | B44: =SUMIFS(Détail!$E:$E,Détail!$D:$D,"SONDER.COM",Détail!$A:$A,">="&DATE(2025,8,1),Détail!$A:$A,"<"&EDATE(DATE(2025,8,1),1)) -> 0
A45: Septembre 2025 | B45: =SUMIFS(Détail!$E:$E,Détail!$D:$D,"SONDER.COM",Détail!$A:$A,">="&DATE(2025,9,1),Détail!$A:$A,"<"&EDATE(DATE(2025,9,1),1)) -> 0
A46: Octobre 2025 | B46: =SUMIFS(Détail!$E:$E,Détail!$D:$D,"SONDER.COM",Détail!$A:$A,">="&DATE(2025,10,1),Détail!$A:$A,"<"&EDATE(DATE(2025,10,1),1)) -> -1586.9
A47: Novembre 2025 | B47: =SUMIFS(Détail!$E:$E,Détail!$D:$D,"SONDER.COM",Détail!$A:$A,">="&DATE(2025,11,1),Détail!$A:$A,"<"&EDATE(DATE(2025,11,1),1)) -> 0
A48: Décembre 2025 | B48: =SUMIFS(Détail!$E:$E,Détail!$D:$D,"SONDER.COM",Détail!$A:$A,">="&DATE(2025,12,1),Détail!$A:$A,"<"&EDATE(DATE(2025,12,1),1)) -> 0
A51: Five Luxe Hotel | C51: =SUMIF(Détail!$D:$D,"FIVE LUXE HOTEL",Détail!$E:$E) -> -1402.94
A52: Mois | B52: Montant
A53: Janvier 2025 | B53: =SUMIFS(Détail!$E:$E,Détail!$D:$D,"FIVE LUXE HOTEL",Détail!$A:$A,">="&DATE(2025,1,1),Détail!$A:$A,"<"&EDATE(DATE(2025,1,1),1)) -> 0
A54: Février 2025 | B54: =SUMIFS(Détail!$E:$E,Détail!$D:$D,"FIVE LUXE HOTEL",Détail!$A:$A,">="&DATE(2025,2,1),Détail!$A:$A,"<"&EDATE(DATE(2025,2,1),1)) -> 0
A55: Mars 2025 | B55: =SUMIFS(Détail!$E:$E,Détail!$D:$D,"FIVE LUXE HOTEL",Détail!$A:$A,">="&DATE(2025,3,1),Détail!$A:$A,"<"&EDATE(DATE(2025,3,1),1)) -> 0
A56: Avril 2025 | B56: =SUMIFS(Détail!$E:$E,Détail!$D:$D,"FIVE LUXE HOTEL",Détail!$A:$A,">="&DATE(2025,4,1),Détail!$A:$A,"<"&EDATE(DATE(2025,4,1),1)) -> -1402.94
A57: Mai 2025 | B57: =SUMIFS(Détail!$E:$E,Détail!$D:$D,"FIVE LUXE HOTEL",Détail!$A:$A,">="&DATE(2025,5,1),Détail!$A:$A,"<"&EDATE(DATE(2025,5,1),1)) -> 0
A58: Juin 2025 | B58: =SUMIFS(Détail!$E:$E,Détail!$D:$D,"FIVE LUXE HOTEL",Détail!$A:$A,">="&DATE(2025,6,1),Détail!$A:$A,"<"&EDATE(DATE(2025,6,1),1)) -> 0
A59: Juillet 2025 | B59: =SUMIFS(Détail!$E:$E,Détail!$D:$D,"FIVE LUXE HOTEL",Détail!$A:$A,">="&DATE(2025,7,1),Détail!$A:$A,"<"&EDATE(DATE(2025,7,1),1)) -> 0
A60: Août 2025 | B60: =SUMIFS(Détail!$E:$E,Détail!$D:$D,"FIVE LUXE HOTEL",Détail!$A:$A,">="&DATE(2025,8,1),Détail!$A:$A,"<"&EDATE(DATE(2025,8,1),1)) -> 0
A61: Septembre 2025 | B61: =SUMIFS(Détail!$E:$E,Détail!$D:$D,"FIVE LUXE HOTEL",Détail!$A:$A,">="&DATE(2025,9,1),Détail!$A:$A,"<"&EDATE(DATE(2025,9,1),1)) -> 0
A62: Octobre 2025 | B62: =SUMIFS(Détail!$E:$E,Détail!$D:$D,"FIVE LUXE HOTEL",Détail!$A:$A,">="&DATE(2025,10,1),Détail!$A:$A,"<"&EDATE(DATE(2025,10,1),1)) -> 0
A63: Novembre 2025 | B63: =SUMIFS(Détail!$E:$E,Détail!$D:$D,"FIVE LUXE HOTEL",Détail!$A:$A,">="&DATE(2025,11,1),Détail!$A:$A,"<"&EDATE(DATE(2025,11,1),1)) -> 0
A64: Décembre 2025 | B64: =SUMIFS(Détail!$E:$E,Détail!$D:$D,"FIVE LUXE HOTEL",Détail!$A:$A,">="&DATE(2025,12,1),Détail!$A:$A,"<"&EDATE(DATE(2025,12,1),1)) -> 0
A67: Lord Byron | C67: =SUMIF(Détail!$D:$D,"LORD BYRON",Détail!$E:$E) -> -1273.6
A68: Mois | B68: Montant
A69: Janvier 2025 | B69: =SUMIFS(Détail!$E:$E,Détail!$D:$D,"LORD BYRON",Détail!$A:$A,">="&DATE(2025,1,1),Détail!$A:$A,"<"&EDATE(DATE(2025,1,1),1)) -> 0
A70: Février 2025 | B70: =SUMIFS(Détail!$E:$E,Détail!$D:$D,"LORD BYRON",Détail!$A:$A,">="&DATE(2025,2,1),Détail!$A:$A,"<"&EDATE(DATE(2025,2,1),1)) -> 0
A71: Mars 2025 | B71: =SUMIFS(Détail!$E:$E,Détail!$D:$D,"LORD BYRON",Détail!$A:$A,">="&DATE(2025,3,1),Détail!$A:$A,"<"&EDATE(DATE(2025,3,1),1)) -> 0
A72: Avril 2025 | B72: =SUMIFS(Détail!$E:$E,Détail!$D:$D,"LORD BYRON",Détail!$A:$A,">="&DATE(2025,4,1),Détail!$A:$A,"<"&EDATE(DATE(2025,4,1),1)) -> 0
A73: Mai 2025 | B73: =SUMIFS(Détail!$E:$E,Détail!$D:$D,"LORD BYRON",Détail!$A:$A,">="&DATE(2025,5,1),Détail!$A:$A,"<"&EDATE(DATE(2025,5,1),1)) -> 0
A74: Juin 2025 | B74: =SUMIFS(Détail!$E:$E,Détail!$D:$D,"LORD BYRON",Détail!$A:$A,">="&DATE(2025,6,1),Détail!$A:$A,"<"&EDATE(DATE(2025,6,1),1)) -> 0
A75: Juillet 2025 | B75: =SUMIFS(Détail!$E:$E,Détail!$D:$D,"LORD BYRON",Détail!$A:$A,">="&DATE(2025,7,1),Détail!$A:$A,"<"&EDATE(DATE(2025,7,1),1)) -> 0
A76: Août 2025 | B76: =SUMIFS(Détail!$E:$E,Détail!$D:$D,"LORD BYRON",Détail!$A:$A,">="&DATE(2025,8,1),Détail!$A:$A,"<"&EDATE(DATE(2025,8,1),1)) -> 0
A77: Septembre 2025 | B77: =SUMIFS(Détail!$E:$E,Détail!$D:$D,"LORD BYRON",Détail!$A:$A,">="&DATE(2025,9,1),Détail!$A:$A,"<"&EDATE(DATE(2025,9,1),1)) -> 0
A78: Octobre 2025 | B78: =SUMIFS(Détail!$E:$E,Détail!$D:$D,"LORD BYRON",Détail!$A:$A,">="&DATE(2025,10,1),Détail!$A:$A,"<"&EDATE(DATE(2025,10,1),1)) -> 0
A79: Novembre 2025 | B79: =SUMIFS(Détail!$E:$E,Détail!$D:$D,"LORD BYRON",Détail!$A:$A,">="&DATE(2025,11,1),Détail!$A:$A,"<"&EDATE(DATE(2025,11,1),1)) -> -1273.6
A80: Décembre 2025 | B80: =SUMIFS(Détail!$E:$E,Détail!$D:$D,"LORD BYRON",Détail!$A:$A,">="&DATE(2025,12,1),Détail!$A:$A,"<"&EDATE(DATE(2025,12,1),1)) -> 0
A83: La Vie Vacation Homes Rental Llc | C83: =SUMIF(Détail!$D:$D,"LA VIE VACATION HOMES RENTAL LLC",Détail!$E:$E) -> -813
A84: Mois | B84: Montant
A85: Janvier 2025 | B85: =SUMIFS(Détail!$E:$E,Détail!$D:$D,"LA VIE VACATION HOMES RENTAL LLC",Détail!$A:$A,">="&DATE(2025,1,1),Détail!$A:$A,"<"&EDATE(DATE(2025,1,1),1)) -> 0
A86: Février 2025 | B86: =SUMIFS(Détail!$E:$E,Détail!$D:$D,"LA VIE VACATION HOMES RENTAL LLC",Détail!$A:$A,">="&DATE(2025,2,1),Détail!$A:$A,"<"&EDATE(DATE(2025,2,1),1)) -> 0
A87: Mars 2025 | B87: =SUMIFS(Détail!$E:$E,Détail!$D:$D,"LA VIE VACATION HOMES RENTAL LLC",Détail!$A:$A,">="&DATE(2025,3,1),Détail!$A:$A,"<"&EDATE(DATE(2025,3,1),1)) -> 0
A88: Avril 2025 | B88: =SUMIFS(Détail!$E:$E,Détail!$D:$D,"LA VIE VACATION HOMES RENTAL LLC",Détail!$A:$A,">="&DATE(2025,4,1),Détail!$A:$A,"<"&EDATE(DATE(2025,4,1),1)) -> 0
A89: Mai 2025 | B89: =SUMIFS(Détail!$E:$E,Détail!$D:$D,"LA VIE VACATION HOMES RENTAL LLC",Détail!$A:$A,">="&DATE(2025,5,1),Détail!$A:$A,"<"&EDATE(DATE(2025,5,1),1)) -> 0
A90: Juin 2025 | B90: =SUMIFS(Détail!$E:$E,Détail!$D:$D,"LA VIE VACATION HOMES RENTAL LLC",Détail!$A:$A,">="&DATE(2025,6,1),Détail!$A:$A,"<"&EDATE(DATE(2025,6,1),1)) -> 0
A91: Juillet 2025 | B91: =SUMIFS(Détail!$E:$E,Détail!$D:$D,"LA VIE VACATION HOMES RENTAL LLC",Détail!$A:$A,">="&DATE(2025,7,1),Détail!$A:$A,"<"&EDATE(DATE(2025,7,1),1)) -> 0
A92: Août 2025 | B92: =SUMIFS(Détail!$E:$E,Détail!$D:$D,"LA VIE VACATION HOMES RENTAL LLC",Détail!$A:$A,">="&DATE(2025,8,1),Détail!$A:$A,"<"&EDATE(DATE(2025,8,1),1)) -> 0
A93: Septembre 2025 | B93: =SUMIFS(Détail!$E:$E,Détail!$D:$D,"LA VIE VACATION HOMES RENTAL LLC",Détail!$A:$A,">="&DATE(2025,9,1),Détail!$A:$A,"<"&EDATE(DATE(2025,9,1),1)) -> -813
A94: Octobre 2025 | B94: =SUMIFS(Détail!$E:$E,Détail!$D:$D,"LA VIE VACATION HOMES RENTAL LLC",Détail!$A:$A,">="&DATE(2025,10,1),Détail!$A:$A,"<"&EDATE(DATE(2025,10,1),1)) -> 0
A95: Novembre 2025 | B95: =SUMIFS(Détail!$E:$E,Détail!$D:$D,"LA VIE VACATION HOMES RENTAL LLC",Détail!$A:$A,">="&DATE(2025,11,1),Détail!$A:$A,"<"&EDATE(DATE(2025,11,1),1)) -> 0
A96: Décembre 2025 | B96: =SUMIFS(Détail!$E:$E,Détail!$D:$D,"LA VIE VACATION HOMES RENTAL LLC",Détail!$A:$A,">="&DATE(2025,12,1),Détail!$A:$A,"<"&EDATE(DATE(2025,12,1),1)) -> 0
A99: Travel Reservat | C99: =SUMIF(Détail!$D:$D,"TRAVEL RESERVAT",Détail!$E:$E) -> -737.42
A100: Mois | B100: Montant
A101: Janvier 2025 | B101: =SUMIFS(Détail!$E:$E,Détail!$D:$D,"TRAVEL RESERVAT",Détail!$A:$A,">="&DATE(2025,1,1),Détail!$A:$A,"<"&EDATE(DATE(2025,1,1),1)) -> 0
A102: Février 2025 | B102: =SUMIFS(Détail!$E:$E,Détail!$D:$D,"TRAVEL RESERVAT",Détail!$A:$A,">="&DATE(2025,2,1),Détail!$A:$A,"<"&EDATE(DATE(2025,2,1),1)) -> 0
A103: Mars 2025 | B103: =SUMIFS(Détail!$E:$E,Détail!$D:$D,"TRAVEL RESERVAT",Détail!$A:$A,">="&DATE(2025,3,1),Détail!$A:$A,"<"&EDATE(DATE(2025,3,1),1)) -> 0
A104: Avril 2025 | B104: =SUMIFS(Détail!$E:$E,Détail!$D:$D,"TRAVEL RESERVAT",Détail!$A:$A,">="&DATE(2025,4,1),Détail!$A:$A,"<"&EDATE(DATE(2025,4,1),1)) -> -737.42
A105: Mai 2025 | B105: =SUMIFS(Détail!$E:$E,Détail!$D:$D,"TRAVEL RESERVAT",Détail!$A:$A,">="&DATE(2025,5,1),Détail!$A:$A,"<"&EDATE(DATE(2025,5,1),1)) -> 0
A106: Juin 2025 | B106: =SUMIFS(Détail!$E:$E,Détail!$D:$D,"TRAVEL RESERVAT",Détail!$A:$A,">="&DATE(2025,6,1),Détail!$A:$A,"<"&EDATE(DATE(2025,6,1),1)) -> 0
A107: Juillet 2025 | B107: =SUMIFS(Détail!$E:$E,Détail!$D:$D,"TRAVEL RESERVAT",Détail!$A:$A,">="&DATE(2025,7,1),Détail!$A:$A,"<"&EDATE(DATE(2025,7,1),1)) -> 0
A108: Août 2025 | B108: =SUMIFS(Détail!$E:$E,Détail!$D:$D,"TRAVEL RESERVAT",Détail!$A:$A,">="&DATE(2025,8,1),Détail!$A:$A,"<"&EDATE(DATE(2025,8,1),1)) -> 0
A109: Septembre 2025 | B109: =SUMIFS(Détail!$E:$E,Détail!$D:$D,"TRAVEL RESERVAT",Détail!$A:$A,">="&DATE(2025,9,1),Détail!$A:$A,"<"&EDATE(DATE(2025,9,1),1)) -> 0
A110: Octobre 2025 | B110: =SUMIFS(Détail!$E:$E,Détail!$D:$D,"TRAVEL RESERVAT",Détail!$A:$A,">="&DATE(2025,10,1),Détail!$A:$A,"<"&EDATE(DATE(2025,10,1),1)) -> 0
A111: Novembre 2025 | B111: =SUMIFS(Détail!$E:$E,Détail!$D:$D,"TRAVEL RESERVAT",Détail!$A:$A,">="&DATE(2025,11,1),Détail!$A:$A,"<"&EDATE(DATE(2025,11,1),1)) -> 0
A112: Décembre 2025 | B112: =SUMIFS(Détail!$E:$E,Détail!$D:$D,"TRAVEL RESERVAT",Détail!$A:$A,">="&DATE(2025,12,1),Détail!$A:$A,"<"&EDATE(DATE(2025,12,1),1)) -> 0
A115: Dubai World Tra | C115: =SUMIF(Détail!$D:$D,"DUBAI WORLD TRA",Détail!$E:$E) -> -585.13
...

Sheet Téléphone-Internet détail
A1: Téléphone / Internet / Logiciels — détail par prestataire (2025)
A3: Orange Sa | C3: =SUMIF(Détail!$D:$D,"ORANGE SA",Détail!$E:$E) -> -6873.65
A4: Mois | B4: Montant
A5: Janvier 2025 | B5: =SUMIFS(Détail!$E:$E,Détail!$D:$D,"ORANGE SA",Détail!$A:$A,">="&DATE(2025,1,1),Détail!$A:$A,"<"&EDATE(DATE(2025,1,1),1)) -> -443.79
A6: Février 2025 | B6: =SUMIFS(Détail!$E:$E,Détail!$D:$D,"ORANGE SA",Détail!$A:$A,">="&DATE(2025,2,1),Détail!$A:$A,"<"&EDATE(DATE(2025,2,1),1)) -> -448.53
A7: Mars 2025 | B7: =SUMIFS(Détail!$E:$E,Détail!$D:$D,"ORANGE SA",Détail!$A:$A,">="&DATE(2025,3,1),Détail!$A:$A,"<"&EDATE(DATE(2025,3,1),1)) -> -441.74
A8: Avril 2025 | B8: =SUMIFS(Détail!$E:$E,Détail!$D:$D,"ORANGE SA",Détail!$A:$A,">="&DATE(2025,4,1),Détail!$A:$A,"<"&EDATE(DATE(2025,4,1),1)) -> -531.18
A9: Mai 2025 | B9: =SUMIFS(Détail!$E:$E,Détail!$D:$D,"ORANGE SA",Détail!$A:$A,">="&DATE(2025,5,1),Détail!$A:$A,"<"&EDATE(DATE(2025,5,1),1)) -> -488.91
A10: Juin 2025 | B10: =SUMIFS(Détail!$E:$E,Détail!$D:$D,"ORANGE SA",Détail!$A:$A,">="&DATE(2025,6,1),Détail!$A:$A,"<"&EDATE(DATE(2025,6,1),1)) -> -531.8
A11: Juillet 2025 | B11: =SUMIFS(Détail!$E:$E,Détail!$D:$D,"ORANGE SA",Détail!$A:$A,">="&DATE(2025,7,1),Détail!$A:$A,"<"&EDATE(DATE(2025,7,1),1)) -> -471.5
A12: Août 2025 | B12: =SUMIFS(Détail!$E:$E,Détail!$D:$D,"ORANGE SA",Détail!$A:$A,">="&DATE(2025,8,1),Détail!$A:$A,"<"&EDATE(DATE(2025,8,1),1)) -> -474.9
A13: Septembre 2025 | B13: =SUMIFS(Détail!$E:$E,Détail!$D:$D,"ORANGE SA",Détail!$A:$A,">="&DATE(2025,9,1),Détail!$A:$A,"<"&EDATE(DATE(2025,9,1),1)) -> -1318.82
A14: Octobre 2025 | B14: =SUMIFS(Détail!$E:$E,Détail!$D:$D,"ORANGE SA",Détail!$A:$A,">="&DATE(2025,10,1),Détail!$A:$A,"<"&EDATE(DATE(2025,10,1),1)) -> -551.67
A15: Novembre 2025 | B15: =SUMIFS(Détail!$E:$E,Détail!$D:$D,"ORANGE SA",Détail!$A:$A,">="&DATE(2025,11,1),Détail!$A:$A,"<"&EDATE(DATE(2025,11,1),1)) -> -682.48
A16: Décembre 2025 | B16: =SUMIFS(Détail!$E:$E,Détail!$D:$D,"ORANGE SA",Détail!$A:$A,">="&DATE(2025,12,1),Détail!$A:$A,"<"&EDATE(DATE(2025,12,1),1)) -> -488.33
A19: Google Workspace | C19: =SUMIF(Détail!$D:$D,"GOOGLE WORKSPACE",Détail!$E:$E) -> -1676.8
A20: Mois | B20: Montant
A21: Janvier 2025 | B21: =SUMIFS(Détail!$E:$E,Détail!$D:$D,"GOOGLE WORKSPACE",Détail!$A:$A,">="&DATE(2025,1,1),Détail!$A:$A,"<"&EDATE(DATE(2025,1,1),1)) -> -215.28
A22: Février 2025 | B22: =SUMIFS(Détail!$E:$E,Détail!$D:$D,"GOOGLE WORKSPACE",Détail!$A:$A,">="&DATE(2025,2,1),Détail!$A:$A,"<"&EDATE(DATE(2025,2,1),1)) -> -107.63
A23: Mars 2025 | B23: =SUMIFS(Détail!$E:$E,Détail!$D:$D,"GOOGLE WORKSPACE",Détail!$A:$A,">="&DATE(2025,3,1),Détail!$A:$A,"<"&EDATE(DATE(2025,3,1),1)) -> -107.64
A24: Avril 2025 | B24: =SUMIFS(Détail!$E:$E,Détail!$D:$D,"GOOGLE WORKSPACE",Détail!$A:$A,">="&DATE(2025,4,1),Détail!$A:$A,"<"&EDATE(DATE(2025,4,1),1)) -> -111.85
A25: Mai 2025 | B25: =SUMIFS(Détail!$E:$E,Détail!$D:$D,"GOOGLE WORKSPACE",Détail!$A:$A,">="&DATE(2025,5,1),Détail!$A:$A,"<"&EDATE(DATE(2025,5,1),1)) -> -126.36
A26: Juin 2025 | B26: =SUMIFS(Détail!$E:$E,Détail!$D:$D,"GOOGLE WORKSPACE",Détail!$A:$A,">="&DATE(2025,6,1),Détail!$A:$A,"<"&EDATE(DATE(2025,6,1),1)) -> -133.56
A27: Juillet 2025 | B27: =SUMIFS(Détail!$E:$E,Détail!$D:$D,"GOOGLE WORKSPACE",Détail!$A:$A,">="&DATE(2025,7,1),Détail!$A:$A,"<"&EDATE(DATE(2025,7,1),1)) -> -145.48
A28: Août 2025 | B28: =SUMIFS(Détail!$E:$E,Détail!$D:$D,"GOOGLE WORKSPACE",Détail!$A:$A,">="&DATE(2025,8,1),Détail!$A:$A,"<"&EDATE(DATE(2025,8,1),1)) -> -145.8
A29: Septembre 2025 | B29: =SUMIFS(Détail!$E:$E,Détail!$D:$D,"GOOGLE WORKSPACE",Détail!$A:$A,">="&DATE(2025,9,1),Détail!$A:$A,"<"&EDATE(DATE(2025,9,1),1)) -> -145.8
A30: Octobre 2025 | B30: =SUMIFS(Détail!$E:$E,Détail!$D:$D,"GOOGLE WORKSPACE",Détail!$A:$A,">="&DATE(2025,10,1),Détail!$A:$A,"<"&EDATE(DATE(2025,10,1),1)) -> -145.8
A31: Novembre 2025 | B31: =SUMIFS(Détail!$E:$E,Détail!$D:$D,"GOOGLE WORKSPACE",Détail!$A:$A,">="&DATE(2025,11,1),Détail!$A:$A,"<"&EDATE(DATE(2025,11,1),1)) -> -145.8
A32: Décembre 2025 | B32: =SUMIFS(Détail!$E:$E,Détail!$D:$D,"GOOGLE WORKSPACE",Détail!$A:$A,">="&DATE(2025,12,1),Détail!$A:$A,"<"&EDATE(DATE(2025,12,1),1)) -> -145.8
A35: Boutique Orange | C35: =SUMIF(Détail!$D:$D,"BOUTIQUE ORANGE",Détail!$E:$E) -> -1120.96
A36: Mois | B36: Montant
A37: Janvier 2025 | B37: =SUMIFS(Détail!$E:$E,Détail!$D:$D,"BOUTIQUE ORANGE",Détail!$A:$A,">="&DATE(2025,1,1),Détail!$A:$A,"<"&EDATE(DATE(2025,1,1),1)) -> 0
A38: Février 2025 | B38: =SUMIFS(Détail!$E:$E,Détail!$D:$D,"BOUTIQUE ORANGE",Détail!$A:$A,">="&DATE(2025,2,1),Détail!$A:$A,"<"&EDATE(DATE(2025,2,1),1)) -> 0
A39: Mars 2025 | B39: =SUMIFS(Détail!$E:$E,Détail!$D:$D,"BOUTIQUE ORANGE",Détail!$A:$A,">="&DATE(2025,3,1),Détail!$A:$A,"<"&EDATE(DATE(2025,3,1),1)) -> 0
A40: Avril 2025 | B40: =SUMIFS(Détail!$E:$E,Détail!$D:$D,"BOUTIQUE ORANGE",Détail!$A:$A,">="&DATE(2025,4,1),Détail!$A:$A,"<"&EDATE(DATE(2025,4,1),1)) -> 0
A41: Mai 2025 | B41: =SUMIFS(Détail!$E:$E,Détail!$D:$D,"BOUTIQUE ORANGE",Détail!$A:$A,">="&DATE(2025,5,1),Détail!$A:$A,"<"&EDATE(DATE(2025,5,1),1)) -> 0
A42: Juin 2025 | B42: =SUMIFS(Détail!$E:$E,Détail!$D:$D,"BOUTIQUE ORANGE",Détail!$A:$A,">="&DATE(2025,6,1),Détail!$A:$A,"<"&EDATE(DATE(2025,6,1),1)) -> 0
A43: Juillet 2025 | B43: =SUMIFS(Détail!$E:$E,Détail!$D:$D,"BOUTIQUE ORANGE",Détail!$A:$A,">="&DATE(2025,7,1),Détail!$A:$A,"<"&EDATE(DATE(2025,7,1),1)) -> 0
A44: Août 2025 | B44: =SUMIFS(Détail!$E:$E,Détail!$D:$D,"BOUTIQUE ORANGE",Détail!$A:$A,">="&DATE(2025,8,1),Détail!$A:$A,"<"&EDATE(DATE(2025,8,1),1)) -> 0
A45: Septembre 2025 | B45: =SUMIFS(Détail!$E:$E,Détail!$D:$D,"BOUTIQUE ORANGE",Détail!$A:$A,">="&DATE(2025,9,1),Détail!$A:$A,"<"&EDATE(DATE(2025,9,1),1)) -> -1120.96
A46: Octobre 2025 | B46: =SUMIFS(Détail!$E:$E,Détail!$D:$D,"BOUTIQUE ORANGE",Détail!$A:$A,">="&DATE(2025,10,1),Détail!$A:$A,"<"&EDATE(DATE(2025,10,1),1)) -> 0
A47: Novembre 2025 | B47: =SUMIFS(Détail!$E:$E,Détail!$D:$D,"BOUTIQUE ORANGE",Détail!$A:$A,">="&DATE(2025,11,1),Détail!$A:$A,"<"&EDATE(DATE(2025,11,1),1)) -> 0
A48: Décembre 2025 | B48: =SUMIFS(Détail!$E:$E,Détail!$D:$D,"BOUTIQUE ORANGE",Détail!$A:$A,">="&DATE(2025,12,1),Détail!$A:$A,"<"&EDATE(DATE(2025,12,1),1)) -> 0
A51: Adobe | C51: =SUMIF(Détail!$D:$D,"ADOBE",Détail!$E:$E) -> -679.78
A52: Mois | B52: Montant
A53: Janvier 2025 | B53: =SUMIFS(Détail!$E:$E,Détail!$D:$D,"ADOBE",Détail!$A:$A,">="&DATE(2025,1,1),Détail!$A:$A,"<"&EDATE(DATE(2025,1,1),1)) -> -55.84
A54: Février 2025 | B54: =SUMIFS(Détail!$E:$E,Détail!$D:$D,"ADOBE",Détail!$A:$A,">="&DATE(2025,2,1),Détail!$A:$A,"<"&EDATE(DATE(2025,2,1),1)) -> 0
A55: Mars 2025 | B55: =SUMIFS(Détail!$E:$E,Détail!$D:$D,"ADOBE",Détail!$A:$A,">="&DATE(2025,3,1),Détail!$A:$A,"<"&EDATE(DATE(2025,3,1),1)) -> -111.68
A56: Avril 2025 | B56: =SUMIFS(Détail!$E:$E,Détail!$D:$D,"ADOBE",Détail!$A:$A,">="&DATE(2025,4,1),Détail!$A:$A,"<"&EDATE(DATE(2025,4,1),1)) -> -55.84
A57: Mai 2025 | B57: =SUMIFS(Détail!$E:$E,Détail!$D:$D,"ADOBE",Détail!$A:$A,">="&DATE(2025,5,1),Détail!$A:$A,"<"&EDATE(DATE(2025,5,1),1)) -> -55.84
A58: Juin 2025 | B58: =SUMIFS(Détail!$E:$E,Détail!$D:$D,"ADOBE",Détail!$A:$A,">="&DATE(2025,6,1),Détail!$A:$A,"<"&EDATE(DATE(2025,6,1),1)) -> -55.84
A59: Juillet 2025 | B59: =SUMIFS(Détail!$E:$E,Détail!$D:$D,"ADOBE",Détail!$A:$A,">="&DATE(2025,7,1),Détail!$A:$A,"<"&EDATE(DATE(2025,7,1),1)) -> -55.84
A60: Août 2025 | B60: =SUMIFS(Détail!$E:$E,Détail!$D:$D,"ADOBE",Détail!$A:$A,">="&DATE(2025,8,1),Détail!$A:$A,"<"&EDATE(DATE(2025,8,1),1)) -> -55.84
A61: Septembre 2025 | B61: =SUMIFS(Détail!$E:$E,Détail!$D:$D,"ADOBE",Détail!$A:$A,">="&DATE(2025,9,1),Détail!$A:$A,"<"&EDATE(DATE(2025,9,1),1)) -> -55.84
A62: Octobre 2025 | B62: =SUMIFS(Détail!$E:$E,Détail!$D:$D,"ADOBE",Détail!$A:$A,">="&DATE(2025,10,1),Détail!$A:$A,"<"&EDATE(DATE(2025,10,1),1)) -> -55.84
A63: Novembre 2025 | B63: =SUMIFS(Détail!$E:$E,Détail!$D:$D,"ADOBE",Détail!$A:$A,">="&DATE(2025,11,1),Détail!$A:$A,"<"&EDATE(DATE(2025,11,1),1)) -> 0
A64: Décembre 2025 | B64: =SUMIFS(Détail!$E:$E,Détail!$D:$D,"ADOBE",Détail!$A:$A,">="&DATE(2025,12,1),Détail!$A:$A,"<"&EDATE(DATE(2025,12,1),1)) -> -121.38
A67: Shopify | C67: =SUMIF(Détail!$D:$D,"SHOPIFY",Détail!$E:$E) -> -519.19
A68: Mois | B68: Montant
A69: Janvier 2025 | B69: =SUMIFS(Détail!$E:$E,Détail!$D:$D,"SHOPIFY",Détail!$A:$A,">="&DATE(2025,1,1),Détail!$A:$A,"<"&EDATE(DATE(2025,1,1),1)) -> -85.14
A70: Février 2025 | B70: =SUMIFS(Détail!$E:$E,Détail!$D:$D,"SHOPIFY",Détail!$A:$A,">="&DATE(2025,2,1),Détail!$A:$A,"<"&EDATE(DATE(2025,2,1),1)) -> -38.46
A71: Mars 2025 | B71: =SUMIFS(Détail!$E:$E,Détail!$D:$D,"SHOPIFY",Détail!$A:$A,">="&DATE(2025,3,1),Détail!$A:$A,"<"&EDATE(DATE(2025,3,1),1)) -> -41.64
A72: Avril 2025 | B72: =SUMIFS(Détail!$E:$E,Détail!$D:$D,"SHOPIFY",Détail!$A:$A,">="&DATE(2025,4,1),Détail!$A:$A,"<"&EDATE(DATE(2025,4,1),1)) -> -37.9
A73: Mai 2025 | B73: =SUMIFS(Détail!$E:$E,Détail!$D:$D,"SHOPIFY",Détail!$A:$A,">="&DATE(2025,5,1),Détail!$A:$A,"<"&EDATE(DATE(2025,5,1),1)) -> -41.56
A74: Juin 2025 | B74: =SUMIFS(Détail!$E:$E,Détail!$D:$D,"SHOPIFY",Détail!$A:$A,">="&DATE(2025,6,1),Détail!$A:$A,"<"&EDATE(DATE(2025,6,1),1)) -> -40.18
A75: Juillet 2025 | B75: =SUMIFS(Détail!$E:$E,Détail!$D:$D,"SHOPIFY",Détail!$A:$A,">="&DATE(2025,7,1),Détail!$A:$A,"<"&EDATE(DATE(2025,7,1),1)) -> -41.61
A76: Août 2025 | B76: =SUMIFS(Détail!$E:$E,Détail!$D:$D,"SHOPIFY",Détail!$A:$A,">="&DATE(2025,8,1),Détail!$A:$A,"<"&EDATE(DATE(2025,8,1),1)) -> -37.06
A77: Septembre 2025 | B77: =SUMIFS(Détail!$E:$E,Détail!$D:$D,"SHOPIFY",Détail!$A:$A,">="&DATE(2025,9,1),Détail!$A:$A,"<"&EDATE(DATE(2025,9,1),1)) -> -41.86
A78: Octobre 2025 | B78: =SUMIFS(Détail!$E:$E,Détail!$D:$D,"SHOPIFY",Détail!$A:$A,">="&DATE(2025,10,1),Détail!$A:$A,"<"&EDATE(DATE(2025,10,1),1)) -> -39.89
A79: Novembre 2025 | B79: =SUMIFS(Détail!$E:$E,Détail!$D:$D,"SHOPIFY",Détail!$A:$A,">="&DATE(2025,11,1),Détail!$A:$A,"<"&EDATE(DATE(2025,11,1),1)) -> -39.81
A80: Décembre 2025 | B80: =SUMIFS(Détail!$E:$E,Détail!$D:$D,"SHOPIFY",Détail!$A:$A,">="&DATE(2025,12,1),Détail!$A:$A,"<"&EDATE(DATE(2025,12,1),1)) -> -34.08
A83: Apple | C83: =SUMIF(Détail!$D:$D,"APPLE",Détail!$E:$E) -> -223.72
A84: Mois | B84: Montant
A85: Janvier 2025 | B85: =SUMIFS(Détail!$E:$E,Détail!$D:$D,"APPLE",Détail!$A:$A,">="&DATE(2025,1,1),Détail!$A:$A,"<"&EDATE(DATE(2025,1,1),1)) -> 0
A86: Février 2025 | B86: =SUMIFS(Détail!$E:$E,Détail!$D:$D,"APPLE",Détail!$A:$A,">="&DATE(2025,2,1),Détail!$A:$A,"<"&EDATE(DATE(2025,2,1),1)) -> -69.99
A87: Mars 2025 | B87: =SUMIFS(Détail!$E:$E,Détail!$D:$D,"APPLE",Détail!$A:$A,">="&DATE(2025,3,1),Détail!$A:$A,"<"&EDATE(DATE(2025,3,1),1)) -> 0
A88: Avril 2025 | B88: =SUMIFS(Détail!$E:$E,Détail!$D:$D,"APPLE",Détail!$A:$A,">="&DATE(2025,4,1),Détail!$A:$A,"<"&EDATE(DATE(2025,4,1),1)) -> -49.99
A89: Mai 2025 | B89: =SUMIFS(Détail!$E:$E,Détail!$D:$D,"APPLE",Détail!$A:$A,">="&DATE(2025,5,1),Détail!$A:$A,"<"&EDATE(DATE(2025,5,1),1)) -> 0
A90: Juin 2025 | B90: =SUMIFS(Détail!$E:$E,Détail!$D:$D,"APPLE",Détail!$A:$A,">="&DATE(2025,6,1),Détail!$A:$A,"<"&EDATE(DATE(2025,6,1),1)) -> 0
A91: Juillet 2025 | B91: =SUMIFS(Détail!$E:$E,Détail!$D:$D,"APPLE",Détail!$A:$A,">="&DATE(2025,7,1),Détail!$A:$A,"<"&EDATE(DATE(2025,7,1),1)) -> -15.96
A92: Août 2025 | B92: =SUMIFS(Détail!$E:$E,Détail!$D:$D,"APPLE",Détail!$A:$A,">="&DATE(2025,8,1),Détail!$A:$A,"<"&EDATE(DATE(2025,8,1),1)) -> -15.96
A93: Septembre 2025 | B93: =SUMIFS(Détail!$E:$E,Détail!$D:$D,"APPLE",Détail!$A:$A,">="&DATE(2025,9,1),Détail!$A:$A,"<"&EDATE(DATE(2025,9,1),1)) -> -15.96
A94: Octobre 2025 | B94: =SUMIFS(Détail!$E:$E,Détail!$D:$D,"APPLE",Détail!$A:$A,">="&DATE(2025,10,1),Détail!$A:$A,"<"&EDATE(DATE(2025,10,1),1)) -> -19.95
A95: Novembre 2025 | B95: =SUMIFS(Détail!$E:$E,Détail!$D:$D,"APPLE",Détail!$A:$A,">="&DATE(2025,11,1),Détail!$A:$A,"<"&EDATE(DATE(2025,11,1),1)) -> -15.96
A96: Décembre 2025 | B96: =SUMIFS(Détail!$E:$E,Détail!$D:$D,"APPLE",Détail!$A:$A,">="&DATE(2025,12,1),Détail!$A:$A,"<"&EDATE(DATE(2025,12,1),1)) -> -19.95
A99: Ovh Sas | C99: =SUMIF(Détail!$D:$D,"OVH SAS",Détail!$E:$E) -> -200.15
A100: Mois | B100: Montant
A101: Janvier 2025 | B101: =SUMIFS(Détail!$E:$E,Détail!$D:$D,"OVH SAS",Détail!$A:$A,">="&DATE(2025,1,1),Détail!$A:$A,"<"&EDATE(DATE(2025,1,1),1)) -> 0
A102: Février 2025 | B102: =SUMIFS(Détail!$E:$E,Détail!$D:$D,"OVH SAS",Détail!$A:$A,">="&DATE(2025,2,1),Détail!$A:$A,"<"&EDATE(DATE(2025,2,1),1)) -> 0
A103: Mars 2025 | B103: =SUMIFS(Détail!$E:$E,Détail!$D:$D,"OVH SAS",Détail!$A:$A,">="&DATE(2025,3,1),Détail!$A:$A,"<"&EDATE(DATE(2025,3,1),1)) -> -88.66
A104: Avril 2025 | B104: =SUMIFS(Détail!$E:$E,Détail!$D:$D,"OVH SAS",Détail!$A:$A,">="&DATE(2025,4,1),Détail!$A:$A,"<"&EDATE(DATE(2025,4,1),1)) -> 0
A105: Mai 2025 | B105: =SUMIFS(Détail!$E:$E,Détail!$D:$D,"OVH SAS",Détail!$A:$A,">="&DATE(2025,5,1),Détail!$A:$A,"<"&EDATE(DATE(2025,5,1),1)) -> 0
A106: Juin 2025 | B106: =SUMIFS(Détail!$E:$E,Détail!$D:$D,"OVH SAS",Détail!$A:$A,">="&DATE(2025,6,1),Détail!$A:$A,"<"&EDATE(DATE(2025,6,1),1)) -> 0
A107: Juillet 2025 | B107: =SUMIFS(Détail!$E:$E,Détail!$D:$D,"OVH SAS",Détail!$A:$A,">="&DATE(2025,7,1),Détail!$A:$A,"<"&EDATE(DATE(2025,7,1),1)) -> 0
A108: Août 2025 | B108: =SUMIFS(Détail!$E:$E,Détail!$D:$D,"OVH SAS",Détail!$A:$A,">="&DATE(2025,8,1),Détail!$A:$A,"<"&EDATE(DATE(2025,8,1),1)) -> 0
A109: Septembre 2025 | B109: =SUMIFS(Détail!$E:$E,Détail!$D:$D,"OVH SAS",Détail!$A:$A,">="&DATE(2025,9,1),Détail!$A:$A,"<"&EDATE(DATE(2025,9,1),1)) -> 0
A110: Octobre 2025 | B110: =SUMIFS(Détail!$E:$E,Détail!$D:$D,"OVH SAS",Détail!$A:$A,">="&DATE(2025,10,1),Détail!$A:$A,"<"&EDATE(DATE(2025,10,1),1)) -> -111.08
A111: Novembre 2025 | B111: =SUMIFS(Détail!$E:$E,Détail!$D:$D,"OVH SAS",Détail!$A:$A,">="&DATE(2025,11,1),Détail!$A:$A,"<"&EDATE(DATE(2025,11,1),1)) -> 0
A112: Décembre 2025 | B112: =SUMIFS(Détail!$E:$E,Détail!$D:$D,"OVH SAS",Détail!$A:$A,">="&DATE(2025,12,1),Détail!$A:$A,"<"&EDATE(DATE(2025,12,1),1)) -> -0.41
A115: Microsoft | C115: =SUMIF(Détail!$D:$D,"MICROSOFT",Détail!$E:$E) -> -130
...

Sheet Commission vendeur détail
A1: Commission vendeur — détail (2025)
A2: Commission versée à un apporteur d'affaires (a trouvé un client).
A4: Mr Riadh Chebhouni | C4: =SUMIF(Détail!$D:$D,"MR RIADH CHEBHOUNI",Détail!$E:$E) -> -9359.1
A5: Mois | B5: Montant
A6: Septembre 2025 | B6: =SUMIFS(Détail!$E:$E,Détail!$D:$D,"MR RIADH CHEBHOUNI",Détail!$A:$A,">="&DATE(2025,9,1),Détail!$A:$A,"<"&EDATE(DATE(2025,9,1),1)) -> -9359.1

Sheet Frais pro divers détail
A1: Frais professionnels divers — détail par prestataire (2025)
A3: Messe Frankfurt Middle East Gmbh | C3: =SUMIF(Détail!$D:$D,"MESSE FRANKFURT MIDDLE EAST GMBH",Détail!$E:$E) -> -4482.37
A4: Mois | B4: Montant
A5: Janvier 2025 | B5: =SUMIFS(Détail!$E:$E,Détail!$D:$D,"MESSE FRANKFURT MIDDLE EAST GMBH",Détail!$A:$A,">="&DATE(2025,1,1),Détail!$A:$A,"<"&EDATE(DATE(2025,1,1),1)) -> 0
A6: Février 2025 | B6: =SUMIFS(Détail!$E:$E,Détail!$D:$D,"MESSE FRANKFURT MIDDLE EAST GMBH",Détail!$A:$A,">="&DATE(2025,2,1),Détail!$A:$A,"<"&EDATE(DATE(2025,2,1),1)) -> 0
A7: Mars 2025 | B7: =SUMIFS(Détail!$E:$E,Détail!$D:$D,"MESSE FRANKFURT MIDDLE EAST GMBH",Détail!$A:$A,">="&DATE(2025,3,1),Détail!$A:$A,"<"&EDATE(DATE(2025,3,1),1)) -> 0
A8: Avril 2025 | B8: =SUMIFS(Détail!$E:$E,Détail!$D:$D,"MESSE FRANKFURT MIDDLE EAST GMBH",Détail!$A:$A,">="&DATE(2025,4,1),Détail!$A:$A,"<"&EDATE(DATE(2025,4,1),1)) -> 0
A9: Mai 2025 | B9: =SUMIFS(Détail!$E:$E,Détail!$D:$D,"MESSE FRANKFURT MIDDLE EAST GMBH",Détail!$A:$A,">="&DATE(2025,5,1),Détail!$A:$A,"<"&EDATE(DATE(2025,5,1),1)) -> 0
A10: Juin 2025 | B10: =SUMIFS(Détail!$E:$E,Détail!$D:$D,"MESSE FRANKFURT MIDDLE EAST GMBH",Détail!$A:$A,">="&DATE(2025,6,1),Détail!$A:$A,"<"&EDATE(DATE(2025,6,1),1)) -> -4482.37
A11: Juillet 2025 | B11: =SUMIFS(Détail!$E:$E,Détail!$D:$D,"MESSE FRANKFURT MIDDLE EAST GMBH",Détail!$A:$A,">="&DATE(2025,7,1),Détail!$A:$A,"<"&EDATE(DATE(2025,7,1),1)) -> 0
A12: Août 2025 | B12: =SUMIFS(Détail!$E:$E,Détail!$D:$D,"MESSE FRANKFURT MIDDLE EAST GMBH",Détail!$A:$A,">="&DATE(2025,8,1),Détail!$A:$A,"<"&EDATE(DATE(2025,8,1),1)) -> 0
A13: Septembre 2025 | B13: =SUMIFS(Détail!$E:$E,Détail!$D:$D,"MESSE FRANKFURT MIDDLE EAST GMBH",Détail!$A:$A,">="&DATE(2025,9,1),Détail!$A:$A,"<"&EDATE(DATE(2025,9,1),1)) -> 0
A14: Octobre 2025 | B14: =SUMIFS(Détail!$E:$E,Détail!$D:$D,"MESSE FRANKFURT MIDDLE EAST GMBH",Détail!$A:$A,">="&DATE(2025,10,1),Détail!$A:$A,"<"&EDATE(DATE(2025,10,1),1)) -> 0
A15: Novembre 2025 | B15: =SUMIFS(Détail!$E:$E,Détail!$D:$D,"MESSE FRANKFURT MIDDLE EAST GMBH",Détail!$A:$A,">="&DATE(2025,11,1),Détail!$A:$A,"<"&EDATE(DATE(2025,11,1),1)) -> 0
A16: Décembre 2025 | B16: =SUMIFS(Détail!$E:$E,Détail!$D:$D,"MESSE FRANKFURT MIDDLE EAST GMBH",Détail!$A:$A,">="&DATE(2025,12,1),Détail!$A:$A,"<"&EDATE(DATE(2025,12,1),1)) -> 0
A19: Sas Somexing | C19: =SUMIF(Détail!$D:$D,"SAS SOMEXING",Détail!$E:$E) -> -3905
A20: Mois | B20: Montant
A21: Janvier 2025 | B21: =SUMIFS(Détail!$E:$E,Détail!$D:$D,"SAS SOMEXING",Détail!$A:$A,">="&DATE(2025,1,1),Détail!$A:$A,"<"&EDATE(DATE(2025,1,1),1)) -> 0
A22: Février 2025 | B22: =SUMIFS(Détail!$E:$E,Détail!$D:$D,"SAS SOMEXING",Détail!$A:$A,">="&DATE(2025,2,1),Détail!$A:$A,"<"&EDATE(DATE(2025,2,1),1)) -> 0
A23: Mars 2025 | B23: =SUMIFS(Détail!$E:$E,Détail!$D:$D,"SAS SOMEXING",Détail!$A:$A,">="&DATE(2025,3,1),Détail!$A:$A,"<"&EDATE(DATE(2025,3,1),1)) -> 0
A24: Avril 2025 | B24: =SUMIFS(Détail!$E:$E,Détail!$D:$D,"SAS SOMEXING",Détail!$A:$A,">="&DATE(2025,4,1),Détail!$A:$A,"<"&EDATE(DATE(2025,4,1),1)) -> 0
A25: Mai 2025 | B25: =SUMIFS(Détail!$E:$E,Détail!$D:$D,"SAS SOMEXING",Détail!$A:$A,">="&DATE(2025,5,1),Détail!$A:$A,"<"&EDATE(DATE(2025,5,1),1)) -> 0
A26: Juin 2025 | B26: =SUMIFS(Détail!$E:$E,Détail!$D:$D,"SAS SOMEXING",Détail!$A:$A,">="&DATE(2025,6,1),Détail!$A:$A,"<"&EDATE(DATE(2025,6,1),1)) -> -1952.5
A27: Juillet 2025 | B27: =SUMIFS(Détail!$E:$E,Détail!$D:$D,"SAS SOMEXING",Détail!$A:$A,">="&DATE(2025,7,1),Détail!$A:$A,"<"&EDATE(DATE(2025,7,1),1)) -> 0
A28: Août 2025 | B28: =SUMIFS(Détail!$E:$E,Détail!$D:$D,"SAS SOMEXING",Détail!$A:$A,">="&DATE(2025,8,1),Détail!$A:$A,"<"&EDATE(DATE(2025,8,1),1)) -> 0
A29: Septembre 2025 | B29: =SUMIFS(Détail!$E:$E,Détail!$D:$D,"SAS SOMEXING",Détail!$A:$A,">="&DATE(2025,9,1),Détail!$A:$A,"<"&EDATE(DATE(2025,9,1),1)) -> 0
A30: Octobre 2025 | B30: =SUMIFS(Détail!$E:$E,Détail!$D:$D,"SAS SOMEXING",Détail!$A:$A,">="&DATE(2025,10,1),Détail!$A:$A,"<"&EDATE(DATE(2025,10,1),1)) -> 0
A31: Novembre 2025 | B31: =SUMIFS(Détail!$E:$E,Détail!$D:$D,"SAS SOMEXING",Détail!$A:$A,">="&DATE(2025,11,1),Détail!$A:$A,"<"&EDATE(DATE(2025,11,1),1)) -> -1952.5
A32: Décembre 2025 | B32: =SUMIFS(Détail!$E:$E,Détail!$D:$D,"SAS SOMEXING",Détail!$A:$A,">="&DATE(2025,12,1),Détail!$A:$A,"<"&EDATE(DATE(2025,12,1),1)) -> 0
A35: Sa Liatech | C35: =SUMIF(Détail!$D:$D,"SA LIATECH",Détail!$E:$E) -> -2840
A36: Mois | B36: Montant
A37: Janvier 2025 | B37: =SUMIFS(Détail!$E:$E,Détail!$D:$D,"SA LIATECH",Détail!$A:$A,">="&DATE(2025,1,1),Détail!$A:$A,"<"&EDATE(DATE(2025,1,1),1)) -> 0
A38: Février 2025 | B38: =SUMIFS(Détail!$E:$E,Détail!$D:$D,"SA LIATECH",Détail!$A:$A,">="&DATE(2025,2,1),Détail!$A:$A,"<"&EDATE(DATE(2025,2,1),1)) -> 0
A39: Mars 2025 | B39: =SUMIFS(Détail!$E:$E,Détail!$D:$D,"SA LIATECH",Détail!$A:$A,">="&DATE(2025,3,1),Détail!$A:$A,"<"&EDATE(DATE(2025,3,1),1)) -> 0
A40: Avril 2025 | B40: =SUMIFS(Détail!$E:$E,Détail!$D:$D,"SA LIATECH",Détail!$A:$A,">="&DATE(2025,4,1),Détail!$A:$A,"<"&EDATE(DATE(2025,4,1),1)) -> 0
A41: Mai 2025 | B41: =SUMIFS(Détail!$E:$E,Détail!$D:$D,"SA LIATECH",Détail!$A:$A,">="&DATE(2025,5,1),Détail!$A:$A,"<"&EDATE(DATE(2025,5,1),1)) -> 0
A42: Juin 2025 | B42: =SUMIFS(Détail!$E:$E,Détail!$D:$D,"SA LIATECH",Détail!$A:$A,">="&DATE(2025,6,1),Détail!$A:$A,"<"&EDATE(DATE(2025,6,1),1)) -> 0
A43: Juillet 2025 | B43: =SUMIFS(Détail!$E:$E,Détail!$D:$D,"SA LIATECH",Détail!$A:$A,">="&DATE(2025,7,1),Détail!$A:$A,"<"&EDATE(DATE(2025,7,1),1)) -> 0
A44: Août 2025 | B44: =SUMIFS(Détail!$E:$E,Détail!$D:$D,"SA LIATECH",Détail!$A:$A,">="&DATE(2025,8,1),Détail!$A:$A,"<"&EDATE(DATE(2025,8,1),1)) -> 0
A45: Septembre 2025 | B45: =SUMIFS(Détail!$E:$E,Détail!$D:$D,"SA LIATECH",Détail!$A:$A,">="&DATE(2025,9,1),Détail!$A:$A,"<"&EDATE(DATE(2025,9,1),1)) -> -2840
A46: Octobre 2025 | B46: =SUMIFS(Détail!$E:$E,Détail!$D:$D,"SA LIATECH",Détail!$A:$A,">="&DATE(2025,10,1),Détail!$A:$A,"<"&EDATE(DATE(2025,10,1),1)) -> 0
A47: Novembre 2025 | B47: =SUMIFS(Détail!$E:$E,Détail!$D:$D,"SA LIATECH",Détail!$A:$A,">="&DATE(2025,11,1),Détail!$A:$A,"<"&EDATE(DATE(2025,11,1),1)) -> 0
A48: Décembre 2025 | B48: =SUMIFS(Détail!$E:$E,Détail!$D:$D,"SA LIATECH",Détail!$A:$A,">="&DATE(2025,12,1),Détail!$A:$A,"<"&EDATE(DATE(2025,12,1),1)) -> 0
A51: Esi | C51: =SUMIF(Détail!$D:$D,"ESI",Détail!$E:$E) -> -2091
A52: Mois | B52: Montant
A53: Janvier 2025 | B53: =SUMIFS(Détail!$E:$E,Détail!$D:$D,"ESI",Détail!$A:$A,">="&DATE(2025,1,1),Détail!$A:$A,"<"&EDATE(DATE(2025,1,1),1)) -> 0
A54: Février 2025 | B54: =SUMIFS(Détail!$E:$E,Détail!$D:$D,"ESI",Détail!$A:$A,">="&DATE(2025,2,1),Détail!$A:$A,"<"&EDATE(DATE(2025,2,1),1)) -> 0
A55: Mars 2025 | B55: =SUMIFS(Détail!$E:$E,Détail!$D:$D,"ESI",Détail!$A:$A,">="&DATE(2025,3,1),Détail!$A:$A,"<"&EDATE(DATE(2025,3,1),1)) -> 0
A56: Avril 2025 | B56: =SUMIFS(Détail!$E:$E,Détail!$D:$D,"ESI",Détail!$A:$A,">="&DATE(2025,4,1),Détail!$A:$A,"<"&EDATE(DATE(2025,4,1),1)) -> 0
A57: Mai 2025 | B57: =SUMIFS(Détail!$E:$E,Détail!$D:$D,"ESI",Détail!$A:$A,">="&DATE(2025,5,1),Détail!$A:$A,"<"&EDATE(DATE(2025,5,1),1)) -> 0
A58: Juin 2025 | B58: =SUMIFS(Détail!$E:$E,Détail!$D:$D,"ESI",Détail!$A:$A,">="&DATE(2025,6,1),Détail!$A:$A,"<"&EDATE(DATE(2025,6,1),1)) -> 0
A59: Juillet 2025 | B59: =SUMIFS(Détail!$E:$E,Détail!$D:$D,"ESI",Détail!$A:$A,">="&DATE(2025,7,1),Détail!$A:$A,"<"&EDATE(DATE(2025,7,1),1)) -> 0
A60: Août 2025 | B60: =SUMIFS(Détail!$E:$E,Détail!$D:$D,"ESI",Détail!$A:$A,">="&DATE(2025,8,1),Détail!$A:$A,"<"&EDATE(DATE(2025,8,1),1)) -> 0
A61: Septembre 2025 | B61: =SUMIFS(Détail!$E:$E,Détail!$D:$D,"ESI",Détail!$A:$A,">="&DATE(2025,9,1),Détail!$A:$A,"<"&EDATE(DATE(2025,9,1),1)) -> 0
A62: Octobre 2025 | B62: =SUMIFS(Détail!$E:$E,Détail!$D:$D,"ESI",Détail!$A:$A,">="&DATE(2025,10,1),Détail!$A:$A,"<"&EDATE(DATE(2025,10,1),1)) -> 0
A63: Novembre 2025 | B63: =SUMIFS(Détail!$E:$E,Détail!$D:$D,"ESI",Détail!$A:$A,">="&DATE(2025,11,1),Détail!$A:$A,"<"&EDATE(DATE(2025,11,1),1)) -> -2091
A64: Décembre 2025 | B64: =SUMIFS(Détail!$E:$E,Détail!$D:$D,"ESI",Détail!$A:$A,">="&DATE(2025,12,1),Détail!$A:$A,"<"&EDATE(DATE(2025,12,1),1)) -> 0
A67: Sylvie De France | C67: =SUMIF(Détail!$D:$D,"SYLVIE DE FRANCE",Détail!$E:$E) -> -4928
A68: Mois | B68: Montant
A69: Janvier 2025 | B69: =SUMIFS(Détail!$E:$E,Détail!$D:$D,"SYLVIE DE FRANCE",Détail!$A:$A,">="&DATE(2025,1,1),Détail!$A:$A,"<"&EDATE(DATE(2025,1,1),1)) -> 0
A70: Février 2025 | B70: =SUMIFS(Détail!$E:$E,Détail!$D:$D,"SYLVIE DE FRANCE",Détail!$A:$A,">="&DATE(2025,2,1),Détail!$A:$A,"<"&EDATE(DATE(2025,2,1),1)) -> -2940
A71: Mars 2025 | B71: =SUMIFS(Détail!$E:$E,Détail!$D:$D,"SYLVIE DE FRANCE",Détail!$A:$A,">="&DATE(2025,3,1),Détail!$A:$A,"<"&EDATE(DATE(2025,3,1),1)) -> 0
A72: Avril 2025 | B72: =SUMIFS(Détail!$E:$E,Détail!$D:$D,"SYLVIE DE FRANCE",Détail!$A:$A,">="&DATE(2025,4,1),Détail!$A:$A,"<"&EDATE(DATE(2025,4,1),1)) -> 0
A73: Mai 2025 | B73: =SUMIFS(Détail!$E:$E,Détail!$D:$D,"SYLVIE DE FRANCE",Détail!$A:$A,">="&DATE(2025,5,1),Détail!$A:$A,"<"&EDATE(DATE(2025,5,1),1)) -> 0
A74: Juin 2025 | B74: =SUMIFS(Détail!$E:$E,Détail!$D:$D,"SYLVIE DE FRANCE",Détail!$A:$A,">="&DATE(2025,6,1),Détail!$A:$A,"<"&EDATE(DATE(2025,6,1),1)) -> 0
A75: Juillet 2025 | B75: =SUMIFS(Détail!$E:$E,Détail!$D:$D,"SYLVIE DE FRANCE",Détail!$A:$A,">="&DATE(2025,7,1),Détail!$A:$A,"<"&EDATE(DATE(2025,7,1),1)) -> 0
A76: Août 2025 | B76: =SUMIFS(Détail!$E:$E,Détail!$D:$D,"SYLVIE DE FRANCE",Détail!$A:$A,">="&DATE(2025,8,1),Détail!$A:$A,"<"&EDATE(DATE(2025,8,1),1)) -> 0
A77: Septembre 2025 | B77: =SUMIFS(Détail!$E:$E,Détail!$D:$D,"SYLVIE DE FRANCE",Détail!$A:$A,">="&DATE(2025,9,1),Détail!$A:$A,"<"&EDATE(DATE(2025,9,1),1)) -> 0
A78: Octobre 2025 | B78: =SUMIFS(Détail!$E:$E,Détail!$D:$D,"SYLVIE DE FRANCE",Détail!$A:$A,">="&DATE(2025,10,1),Détail!$A:$A,"<"&EDATE(DATE(2025,10,1),1)) -> -828
A79: Novembre 2025 | B79: =SUMIFS(Détail!$E:$E,Détail!$D:$D,"SYLVIE DE FRANCE",Détail!$A:$A,">="&DATE(2025,11,1),Détail!$A:$A,"<"&EDATE(DATE(2025,11,1),1)) -> -440
A80: Décembre 2025 | B80: =SUMIFS(Détail!$E:$E,Détail!$D:$D,"SYLVIE DE FRANCE",Détail!$A:$A,">="&DATE(2025,12,1),Détail!$A:$A,"<"&EDATE(DATE(2025,12,1),1)) -> -720
A83: Web Print Services | C83: =SUMIF(Détail!$D:$D,"WEB PRINT SERVICES",Détail!$E:$E) -> -1570
A84: Mois | B84: Montant
A85: Janvier 2025 | B85: =SUMIFS(Détail!$E:$E,Détail!$D:$D,"WEB PRINT SERVICES",Détail!$A:$A,">="&DATE(2025,1,1),Détail!$A:$A,"<"&EDATE(DATE(2025,1,1),1)) -> -635
A86: Février 2025 | B86: =SUMIFS(Détail!$E:$E,Détail!$D:$D,"WEB PRINT SERVICES",Détail!$A:$A,">="&DATE(2025,2,1),Détail!$A:$A,"<"&EDATE(DATE(2025,2,1),1)) -> 0
A87: Mars 2025 | B87: =SUMIFS(Détail!$E:$E,Détail!$D:$D,"WEB PRINT SERVICES",Détail!$A:$A,">="&DATE(2025,3,1),Détail!$A:$A,"<"&EDATE(DATE(2025,3,1),1)) -> -295
A88: Avril 2025 | B88: =SUMIFS(Détail!$E:$E,Détail!$D:$D,"WEB PRINT SERVICES",Détail!$A:$A,">="&DATE(2025,4,1),Détail!$A:$A,"<"&EDATE(DATE(2025,4,1),1)) -> 0
A89: Mai 2025 | B89: =SUMIFS(Détail!$E:$E,Détail!$D:$D,"WEB PRINT SERVICES",Détail!$A:$A,">="&DATE(2025,5,1),Détail!$A:$A,"<"&EDATE(DATE(2025,5,1),1)) -> 0
A90: Juin 2025 | B90: =SUMIFS(Détail!$E:$E,Détail!$D:$D,"WEB PRINT SERVICES",Détail!$A:$A,">="&DATE(2025,6,1),Détail!$A:$A,"<"&EDATE(DATE(2025,6,1),1)) -> 0
A91: Juillet 2025 | B91: =SUMIFS(Détail!$E:$E,Détail!$D:$D,"WEB PRINT SERVICES",Détail!$A:$A,">="&DATE(2025,7,1),Détail!$A:$A,"<"&EDATE(DATE(2025,7,1),1)) -> 0
A92: Août 2025 | B92: =SUMIFS(Détail!$E:$E,Détail!$D:$D,"WEB PRINT SERVICES",Détail!$A:$A,">="&DATE(2025,8,1),Détail!$A:$A,"<"&EDATE(DATE(2025,8,1),1)) -> 0
A93: Septembre 2025 | B93: =SUMIFS(Détail!$E:$E,Détail!$D:$D,"WEB PRINT SERVICES",Détail!$A:$A,">="&DATE(2025,9,1),Détail!$A:$A,"<"&EDATE(DATE(2025,9,1),1)) -> 0
A94: Octobre 2025 | B94: =SUMIFS(Détail!$E:$E,Détail!$D:$D,"WEB PRINT SERVICES",Détail!$A:$A,">="&DATE(2025,10,1),Détail!$A:$A,"<"&EDATE(DATE(2025,10,1),1)) -> -530
A95: Novembre 2025 | B95: =SUMIFS(Détail!$E:$E,Détail!$D:$D,"WEB PRINT SERVICES",Détail!$A:$A,">="&DATE(2025,11,1),Détail!$A:$A,"<"&EDATE(DATE(2025,11,1),1)) -> -110
A96: Décembre 2025 | B96: =SUMIFS(Détail!$E:$E,Détail!$D:$D,"WEB PRINT SERVICES",Détail!$A:$A,">="&DATE(2025,12,1),Détail!$A:$A,"<"&EDATE(DATE(2025,12,1),1)) -> 0
A99: Tuv Rheinland France Sas | C99: =SUMIF(Détail!$D:$D,"TUV RHEINLAND FRANCE SAS",Détail!$E:$E) -> -1441.6
A100: Mois | B100: Montant
A101: Janvier 2025 | B101: =SUMIFS(Détail!$E:$E,Détail!$D:$D,"TUV RHEINLAND FRANCE SAS",Détail!$A:$A,">="&DATE(2025,1,1),Détail!$A:$A,"<"&EDATE(DATE(2025,1,1),1)) -> 0
A102: Février 2025 | B102: =SUMIFS(Détail!$E:$E,Détail!$D:$D,"TUV RHEINLAND FRANCE SAS",Détail!$A:$A,">="&DATE(2025,2,1),Détail!$A:$A,"<"&EDATE(DATE(2025,2,1),1)) -> 0
A103: Mars 2025 | B103: =SUMIFS(Détail!$E:$E,Détail!$D:$D,"TUV RHEINLAND FRANCE SAS",Détail!$A:$A,">="&DATE(2025,3,1),Détail!$A:$A,"<"&EDATE(DATE(2025,3,1),1)) -> 0
A104: Avril 2025 | B104: =SUMIFS(Détail!$E:$E,Détail!$D:$D,"TUV RHEINLAND FRANCE SAS",Détail!$A:$A,">="&DATE(2025,4,1),Détail!$A:$A,"<"&EDATE(DATE(2025,4,1),1)) -> 0
A105: Mai 2025 | B105: =SUMIFS(Détail!$E:$E,Détail!$D:$D,"TUV RHEINLAND FRANCE SAS",Détail!$A:$A,">="&DATE(2025,5,1),Détail!$A:$A,"<"&EDATE(DATE(2025,5,1),1)) -> 0
A106: Juin 2025 | B106: =SUMIFS(Détail!$E:$E,Détail!$D:$D,"TUV RHEINLAND FRANCE SAS",Détail!$A:$A,">="&DATE(2025,6,1),Détail!$A:$A,"<"&EDATE(DATE(2025,6,1),1)) -> 0
A107: Juillet 2025 | B107: =SUMIFS(Détail!$E:$E,Détail!$D:$D,"TUV RHEINLAND FRANCE SAS",Détail!$A:$A,">="&DATE(2025,7,1),Détail!$A:$A,"<"&EDATE(DATE(2025,7,1),1)) -> 0
A108: Août 2025 | B108: =SUMIFS(Détail!$E:$E,Détail!$D:$D,"TUV RHEINLAND FRANCE SAS",Détail!$A:$A,">="&DATE(2025,8,1),Détail!$A:$A,"<"&EDATE(DATE(2025,8,1),1)) -> 0
A109: Septembre 2025 | B109: =SUMIFS(Détail!$E:$E,Détail!$D:$D,"TUV RHEINLAND FRANCE SAS",Détail!$A:$A,">="&DATE(2025,9,1),Détail!$A:$A,"<"&EDATE(DATE(2025,9,1),1)) -> -1441.6
A110: Octobre 2025 | B110: =SUMIFS(Détail!$E:$E,Détail!$D:$D,"TUV RHEINLAND FRANCE SAS",Détail!$A:$A,">="&DATE(2025,10,1),Détail!$A:$A,"<"&EDATE(DATE(2025,10,1),1)) -> 0
A111: Novembre 2025 | B111: =SUMIFS(Détail!$E:$E,Détail!$D:$D,"TUV RHEINLAND FRANCE SAS",Détail!$A:$A,">="&DATE(2025,11,1),Détail!$A:$A,"<"&EDATE(DATE(2025,11,1),1)) -> 0
A112: Décembre 2025 | B112: =SUMIFS(Détail!$E:$E,Détail!$D:$D,"TUV RHEINLAND FRANCE SAS",Détail!$A:$A,">="&DATE(2025,12,1),Détail!$A:$A,"<"&EDATE(DATE(2025,12,1),1)) -> 0
A115: Ccip Dfce Gefi | C115: =SUMIF(Détail!$D:$D,"CCIP DFCE GEFI",Détail!$E:$E) -> -1281
...

Sheet Électricité Gaz détail
A1: Électricité / Gaz — détail mensuel (2025)
A3: Totalenergies Electricite Et Gaz France | C3: =SUMIF(Détail!$D:$D,"TOTALENERGIES ELECTRICITE ET GAZ FRANCE",Détail!$E:$E) -> -8727.96
A4: Mois | B4: Montant
A5: Janvier 2025 | B5: =SUMIFS(Détail!$E:$E,Détail!$D:$D,"TOTALENERGIES ELECTRICITE ET GAZ FRANCE",Détail!$A:$A,">="&DATE(2025,1,1),Détail!$A:$A,"<"&EDATE(DATE(2025,1,1),1)) -> -2033.74
A6: Février 2025 | B6: =SUMIFS(Détail!$E:$E,Détail!$D:$D,"TOTALENERGIES ELECTRICITE ET GAZ FRANCE",Détail!$A:$A,">="&DATE(2025,2,1),Détail!$A:$A,"<"&EDATE(DATE(2025,2,1),1)) -> -179.27
A7: Mars 2025 | B7: =SUMIFS(Détail!$E:$E,Détail!$D:$D,"TOTALENERGIES ELECTRICITE ET GAZ FRANCE",Détail!$A:$A,">="&DATE(2025,3,1),Détail!$A:$A,"<"&EDATE(DATE(2025,3,1),1)) -> -1983.15
A8: Avril 2025 | B8: =SUMIFS(Détail!$E:$E,Détail!$D:$D,"TOTALENERGIES ELECTRICITE ET GAZ FRANCE",Détail!$A:$A,">="&DATE(2025,4,1),Détail!$A:$A,"<"&EDATE(DATE(2025,4,1),1)) -> -187.16
A9: Mai 2025 | B9: =SUMIFS(Détail!$E:$E,Détail!$D:$D,"TOTALENERGIES ELECTRICITE ET GAZ FRANCE",Détail!$A:$A,">="&DATE(2025,5,1),Détail!$A:$A,"<"&EDATE(DATE(2025,5,1),1)) -> -707.99
A10: Juin 2025 | B10: =SUMIFS(Détail!$E:$E,Détail!$D:$D,"TOTALENERGIES ELECTRICITE ET GAZ FRANCE",Détail!$A:$A,">="&DATE(2025,6,1),Détail!$A:$A,"<"&EDATE(DATE(2025,6,1),1)) -> -403.51
A11: Juillet 2025 | B11: =SUMIFS(Détail!$E:$E,Détail!$D:$D,"TOTALENERGIES ELECTRICITE ET GAZ FRANCE",Détail!$A:$A,">="&DATE(2025,7,1),Détail!$A:$A,"<"&EDATE(DATE(2025,7,1),1)) -> -415.36
A12: Septembre 2025 | B12: =SUMIFS(Détail!$E:$E,Détail!$D:$D,"TOTALENERGIES ELECTRICITE ET GAZ FRANCE",Détail!$A:$A,">="&DATE(2025,9,1),Détail!$A:$A,"<"&EDATE(DATE(2025,9,1),1)) -> -213.49
A13: Octobre 2025 | B13: =SUMIFS(Détail!$E:$E,Détail!$D:$D,"TOTALENERGIES ELECTRICITE ET GAZ FRANCE",Détail!$A:$A,">="&DATE(2025,10,1),Détail!$A:$A,"<"&EDATE(DATE(2025,10,1),1)) -> -651.02
A14: Novembre 2025 | B14: =SUMIFS(Détail!$E:$E,Détail!$D:$D,"TOTALENERGIES ELECTRICITE ET GAZ FRANCE",Détail!$A:$A,">="&DATE(2025,11,1),Détail!$A:$A,"<"&EDATE(DATE(2025,11,1),1)) -> -207.3
A15: Décembre 2025 | B15: =SUMIFS(Détail!$E:$E,Détail!$D:$D,"TOTALENERGIES ELECTRICITE ET GAZ FRANCE",Détail!$A:$A,">="&DATE(2025,12,1),Détail!$A:$A,"<"&EDATE(DATE(2025,12,1),1)) -> -1745.97

Sheet Comptabilité détail
A1: Comptabilité / expert-comptable — détail (2025)
A3: Cabinet Sas Daran | C3: =SUMIF(Détail!$D:$D,"CABINET SAS DARAN",Détail!$E:$E) -> -6812.93
A4: Mois | B4: Montant
A5: Janvier 2025 | B5: =SUMIFS(Détail!$E:$E,Détail!$D:$D,"CABINET SAS DARAN",Détail!$A:$A,">="&DATE(2025,1,1),Détail!$A:$A,"<"&EDATE(DATE(2025,1,1),1)) -> -420
A6: Février 2025 | B6: =SUMIFS(Détail!$E:$E,Détail!$D:$D,"CABINET SAS DARAN",Détail!$A:$A,">="&DATE(2025,2,1),Détail!$A:$A,"<"&EDATE(DATE(2025,2,1),1)) -> -420
A7: Mars 2025 | B7: =SUMIFS(Détail!$E:$E,Détail!$D:$D,"CABINET SAS DARAN",Détail!$A:$A,">="&DATE(2025,3,1),Détail!$A:$A,"<"&EDATE(DATE(2025,3,1),1)) -> -420
A8: Avril 2025 | B8: =SUMIFS(Détail!$E:$E,Détail!$D:$D,"CABINET SAS DARAN",Détail!$A:$A,">="&DATE(2025,4,1),Détail!$A:$A,"<"&EDATE(DATE(2025,4,1),1)) -> -420
A9: Mai 2025 | B9: =SUMIFS(Détail!$E:$E,Détail!$D:$D,"CABINET SAS DARAN",Détail!$A:$A,">="&DATE(2025,5,1),Détail!$A:$A,"<"&EDATE(DATE(2025,5,1),1)) -> -504
A10: Juin 2025 | B10: =SUMIFS(Détail!$E:$E,Détail!$D:$D,"CABINET SAS DARAN",Détail!$A:$A,">="&DATE(2025,6,1),Détail!$A:$A,"<"&EDATE(DATE(2025,6,1),1)) -> -504
A11: Juillet 2025 | B11: =SUMIFS(Détail!$E:$E,Détail!$D:$D,"CABINET SAS DARAN",Détail!$A:$A,">="&DATE(2025,7,1),Détail!$A:$A,"<"&EDATE(DATE(2025,7,1),1)) -> -504
A12: Août 2025 | B12: =SUMIFS(Détail!$E:$E,Détail!$D:$D,"CABINET SAS DARAN",Détail!$A:$A,">="&DATE(2025,8,1),Détail!$A:$A,"<"&EDATE(DATE(2025,8,1),1)) -> -1604.93
A13: Septembre 2025 | B13: =SUMIFS(Détail!$E:$E,Détail!$D:$D,"CABINET SAS DARAN",Détail!$A:$A,">="&DATE(2025,9,1),Détail!$A:$A,"<"&EDATE(DATE(2025,9,1),1)) -> -504
A14: Octobre 2025 | B14: =SUMIFS(Détail!$E:$E,Détail!$D:$D,"CABINET SAS DARAN",Détail!$A:$A,">="&DATE(2025,10,1),Détail!$A:$A,"<"&EDATE(DATE(2025,10,1),1)) -> -504
A15: Novembre 2025 | B15: =SUMIFS(Détail!$E:$E,Détail!$D:$D,"CABINET SAS DARAN",Détail!$A:$A,">="&DATE(2025,11,1),Détail!$A:$A,"<"&EDATE(DATE(2025,11,1),1)) -> -504
A16: Décembre 2025 | B16: =SUMIFS(Détail!$E:$E,Détail!$D:$D,"CABINET SAS DARAN",Détail!$A:$A,">="&DATE(2025,12,1),Détail!$A:$A,"<"&EDATE(DATE(2025,12,1),1)) -> -504
A19: Ebp France-E B P Informatique | C19: =SUMIF(Détail!$D:$D,"EBP FRANCE-E B P INFORMATIQUE",Détail!$E:$E) -> -504
A20: Mois | B20: Montant
A21: Janvier 2025 | B21: =SUMIFS(Détail!$E:$E,Détail!$D:$D,"EBP FRANCE-E B P INFORMATIQUE",Détail!$A:$A,">="&DATE(2025,1,1),Détail!$A:$A,"<"&EDATE(DATE(2025,1,1),1)) -> 0
A22: Février 2025 | B22: =SUMIFS(Détail!$E:$E,Détail!$D:$D,"EBP FRANCE-E B P INFORMATIQUE",Détail!$A:$A,">="&DATE(2025,2,1),Détail!$A:$A,"<"&EDATE(DATE(2025,2,1),1)) -> -504
A23: Mars 2025 | B23: =SUMIFS(Détail!$E:$E,Détail!$D:$D,"EBP FRANCE-E B P INFORMATIQUE",Détail!$A:$A,">="&DATE(2025,3,1),Détail!$A:$A,"<"&EDATE(DATE(2025,3,1),1)) -> 0
A24: Avril 2025 | B24: =SUMIFS(Détail!$E:$E,Détail!$D:$D,"EBP FRANCE-E B P INFORMATIQUE",Détail!$A:$A,">="&DATE(2025,4,1),Détail!$A:$A,"<"&EDATE(DATE(2025,4,1),1)) -> 0
A25: Mai 2025 | B25: =SUMIFS(Détail!$E:$E,Détail!$D:$D,"EBP FRANCE-E B P INFORMATIQUE",Détail!$A:$A,">="&DATE(2025,5,1),Détail!$A:$A,"<"&EDATE(DATE(2025,5,1),1)) -> 0
A26: Juin 2025 | B26: =SUMIFS(Détail!$E:$E,Détail!$D:$D,"EBP FRANCE-E B P INFORMATIQUE",Détail!$A:$A,">="&DATE(2025,6,1),Détail!$A:$A,"<"&EDATE(DATE(2025,6,1),1)) -> 0
A27: Juillet 2025 | B27: =SUMIFS(Détail!$E:$E,Détail!$D:$D,"EBP FRANCE-E B P INFORMATIQUE",Détail!$A:$A,">="&DATE(2025,7,1),Détail!$A:$A,"<"&EDATE(DATE(2025,7,1),1)) -> 0
A28: Août 2025 | B28: =SUMIFS(Détail!$E:$E,Détail!$D:$D,"EBP FRANCE-E B P INFORMATIQUE",Détail!$A:$A,">="&DATE(2025,8,1),Détail!$A:$A,"<"&EDATE(DATE(2025,8,1),1)) -> 0
A29: Septembre 2025 | B29: =SUMIFS(Détail!$E:$E,Détail!$D:$D,"EBP FRANCE-E B P INFORMATIQUE",Détail!$A:$A,">="&DATE(2025,9,1),Détail!$A:$A,"<"&EDATE(DATE(2025,9,1),1)) -> 0
A30: Octobre 2025 | B30: =SUMIFS(Détail!$E:$E,Détail!$D:$D,"EBP FRANCE-E B P INFORMATIQUE",Détail!$A:$A,">="&DATE(2025,10,1),Détail!$A:$A,"<"&EDATE(DATE(2025,10,1),1)) -> 0
A31: Novembre 2025 | B31: =SUMIFS(Détail!$E:$E,Détail!$D:$D,"EBP FRANCE-E B P INFORMATIQUE",Détail!$A:$A,">="&DATE(2025,11,1),Détail!$A:$A,"<"&EDATE(DATE(2025,11,1),1)) -> 0
A32: Décembre 2025 | B32: =SUMIFS(Détail!$E:$E,Détail!$D:$D,"EBP FRANCE-E B P INFORMATIQUE",Détail!$A:$A,">="&DATE(2025,12,1),Détail!$A:$A,"<"&EDATE(DATE(2025,12,1),1)) -> 0

Sheet Frais bancaires détail
A1: Frais bancaires & financiers — détail par type de frais (2025)
A2: Groupé par type d'opération bancaire (pas de nom de prestataire sur ces lignes).
A4: Interets | C4: =SUMIF(Détail!$C:$C,"INTERETS",Détail!$E:$E) -> -1601.29
A5: Mois | B5: Montant
A6: Janvier 2025 | B6: =SUMIFS(Détail!$E:$E,Détail!$C:$C,"INTERETS",Détail!$A:$A,">="&DATE(2025,1,1),Détail!$A:$A,"<"&EDATE(DATE(2025,1,1),1)) -> -292.18
A7: Février 2025 | B7: =SUMIFS(Détail!$E:$E,Détail!$C:$C,"INTERETS",Détail!$A:$A,">="&DATE(2025,2,1),Détail!$A:$A,"<"&EDATE(DATE(2025,2,1),1)) -> 0
A8: Mars 2025 | B8: =SUMIFS(Détail!$E:$E,Détail!$C:$C,"INTERETS",Détail!$A:$A,">="&DATE(2025,3,1),Détail!$A:$A,"<"&EDATE(DATE(2025,3,1),1)) -> 0
A9: Avril 2025 | B9: =SUMIFS(Détail!$E:$E,Détail!$C:$C,"INTERETS",Détail!$A:$A,">="&DATE(2025,4,1),Détail!$A:$A,"<"&EDATE(DATE(2025,4,1),1)) -> -392.69
A10: Mai 2025 | B10: =SUMIFS(Détail!$E:$E,Détail!$C:$C,"INTERETS",Détail!$A:$A,">="&DATE(2025,5,1),Détail!$A:$A,"<"&EDATE(DATE(2025,5,1),1)) -> 0
A11: Juin 2025 | B11: =SUMIFS(Détail!$E:$E,Détail!$C:$C,"INTERETS",Détail!$A:$A,">="&DATE(2025,6,1),Détail!$A:$A,"<"&EDATE(DATE(2025,6,1),1)) -> 0
A12: Juillet 2025 | B12: =SUMIFS(Détail!$E:$E,Détail!$C:$C,"INTERETS",Détail!$A:$A,">="&DATE(2025,7,1),Détail!$A:$A,"<"&EDATE(DATE(2025,7,1),1)) -> -377.34
A13: Août 2025 | B13: =SUMIFS(Détail!$E:$E,Détail!$C:$C,"INTERETS",Détail!$A:$A,">="&DATE(2025,8,1),Détail!$A:$A,"<"&EDATE(DATE(2025,8,1),1)) -> 0
A14: Septembre 2025 | B14: =SUMIFS(Détail!$E:$E,Détail!$C:$C,"INTERETS",Détail!$A:$A,">="&DATE(2025,9,1),Détail!$A:$A,"<"&EDATE(DATE(2025,9,1),1)) -> 0
A15: Octobre 2025 | B15: =SUMIFS(Détail!$E:$E,Détail!$C:$C,"INTERETS",Détail!$A:$A,">="&DATE(2025,10,1),Détail!$A:$A,"<"&EDATE(DATE(2025,10,1),1)) -> -539.08
A16: Novembre 2025 | B16: =SUMIFS(Détail!$E:$E,Détail!$C:$C,"INTERETS",Détail!$A:$A,">="&DATE(2025,11,1),Détail!$A:$A,"<"&EDATE(DATE(2025,11,1),1)) -> 0
A17: Décembre 2025 | B17: =SUMIFS(Détail!$E:$E,Détail!$C:$C,"INTERETS",Détail!$A:$A,">="&DATE(2025,12,1),Détail!$A:$A,"<"&EDATE(DATE(2025,12,1),1)) -> 0
A20: Frais Banque Etrangere | C20: =SUMIF(Détail!$C:$C,"FRAIS BANQUE ETRANGERE",Détail!$E:$E) -> -705
A21: Mois | B21: Montant
A22: Janvier 2025 | B22: =SUMIFS(Détail!$E:$E,Détail!$C:$C,"FRAIS BANQUE ETRANGERE",Détail!$A:$A,">="&DATE(2025,1,1),Détail!$A:$A,"<"&EDATE(DATE(2025,1,1),1)) -> -84.6
A23: Février 2025 | B23: =SUMIFS(Détail!$E:$E,Détail!$C:$C,"FRAIS BANQUE ETRANGERE",Détail!$A:$A,">="&DATE(2025,2,1),Détail!$A:$A,"<"&EDATE(DATE(2025,2,1),1)) -> 0
A24: Mars 2025 | B24: =SUMIFS(Détail!$E:$E,Détail!$C:$C,"FRAIS BANQUE ETRANGERE",Détail!$A:$A,">="&DATE(2025,3,1),Détail!$A:$A,"<"&EDATE(DATE(2025,3,1),1)) -> -56.4
A25: Avril 2025 | B25: =SUMIFS(Détail!$E:$E,Détail!$C:$C,"FRAIS BANQUE ETRANGERE",Détail!$A:$A,">="&DATE(2025,4,1),Détail!$A:$A,"<"&EDATE(DATE(2025,4,1),1)) -> -112.8
A26: Mai 2025 | B26: =SUMIFS(Détail!$E:$E,Détail!$C:$C,"FRAIS BANQUE ETRANGERE",Détail!$A:$A,">="&DATE(2025,5,1),Détail!$A:$A,"<"&EDATE(DATE(2025,5,1),1)) -> -56.4
A27: Juin 2025 | B27: =SUMIFS(Détail!$E:$E,Détail!$C:$C,"FRAIS BANQUE ETRANGERE",Détail!$A:$A,">="&DATE(2025,6,1),Détail!$A:$A,"<"&EDATE(DATE(2025,6,1),1)) -> -112.8
A28: Juillet 2025 | B28: =SUMIFS(Détail!$E:$E,Détail!$C:$C,"FRAIS BANQUE ETRANGERE",Détail!$A:$A,">="&DATE(2025,7,1),Détail!$A:$A,"<"&EDATE(DATE(2025,7,1),1)) -> 0
A29: Août 2025 | B29: =SUMIFS(Détail!$E:$E,Détail!$C:$C,"FRAIS BANQUE ETRANGERE",Détail!$A:$A,">="&DATE(2025,8,1),Détail!$A:$A,"<"&EDATE(DATE(2025,8,1),1)) -> 0
A30: Septembre 2025 | B30: =SUMIFS(Détail!$E:$E,Détail!$C:$C,"FRAIS BANQUE ETRANGERE",Détail!$A:$A,">="&DATE(2025,9,1),Détail!$A:$A,"<"&EDATE(DATE(2025,9,1),1)) -> -84.6
A31: Octobre 2025 | B31: =SUMIFS(Détail!$E:$E,Détail!$C:$C,"FRAIS BANQUE ETRANGERE",Détail!$A:$A,">="&DATE(2025,10,1),Détail!$A:$A,"<"&EDATE(DATE(2025,10,1),1)) -> -84.6
A32: Novembre 2025 | B32: =SUMIFS(Détail!$E:$E,Détail!$C:$C,"FRAIS BANQUE ETRANGERE",Détail!$A:$A,">="&DATE(2025,11,1),Détail!$A:$A,"<"&EDATE(DATE(2025,11,1),1)) -> -28.2
A33: Décembre 2025 | B33: =SUMIFS(Détail!$E:$E,Détail!$C:$C,"FRAIS BANQUE ETRANGERE",Détail!$A:$A,">="&DATE(2025,12,1),Détail!$A:$A,"<"&EDATE(DATE(2025,12,1),1)) -> -84.6
A36: Frais Virement International | C36: =SUMIF(Détail!$C:$C,"FRAIS VIREMENT INTERNATIONAL",Détail!$E:$E) -> -483.6
A37: Mois | B37: Montant
A38: Janvier 2025 | B38: =SUMIFS(Détail!$E:$E,Détail!$C:$C,"FRAIS VIREMENT INTERNATIONAL",Détail!$A:$A,">="&DATE(2025,1,1),Détail!$A:$A,"<"&EDATE(DATE(2025,1,1),1)) -> -46.8
A39: Février 2025 | B39: =SUMIFS(Détail!$E:$E,Détail!$C:$C,"FRAIS VIREMENT INTERNATIONAL",Détail!$A:$A,">="&DATE(2025,2,1),Détail!$A:$A,"<"&EDATE(DATE(2025,2,1),1)) -> 0
A40: Mars 2025 | B40: =SUMIFS(Détail!$E:$E,Détail!$C:$C,"FRAIS VIREMENT INTERNATIONAL",Détail!$A:$A,">="&DATE(2025,3,1),Détail!$A:$A,"<"&EDATE(DATE(2025,3,1),1)) -> -37.2
A41: Avril 2025 | B41: =SUMIFS(Détail!$E:$E,Détail!$C:$C,"FRAIS VIREMENT INTERNATIONAL",Détail!$A:$A,">="&DATE(2025,4,1),Détail!$A:$A,"<"&EDATE(DATE(2025,4,1),1)) -> -62.4
A42: Mai 2025 | B42: =SUMIFS(Détail!$E:$E,Détail!$C:$C,"FRAIS VIREMENT INTERNATIONAL",Détail!$A:$A,">="&DATE(2025,5,1),Détail!$A:$A,"<"&EDATE(DATE(2025,5,1),1)) -> -37.2
A43: Juin 2025 | B43: =SUMIFS(Détail!$E:$E,Détail!$C:$C,"FRAIS VIREMENT INTERNATIONAL",Détail!$A:$A,">="&DATE(2025,6,1),Détail!$A:$A,"<"&EDATE(DATE(2025,6,1),1)) -> -68.4
A44: Juillet 2025 | B44: =SUMIFS(Détail!$E:$E,Détail!$C:$C,"FRAIS VIREMENT INTERNATIONAL",Détail!$A:$A,">="&DATE(2025,7,1),Détail!$A:$A,"<"&EDATE(DATE(2025,7,1),1)) -> 0
A45: Août 2025 | B45: =SUMIFS(Détail!$E:$E,Détail!$C:$C,"FRAIS VIREMENT INTERNATIONAL",Détail!$A:$A,">="&DATE(2025,8,1),Détail!$A:$A,"<"&EDATE(DATE(2025,8,1),1)) -> 0
A46: Septembre 2025 | B46: =SUMIFS(Détail!$E:$E,Détail!$C:$C,"FRAIS VIREMENT INTERNATIONAL",Détail!$A:$A,">="&DATE(2025,9,1),Détail!$A:$A,"<"&EDATE(DATE(2025,9,1),1)) -> -58.8
A47: Octobre 2025 | B47: =SUMIFS(Détail!$E:$E,Détail!$C:$C,"FRAIS VIREMENT INTERNATIONAL",Détail!$A:$A,">="&DATE(2025,10,1),Détail!$A:$A,"<"&EDATE(DATE(2025,10,1),1)) -> -86.4
A48: Novembre 2025 | B48: =SUMIFS(Détail!$E:$E,Détail!$C:$C,"FRAIS VIREMENT INTERNATIONAL",Détail!$A:$A,">="&DATE(2025,11,1),Détail!$A:$A,"<"&EDATE(DATE(2025,11,1),1)) -> -21.6
A49: Décembre 2025 | B49: =SUMIFS(Détail!$E:$E,Détail!$C:$C,"FRAIS VIREMENT INTERNATIONAL",Détail!$A:$A,">="&DATE(2025,12,1),Détail!$A:$A,"<"&EDATE(DATE(2025,12,1),1)) -> -64.8
A52: Frais De Change | C52: =SUMIF(Détail!$C:$C,"FRAIS DE CHANGE",Détail!$E:$E) -> -463.21
A53: Mois | B53: Montant
A54: Janvier 2025 | B54: =SUMIFS(Détail!$E:$E,Détail!$C:$C,"FRAIS DE CHANGE",Détail!$A:$A,">="&DATE(2025,1,1),Détail!$A:$A,"<"&EDATE(DATE(2025,1,1),1)) -> -34
A55: Février 2025 | B55: =SUMIFS(Détail!$E:$E,Détail!$C:$C,"FRAIS DE CHANGE",Détail!$A:$A,">="&DATE(2025,2,1),Détail!$A:$A,"<"&EDATE(DATE(2025,2,1),1)) -> 0
A56: Mars 2025 | B56: =SUMIFS(Détail!$E:$E,Détail!$C:$C,"FRAIS DE CHANGE",Détail!$A:$A,">="&DATE(2025,3,1),Détail!$A:$A,"<"&EDATE(DATE(2025,3,1),1)) -> -38.5
A57: Avril 2025 | B57: =SUMIFS(Détail!$E:$E,Détail!$C:$C,"FRAIS DE CHANGE",Détail!$A:$A,">="&DATE(2025,4,1),Détail!$A:$A,"<"&EDATE(DATE(2025,4,1),1)) -> -34
A58: Mai 2025 | B58: =SUMIFS(Détail!$E:$E,Détail!$C:$C,"FRAIS DE CHANGE",Détail!$A:$A,">="&DATE(2025,5,1),Détail!$A:$A,"<"&EDATE(DATE(2025,5,1),1)) -> -38.5
A59: Juin 2025 | B59: =SUMIFS(Détail!$E:$E,Détail!$C:$C,"FRAIS DE CHANGE",Détail!$A:$A,">="&DATE(2025,6,1),Détail!$A:$A,"<"&EDATE(DATE(2025,6,1),1)) -> -88.2
A60: Juillet 2025 | B60: =SUMIFS(Détail!$E:$E,Détail!$C:$C,"FRAIS DE CHANGE",Détail!$A:$A,">="&DATE(2025,7,1),Détail!$A:$A,"<"&EDATE(DATE(2025,7,1),1)) -> 0
A61: Août 2025 | B61: =SUMIFS(Détail!$E:$E,Détail!$C:$C,"FRAIS DE CHANGE",Détail!$A:$A,">="&DATE(2025,8,1),Détail!$A:$A,"<"&EDATE(DATE(2025,8,1),1)) -> 0
A62: Septembre 2025 | B62: =SUMIFS(Détail!$E:$E,Détail!$C:$C,"FRAIS DE CHANGE",Détail!$A:$A,">="&DATE(2025,9,1),Détail!$A:$A,"<"&EDATE(DATE(2025,9,1),1)) -> -38.5
A63: Octobre 2025 | B63: =SUMIFS(Détail!$E:$E,Détail!$C:$C,"FRAIS DE CHANGE",Détail!$A:$A,">="&DATE(2025,10,1),Détail!$A:$A,"<"&EDATE(DATE(2025,10,1),1)) -> -86
A64: Novembre 2025 | B64: =SUMIFS(Détail!$E:$E,Détail!$C:$C,"FRAIS DE CHANGE",Détail!$A:$A,">="&DATE(2025,11,1),Détail!$A:$A,"<"&EDATE(DATE(2025,11,1),1)) -> -21.5
A65: Décembre 2025 | B65: =SUMIFS(Détail!$E:$E,Détail!$C:$C,"FRAIS DE CHANGE",Détail!$A:$A,">="&DATE(2025,12,1),Détail!$A:$A,"<"&EDATE(DATE(2025,12,1),1)) -> -84.01
A68: Abonnement Transbred.Com | C68: =SUMIF(Détail!$C:$C,"ABONNEMENT TRANSBRED.COM",Détail!$E:$E) -> -378
A69: Mois | B69: Montant
A70: Janvier 2025 | B70: =SUMIFS(Détail!$E:$E,Détail!$C:$C,"ABONNEMENT TRANSBRED.COM",Détail!$A:$A,">="&DATE(2025,1,1),Détail!$A:$A,"<"&EDATE(DATE(2025,1,1),1)) -> -42
A71: Février 2025 | B71: =SUMIFS(Détail!$E:$E,Détail!$C:$C,"ABONNEMENT TRANSBRED.COM",Détail!$A:$A,">="&DATE(2025,2,1),Détail!$A:$A,"<"&EDATE(DATE(2025,2,1),1)) -> -42
A72: Mars 2025 | B72: =SUMIFS(Détail!$E:$E,Détail!$C:$C,"ABONNEMENT TRANSBRED.COM",Détail!$A:$A,">="&DATE(2025,3,1),Détail!$A:$A,"<"&EDATE(DATE(2025,3,1),1)) -> -42
A73: Avril 2025 | B73: =SUMIFS(Détail!$E:$E,Détail!$C:$C,"ABONNEMENT TRANSBRED.COM",Détail!$A:$A,">="&DATE(2025,4,1),Détail!$A:$A,"<"&EDATE(DATE(2025,4,1),1)) -> -42
A74: Mai 2025 | B74: =SUMIFS(Détail!$E:$E,Détail!$C:$C,"ABONNEMENT TRANSBRED.COM",Détail!$A:$A,">="&DATE(2025,5,1),Détail!$A:$A,"<"&EDATE(DATE(2025,5,1),1)) -> -42
A75: Juin 2025 | B75: =SUMIFS(Détail!$E:$E,Détail!$C:$C,"ABONNEMENT TRANSBRED.COM",Détail!$A:$A,">="&DATE(2025,6,1),Détail!$A:$A,"<"&EDATE(DATE(2025,6,1),1)) -> -42
A76: Juillet 2025 | B76: =SUMIFS(Détail!$E:$E,Détail!$C:$C,"ABONNEMENT TRANSBRED.COM",Détail!$A:$A,">="&DATE(2025,7,1),Détail!$A:$A,"<"&EDATE(DATE(2025,7,1),1)) -> -42
A77: Août 2025 | B77: =SUMIFS(Détail!$E:$E,Détail!$C:$C,"ABONNEMENT TRANSBRED.COM",Détail!$A:$A,">="&DATE(2025,8,1),Détail!$A:$A,"<"&EDATE(DATE(2025,8,1),1)) -> -42
A78: Septembre 2025 | B78: =SUMIFS(Détail!$E:$E,Détail!$C:$C,"ABONNEMENT TRANSBRED.COM",Détail!$A:$A,">="&DATE(2025,9,1),Détail!$A:$A,"<"&EDATE(DATE(2025,9,1),1)) -> -42
A79: Octobre 2025 | B79: =SUMIFS(Détail!$E:$E,Détail!$C:$C,"ABONNEMENT TRANSBRED.COM",Détail!$A:$A,">="&DATE(2025,10,1),Détail!$A:$A,"<"&EDATE(DATE(2025,10,1),1)) -> 0
A80: Novembre 2025 | B80: =SUMIFS(Détail!$E:$E,Détail!$C:$C,"ABONNEMENT TRANSBRED.COM",Détail!$A:$A,">="&DATE(2025,11,1),Détail!$A:$A,"<"&EDATE(DATE(2025,11,1),1)) -> 0
A81: Décembre 2025 | B81: =SUMIFS(Détail!$E:$E,Détail!$C:$C,"ABONNEMENT TRANSBRED.COM",Détail!$A:$A,">="&DATE(2025,12,1),Détail!$A:$A,"<"&EDATE(DATE(2025,12,1),1)) -> 0
A84: Cotisation | C84: =SUMIF(Détail!$C:$C,"COTISATION",Détail!$E:$E) -> -364.32
A85: Mois | B85: Montant
A86: Janvier 2025 | B86: =SUMIFS(Détail!$E:$E,Détail!$C:$C,"COTISATION",Détail!$A:$A,">="&DATE(2025,1,1),Détail!$A:$A,"<"&EDATE(DATE(2025,1,1),1)) -> -24.03
A87: Février 2025 | B87: =SUMIFS(Détail!$E:$E,Détail!$C:$C,"COTISATION",Détail!$A:$A,">="&DATE(2025,2,1),Détail!$A:$A,"<"&EDATE(DATE(2025,2,1),1)) -> -24.03
A88: Mars 2025 | B88: =SUMIFS(Détail!$E:$E,Détail!$C:$C,"COTISATION",Détail!$A:$A,">="&DATE(2025,3,1),Détail!$A:$A,"<"&EDATE(DATE(2025,3,1),1)) -> -24.03
A89: Avril 2025 | B89: =SUMIFS(Détail!$E:$E,Détail!$C:$C,"COTISATION",Détail!$A:$A,">="&DATE(2025,4,1),Détail!$A:$A,"<"&EDATE(DATE(2025,4,1),1)) -> -24.03
A90: Mai 2025 | B90: =SUMIFS(Détail!$E:$E,Détail!$C:$C,"COTISATION",Détail!$A:$A,">="&DATE(2025,5,1),Détail!$A:$A,"<"&EDATE(DATE(2025,5,1),1)) -> -24.03
A91: Juin 2025 | B91: =SUMIFS(Détail!$E:$E,Détail!$C:$C,"COTISATION",Détail!$A:$A,">="&DATE(2025,6,1),Détail!$A:$A,"<"&EDATE(DATE(2025,6,1),1)) -> -24.03
A92: Juillet 2025 | B92: =SUMIFS(Détail!$E:$E,Détail!$C:$C,"COTISATION",Détail!$A:$A,">="&DATE(2025,7,1),Détail!$A:$A,"<"&EDATE(DATE(2025,7,1),1)) -> -24.03
A93: Août 2025 | B93: =SUMIFS(Détail!$E:$E,Détail!$C:$C,"COTISATION",Détail!$A:$A,">="&DATE(2025,8,1),Détail!$A:$A,"<"&EDATE(DATE(2025,8,1),1)) -> -24.03
A94: Septembre 2025 | B94: =SUMIFS(Détail!$E:$E,Détail!$C:$C,"COTISATION",Détail!$A:$A,">="&DATE(2025,9,1),Détail!$A:$A,"<"&EDATE(DATE(2025,9,1),1)) -> -24.03
A95: Octobre 2025 | B95: =SUMIFS(Détail!$E:$E,Détail!$C:$C,"COTISATION",Détail!$A:$A,">="&DATE(2025,10,1),Détail!$A:$A,"<"&EDATE(DATE(2025,10,1),1)) -> -49.35
A96: Novembre 2025 | B96: =SUMIFS(Détail!$E:$E,Détail!$C:$C,"COTISATION",Détail!$A:$A,">="&DATE(2025,11,1),Détail!$A:$A,"<"&EDATE(DATE(2025,11,1),1)) -> -49.35
A97: Décembre 2025 | B97: =SUMIFS(Détail!$E:$E,Détail!$C:$C,"COTISATION",Détail!$A:$A,">="&DATE(2025,12,1),Détail!$A:$A,"<"&EDATE(DATE(2025,12,1),1)) -> -49.35
A100: Frais Transaction Carte | C100: =SUMIF(Détail!$C:$C,"FRAIS TRANSACTION CARTE",Détail!$E:$E) -> -288.6
A101: Mois | B101: Montant
A102: Janvier 2025 | B102: =SUMIFS(Détail!$E:$E,Détail!$C:$C,"FRAIS TRANSACTION CARTE",Détail!$A:$A,">="&DATE(2025,1,1),Détail!$A:$A,"<"&EDATE(DATE(2025,1,1),1)) -> -1.25
A103: Février 2025 | B103: =SUMIFS(Détail!$E:$E,Détail!$C:$C,"FRAIS TRANSACTION CARTE",Détail!$A:$A,">="&DATE(2025,2,1),Détail!$A:$A,"<"&EDATE(DATE(2025,2,1),1)) -> -0.56
A104: Mars 2025 | B104: =SUMIFS(Détail!$E:$E,Détail!$C:$C,"FRAIS TRANSACTION CARTE",Détail!$A:$A,">="&DATE(2025,3,1),Détail!$A:$A,"<"&EDATE(DATE(2025,3,1),1)) -> -0.61
A105: Avril 2025 | B105: =SUMIFS(Détail!$E:$E,Détail!$C:$C,"FRAIS TRANSACTION CARTE",Détail!$A:$A,">="&DATE(2025,4,1),Détail!$A:$A,"<"&EDATE(DATE(2025,4,1),1)) -> -69.58
A106: Mai 2025 | B106: =SUMIFS(Détail!$E:$E,Détail!$C:$C,"FRAIS TRANSACTION CARTE",Détail!$A:$A,">="&DATE(2025,5,1),Détail!$A:$A,"<"&EDATE(DATE(2025,5,1),1)) -> -0.61
A107: Juin 2025 | B107: =SUMIFS(Détail!$E:$E,Détail!$C:$C,"FRAIS TRANSACTION CARTE",Détail!$A:$A,">="&DATE(2025,6,1),Détail!$A:$A,"<"&EDATE(DATE(2025,6,1),1)) -> -0.59
A108: Juillet 2025 | B108: =SUMIFS(Détail!$E:$E,Détail!$C:$C,"FRAIS TRANSACTION CARTE",Détail!$A:$A,">="&DATE(2025,7,1),Détail!$A:$A,"<"&EDATE(DATE(2025,7,1),1)) -> -1.24
A109: Août 2025 | B109: =SUMIFS(Détail!$E:$E,Détail!$C:$C,"FRAIS TRANSACTION CARTE",Détail!$A:$A,">="&DATE(2025,8,1),Détail!$A:$A,"<"&EDATE(DATE(2025,8,1),1)) -> -0.54
A110: Septembre 2025 | B110: =SUMIFS(Détail!$E:$E,Détail!$C:$C,"FRAIS TRANSACTION CARTE",Détail!$A:$A,">="&DATE(2025,9,1),Détail!$A:$A,"<"&EDATE(DATE(2025,9,1),1)) -> -92.26
A111: Octobre 2025 | B111: =SUMIFS(Détail!$E:$E,Détail!$C:$C,"FRAIS TRANSACTION CARTE",Détail!$A:$A,">="&DATE(2025,10,1),Détail!$A:$A,"<"&EDATE(DATE(2025,10,1),1)) -> -105.71
A112: Novembre 2025 | B112: =SUMIFS(Détail!$E:$E,Détail!$C:$C,"FRAIS TRANSACTION CARTE",Détail!$A:$A,">="&DATE(2025,11,1),Détail!$A:$A,"<"&EDATE(DATE(2025,11,1),1)) -> -15.15
A113: Décembre 2025 | B113: =SUMIFS(Détail!$E:$E,Détail!$C:$C,"FRAIS TRANSACTION CARTE",Détail!$A:$A,">="&DATE(2025,12,1),Détail!$A:$A,"<"&EDATE(DATE(2025,12,1),1)) -> -0.5
...

Sheet Mutuelle détail
A1: Mutuelle / prévoyance salariés — détail par organisme (2025)
A3: Amm Cot Sante Des Entreprises-Apivia Macif Mutuelle | C3: =SUMIF(Détail!$D:$D,"AMM COT SANTE DES ENTREPRISES-APIVIA MACIF MUTUELLE",Détail!$E:$E) -> -2444.76
A4: Mois | B4: Montant
A5: Janvier 2025 | B5: =SUMIFS(Détail!$E:$E,Détail!$D:$D,"AMM COT SANTE DES ENTREPRISES-APIVIA MACIF MUTUELLE",Détail!$A:$A,">="&DATE(2025,1,1),Détail!$A:$A,"<"&EDATE(DATE(2025,1,1),1)) -> -199
A6: Février 2025 | B6: =SUMIFS(Détail!$E:$E,Détail!$D:$D,"AMM COT SANTE DES ENTREPRISES-APIVIA MACIF MUTUELLE",Détail!$A:$A,">="&DATE(2025,2,1),Détail!$A:$A,"<"&EDATE(DATE(2025,2,1),1)) -> -204.16
A7: Mars 2025 | B7: =SUMIFS(Détail!$E:$E,Détail!$D:$D,"AMM COT SANTE DES ENTREPRISES-APIVIA MACIF MUTUELLE",Détail!$A:$A,">="&DATE(2025,3,1),Détail!$A:$A,"<"&EDATE(DATE(2025,3,1),1)) -> -204.16
A8: Avril 2025 | B8: =SUMIFS(Détail!$E:$E,Détail!$D:$D,"AMM COT SANTE DES ENTREPRISES-APIVIA MACIF MUTUELLE",Détail!$A:$A,">="&DATE(2025,4,1),Détail!$A:$A,"<"&EDATE(DATE(2025,4,1),1)) -> -125.16
A9: Mai 2025 | B9: =SUMIFS(Détail!$E:$E,Détail!$D:$D,"AMM COT SANTE DES ENTREPRISES-APIVIA MACIF MUTUELLE",Détail!$A:$A,">="&DATE(2025,5,1),Détail!$A:$A,"<"&EDATE(DATE(2025,5,1),1)) -> -283.16
A10: Juin 2025 | B10: =SUMIFS(Détail!$E:$E,Détail!$D:$D,"AMM COT SANTE DES ENTREPRISES-APIVIA MACIF MUTUELLE",Détail!$A:$A,">="&DATE(2025,6,1),Détail!$A:$A,"<"&EDATE(DATE(2025,6,1),1)) -> -204.16
A11: Juillet 2025 | B11: =SUMIFS(Détail!$E:$E,Détail!$D:$D,"AMM COT SANTE DES ENTREPRISES-APIVIA MACIF MUTUELLE",Détail!$A:$A,">="&DATE(2025,7,1),Détail!$A:$A,"<"&EDATE(DATE(2025,7,1),1)) -> -204.16
A12: Août 2025 | B12: =SUMIFS(Détail!$E:$E,Détail!$D:$D,"AMM COT SANTE DES ENTREPRISES-APIVIA MACIF MUTUELLE",Détail!$A:$A,">="&DATE(2025,8,1),Détail!$A:$A,"<"&EDATE(DATE(2025,8,1),1)) -> -204.16
A13: Septembre 2025 | B13: =SUMIFS(Détail!$E:$E,Détail!$D:$D,"AMM COT SANTE DES ENTREPRISES-APIVIA MACIF MUTUELLE",Détail!$A:$A,">="&DATE(2025,9,1),Détail!$A:$A,"<"&EDATE(DATE(2025,9,1),1)) -> -204.16
A14: Octobre 2025 | B14: =SUMIFS(Détail!$E:$E,Détail!$D:$D,"AMM COT SANTE DES ENTREPRISES-APIVIA MACIF MUTUELLE",Détail!$A:$A,">="&DATE(2025,10,1),Détail!$A:$A,"<"&EDATE(DATE(2025,10,1),1)) -> -204.16
A15: Novembre 2025 | B15: =SUMIFS(Détail!$E:$E,Détail!$D:$D,"AMM COT SANTE DES ENTREPRISES-APIVIA MACIF MUTUELLE",Détail!$A:$A,">="&DATE(2025,11,1),Détail!$A:$A,"<"&EDATE(DATE(2025,11,1),1)) -> -204.16
A16: Décembre 2025 | B16: =SUMIFS(Détail!$E:$E,Détail!$D:$D,"AMM COT SANTE DES ENTREPRISES-APIVIA MACIF MUTUELLE",Détail!$A:$A,">="&DATE(2025,12,1),Détail!$A:$A,"<"&EDATE(DATE(2025,12,1),1)) -> -204.16
A19: Macif Idf Production-Macif | C19: =SUMIF(Détail!$D:$D,"MACIF IDF PRODUCTION-MACIF",Détail!$E:$E) -> -1573.13
A20: Mois | B20: Montant
A21: Janvier 2025 | B21: =SUMIFS(Détail!$E:$E,Détail!$D:$D,"MACIF IDF PRODUCTION-MACIF",Détail!$A:$A,">="&DATE(2025,1,1),Détail!$A:$A,"<"&EDATE(DATE(2025,1,1),1)) -> -132.36
A22: Février 2025 | B22: =SUMIFS(Détail!$E:$E,Détail!$D:$D,"MACIF IDF PRODUCTION-MACIF",Détail!$A:$A,">="&DATE(2025,2,1),Détail!$A:$A,"<"&EDATE(DATE(2025,2,1),1)) -> -132.36
A23: Mars 2025 | B23: =SUMIFS(Détail!$E:$E,Détail!$D:$D,"MACIF IDF PRODUCTION-MACIF",Détail!$A:$A,">="&DATE(2025,3,1),Détail!$A:$A,"<"&EDATE(DATE(2025,3,1),1)) -> -132.36
A24: Avril 2025 | B24: =SUMIFS(Détail!$E:$E,Détail!$D:$D,"MACIF IDF PRODUCTION-MACIF",Détail!$A:$A,">="&DATE(2025,4,1),Détail!$A:$A,"<"&EDATE(DATE(2025,4,1),1)) -> -130.69
A25: Mai 2025 | B25: =SUMIFS(Détail!$E:$E,Détail!$D:$D,"MACIF IDF PRODUCTION-MACIF",Détail!$A:$A,">="&DATE(2025,5,1),Détail!$A:$A,"<"&EDATE(DATE(2025,5,1),1)) -> -130.67
A26: Juin 2025 | B26: =SUMIFS(Détail!$E:$E,Détail!$D:$D,"MACIF IDF PRODUCTION-MACIF",Détail!$A:$A,">="&DATE(2025,6,1),Détail!$A:$A,"<"&EDATE(DATE(2025,6,1),1)) -> -130.67
A27: Juillet 2025 | B27: =SUMIFS(Détail!$E:$E,Détail!$D:$D,"MACIF IDF PRODUCTION-MACIF",Détail!$A:$A,">="&DATE(2025,7,1),Détail!$A:$A,"<"&EDATE(DATE(2025,7,1),1)) -> -130.67
A28: Août 2025 | B28: =SUMIFS(Détail!$E:$E,Détail!$D:$D,"MACIF IDF PRODUCTION-MACIF",Détail!$A:$A,">="&DATE(2025,8,1),Détail!$A:$A,"<"&EDATE(DATE(2025,8,1),1)) -> -130.67
A29: Septembre 2025 | B29: =SUMIFS(Détail!$E:$E,Détail!$D:$D,"MACIF IDF PRODUCTION-MACIF",Détail!$A:$A,">="&DATE(2025,9,1),Détail!$A:$A,"<"&EDATE(DATE(2025,9,1),1)) -> -130.67
A30: Octobre 2025 | B30: =SUMIFS(Détail!$E:$E,Détail!$D:$D,"MACIF IDF PRODUCTION-MACIF",Détail!$A:$A,">="&DATE(2025,10,1),Détail!$A:$A,"<"&EDATE(DATE(2025,10,1),1)) -> -130.67
A31: Novembre 2025 | B31: =SUMIFS(Détail!$E:$E,Détail!$D:$D,"MACIF IDF PRODUCTION-MACIF",Détail!$A:$A,">="&DATE(2025,11,1),Détail!$A:$A,"<"&EDATE(DATE(2025,11,1),1)) -> -130.67
A32: Décembre 2025 | B32: =SUMIFS(Détail!$E:$E,Détail!$D:$D,"MACIF IDF PRODUCTION-MACIF",Détail!$A:$A,">="&DATE(2025,12,1),Détail!$A:$A,"<"&EDATE(DATE(2025,12,1),1)) -> -130.67
A35: Cep Treso Sante Prev | C35: =SUMIF(Détail!$D:$D,"CEP TRESO SANTE PREV",Détail!$E:$E) -> -661.86
A36: Mois | B36: Montant
A37: Janvier 2025 | B37: =SUMIFS(Détail!$E:$E,Détail!$D:$D,"CEP TRESO SANTE PREV",Détail!$A:$A,">="&DATE(2025,1,1),Détail!$A:$A,"<"&EDATE(DATE(2025,1,1),1)) -> -244.1
A38: Février 2025 | B38: =SUMIFS(Détail!$E:$E,Détail!$D:$D,"CEP TRESO SANTE PREV",Détail!$A:$A,">="&DATE(2025,2,1),Détail!$A:$A,"<"&EDATE(DATE(2025,2,1),1)) -> 0
A39: Mars 2025 | B39: =SUMIFS(Détail!$E:$E,Détail!$D:$D,"CEP TRESO SANTE PREV",Détail!$A:$A,">="&DATE(2025,3,1),Détail!$A:$A,"<"&EDATE(DATE(2025,3,1),1)) -> 0
A40: Avril 2025 | B40: =SUMIFS(Détail!$E:$E,Détail!$D:$D,"CEP TRESO SANTE PREV",Détail!$A:$A,">="&DATE(2025,4,1),Détail!$A:$A,"<"&EDATE(DATE(2025,4,1),1)) -> -93.11
A41: Mai 2025 | B41: =SUMIFS(Détail!$E:$E,Détail!$D:$D,"CEP TRESO SANTE PREV",Détail!$A:$A,">="&DATE(2025,5,1),Détail!$A:$A,"<"&EDATE(DATE(2025,5,1),1)) -> 0
A42: Juin 2025 | B42: =SUMIFS(Détail!$E:$E,Détail!$D:$D,"CEP TRESO SANTE PREV",Détail!$A:$A,">="&DATE(2025,6,1),Détail!$A:$A,"<"&EDATE(DATE(2025,6,1),1)) -> 0
A43: Juillet 2025 | B43: =SUMIFS(Détail!$E:$E,Détail!$D:$D,"CEP TRESO SANTE PREV",Détail!$A:$A,">="&DATE(2025,7,1),Détail!$A:$A,"<"&EDATE(DATE(2025,7,1),1)) -> -98.12
A44: Août 2025 | B44: =SUMIFS(Détail!$E:$E,Détail!$D:$D,"CEP TRESO SANTE PREV",Détail!$A:$A,">="&DATE(2025,8,1),Détail!$A:$A,"<"&EDATE(DATE(2025,8,1),1)) -> 0
A45: Septembre 2025 | B45: =SUMIFS(Détail!$E:$E,Détail!$D:$D,"CEP TRESO SANTE PREV",Détail!$A:$A,">="&DATE(2025,9,1),Détail!$A:$A,"<"&EDATE(DATE(2025,9,1),1)) -> 0
A46: Octobre 2025 | B46: =SUMIFS(Détail!$E:$E,Détail!$D:$D,"CEP TRESO SANTE PREV",Détail!$A:$A,">="&DATE(2025,10,1),Détail!$A:$A,"<"&EDATE(DATE(2025,10,1),1)) -> -226.53
A47: Novembre 2025 | B47: =SUMIFS(Détail!$E:$E,Détail!$D:$D,"CEP TRESO SANTE PREV",Détail!$A:$A,">="&DATE(2025,11,1),Détail!$A:$A,"<"&EDATE(DATE(2025,11,1),1)) -> 0
A48: Décembre 2025 | B48: =SUMIFS(Détail!$E:$E,Détail!$D:$D,"CEP TRESO SANTE PREV",Détail!$A:$A,">="&DATE(2025,12,1),Détail!$A:$A,"<"&EDATE(DATE(2025,12,1),1)) -> 0

Sheet Fournitures bureau détail
A1: Fournitures bureau / colis / achats en ligne — détail par prestataire (2025)
A3: Boulanger | C3: =SUMIF(Détail!$D:$D,"BOULANGER",Détail!$E:$E) -> -854.84
A4: Mois | B4: Montant
A5: Janvier 2025 | B5: =SUMIFS(Détail!$E:$E,Détail!$D:$D,"BOULANGER",Détail!$A:$A,">="&DATE(2025,1,1),Détail!$A:$A,"<"&EDATE(DATE(2025,1,1),1)) -> 0
A6: Février 2025 | B6: =SUMIFS(Détail!$E:$E,Détail!$D:$D,"BOULANGER",Détail!$A:$A,">="&DATE(2025,2,1),Détail!$A:$A,"<"&EDATE(DATE(2025,2,1),1)) -> 0
A7: Mars 2025 | B7: =SUMIFS(Détail!$E:$E,Détail!$D:$D,"BOULANGER",Détail!$A:$A,">="&DATE(2025,3,1),Détail!$A:$A,"<"&EDATE(DATE(2025,3,1),1)) -> -74.91
A8: Avril 2025 | B8: =SUMIFS(Détail!$E:$E,Détail!$D:$D,"BOULANGER",Détail!$A:$A,">="&DATE(2025,4,1),Détail!$A:$A,"<"&EDATE(DATE(2025,4,1),1)) -> 0
A9: Mai 2025 | B9: =SUMIFS(Détail!$E:$E,Détail!$D:$D,"BOULANGER",Détail!$A:$A,">="&DATE(2025,5,1),Détail!$A:$A,"<"&EDATE(DATE(2025,5,1),1)) -> -779.93
A10: Juillet 2025 | B10: =SUMIFS(Détail!$E:$E,Détail!$D:$D,"BOULANGER",Détail!$A:$A,">="&DATE(2025,7,1),Détail!$A:$A,"<"&EDATE(DATE(2025,7,1),1)) -> 0
A11: Août 2025 | B11: =SUMIFS(Détail!$E:$E,Détail!$D:$D,"BOULANGER",Détail!$A:$A,">="&DATE(2025,8,1),Détail!$A:$A,"<"&EDATE(DATE(2025,8,1),1)) -> 0
A12: Septembre 2025 | B12: =SUMIFS(Détail!$E:$E,Détail!$D:$D,"BOULANGER",Détail!$A:$A,">="&DATE(2025,9,1),Détail!$A:$A,"<"&EDATE(DATE(2025,9,1),1)) -> 0
A13: Novembre 2025 | B13: =SUMIFS(Détail!$E:$E,Détail!$D:$D,"BOULANGER",Détail!$A:$A,">="&DATE(2025,11,1),Détail!$A:$A,"<"&EDATE(DATE(2025,11,1),1)) -> 0
A16: Amazon Payments | C16: =SUMIF(Détail!$D:$D,"AMAZON PAYMENTS",Détail!$E:$E) -> -654.08
A17: Mois | B17: Montant
A18: Janvier 2025 | B18: =SUMIFS(Détail!$E:$E,Détail!$D:$D,"AMAZON PAYMENTS",Détail!$A:$A,">="&DATE(2025,1,1),Détail!$A:$A,"<"&EDATE(DATE(2025,1,1),1)) -> 0
A19: Février 2025 | B19: =SUMIFS(Détail!$E:$E,Détail!$D:$D,"AMAZON PAYMENTS",Détail!$A:$A,">="&DATE(2025,2,1),Détail!$A:$A,"<"&EDATE(DATE(2025,2,1),1)) -> 0
A20: Mars 2025 | B20: =SUMIFS(Détail!$E:$E,Détail!$D:$D,"AMAZON PAYMENTS",Détail!$A:$A,">="&DATE(2025,3,1),Détail!$A:$A,"<"&EDATE(DATE(2025,3,1),1)) -> 0
A21: Avril 2025 | B21: =SUMIFS(Détail!$E:$E,Détail!$D:$D,"AMAZON PAYMENTS",Détail!$A:$A,">="&DATE(2025,4,1),Détail!$A:$A,"<"&EDATE(DATE(2025,4,1),1)) -> -15.64
A22: Mai 2025 | B22: =SUMIFS(Détail!$E:$E,Détail!$D:$D,"AMAZON PAYMENTS",Détail!$A:$A,">="&DATE(2025,5,1),Détail!$A:$A,"<"&EDATE(DATE(2025,5,1),1)) -> -169.78
A23: Juillet 2025 | B23: =SUMIFS(Détail!$E:$E,Détail!$D:$D,"AMAZON PAYMENTS",Détail!$A:$A,">="&DATE(2025,7,1),Détail!$A:$A,"<"&EDATE(DATE(2025,7,1),1)) -> -158.02
A24: Août 2025 | B24: =SUMIFS(Détail!$E:$E,Détail!$D:$D,"AMAZON PAYMENTS",Détail!$A:$A,">="&DATE(2025,8,1),Détail!$A:$A,"<"&EDATE(DATE(2025,8,1),1)) -> 0
A25: Septembre 2025 | B25: =SUMIFS(Détail!$E:$E,Détail!$D:$D,"AMAZON PAYMENTS",Détail!$A:$A,">="&DATE(2025,9,1),Détail!$A:$A,"<"&EDATE(DATE(2025,9,1),1)) -> -128.04
A26: Novembre 2025 | B26: =SUMIFS(Détail!$E:$E,Détail!$D:$D,"AMAZON PAYMENTS",Détail!$A:$A,">="&DATE(2025,11,1),Détail!$A:$A,"<"&EDATE(DATE(2025,11,1),1)) -> -182.6
A29: Castorama | C29: =SUMIF(Détail!$D:$D,"CASTORAMA",Détail!$E:$E) -> -86.78
A30: Mois | B30: Montant
A31: Janvier 2025 | B31: =SUMIFS(Détail!$E:$E,Détail!$D:$D,"CASTORAMA",Détail!$A:$A,">="&DATE(2025,1,1),Détail!$A:$A,"<"&EDATE(DATE(2025,1,1),1)) -> 0
A32: Février 2025 | B32: =SUMIFS(Détail!$E:$E,Détail!$D:$D,"CASTORAMA",Détail!$A:$A,">="&DATE(2025,2,1),Détail!$A:$A,"<"&EDATE(DATE(2025,2,1),1)) -> 0
A33: Mars 2025 | B33: =SUMIFS(Détail!$E:$E,Détail!$D:$D,"CASTORAMA",Détail!$A:$A,">="&DATE(2025,3,1),Détail!$A:$A,"<"&EDATE(DATE(2025,3,1),1)) -> 0
A34: Avril 2025 | B34: =SUMIFS(Détail!$E:$E,Détail!$D:$D,"CASTORAMA",Détail!$A:$A,">="&DATE(2025,4,1),Détail!$A:$A,"<"&EDATE(DATE(2025,4,1),1)) -> 0
A35: Mai 2025 | B35: =SUMIFS(Détail!$E:$E,Détail!$D:$D,"CASTORAMA",Détail!$A:$A,">="&DATE(2025,5,1),Détail!$A:$A,"<"&EDATE(DATE(2025,5,1),1)) -> 0
A36: Juillet 2025 | B36: =SUMIFS(Détail!$E:$E,Détail!$D:$D,"CASTORAMA",Détail!$A:$A,">="&DATE(2025,7,1),Détail!$A:$A,"<"&EDATE(DATE(2025,7,1),1)) -> 0
A37: Août 2025 | B37: =SUMIFS(Détail!$E:$E,Détail!$D:$D,"CASTORAMA",Détail!$A:$A,">="&DATE(2025,8,1),Détail!$A:$A,"<"&EDATE(DATE(2025,8,1),1)) -> 0
A38: Septembre 2025 | B38: =SUMIFS(Détail!$E:$E,Détail!$D:$D,"CASTORAMA",Détail!$A:$A,">="&DATE(2025,9,1),Détail!$A:$A,"<"&EDATE(DATE(2025,9,1),1)) -> -86.78
A39: Novembre 2025 | B39: =SUMIFS(Détail!$E:$E,Détail!$D:$D,"CASTORAMA",Détail!$A:$A,">="&DATE(2025,11,1),Détail!$A:$A,"<"&EDATE(DATE(2025,11,1),1)) -> 0
A42: Leroy Merlin | C42: =SUMIF(Détail!$D:$D,"LEROY MERLIN",Détail!$E:$E) -> -60.64
A43: Mois | B43: Montant
A44: Janvier 2025 | B44: =SUMIFS(Détail!$E:$E,Détail!$D:$D,"LEROY MERLIN",Détail!$A:$A,">="&DATE(2025,1,1),Détail!$A:$A,"<"&EDATE(DATE(2025,1,1),1)) -> 0
A45: Février 2025 | B45: =SUMIFS(Détail!$E:$E,Détail!$D:$D,"LEROY MERLIN",Détail!$A:$A,">="&DATE(2025,2,1),Détail!$A:$A,"<"&EDATE(DATE(2025,2,1),1)) -> 0
A46: Mars 2025 | B46: =SUMIFS(Détail!$E:$E,Détail!$D:$D,"LEROY MERLIN",Détail!$A:$A,">="&DATE(2025,3,1),Détail!$A:$A,"<"&EDATE(DATE(2025,3,1),1)) -> 0
A47: Avril 2025 | B47: =SUMIFS(Détail!$E:$E,Détail!$D:$D,"LEROY MERLIN",Détail!$A:$A,">="&DATE(2025,4,1),Détail!$A:$A,"<"&EDATE(DATE(2025,4,1),1)) -> 0
A48: Mai 2025 | B48: =SUMIFS(Détail!$E:$E,Détail!$D:$D,"LEROY MERLIN",Détail!$A:$A,">="&DATE(2025,5,1),Détail!$A:$A,"<"&EDATE(DATE(2025,5,1),1)) -> 0
A49: Juillet 2025 | B49: =SUMIFS(Détail!$E:$E,Détail!$D:$D,"LEROY MERLIN",Détail!$A:$A,">="&DATE(2025,7,1),Détail!$A:$A,"<"&EDATE(DATE(2025,7,1),1)) -> 0
A50: Août 2025 | B50: =SUMIFS(Détail!$E:$E,Détail!$D:$D,"LEROY MERLIN",Détail!$A:$A,">="&DATE(2025,8,1),Détail!$A:$A,"<"&EDATE(DATE(2025,8,1),1)) -> -60.64
A51: Septembre 2025 | B51: =SUMIFS(Détail!$E:$E,Détail!$D:$D,"LEROY MERLIN",Détail!$A:$A,">="&DATE(2025,9,1),Détail!$A:$A,"<"&EDATE(DATE(2025,9,1),1)) -> 0
A52: Novembre 2025 | B52: =SUMIFS(Détail!$E:$E,Détail!$D:$D,"LEROY MERLIN",Détail!$A:$A,">="&DATE(2025,11,1),Détail!$A:$A,"<"&EDATE(DATE(2025,11,1),1)) -> 0
A55: Leroy Merlin Sc | C55: =SUMIF(Détail!$D:$D,"LEROY MERLIN SC",Détail!$E:$E) -> -47.79
A56: Mois | B56: Montant
A57: Janvier 2025 | B57: =SUMIFS(Détail!$E:$E,Détail!$D:$D,"LEROY MERLIN SC",Détail!$A:$A,">="&DATE(2025,1,1),Détail!$A:$A,"<"&EDATE(DATE(2025,1,1),1)) -> 0
A58: Février 2025 | B58: =SUMIFS(Détail!$E:$E,Détail!$D:$D,"LEROY MERLIN SC",Détail!$A:$A,">="&DATE(2025,2,1),Détail!$A:$A,"<"&EDATE(DATE(2025,2,1),1)) -> 0
A59: Mars 2025 | B59: =SUMIFS(Détail!$E:$E,Détail!$D:$D,"LEROY MERLIN SC",Détail!$A:$A,">="&DATE(2025,3,1),Détail!$A:$A,"<"&EDATE(DATE(2025,3,1),1)) -> 0
A60: Avril 2025 | B60: =SUMIFS(Détail!$E:$E,Détail!$D:$D,"LEROY MERLIN SC",Détail!$A:$A,">="&DATE(2025,4,1),Détail!$A:$A,"<"&EDATE(DATE(2025,4,1),1)) -> 0
A61: Mai 2025 | B61: =SUMIFS(Détail!$E:$E,Détail!$D:$D,"LEROY MERLIN SC",Détail!$A:$A,">="&DATE(2025,5,1),Détail!$A:$A,"<"&EDATE(DATE(2025,5,1),1)) -> 0
A62: Juillet 2025 | B62: =SUMIFS(Détail!$E:$E,Détail!$D:$D,"LEROY MERLIN SC",Détail!$A:$A,">="&DATE(2025,7,1),Détail!$A:$A,"<"&EDATE(DATE(2025,7,1),1)) -> 0
A63: Août 2025 | B63: =SUMIFS(Détail!$E:$E,Détail!$D:$D,"LEROY MERLIN SC",Détail!$A:$A,">="&DATE(2025,8,1),Détail!$A:$A,"<"&EDATE(DATE(2025,8,1),1)) -> -47.79
A64: Septembre 2025 | B64: =SUMIFS(Détail!$E:$E,Détail!$D:$D,"LEROY MERLIN SC",Détail!$A:$A,">="&DATE(2025,9,1),Détail!$A:$A,"<"&EDATE(DATE(2025,9,1),1)) -> 0
A65: Novembre 2025 | B65: =SUMIFS(Détail!$E:$E,Détail!$D:$D,"LEROY MERLIN SC",Détail!$A:$A,">="&DATE(2025,11,1),Détail!$A:$A,"<"&EDATE(DATE(2025,11,1),1)) -> 0
A68: Boulangerie (Divers) | C68: =SUMIF(Détail!$D:$D,"BOULANGERIE (divers)",Détail!$E:$E) -> -13.5
A69: Mois | B69: Montant
A70: Janvier 2025 | B70: =SUMIFS(Détail!$E:$E,Détail!$D:$D,"BOULANGERIE (divers)",Détail!$A:$A,">="&DATE(2025,1,1),Détail!$A:$A,"<"&EDATE(DATE(2025,1,1),1)) -> -13.5
A71: Février 2025 | B71: =SUMIFS(Détail!$E:$E,Détail!$D:$D,"BOULANGERIE (divers)",Détail!$A:$A,">="&DATE(2025,2,1),Détail!$A:$A,"<"&EDATE(DATE(2025,2,1),1)) -> 0
A72: Mars 2025 | B72: =SUMIFS(Détail!$E:$E,Détail!$D:$D,"BOULANGERIE (divers)",Détail!$A:$A,">="&DATE(2025,3,1),Détail!$A:$A,"<"&EDATE(DATE(2025,3,1),1)) -> 0
A73: Avril 2025 | B73: =SUMIFS(Détail!$E:$E,Détail!$D:$D,"BOULANGERIE (divers)",Détail!$A:$A,">="&DATE(2025,4,1),Détail!$A:$A,"<"&EDATE(DATE(2025,4,1),1)) -> 0
A74: Mai 2025 | B74: =SUMIFS(Détail!$E:$E,Détail!$D:$D,"BOULANGERIE (divers)",Détail!$A:$A,">="&DATE(2025,5,1),Détail!$A:$A,"<"&EDATE(DATE(2025,5,1),1)) -> 0
A75: Juillet 2025 | B75: =SUMIFS(Détail!$E:$E,Détail!$D:$D,"BOULANGERIE (divers)",Détail!$A:$A,">="&DATE(2025,7,1),Détail!$A:$A,"<"&EDATE(DATE(2025,7,1),1)) -> 0
A76: Août 2025 | B76: =SUMIFS(Détail!$E:$E,Détail!$D:$D,"BOULANGERIE (divers)",Détail!$A:$A,">="&DATE(2025,8,1),Détail!$A:$A,"<"&EDATE(DATE(2025,8,1),1)) -> 0
A77: Septembre 2025 | B77: =SUMIFS(Détail!$E:$E,Détail!$D:$D,"BOULANGERIE (divers)",Détail!$A:$A,">="&DATE(2025,9,1),Détail!$A:$A,"<"&EDATE(DATE(2025,9,1),1)) -> 0
A78: Novembre 2025 | B78: =SUMIFS(Détail!$E:$E,Détail!$D:$D,"BOULANGERIE (divers)",Détail!$A:$A,">="&DATE(2025,11,1),Détail!$A:$A,"<"&EDATE(DATE(2025,11,1),1)) -> 0
A81: Action 4632 | C81: =SUMIF(Détail!$D:$D,"ACTION 4632",Détail!$E:$E) -> -12.99
A82: Mois | B82: Montant
A83: Janvier 2025 | B83: =SUMIFS(Détail!$E:$E,Détail!$D:$D,"ACTION 4632",Détail!$A:$A,">="&DATE(2025,1,1),Détail!$A:$A,"<"&EDATE(DATE(2025,1,1),1)) -> 0
A84: Février 2025 | B84: =SUMIFS(Détail!$E:$E,Détail!$D:$D,"ACTION 4632",Détail!$A:$A,">="&DATE(2025,2,1),Détail!$A:$A,"<"&EDATE(DATE(2025,2,1),1)) -> -12.99
A85: Mars 2025 | B85: =SUMIFS(Détail!$E:$E,Détail!$D:$D,"ACTION 4632",Détail!$A:$A,">="&DATE(2025,3,1),Détail!$A:$A,"<"&EDATE(DATE(2025,3,1),1)) -> 0
A86: Avril 2025 | B86: =SUMIFS(Détail!$E:$E,Détail!$D:$D,"ACTION 4632",Détail!$A:$A,">="&DATE(2025,4,1),Détail!$A:$A,"<"&EDATE(DATE(2025,4,1),1)) -> 0
A87: Mai 2025 | B87: =SUMIFS(Détail!$E:$E,Détail!$D:$D,"ACTION 4632",Détail!$A:$A,">="&DATE(2025,5,1),Détail!$A:$A,"<"&EDATE(DATE(2025,5,1),1)) -> 0
A88: Juillet 2025 | B88: =SUMIFS(Détail!$E:$E,Détail!$D:$D,"ACTION 4632",Détail!$A:$A,">="&DATE(2025,7,1),Détail!$A:$A,"<"&EDATE(DATE(2025,7,1),1)) -> 0
A89: Août 2025 | B89: =SUMIFS(Détail!$E:$E,Détail!$D:$D,"ACTION 4632",Détail!$A:$A,">="&DATE(2025,8,1),Détail!$A:$A,"<"&EDATE(DATE(2025,8,1),1)) -> 0
A90: Septembre 2025 | B90: =SUMIFS(Détail!$E:$E,Détail!$D:$D,"ACTION 4632",Détail!$A:$A,">="&DATE(2025,9,1),Détail!$A:$A,"<"&EDATE(DATE(2025,9,1),1)) -> 0
A91: Novembre 2025 | B91: =SUMIFS(Détail!$E:$E,Détail!$D:$D,"ACTION 4632",Détail!$A:$A,">="&DATE(2025,11,1),Détail!$A:$A,"<"&EDATE(DATE(2025,11,1),1)) -> 0

Sheet Transport livraison détail
A1: Transport / livraison (colis, courrier) — détail par prestataire (2025)
A3: Ifs | C3: =SUMIF(Détail!$D:$D,"IFS",Détail!$E:$E) -> -78154.2
A4: Mois | B4: Montant
A5: Janvier 2025 | B5: =SUMIFS(Détail!$E:$E,Détail!$D:$D,"IFS",Détail!$A:$A,">="&DATE(2025,1,1),Détail!$A:$A,"<"&EDATE(DATE(2025,1,1),1)) -> -3026.96
A6: Février 2025 | B6: =SUMIFS(Détail!$E:$E,Détail!$D:$D,"IFS",Détail!$A:$A,">="&DATE(2025,2,1),Détail!$A:$A,"<"&EDATE(DATE(2025,2,1),1)) -> -2332.31
A7: Mars 2025 | B7: =SUMIFS(Détail!$E:$E,Détail!$D:$D,"IFS",Détail!$A:$A,">="&DATE(2025,3,1),Détail!$A:$A,"<"&EDATE(DATE(2025,3,1),1)) -> -10464.8
A8: Avril 2025 | B8: =SUMIFS(Détail!$E:$E,Détail!$D:$D,"IFS",Détail!$A:$A,">="&DATE(2025,4,1),Détail!$A:$A,"<"&EDATE(DATE(2025,4,1),1)) -> -3221.8
A9: Mai 2025 | B9: =SUMIFS(Détail!$E:$E,Détail!$D:$D,"IFS",Détail!$A:$A,">="&DATE(2025,5,1),Détail!$A:$A,"<"&EDATE(DATE(2025,5,1),1)) -> 0
A10: Juin 2025 | B10: =SUMIFS(Détail!$E:$E,Détail!$D:$D,"IFS",Détail!$A:$A,">="&DATE(2025,6,1),Détail!$A:$A,"<"&EDATE(DATE(2025,6,1),1)) -> -4051.2
A11: Juillet 2025 | B11: =SUMIFS(Détail!$E:$E,Détail!$D:$D,"IFS",Détail!$A:$A,">="&DATE(2025,7,1),Détail!$A:$A,"<"&EDATE(DATE(2025,7,1),1)) -> -2122.2
A12: Septembre 2025 | B12: =SUMIFS(Détail!$E:$E,Détail!$D:$D,"IFS",Détail!$A:$A,">="&DATE(2025,9,1),Détail!$A:$A,"<"&EDATE(DATE(2025,9,1),1)) -> -7440.2
A13: Octobre 2025 | B13: =SUMIFS(Détail!$E:$E,Détail!$D:$D,"IFS",Détail!$A:$A,">="&DATE(2025,10,1),Détail!$A:$A,"<"&EDATE(DATE(2025,10,1),1)) -> -26358.81
A14: Novembre 2025 | B14: =SUMIFS(Détail!$E:$E,Détail!$D:$D,"IFS",Détail!$A:$A,">="&DATE(2025,11,1),Détail!$A:$A,"<"&EDATE(DATE(2025,11,1),1)) -> 0
A15: Décembre 2025 | B15: =SUMIFS(Détail!$E:$E,Détail!$D:$D,"IFS",Détail!$A:$A,">="&DATE(2025,12,1),Détail!$A:$A,"<"&EDATE(DATE(2025,12,1),1)) -> -19135.92
A18: Dhl Internat. Exp France | C18: =SUMIF(Détail!$D:$D,"DHL INTERNAT. EXP FRANCE",Détail!$E:$E) -> -2401.78
A19: Mois | B19: Montant
A20: Janvier 2025 | B20: =SUMIFS(Détail!$E:$E,Détail!$D:$D,"DHL INTERNAT. EXP FRANCE",Détail!$A:$A,">="&DATE(2025,1,1),Détail!$A:$A,"<"&EDATE(DATE(2025,1,1),1)) -> -443.64
A21: Février 2025 | B21: =SUMIFS(Détail!$E:$E,Détail!$D:$D,"DHL INTERNAT. EXP FRANCE",Détail!$A:$A,">="&DATE(2025,2,1),Détail!$A:$A,"<"&EDATE(DATE(2025,2,1),1)) -> -66.18
A22: Mars 2025 | B22: =SUMIFS(Détail!$E:$E,Détail!$D:$D,"DHL INTERNAT. EXP FRANCE",Détail!$A:$A,">="&DATE(2025,3,1),Détail!$A:$A,"<"&EDATE(DATE(2025,3,1),1)) -> 0
A23: Avril 2025 | B23: =SUMIFS(Détail!$E:$E,Détail!$D:$D,"DHL INTERNAT. EXP FRANCE",Détail!$A:$A,">="&DATE(2025,4,1),Détail!$A:$A,"<"&EDATE(DATE(2025,4,1),1)) -> -119.94
A24: Mai 2025 | B24: =SUMIFS(Détail!$E:$E,Détail!$D:$D,"DHL INTERNAT. EXP FRANCE",Détail!$A:$A,">="&DATE(2025,5,1),Détail!$A:$A,"<"&EDATE(DATE(2025,5,1),1)) -> -108.36
A25: Juin 2025 | B25: =SUMIFS(Détail!$E:$E,Détail!$D:$D,"DHL INTERNAT. EXP FRANCE",Détail!$A:$A,">="&DATE(2025,6,1),Détail!$A:$A,"<"&EDATE(DATE(2025,6,1),1)) -> -440.77
A26: Juillet 2025 | B26: =SUMIFS(Détail!$E:$E,Détail!$D:$D,"DHL INTERNAT. EXP FRANCE",Détail!$A:$A,">="&DATE(2025,7,1),Détail!$A:$A,"<"&EDATE(DATE(2025,7,1),1)) -> 0
A27: Septembre 2025 | B27: =SUMIFS(Détail!$E:$E,Détail!$D:$D,"DHL INTERNAT. EXP FRANCE",Détail!$A:$A,">="&DATE(2025,9,1),Détail!$A:$A,"<"&EDATE(DATE(2025,9,1),1)) -> -205.51
A28: Octobre 2025 | B28: =SUMIFS(Détail!$E:$E,Détail!$D:$D,"DHL INTERNAT. EXP FRANCE",Détail!$A:$A,">="&DATE(2025,10,1),Détail!$A:$A,"<"&EDATE(DATE(2025,10,1),1)) -> -929.08
A29: Novembre 2025 | B29: =SUMIFS(Détail!$E:$E,Détail!$D:$D,"DHL INTERNAT. EXP FRANCE",Détail!$A:$A,">="&DATE(2025,11,1),Détail!$A:$A,"<"&EDATE(DATE(2025,11,1),1)) -> -88.3
A30: Décembre 2025 | B30: =SUMIFS(Détail!$E:$E,Détail!$D:$D,"DHL INTERNAT. EXP FRANCE",Détail!$A:$A,">="&DATE(2025,12,1),Détail!$A:$A,"<"&EDATE(DATE(2025,12,1),1)) -> 0
A33: La Poste.Fr | C33: =SUMIF(Détail!$D:$D,"LA POSTE.FR",Détail!$E:$E) -> -923.4
A34: Mois | B34: Montant
A35: Janvier 2025 | B35: =SUMIFS(Détail!$E:$E,Détail!$D:$D,"LA POSTE.FR",Détail!$A:$A,">="&DATE(2025,1,1),Détail!$A:$A,"<"&EDATE(DATE(2025,1,1),1)) -> -35.75
A36: Février 2025 | B36: =SUMIFS(Détail!$E:$E,Détail!$D:$D,"LA POSTE.FR",Détail!$A:$A,">="&DATE(2025,2,1),Détail!$A:$A,"<"&EDATE(DATE(2025,2,1),1)) -> -10.45
A37: Mars 2025 | B37: =SUMIFS(Détail!$E:$E,Détail!$D:$D,"LA POSTE.FR",Détail!$A:$A,">="&DATE(2025,3,1),Détail!$A:$A,"<"&EDATE(DATE(2025,3,1),1)) -> -66.37
A38: Avril 2025 | B38: =SUMIFS(Détail!$E:$E,Détail!$D:$D,"LA POSTE.FR",Détail!$A:$A,">="&DATE(2025,4,1),Détail!$A:$A,"<"&EDATE(DATE(2025,4,1),1)) -> -102.65
A39: Mai 2025 | B39: =SUMIFS(Détail!$E:$E,Détail!$D:$D,"LA POSTE.FR",Détail!$A:$A,">="&DATE(2025,5,1),Détail!$A:$A,"<"&EDATE(DATE(2025,5,1),1)) -> -29.59
A40: Juin 2025 | B40: =SUMIFS(Détail!$E:$E,Détail!$D:$D,"LA POSTE.FR",Détail!$A:$A,">="&DATE(2025,6,1),Détail!$A:$A,"<"&EDATE(DATE(2025,6,1),1)) -> -102.26
A41: Juillet 2025 | B41: =SUMIFS(Détail!$E:$E,Détail!$D:$D,"LA POSTE.FR",Détail!$A:$A,">="&DATE(2025,7,1),Détail!$A:$A,"<"&EDATE(DATE(2025,7,1),1)) -> -147.73
A42: Septembre 2025 | B42: =SUMIFS(Détail!$E:$E,Détail!$D:$D,"LA POSTE.FR",Détail!$A:$A,">="&DATE(2025,9,1),Détail!$A:$A,"<"&EDATE(DATE(2025,9,1),1)) -> -136.3
A43: Octobre 2025 | B43: =SUMIFS(Détail!$E:$E,Détail!$D:$D,"LA POSTE.FR",Détail!$A:$A,">="&DATE(2025,10,1),Détail!$A:$A,"<"&EDATE(DATE(2025,10,1),1)) -> -100.15
A44: Novembre 2025 | B44: =SUMIFS(Détail!$E:$E,Détail!$D:$D,"LA POSTE.FR",Détail!$A:$A,">="&DATE(2025,11,1),Détail!$A:$A,"<"&EDATE(DATE(2025,11,1),1)) -> -192.15
A45: Décembre 2025 | B45: =SUMIFS(Détail!$E:$E,Détail!$D:$D,"LA POSTE.FR",Détail!$A:$A,">="&DATE(2025,12,1),Détail!$A:$A,"<"&EDATE(DATE(2025,12,1),1)) -> 0
A48: Fedex Express | C48: =SUMIF(Détail!$D:$D,"FEDEX EXPRESS",Détail!$E:$E) -> -71
A49: Mois | B49: Montant
A50: Janvier 2025 | B50: =SUMIFS(Détail!$E:$E,Détail!$D:$D,"FEDEX EXPRESS",Détail!$A:$A,">="&DATE(2025,1,1),Détail!$A:$A,"<"&EDATE(DATE(2025,1,1),1)) -> 0
A51: Février 2025 | B51: =SUMIFS(Détail!$E:$E,Détail!$D:$D,"FEDEX EXPRESS",Détail!$A:$A,">="&DATE(2025,2,1),Détail!$A:$A,"<"&EDATE(DATE(2025,2,1),1)) -> 0
A52: Mars 2025 | B52: =SUMIFS(Détail!$E:$E,Détail!$D:$D,"FEDEX EXPRESS",Détail!$A:$A,">="&DATE(2025,3,1),Détail!$A:$A,"<"&EDATE(DATE(2025,3,1),1)) -> 0
A53: Avril 2025 | B53: =SUMIFS(Détail!$E:$E,Détail!$D:$D,"FEDEX EXPRESS",Détail!$A:$A,">="&DATE(2025,4,1),Détail!$A:$A,"<"&EDATE(DATE(2025,4,1),1)) -> 0
A54: Mai 2025 | B54: =SUMIFS(Détail!$E:$E,Détail!$D:$D,"FEDEX EXPRESS",Détail!$A:$A,">="&DATE(2025,5,1),Détail!$A:$A,"<"&EDATE(DATE(2025,5,1),1)) -> 0
A55: Juin 2025 | B55: =SUMIFS(Détail!$E:$E,Détail!$D:$D,"FEDEX EXPRESS",Détail!$A:$A,">="&DATE(2025,6,1),Détail!$A:$A,"<"&EDATE(DATE(2025,6,1),1)) -> -49.8
A56: Juillet 2025 | B56: =SUMIFS(Détail!$E:$E,Détail!$D:$D,"FEDEX EXPRESS",Détail!$A:$A,">="&DATE(2025,7,1),Détail!$A:$A,"<"&EDATE(DATE(2025,7,1),1)) -> 0
A57: Septembre 2025 | B57: =SUMIFS(Détail!$E:$E,Détail!$D:$D,"FEDEX EXPRESS",Détail!$A:$A,">="&DATE(2025,9,1),Détail!$A:$A,"<"&EDATE(DATE(2025,9,1),1)) -> 0
A58: Octobre 2025 | B58: =SUMIFS(Détail!$E:$E,Détail!$D:$D,"FEDEX EXPRESS",Détail!$A:$A,">="&DATE(2025,10,1),Détail!$A:$A,"<"&EDATE(DATE(2025,10,1),1)) -> -21.2
A59: Novembre 2025 | B59: =SUMIFS(Détail!$E:$E,Détail!$D:$D,"FEDEX EXPRESS",Détail!$A:$A,">="&DATE(2025,11,1),Détail!$A:$A,"<"&EDATE(DATE(2025,11,1),1)) -> 0
A60: Décembre 2025 | B60: =SUMIFS(Détail!$E:$E,Détail!$D:$D,"FEDEX EXPRESS",Détail!$A:$A,">="&DATE(2025,12,1),Détail!$A:$A,"<"&EDATE(DATE(2025,12,1),1)) -> 0

Sheet Prêt détail
A1: Prêt professionnel — détail (2025)
A3: Bpifrance | C3: =SUMIF(Détail!$D:$D,"BPIFRANCE",Détail!$E:$E) -> -125.06
A4: Mois | B4: Montant
A5: Février 2025 | B5: =SUMIFS(Détail!$E:$E,Détail!$D:$D,"BPIFRANCE",Détail!$A:$A,">="&DATE(2025,2,1),Détail!$A:$A,"<"&EDATE(DATE(2025,2,1),1)) -> -28.86
A6: Mars 2025 | B6: =SUMIFS(Détail!$E:$E,Détail!$D:$D,"BPIFRANCE",Détail!$A:$A,">="&DATE(2025,3,1),Détail!$A:$A,"<"&EDATE(DATE(2025,3,1),1)) -> -19.24
A7: Avril 2025 | B7: =SUMIFS(Détail!$E:$E,Détail!$D:$D,"BPIFRANCE",Détail!$A:$A,">="&DATE(2025,4,1),Détail!$A:$A,"<"&EDATE(DATE(2025,4,1),1)) -> -19.24
A8: Mai 2025 | B8: =SUMIFS(Détail!$E:$E,Détail!$D:$D,"BPIFRANCE",Détail!$A:$A,">="&DATE(2025,5,1),Détail!$A:$A,"<"&EDATE(DATE(2025,5,1),1)) -> -28.86
A9: Juin 2025 | B9: =SUMIFS(Détail!$E:$E,Détail!$D:$D,"BPIFRANCE",Détail!$A:$A,">="&DATE(2025,6,1),Détail!$A:$A,"<"&EDATE(DATE(2025,6,1),1)) -> 0
A10: Juillet 2025 | B10: =SUMIFS(Détail!$E:$E,Détail!$D:$D,"BPIFRANCE",Détail!$A:$A,">="&DATE(2025,7,1),Détail!$A:$A,"<"&EDATE(DATE(2025,7,1),1)) -> -28.86
A11: Août 2025 | B11: =SUMIFS(Détail!$E:$E,Détail!$D:$D,"BPIFRANCE",Détail!$A:$A,">="&DATE(2025,8,1),Détail!$A:$A,"<"&EDATE(DATE(2025,8,1),1)) -> 0
A12: Septembre 2025 | B12: =SUMIFS(Détail!$E:$E,Détail!$D:$D,"BPIFRANCE",Détail!$A:$A,">="&DATE(2025,9,1),Détail!$A:$A,"<"&EDATE(DATE(2025,9,1),1)) -> 0

Sheet Alimentation détail
A1: Alimentation / supermarché — détail par enseigne (2025)
A3: Supermarche L' | C3: =SUMIF(Détail!$D:$D,"SUPERMARCHE L'",Détail!$E:$E) -> -428.37
A4: Mois | B4: Montant
A5: Janvier 2025 | B5: =SUMIFS(Détail!$E:$E,Détail!$D:$D,"SUPERMARCHE L'",Détail!$A:$A,">="&DATE(2025,1,1),Détail!$A:$A,"<"&EDATE(DATE(2025,1,1),1)) -> -7.37
A6: Février 2025 | B6: =SUMIFS(Détail!$E:$E,Détail!$D:$D,"SUPERMARCHE L'",Détail!$A:$A,">="&DATE(2025,2,1),Détail!$A:$A,"<"&EDATE(DATE(2025,2,1),1)) -> -41.79
A7: Mars 2025 | B7: =SUMIFS(Détail!$E:$E,Détail!$D:$D,"SUPERMARCHE L'",Détail!$A:$A,">="&DATE(2025,3,1),Détail!$A:$A,"<"&EDATE(DATE(2025,3,1),1)) -> 0
A8: Avril 2025 | B8: =SUMIFS(Détail!$E:$E,Détail!$D:$D,"SUPERMARCHE L'",Détail!$A:$A,">="&DATE(2025,4,1),Détail!$A:$A,"<"&EDATE(DATE(2025,4,1),1)) -> -2.76
A9: Mai 2025 | B9: =SUMIFS(Détail!$E:$E,Détail!$D:$D,"SUPERMARCHE L'",Détail!$A:$A,">="&DATE(2025,5,1),Détail!$A:$A,"<"&EDATE(DATE(2025,5,1),1)) -> -25.41
A10: Juin 2025 | B10: =SUMIFS(Détail!$E:$E,Détail!$D:$D,"SUPERMARCHE L'",Détail!$A:$A,">="&DATE(2025,6,1),Détail!$A:$A,"<"&EDATE(DATE(2025,6,1),1)) -> -112.12
A11: Juillet 2025 | B11: =SUMIFS(Détail!$E:$E,Détail!$D:$D,"SUPERMARCHE L'",Détail!$A:$A,">="&DATE(2025,7,1),Détail!$A:$A,"<"&EDATE(DATE(2025,7,1),1)) -> 0
A12: Septembre 2025 | B12: =SUMIFS(Détail!$E:$E,Détail!$D:$D,"SUPERMARCHE L'",Détail!$A:$A,">="&DATE(2025,9,1),Détail!$A:$A,"<"&EDATE(DATE(2025,9,1),1)) -> -32.21
A13: Octobre 2025 | B13: =SUMIFS(Détail!$E:$E,Détail!$D:$D,"SUPERMARCHE L'",Détail!$A:$A,">="&DATE(2025,10,1),Détail!$A:$A,"<"&EDATE(DATE(2025,10,1),1)) -> -76.3
A14: Décembre 2025 | B14: =SUMIFS(Détail!$E:$E,Détail!$D:$D,"SUPERMARCHE L'",Détail!$A:$A,">="&DATE(2025,12,1),Détail!$A:$A,"<"&EDATE(DATE(2025,12,1),1)) -> -130.41
A17: E.Leclerc | C17: =SUMIF(Détail!$D:$D,"E.LECLERC",Détail!$E:$E) -> -189.67
A18: Mois | B18: Montant
A19: Janvier 2025 | B19: =SUMIFS(Détail!$E:$E,Détail!$D:$D,"E.LECLERC",Détail!$A:$A,">="&DATE(2025,1,1),Détail!$A:$A,"<"&EDATE(DATE(2025,1,1),1)) -> -97.34
A20: Février 2025 | B20: =SUMIFS(Détail!$E:$E,Détail!$D:$D,"E.LECLERC",Détail!$A:$A,">="&DATE(2025,2,1),Détail!$A:$A,"<"&EDATE(DATE(2025,2,1),1)) -> -80
A21: Mars 2025 | B21: =SUMIFS(Détail!$E:$E,Détail!$D:$D,"E.LECLERC",Détail!$A:$A,">="&DATE(2025,3,1),Détail!$A:$A,"<"&EDATE(DATE(2025,3,1),1)) -> 0
A22: Avril 2025 | B22: =SUMIFS(Détail!$E:$E,Détail!$D:$D,"E.LECLERC",Détail!$A:$A,">="&DATE(2025,4,1),Détail!$A:$A,"<"&EDATE(DATE(2025,4,1),1)) -> 0
A23: Mai 2025 | B23: =SUMIFS(Détail!$E:$E,Détail!$D:$D,"E.LECLERC",Détail!$A:$A,">="&DATE(2025,5,1),Détail!$A:$A,"<"&EDATE(DATE(2025,5,1),1)) -> 0
A24: Juin 2025 | B24: =SUMIFS(Détail!$E:$E,Détail!$D:$D,"E.LECLERC",Détail!$A:$A,">="&DATE(2025,6,1),Détail!$A:$A,"<"&EDATE(DATE(2025,6,1),1)) -> -12.33
A25: Juillet 2025 | B25: =SUMIFS(Détail!$E:$E,Détail!$D:$D,"E.LECLERC",Détail!$A:$A,">="&DATE(2025,7,1),Détail!$A:$A,"<"&EDATE(DATE(2025,7,1),1)) -> 0
A26: Septembre 2025 | B26: =SUMIFS(Détail!$E:$E,Détail!$D:$D,"E.LECLERC",Détail!$A:$A,">="&DATE(2025,9,1),Détail!$A:$A,"<"&EDATE(DATE(2025,9,1),1)) -> 0
A27: Octobre 2025 | B27: =SUMIFS(Détail!$E:$E,Détail!$D:$D,"E.LECLERC",Détail!$A:$A,">="&DATE(2025,10,1),Détail!$A:$A,"<"&EDATE(DATE(2025,10,1),1)) -> 0
A28: Décembre 2025 | B28: =SUMIFS(Détail!$E:$E,Détail!$D:$D,"E.LECLERC",Détail!$A:$A,">="&DATE(2025,12,1),Détail!$A:$A,"<"&EDATE(DATE(2025,12,1),1)) -> 0
A31: Nespresso | C31: =SUMIF(Détail!$D:$D,"NESPRESSO",Détail!$E:$E) -> -166
A32: Mois | B32: Montant
A33: Janvier 2025 | B33: =SUMIFS(Détail!$E:$E,Détail!$D:$D,"NESPRESSO",Détail!$A:$A,">="&DATE(2025,1,1),Détail!$A:$A,"<"&EDATE(DATE(2025,1,1),1)) -> 0
A34: Février 2025 | B34: =SUMIFS(Détail!$E:$E,Détail!$D:$D,"NESPRESSO",Détail!$A:$A,">="&DATE(2025,2,1),Détail!$A:$A,"<"&EDATE(DATE(2025,2,1),1)) -> 0
A35: Mars 2025 | B35: =SUMIFS(Détail!$E:$E,Détail!$D:$D,"NESPRESSO",Détail!$A:$A,">="&DATE(2025,3,1),Détail!$A:$A,"<"&EDATE(DATE(2025,3,1),1)) -> -166
A36: Avril 2025 | B36: =SUMIFS(Détail!$E:$E,Détail!$D:$D,"NESPRESSO",Détail!$A:$A,">="&DATE(2025,4,1),Détail!$A:$A,"<"&EDATE(DATE(2025,4,1),1)) -> 0
A37: Mai 2025 | B37: =SUMIFS(Détail!$E:$E,Détail!$D:$D,"NESPRESSO",Détail!$A:$A,">="&DATE(2025,5,1),Détail!$A:$A,"<"&EDATE(DATE(2025,5,1),1)) -> 0
A38: Juin 2025 | B38: =SUMIFS(Détail!$E:$E,Détail!$D:$D,"NESPRESSO",Détail!$A:$A,">="&DATE(2025,6,1),Détail!$A:$A,"<"&EDATE(DATE(2025,6,1),1)) -> 0
A39: Juillet 2025 | B39: =SUMIFS(Détail!$E:$E,Détail!$D:$D,"NESPRESSO",Détail!$A:$A,">="&DATE(2025,7,1),Détail!$A:$A,"<"&EDATE(DATE(2025,7,1),1)) -> 0
A40: Septembre 2025 | B40: =SUMIFS(Détail!$E:$E,Détail!$D:$D,"NESPRESSO",Détail!$A:$A,">="&DATE(2025,9,1),Détail!$A:$A,"<"&EDATE(DATE(2025,9,1),1)) -> 0
A41: Octobre 2025 | B41: =SUMIFS(Détail!$E:$E,Détail!$D:$D,"NESPRESSO",Détail!$A:$A,">="&DATE(2025,10,1),Détail!$A:$A,"<"&EDATE(DATE(2025,10,1),1)) -> 0
A42: Décembre 2025 | B42: =SUMIFS(Détail!$E:$E,Détail!$D:$D,"NESPRESSO",Détail!$A:$A,">="&DATE(2025,12,1),Détail!$A:$A,"<"&EDATE(DATE(2025,12,1),1)) -> 0
A45: Carrefour | C45: =SUMIF(Détail!$D:$D,"CARREFOUR",Détail!$E:$E) -> -152.69
A46: Mois | B46: Montant
A47: Janvier 2025 | B47: =SUMIFS(Détail!$E:$E,Détail!$D:$D,"CARREFOUR",Détail!$A:$A,">="&DATE(2025,1,1),Détail!$A:$A,"<"&EDATE(DATE(2025,1,1),1)) -> 0
A48: Février 2025 | B48: =SUMIFS(Détail!$E:$E,Détail!$D:$D,"CARREFOUR",Détail!$A:$A,">="&DATE(2025,2,1),Détail!$A:$A,"<"&EDATE(DATE(2025,2,1),1)) -> -61.49
A49: Mars 2025 | B49: =SUMIFS(Détail!$E:$E,Détail!$D:$D,"CARREFOUR",Détail!$A:$A,">="&DATE(2025,3,1),Détail!$A:$A,"<"&EDATE(DATE(2025,3,1),1)) -> 0
A50: Avril 2025 | B50: =SUMIFS(Détail!$E:$E,Détail!$D:$D,"CARREFOUR",Détail!$A:$A,">="&DATE(2025,4,1),Détail!$A:$A,"<"&EDATE(DATE(2025,4,1),1)) -> 0
A51: Mai 2025 | B51: =SUMIFS(Détail!$E:$E,Détail!$D:$D,"CARREFOUR",Détail!$A:$A,">="&DATE(2025,5,1),Détail!$A:$A,"<"&EDATE(DATE(2025,5,1),1)) -> 0
A52: Juin 2025 | B52: =SUMIFS(Détail!$E:$E,Détail!$D:$D,"CARREFOUR",Détail!$A:$A,">="&DATE(2025,6,1),Détail!$A:$A,"<"&EDATE(DATE(2025,6,1),1)) -> 0
A53: Juillet 2025 | B53: =SUMIFS(Détail!$E:$E,Détail!$D:$D,"CARREFOUR",Détail!$A:$A,">="&DATE(2025,7,1),Détail!$A:$A,"<"&EDATE(DATE(2025,7,1),1)) -> 0
A54: Septembre 2025 | B54: =SUMIFS(Détail!$E:$E,Détail!$D:$D,"CARREFOUR",Détail!$A:$A,">="&DATE(2025,9,1),Détail!$A:$A,"<"&EDATE(DATE(2025,9,1),1)) -> 0
A55: Octobre 2025 | B55: =SUMIFS(Détail!$E:$E,Détail!$D:$D,"CARREFOUR",Détail!$A:$A,">="&DATE(2025,10,1),Détail!$A:$A,"<"&EDATE(DATE(2025,10,1),1)) -> -91.2
A56: Décembre 2025 | B56: =SUMIFS(Détail!$E:$E,Détail!$D:$D,"CARREFOUR",Détail!$A:$A,">="&DATE(2025,12,1),Détail!$A:$A,"<"&EDATE(DATE(2025,12,1),1)) -> 0
A59: Freshmart | C59: =SUMIF(Détail!$D:$D,"FRESHMART",Détail!$E:$E) -> -88.72
A60: Mois | B60: Montant
A61: Janvier 2025 | B61: =SUMIFS(Détail!$E:$E,Détail!$D:$D,"FRESHMART",Détail!$A:$A,">="&DATE(2025,1,1),Détail!$A:$A,"<"&EDATE(DATE(2025,1,1),1)) -> 0
A62: Février 2025 | B62: =SUMIFS(Détail!$E:$E,Détail!$D:$D,"FRESHMART",Détail!$A:$A,">="&DATE(2025,2,1),Détail!$A:$A,"<"&EDATE(DATE(2025,2,1),1)) -> 0
A63: Mars 2025 | B63: =SUMIFS(Détail!$E:$E,Détail!$D:$D,"FRESHMART",Détail!$A:$A,">="&DATE(2025,3,1),Détail!$A:$A,"<"&EDATE(DATE(2025,3,1),1)) -> 0
A64: Avril 2025 | B64: =SUMIFS(Détail!$E:$E,Détail!$D:$D,"FRESHMART",Détail!$A:$A,">="&DATE(2025,4,1),Détail!$A:$A,"<"&EDATE(DATE(2025,4,1),1)) -> 0
A65: Mai 2025 | B65: =SUMIFS(Détail!$E:$E,Détail!$D:$D,"FRESHMART",Détail!$A:$A,">="&DATE(2025,5,1),Détail!$A:$A,"<"&EDATE(DATE(2025,5,1),1)) -> 0
A66: Juin 2025 | B66: =SUMIFS(Détail!$E:$E,Détail!$D:$D,"FRESHMART",Détail!$A:$A,">="&DATE(2025,6,1),Détail!$A:$A,"<"&EDATE(DATE(2025,6,1),1)) -> 0
A67: Juillet 2025 | B67: =SUMIFS(Détail!$E:$E,Détail!$D:$D,"FRESHMART",Détail!$A:$A,">="&DATE(2025,7,1),Détail!$A:$A,"<"&EDATE(DATE(2025,7,1),1)) -> 0
A68: Septembre 2025 | B68: =SUMIFS(Détail!$E:$E,Détail!$D:$D,"FRESHMART",Détail!$A:$A,">="&DATE(2025,9,1),Détail!$A:$A,"<"&EDATE(DATE(2025,9,1),1)) -> 0
A69: Octobre 2025 | B69: =SUMIFS(Détail!$E:$E,Détail!$D:$D,"FRESHMART",Détail!$A:$A,">="&DATE(2025,10,1),Détail!$A:$A,"<"&EDATE(DATE(2025,10,1),1)) -> -88.72
A70: Décembre 2025 | B70: =SUMIFS(Détail!$E:$E,Détail!$D:$D,"FRESHMART",Détail!$A:$A,">="&DATE(2025,12,1),Détail!$A:$A,"<"&EDATE(DATE(2025,12,1),1)) -> 0
A73: Maxicoffee Gc | C73: =SUMIF(Détail!$D:$D,"MAXICOFFEE GC",Détail!$E:$E) -> -11.1
A74: Mois | B74: Montant
A75: Janvier 2025 | B75: =SUMIFS(Détail!$E:$E,Détail!$D:$D,"MAXICOFFEE GC",Détail!$A:$A,">="&DATE(2025,1,1),Détail!$A:$A,"<"&EDATE(DATE(2025,1,1),1)) -> 0
A76: Février 2025 | B76: =SUMIFS(Détail!$E:$E,Détail!$D:$D,"MAXICOFFEE GC",Détail!$A:$A,">="&DATE(2025,2,1),Détail!$A:$A,"<"&EDATE(DATE(2025,2,1),1)) -> 0
A77: Mars 2025 | B77: =SUMIFS(Détail!$E:$E,Détail!$D:$D,"MAXICOFFEE GC",Détail!$A:$A,">="&DATE(2025,3,1),Détail!$A:$A,"<"&EDATE(DATE(2025,3,1),1)) -> 0
A78: Avril 2025 | B78: =SUMIFS(Détail!$E:$E,Détail!$D:$D,"MAXICOFFEE GC",Détail!$A:$A,">="&DATE(2025,4,1),Détail!$A:$A,"<"&EDATE(DATE(2025,4,1),1)) -> 0
A79: Mai 2025 | B79: =SUMIFS(Détail!$E:$E,Détail!$D:$D,"MAXICOFFEE GC",Détail!$A:$A,">="&DATE(2025,5,1),Détail!$A:$A,"<"&EDATE(DATE(2025,5,1),1)) -> 0
A80: Juin 2025 | B80: =SUMIFS(Détail!$E:$E,Détail!$D:$D,"MAXICOFFEE GC",Détail!$A:$A,">="&DATE(2025,6,1),Détail!$A:$A,"<"&EDATE(DATE(2025,6,1),1)) -> 0
A81: Juillet 2025 | B81: =SUMIFS(Détail!$E:$E,Détail!$D:$D,"MAXICOFFEE GC",Détail!$A:$A,">="&DATE(2025,7,1),Détail!$A:$A,"<"&EDATE(DATE(2025,7,1),1)) -> -8
A82: Septembre 2025 | B82: =SUMIFS(Détail!$E:$E,Détail!$D:$D,"MAXICOFFEE GC",Détail!$A:$A,">="&DATE(2025,9,1),Détail!$A:$A,"<"&EDATE(DATE(2025,9,1),1)) -> 0
A83: Octobre 2025 | B83: =SUMIFS(Détail!$E:$E,Détail!$D:$D,"MAXICOFFEE GC",Détail!$A:$A,">="&DATE(2025,10,1),Détail!$A:$A,"<"&EDATE(DATE(2025,10,1),1)) -> 0
A84: Décembre 2025 | B84: =SUMIFS(Détail!$E:$E,Détail!$D:$D,"MAXICOFFEE GC",Détail!$A:$A,">="&DATE(2025,12,1),Détail!$A:$A,"<"&EDATE(DATE(2025,12,1),1)) -> -3.1
A87: Intermarche Cha | C87: =SUMIF(Détail!$D:$D,"INTERMARCHE CHA",Détail!$E:$E) -> -11.06
A88: Mois | B88: Montant
A89: Janvier 2025 | B89: =SUMIFS(Détail!$E:$E,Détail!$D:$D,"INTERMARCHE CHA",Détail!$A:$A,">="&DATE(2025,1,1),Détail!$A:$A,"<"&EDATE(DATE(2025,1,1),1)) -> 0
A90: Février 2025 | B90: =SUMIFS(Détail!$E:$E,Détail!$D:$D,"INTERMARCHE CHA",Détail!$A:$A,">="&DATE(2025,2,1),Détail!$A:$A,"<"&EDATE(DATE(2025,2,1),1)) -> -11.06
A91: Mars 2025 | B91: =SUMIFS(Détail!$E:$E,Détail!$D:$D,"INTERMARCHE CHA",Détail!$A:$A,">="&DATE(2025,3,1),Détail!$A:$A,"<"&EDATE(DATE(2025,3,1),1)) -> 0
A92: Avril 2025 | B92: =SUMIFS(Détail!$E:$E,Détail!$D:$D,"INTERMARCHE CHA",Détail!$A:$A,">="&DATE(2025,4,1),Détail!$A:$A,"<"&EDATE(DATE(2025,4,1),1)) -> 0
A93: Mai 2025 | B93: =SUMIFS(Détail!$E:$E,Détail!$D:$D,"INTERMARCHE CHA",Détail!$A:$A,">="&DATE(2025,5,1),Détail!$A:$A,"<"&EDATE(DATE(2025,5,1),1)) -> 0
A94: Juin 2025 | B94: =SUMIFS(Détail!$E:$E,Détail!$D:$D,"INTERMARCHE CHA",Détail!$A:$A,">="&DATE(2025,6,1),Détail!$A:$A,"<"&EDATE(DATE(2025,6,1),1)) -> 0
A95: Juillet 2025 | B95: =SUMIFS(Détail!$E:$E,Détail!$D:$D,"INTERMARCHE CHA",Détail!$A:$A,">="&DATE(2025,7,1),Détail!$A:$A,"<"&EDATE(DATE(2025,7,1),1)) -> 0
A96: Septembre 2025 | B96: =SUMIFS(Détail!$E:$E,Détail!$D:$D,"INTERMARCHE CHA",Détail!$A:$A,">="&DATE(2025,9,1),Détail!$A:$A,"<"&EDATE(DATE(2025,9,1),1)) -> 0
A97: Octobre 2025 | B97: =SUMIFS(Détail!$E:$E,Détail!$D:$D,"INTERMARCHE CHA",Détail!$A:$A,">="&DATE(2025,10,1),Détail!$A:$A,"<"&EDATE(DATE(2025,10,1),1)) -> 0
A98: Décembre 2025 | B98: =SUMIFS(Détail!$E:$E,Détail!$D:$D,"INTERMARCHE CHA",Détail!$A:$A,">="&DATE(2025,12,1),Détail!$A:$A,"<"&EDATE(DATE(2025,12,1),1)) -> 0
A101: Epi D Or | C101: =SUMIF(Détail!$D:$D,"EPI D OR",Détail!$E:$E) -> -6.3
A102: Mois | B102: Montant
A103: Janvier 2025 | B103: =SUMIFS(Détail!$E:$E,Détail!$D:$D,"EPI D OR",Détail!$A:$A,">="&DATE(2025,1,1),Détail!$A:$A,"<"&EDATE(DATE(2025,1,1),1)) -> 0
A104: Février 2025 | B104: =SUMIFS(Détail!$E:$E,Détail!$D:$D,"EPI D OR",Détail!$A:$A,">="&DATE(2025,2,1),Détail!$A:$A,"<"&EDATE(DATE(2025,2,1),1)) -> 0
A105: Mars 2025 | B105: =SUMIFS(Détail!$E:$E,Détail!$D:$D,"EPI D OR",Détail!$A:$A,">="&DATE(2025,3,1),Détail!$A:$A,"<"&EDATE(DATE(2025,3,1),1)) -> 0
A106: Avril 2025 | B106: =SUMIFS(Détail!$E:$E,Détail!$D:$D,"EPI D OR",Détail!$A:$A,">="&DATE(2025,4,1),Détail!$A:$A,"<"&EDATE(DATE(2025,4,1),1)) -> 0
A107: Mai 2025 | B107: =SUMIFS(Détail!$E:$E,Détail!$D:$D,"EPI D OR",Détail!$A:$A,">="&DATE(2025,5,1),Détail!$A:$A,"<"&EDATE(DATE(2025,5,1),1)) -> 0
A108: Juin 2025 | B108: =SUMIFS(Détail!$E:$E,Détail!$D:$D,"EPI D OR",Détail!$A:$A,">="&DATE(2025,6,1),Détail!$A:$A,"<"&EDATE(DATE(2025,6,1),1)) -> 0
A109: Juillet 2025 | B109: =SUMIFS(Détail!$E:$E,Détail!$D:$D,"EPI D OR",Détail!$A:$A,">="&DATE(2025,7,1),Détail!$A:$A,"<"&EDATE(DATE(2025,7,1),1)) -> 0
A110: Septembre 2025 | B110: =SUMIFS(Détail!$E:$E,Détail!$D:$D,"EPI D OR",Détail!$A:$A,">="&DATE(2025,9,1),Détail!$A:$A,"<"&EDATE(DATE(2025,9,1),1)) -> -6.3
A111: Octobre 2025 | B111: =SUMIFS(Détail!$E:$E,Détail!$D:$D,"EPI D OR",Détail!$A:$A,">="&DATE(2025,10,1),Détail!$A:$A,"<"&EDATE(DATE(2025,10,1),1)) -> 0
A112: Décembre 2025 | B112: =SUMIFS(Détail!$E:$E,Détail!$D:$D,"EPI D OR",Détail!$A:$A,">="&DATE(2025,12,1),Détail!$A:$A,"<"&EDATE(DATE(2025,12,1),1)) -> 0
A115: A G K Refreshme | C115: =SUMIF(Détail!$D:$D,"A G K REFRESHME",Détail!$E:$E) -> -6.46
A116: Mois | B116: Montant
A117: Janvier 2025 | B117: =SUMIFS(Détail!$E:$E,Détail!$D:$D,"A G K REFRESHME",Détail!$A:$A,">="&DATE(2025,1,1),Détail!$A:$A,"<"&EDATE(DATE(2025,1,1),1)) -> 0
...

Sheet Assurances détail
A1: Assurances — détail (2025)
A3: Swisslife Assurance De Biens | C3: =SUMIF(Détail!$D:$D,"SWISSLIFE ASSURANCE DE BIENS",Détail!$E:$E) -> -870.32
A4: Mois | B4: Montant
A5: Janvier 2025 | B5: =SUMIFS(Détail!$E:$E,Détail!$D:$D,"SWISSLIFE ASSURANCE DE BIENS",Détail!$A:$A,">="&DATE(2025,1,1),Détail!$A:$A,"<"&EDATE(DATE(2025,1,1),1)) -> -67.36
A6: Février 2025 | B6: =SUMIFS(Détail!$E:$E,Détail!$D:$D,"SWISSLIFE ASSURANCE DE BIENS",Détail!$A:$A,">="&DATE(2025,2,1),Détail!$A:$A,"<"&EDATE(DATE(2025,2,1),1)) -> -67.36
A7: Mars 2025 | B7: =SUMIFS(Détail!$E:$E,Détail!$D:$D,"SWISSLIFE ASSURANCE DE BIENS",Détail!$A:$A,">="&DATE(2025,3,1),Détail!$A:$A,"<"&EDATE(DATE(2025,3,1),1)) -> -67.36
A8: Avril 2025 | B8: =SUMIFS(Détail!$E:$E,Détail!$D:$D,"SWISSLIFE ASSURANCE DE BIENS",Détail!$A:$A,">="&DATE(2025,4,1),Détail!$A:$A,"<"&EDATE(DATE(2025,4,1),1)) -> -67.36
A9: Mai 2025 | B9: =SUMIFS(Détail!$E:$E,Détail!$D:$D,"SWISSLIFE ASSURANCE DE BIENS",Détail!$A:$A,">="&DATE(2025,5,1),Détail!$A:$A,"<"&EDATE(DATE(2025,5,1),1)) -> -67.36
A10: Juin 2025 | B10: =SUMIFS(Détail!$E:$E,Détail!$D:$D,"SWISSLIFE ASSURANCE DE BIENS",Détail!$A:$A,">="&DATE(2025,6,1),Détail!$A:$A,"<"&EDATE(DATE(2025,6,1),1)) -> -67.36
A11: Juillet 2025 | B11: =SUMIFS(Détail!$E:$E,Détail!$D:$D,"SWISSLIFE ASSURANCE DE BIENS",Détail!$A:$A,">="&DATE(2025,7,1),Détail!$A:$A,"<"&EDATE(DATE(2025,7,1),1)) -> -67.36
A12: Août 2025 | B12: =SUMIFS(Détail!$E:$E,Détail!$D:$D,"SWISSLIFE ASSURANCE DE BIENS",Détail!$A:$A,">="&DATE(2025,8,1),Détail!$A:$A,"<"&EDATE(DATE(2025,8,1),1)) -> -84.96
A13: Septembre 2025 | B13: =SUMIFS(Détail!$E:$E,Détail!$D:$D,"SWISSLIFE ASSURANCE DE BIENS",Détail!$A:$A,">="&DATE(2025,9,1),Détail!$A:$A,"<"&EDATE(DATE(2025,9,1),1)) -> -78.46
A14: Octobre 2025 | B14: =SUMIFS(Détail!$E:$E,Détail!$D:$D,"SWISSLIFE ASSURANCE DE BIENS",Détail!$A:$A,">="&DATE(2025,10,1),Détail!$A:$A,"<"&EDATE(DATE(2025,10,1),1)) -> -78.46
A15: Novembre 2025 | B15: =SUMIFS(Détail!$E:$E,Détail!$D:$D,"SWISSLIFE ASSURANCE DE BIENS",Détail!$A:$A,">="&DATE(2025,11,1),Détail!$A:$A,"<"&EDATE(DATE(2025,11,1),1)) -> -78.46
A16: Décembre 2025 | B16: =SUMIFS(Détail!$E:$E,Détail!$D:$D,"SWISSLIFE ASSURANCE DE BIENS",Détail!$A:$A,">="&DATE(2025,12,1),Détail!$A:$A,"<"&EDATE(DATE(2025,12,1),1)) -> -78.46

Sheet Restauration détail
A1: Restauration — détail par enseigne (2025)
A3: Fomo Star Cafe | C3: =SUMIF(Détail!$D:$D,"FOMO STAR CAFE",Détail!$E:$E) -> -176.1
A4: Mois | B4: Montant
A5: Janvier 2025 | B5: =SUMIFS(Détail!$E:$E,Détail!$D:$D,"FOMO STAR CAFE",Détail!$A:$A,">="&DATE(2025,1,1),Détail!$A:$A,"<"&EDATE(DATE(2025,1,1),1)) -> 0
A6: Février 2025 | B6: =SUMIFS(Détail!$E:$E,Détail!$D:$D,"FOMO STAR CAFE",Détail!$A:$A,">="&DATE(2025,2,1),Détail!$A:$A,"<"&EDATE(DATE(2025,2,1),1)) -> 0
A7: Mai 2025 | B7: =SUMIFS(Détail!$E:$E,Détail!$D:$D,"FOMO STAR CAFE",Détail!$A:$A,">="&DATE(2025,5,1),Détail!$A:$A,"<"&EDATE(DATE(2025,5,1),1)) -> 0
A8: Juin 2025 | B8: =SUMIFS(Détail!$E:$E,Détail!$D:$D,"FOMO STAR CAFE",Détail!$A:$A,">="&DATE(2025,6,1),Détail!$A:$A,"<"&EDATE(DATE(2025,6,1),1)) -> 0
A9: Juillet 2025 | B9: =SUMIFS(Détail!$E:$E,Détail!$D:$D,"FOMO STAR CAFE",Détail!$A:$A,">="&DATE(2025,7,1),Détail!$A:$A,"<"&EDATE(DATE(2025,7,1),1)) -> 0
A10: Août 2025 | B10: =SUMIFS(Détail!$E:$E,Détail!$D:$D,"FOMO STAR CAFE",Détail!$A:$A,">="&DATE(2025,8,1),Détail!$A:$A,"<"&EDATE(DATE(2025,8,1),1)) -> 0
A11: Septembre 2025 | B11: =SUMIFS(Détail!$E:$E,Détail!$D:$D,"FOMO STAR CAFE",Détail!$A:$A,">="&DATE(2025,9,1),Détail!$A:$A,"<"&EDATE(DATE(2025,9,1),1)) -> 0
A12: Octobre 2025 | B12: =SUMIFS(Détail!$E:$E,Détail!$D:$D,"FOMO STAR CAFE",Détail!$A:$A,">="&DATE(2025,10,1),Détail!$A:$A,"<"&EDATE(DATE(2025,10,1),1)) -> -176.1
A13: Novembre 2025 | B13: =SUMIFS(Détail!$E:$E,Détail!$D:$D,"FOMO STAR CAFE",Détail!$A:$A,">="&DATE(2025,11,1),Détail!$A:$A,"<"&EDATE(DATE(2025,11,1),1)) -> 0
A16: Azure Restauran | C16: =SUMIF(Détail!$D:$D,"AZURE RESTAURAN",Détail!$E:$E) -> -174.28
A17: Mois | B17: Montant
A18: Janvier 2025 | B18: =SUMIFS(Détail!$E:$E,Détail!$D:$D,"AZURE RESTAURAN",Détail!$A:$A,">="&DATE(2025,1,1),Détail!$A:$A,"<"&EDATE(DATE(2025,1,1),1)) -> 0
A19: Février 2025 | B19: =SUMIFS(Détail!$E:$E,Détail!$D:$D,"AZURE RESTAURAN",Détail!$A:$A,">="&DATE(2025,2,1),Détail!$A:$A,"<"&EDATE(DATE(2025,2,1),1)) -> 0
A20: Mai 2025 | B20: =SUMIFS(Détail!$E:$E,Détail!$D:$D,"AZURE RESTAURAN",Détail!$A:$A,">="&DATE(2025,5,1),Détail!$A:$A,"<"&EDATE(DATE(2025,5,1),1)) -> 0
A21: Juin 2025 | B21: =SUMIFS(Détail!$E:$E,Détail!$D:$D,"AZURE RESTAURAN",Détail!$A:$A,">="&DATE(2025,6,1),Détail!$A:$A,"<"&EDATE(DATE(2025,6,1),1)) -> 0
A22: Juillet 2025 | B22: =SUMIFS(Détail!$E:$E,Détail!$D:$D,"AZURE RESTAURAN",Détail!$A:$A,">="&DATE(2025,7,1),Détail!$A:$A,"<"&EDATE(DATE(2025,7,1),1)) -> 0
A23: Août 2025 | B23: =SUMIFS(Détail!$E:$E,Détail!$D:$D,"AZURE RESTAURAN",Détail!$A:$A,">="&DATE(2025,8,1),Détail!$A:$A,"<"&EDATE(DATE(2025,8,1),1)) -> 0
A24: Septembre 2025 | B24: =SUMIFS(Détail!$E:$E,Détail!$D:$D,"AZURE RESTAURAN",Détail!$A:$A,">="&DATE(2025,9,1),Détail!$A:$A,"<"&EDATE(DATE(2025,9,1),1)) -> 0
A25: Octobre 2025 | B25: =SUMIFS(Détail!$E:$E,Détail!$D:$D,"AZURE RESTAURAN",Détail!$A:$A,">="&DATE(2025,10,1),Détail!$A:$A,"<"&EDATE(DATE(2025,10,1),1)) -> 0
A26: Novembre 2025 | B26: =SUMIFS(Détail!$E:$E,Détail!$D:$D,"AZURE RESTAURAN",Détail!$A:$A,">="&DATE(2025,11,1),Détail!$A:$A,"<"&EDATE(DATE(2025,11,1),1)) -> -174.28
A29: Iloli Restauran | C29: =SUMIF(Détail!$D:$D,"ILOLI RESTAURAN",Détail!$E:$E) -> -148.37
A30: Mois | B30: Montant
A31: Janvier 2025 | B31: =SUMIFS(Détail!$E:$E,Détail!$D:$D,"ILOLI RESTAURAN",Détail!$A:$A,">="&DATE(2025,1,1),Détail!$A:$A,"<"&EDATE(DATE(2025,1,1),1)) -> 0
A32: Février 2025 | B32: =SUMIFS(Détail!$E:$E,Détail!$D:$D,"ILOLI RESTAURAN",Détail!$A:$A,">="&DATE(2025,2,1),Détail!$A:$A,"<"&EDATE(DATE(2025,2,1),1)) -> 0
A33: Mai 2025 | B33: =SUMIFS(Détail!$E:$E,Détail!$D:$D,"ILOLI RESTAURAN",Détail!$A:$A,">="&DATE(2025,5,1),Détail!$A:$A,"<"&EDATE(DATE(2025,5,1),1)) -> 0
A34: Juin 2025 | B34: =SUMIFS(Détail!$E:$E,Détail!$D:$D,"ILOLI RESTAURAN",Détail!$A:$A,">="&DATE(2025,6,1),Détail!$A:$A,"<"&EDATE(DATE(2025,6,1),1)) -> 0
A35: Juillet 2025 | B35: =SUMIFS(Détail!$E:$E,Détail!$D:$D,"ILOLI RESTAURAN",Détail!$A:$A,">="&DATE(2025,7,1),Détail!$A:$A,"<"&EDATE(DATE(2025,7,1),1)) -> 0
A36: Août 2025 | B36: =SUMIFS(Détail!$E:$E,Détail!$D:$D,"ILOLI RESTAURAN",Détail!$A:$A,">="&DATE(2025,8,1),Détail!$A:$A,"<"&EDATE(DATE(2025,8,1),1)) -> 0
A37: Septembre 2025 | B37: =SUMIFS(Détail!$E:$E,Détail!$D:$D,"ILOLI RESTAURAN",Détail!$A:$A,">="&DATE(2025,9,1),Détail!$A:$A,"<"&EDATE(DATE(2025,9,1),1)) -> 0
A38: Octobre 2025 | B38: =SUMIFS(Détail!$E:$E,Détail!$D:$D,"ILOLI RESTAURAN",Détail!$A:$A,">="&DATE(2025,10,1),Détail!$A:$A,"<"&EDATE(DATE(2025,10,1),1)) -> -148.37
A39: Novembre 2025 | B39: =SUMIFS(Détail!$E:$E,Détail!$D:$D,"ILOLI RESTAURAN",Détail!$A:$A,">="&DATE(2025,11,1),Détail!$A:$A,"<"&EDATE(DATE(2025,11,1),1)) -> 0
A42: Tribes Carnivor | C42: =SUMIF(Détail!$D:$D,"TRIBES CARNIVOR",Détail!$E:$E) -> -145.2
A43: Mois | B43: Montant
A44: Janvier 2025 | B44: =SUMIFS(Détail!$E:$E,Détail!$D:$D,"TRIBES CARNIVOR",Détail!$A:$A,">="&DATE(2025,1,1),Détail!$A:$A,"<"&EDATE(DATE(2025,1,1),1)) -> 0
A45: Février 2025 | B45: =SUMIFS(Détail!$E:$E,Détail!$D:$D,"TRIBES CARNIVOR",Détail!$A:$A,">="&DATE(2025,2,1),Détail!$A:$A,"<"&EDATE(DATE(2025,2,1),1)) -> 0
A46: Mai 2025 | B46: =SUMIFS(Détail!$E:$E,Détail!$D:$D,"TRIBES CARNIVOR",Détail!$A:$A,">="&DATE(2025,5,1),Détail!$A:$A,"<"&EDATE(DATE(2025,5,1),1)) -> 0
A47: Juin 2025 | B47: =SUMIFS(Détail!$E:$E,Détail!$D:$D,"TRIBES CARNIVOR",Détail!$A:$A,">="&DATE(2025,6,1),Détail!$A:$A,"<"&EDATE(DATE(2025,6,1),1)) -> 0
A48: Juillet 2025 | B48: =SUMIFS(Détail!$E:$E,Détail!$D:$D,"TRIBES CARNIVOR",Détail!$A:$A,">="&DATE(2025,7,1),Détail!$A:$A,"<"&EDATE(DATE(2025,7,1),1)) -> 0
A49: Août 2025 | B49: =SUMIFS(Détail!$E:$E,Détail!$D:$D,"TRIBES CARNIVOR",Détail!$A:$A,">="&DATE(2025,8,1),Détail!$A:$A,"<"&EDATE(DATE(2025,8,1),1)) -> 0
A50: Septembre 2025 | B50: =SUMIFS(Détail!$E:$E,Détail!$D:$D,"TRIBES CARNIVOR",Détail!$A:$A,">="&DATE(2025,9,1),Détail!$A:$A,"<"&EDATE(DATE(2025,9,1),1)) -> 0
A51: Octobre 2025 | B51: =SUMIFS(Détail!$E:$E,Détail!$D:$D,"TRIBES CARNIVOR",Détail!$A:$A,">="&DATE(2025,10,1),Détail!$A:$A,"<"&EDATE(DATE(2025,10,1),1)) -> -145.2
A52: Novembre 2025 | B52: =SUMIFS(Détail!$E:$E,Détail!$D:$D,"TRIBES CARNIVOR",Détail!$A:$A,">="&DATE(2025,11,1),Détail!$A:$A,"<"&EDATE(DATE(2025,11,1),1)) -> 0
A55: Mcdonald'S | C55: =SUMIF(Détail!$D:$D,"MCDONALD'S",Détail!$E:$E) -> -132.16
A56: Mois | B56: Montant
A57: Janvier 2025 | B57: =SUMIFS(Détail!$E:$E,Détail!$D:$D,"MCDONALD'S",Détail!$A:$A,">="&DATE(2025,1,1),Détail!$A:$A,"<"&EDATE(DATE(2025,1,1),1)) -> -25.8
A58: Février 2025 | B58: =SUMIFS(Détail!$E:$E,Détail!$D:$D,"MCDONALD'S",Détail!$A:$A,">="&DATE(2025,2,1),Détail!$A:$A,"<"&EDATE(DATE(2025,2,1),1)) -> -35.6
A59: Mai 2025 | B59: =SUMIFS(Détail!$E:$E,Détail!$D:$D,"MCDONALD'S",Détail!$A:$A,">="&DATE(2025,5,1),Détail!$A:$A,"<"&EDATE(DATE(2025,5,1),1)) -> 0
A60: Juin 2025 | B60: =SUMIFS(Détail!$E:$E,Détail!$D:$D,"MCDONALD'S",Détail!$A:$A,">="&DATE(2025,6,1),Détail!$A:$A,"<"&EDATE(DATE(2025,6,1),1)) -> 0
A61: Juillet 2025 | B61: =SUMIFS(Détail!$E:$E,Détail!$D:$D,"MCDONALD'S",Détail!$A:$A,">="&DATE(2025,7,1),Détail!$A:$A,"<"&EDATE(DATE(2025,7,1),1)) -> 0
A62: Août 2025 | B62: =SUMIFS(Détail!$E:$E,Détail!$D:$D,"MCDONALD'S",Détail!$A:$A,">="&DATE(2025,8,1),Détail!$A:$A,"<"&EDATE(DATE(2025,8,1),1)) -> 0
A63: Septembre 2025 | B63: =SUMIFS(Détail!$E:$E,Détail!$D:$D,"MCDONALD'S",Détail!$A:$A,">="&DATE(2025,9,1),Détail!$A:$A,"<"&EDATE(DATE(2025,9,1),1)) -> 0
A64: Octobre 2025 | B64: =SUMIFS(Détail!$E:$E,Détail!$D:$D,"MCDONALD'S",Détail!$A:$A,">="&DATE(2025,10,1),Détail!$A:$A,"<"&EDATE(DATE(2025,10,1),1)) -> -70.76
A65: Novembre 2025 | B65: =SUMIFS(Détail!$E:$E,Détail!$D:$D,"MCDONALD'S",Détail!$A:$A,">="&DATE(2025,11,1),Détail!$A:$A,"<"&EDATE(DATE(2025,11,1),1)) -> 0
A68: Deliveroo | C68: =SUMIF(Détail!$D:$D,"DELIVEROO",Détail!$E:$E) -> -110.92
A69: Mois | B69: Montant
A70: Janvier 2025 | B70: =SUMIFS(Détail!$E:$E,Détail!$D:$D,"DELIVEROO",Détail!$A:$A,">="&DATE(2025,1,1),Détail!$A:$A,"<"&EDATE(DATE(2025,1,1),1)) -> 0
A71: Février 2025 | B71: =SUMIFS(Détail!$E:$E,Détail!$D:$D,"DELIVEROO",Détail!$A:$A,">="&DATE(2025,2,1),Détail!$A:$A,"<"&EDATE(DATE(2025,2,1),1)) -> 0
A72: Mai 2025 | B72: =SUMIFS(Détail!$E:$E,Détail!$D:$D,"DELIVEROO",Détail!$A:$A,">="&DATE(2025,5,1),Détail!$A:$A,"<"&EDATE(DATE(2025,5,1),1)) -> 0
A73: Juin 2025 | B73: =SUMIFS(Détail!$E:$E,Détail!$D:$D,"DELIVEROO",Détail!$A:$A,">="&DATE(2025,6,1),Détail!$A:$A,"<"&EDATE(DATE(2025,6,1),1)) -> 0
A74: Juillet 2025 | B74: =SUMIFS(Détail!$E:$E,Détail!$D:$D,"DELIVEROO",Détail!$A:$A,">="&DATE(2025,7,1),Détail!$A:$A,"<"&EDATE(DATE(2025,7,1),1)) -> -22.57
A75: Août 2025 | B75: =SUMIFS(Détail!$E:$E,Détail!$D:$D,"DELIVEROO",Détail!$A:$A,">="&DATE(2025,8,1),Détail!$A:$A,"<"&EDATE(DATE(2025,8,1),1)) -> 0
A76: Septembre 2025 | B76: =SUMIFS(Détail!$E:$E,Détail!$D:$D,"DELIVEROO",Détail!$A:$A,">="&DATE(2025,9,1),Détail!$A:$A,"<"&EDATE(DATE(2025,9,1),1)) -> -88.35
A77: Octobre 2025 | B77: =SUMIFS(Détail!$E:$E,Détail!$D:$D,"DELIVEROO",Détail!$A:$A,">="&DATE(2025,10,1),Détail!$A:$A,"<"&EDATE(DATE(2025,10,1),1)) -> 0
A78: Novembre 2025 | B78: =SUMIFS(Détail!$E:$E,Détail!$D:$D,"DELIVEROO",Détail!$A:$A,">="&DATE(2025,11,1),Détail!$A:$A,"<"&EDATE(DATE(2025,11,1),1)) -> 0
A81: La Taverna | C81: =SUMIF(Détail!$D:$D,"LA TAVERNA",Détail!$E:$E) -> -105.5
A82: Mois | B82: Montant
A83: Janvier 2025 | B83: =SUMIFS(Détail!$E:$E,Détail!$D:$D,"LA TAVERNA",Détail!$A:$A,">="&DATE(2025,1,1),Détail!$A:$A,"<"&EDATE(DATE(2025,1,1),1)) -> -105.5
A84: Février 2025 | B84: =SUMIFS(Détail!$E:$E,Détail!$D:$D,"LA TAVERNA",Détail!$A:$A,">="&DATE(2025,2,1),Détail!$A:$A,"<"&EDATE(DATE(2025,2,1),1)) -> 0
A85: Mai 2025 | B85: =SUMIFS(Détail!$E:$E,Détail!$D:$D,"LA TAVERNA",Détail!$A:$A,">="&DATE(2025,5,1),Détail!$A:$A,"<"&EDATE(DATE(2025,5,1),1)) -> 0
A86: Juin 2025 | B86: =SUMIFS(Détail!$E:$E,Détail!$D:$D,"LA TAVERNA",Détail!$A:$A,">="&DATE(2025,6,1),Détail!$A:$A,"<"&EDATE(DATE(2025,6,1),1)) -> 0
A87: Juillet 2025 | B87: =SUMIFS(Détail!$E:$E,Détail!$D:$D,"LA TAVERNA",Détail!$A:$A,">="&DATE(2025,7,1),Détail!$A:$A,"<"&EDATE(DATE(2025,7,1),1)) -> 0
A88: Août 2025 | B88: =SUMIFS(Détail!$E:$E,Détail!$D:$D,"LA TAVERNA",Détail!$A:$A,">="&DATE(2025,8,1),Détail!$A:$A,"<"&EDATE(DATE(2025,8,1),1)) -> 0
A89: Septembre 2025 | B89: =SUMIFS(Détail!$E:$E,Détail!$D:$D,"LA TAVERNA",Détail!$A:$A,">="&DATE(2025,9,1),Détail!$A:$A,"<"&EDATE(DATE(2025,9,1),1)) -> 0
A90: Octobre 2025 | B90: =SUMIFS(Détail!$E:$E,Détail!$D:$D,"LA TAVERNA",Détail!$A:$A,">="&DATE(2025,10,1),Détail!$A:$A,"<"&EDATE(DATE(2025,10,1),1)) -> 0
A91: Novembre 2025 | B91: =SUMIFS(Détail!$E:$E,Détail!$D:$D,"LA TAVERNA",Détail!$A:$A,">="&DATE(2025,11,1),Détail!$A:$A,"<"&EDATE(DATE(2025,11,1),1)) -> 0
A94: Cafe De Paris R | C94: =SUMIF(Détail!$D:$D,"CAFE DE PARIS R",Détail!$E:$E) -> -104.7
A95: Mois | B95: Montant
A96: Janvier 2025 | B96: =SUMIFS(Détail!$E:$E,Détail!$D:$D,"CAFE DE PARIS R",Détail!$A:$A,">="&DATE(2025,1,1),Détail!$A:$A,"<"&EDATE(DATE(2025,1,1),1)) -> 0
A97: Février 2025 | B97: =SUMIFS(Détail!$E:$E,Détail!$D:$D,"CAFE DE PARIS R",Détail!$A:$A,">="&DATE(2025,2,1),Détail!$A:$A,"<"&EDATE(DATE(2025,2,1),1)) -> 0
A98: Mai 2025 | B98: =SUMIFS(Détail!$E:$E,Détail!$D:$D,"CAFE DE PARIS R",Détail!$A:$A,">="&DATE(2025,5,1),Détail!$A:$A,"<"&EDATE(DATE(2025,5,1),1)) -> 0
A99: Juin 2025 | B99: =SUMIFS(Détail!$E:$E,Détail!$D:$D,"CAFE DE PARIS R",Détail!$A:$A,">="&DATE(2025,6,1),Détail!$A:$A,"<"&EDATE(DATE(2025,6,1),1)) -> 0
A100: Juillet 2025 | B100: =SUMIFS(Détail!$E:$E,Détail!$D:$D,"CAFE DE PARIS R",Détail!$A:$A,">="&DATE(2025,7,1),Détail!$A:$A,"<"&EDATE(DATE(2025,7,1),1)) -> 0
A101: Août 2025 | B101: =SUMIFS(Détail!$E:$E,Détail!$D:$D,"CAFE DE PARIS R",Détail!$A:$A,">="&DATE(2025,8,1),Détail!$A:$A,"<"&EDATE(DATE(2025,8,1),1)) -> 0
A102: Septembre 2025 | B102: =SUMIFS(Détail!$E:$E,Détail!$D:$D,"CAFE DE PARIS R",Détail!$A:$A,">="&DATE(2025,9,1),Détail!$A:$A,"<"&EDATE(DATE(2025,9,1),1)) -> 0
A103: Octobre 2025 | B103: =SUMIFS(Détail!$E:$E,Détail!$D:$D,"CAFE DE PARIS R",Détail!$A:$A,">="&DATE(2025,10,1),Détail!$A:$A,"<"&EDATE(DATE(2025,10,1),1)) -> -104.7
A104: Novembre 2025 | B104: =SUMIFS(Détail!$E:$E,Détail!$D:$D,"CAFE DE PARIS R",Détail!$A:$A,">="&DATE(2025,11,1),Détail!$A:$A,"<"&EDATE(DATE(2025,11,1),1)) -> 0
A107: Yula Lounge | C107: =SUMIF(Détail!$D:$D,"YULA LOUNGE",Détail!$E:$E) -> -100.94
A108: Mois | B108: Montant
A109: Janvier 2025 | B109: =SUMIFS(Détail!$E:$E,Détail!$D:$D,"YULA LOUNGE",Détail!$A:$A,">="&DATE(2025,1,1),Détail!$A:$A,"<"&EDATE(DATE(2025,1,1),1)) -> 0
A110: Février 2025 | B110: =SUMIFS(Détail!$E:$E,Détail!$D:$D,"YULA LOUNGE",Détail!$A:$A,">="&DATE(2025,2,1),Détail!$A:$A,"<"&EDATE(DATE(2025,2,1),1)) -> 0
A111: Mai 2025 | B111: =SUMIFS(Détail!$E:$E,Détail!$D:$D,"YULA LOUNGE",Détail!$A:$A,">="&DATE(2025,5,1),Détail!$A:$A,"<"&EDATE(DATE(2025,5,1),1)) -> 0
A112: Juin 2025 | B112: =SUMIFS(Détail!$E:$E,Détail!$D:$D,"YULA LOUNGE",Détail!$A:$A,">="&DATE(2025,6,1),Détail!$A:$A,"<"&EDATE(DATE(2025,6,1),1)) -> 0
A113: Juillet 2025 | B113: =SUMIFS(Détail!$E:$E,Détail!$D:$D,"YULA LOUNGE",Détail!$A:$A,">="&DATE(2025,7,1),Détail!$A:$A,"<"&EDATE(DATE(2025,7,1),1)) -> 0
A114: Août 2025 | B114: =SUMIFS(Détail!$E:$E,Détail!$D:$D,"YULA LOUNGE",Détail!$A:$A,">="&DATE(2025,8,1),Détail!$A:$A,"<"&EDATE(DATE(2025,8,1),1)) -> 0
A115: Septembre 2025 | B115: =SUMIFS(Détail!$E:$E,Détail!$D:$D,"YULA LOUNGE",Détail!$A:$A,">="&DATE(2025,9,1),Détail!$A:$A,"<"&EDATE(DATE(2025,9,1),1)) -> 0
A116: Octobre 2025 | B116: =SUMIFS(Détail!$E:$E,Détail!$D:$D,"YULA LOUNGE",Détail!$A:$A,">="&DATE(2025,10,1),Détail!$A:$A,"<"&EDATE(DATE(2025,10,1),1)) -> -100.94
A117: Novembre 2025 | B117: =SUMIFS(Détail!$E:$E,Détail!$D:$D,"YULA LOUNGE",Détail!$A:$A,">="&DATE(2025,11,1),Détail!$A:$A,"<"&EDATE(DATE(2025,11,1),1)) -> 0
...

Sheet Carburant péages parking détail
A1: Carburant, péages, parking, leasing — détail par poste (2025)
A2: Regroupe carburant (par enseigne, France + étranger), péages, abonnements télépéage, parking et le crédit/leasing véhicule (VW Bank).
A4: Leasing / crédit véhicule (VW Bank) | C4: =SUMIF(Détail!$D:$D,"VW BANK FRANCE",Détail!$E:$E) -> -10472.04
A5: Mois | B5: Montant
A6: Janvier 2025 | B6: =SUMIFS(Détail!$E:$E,Détail!$D:$D,"VW BANK FRANCE",Détail!$A:$A,">="&DATE(2025,1,1),Détail!$A:$A,"<"&EDATE(DATE(2025,1,1),1)) -> -872.67
A7: Février 2025 | B7: =SUMIFS(Détail!$E:$E,Détail!$D:$D,"VW BANK FRANCE",Détail!$A:$A,">="&DATE(2025,2,1),Détail!$A:$A,"<"&EDATE(DATE(2025,2,1),1)) -> -872.67
A8: Mars 2025 | B8: =SUMIFS(Détail!$E:$E,Détail!$D:$D,"VW BANK FRANCE",Détail!$A:$A,">="&DATE(2025,3,1),Détail!$A:$A,"<"&EDATE(DATE(2025,3,1),1)) -> -872.67
A9: Avril 2025 | B9: =SUMIFS(Détail!$E:$E,Détail!$D:$D,"VW BANK FRANCE",Détail!$A:$A,">="&DATE(2025,4,1),Détail!$A:$A,"<"&EDATE(DATE(2025,4,1),1)) -> -872.67
A10: Mai 2025 | B10: =SUMIFS(Détail!$E:$E,Détail!$D:$D,"VW BANK FRANCE",Détail!$A:$A,">="&DATE(2025,5,1),Détail!$A:$A,"<"&EDATE(DATE(2025,5,1),1)) -> -872.67
A11: Juin 2025 | B11: =SUMIFS(Détail!$E:$E,Détail!$D:$D,"VW BANK FRANCE",Détail!$A:$A,">="&DATE(2025,6,1),Détail!$A:$A,"<"&EDATE(DATE(2025,6,1),1)) -> -872.67
A12: Juillet 2025 | B12: =SUMIFS(Détail!$E:$E,Détail!$D:$D,"VW BANK FRANCE",Détail!$A:$A,">="&DATE(2025,7,1),Détail!$A:$A,"<"&EDATE(DATE(2025,7,1),1)) -> -872.67
A13: Août 2025 | B13: =SUMIFS(Détail!$E:$E,Détail!$D:$D,"VW BANK FRANCE",Détail!$A:$A,">="&DATE(2025,8,1),Détail!$A:$A,"<"&EDATE(DATE(2025,8,1),1)) -> -872.67
A14: Septembre 2025 | B14: =SUMIFS(Détail!$E:$E,Détail!$D:$D,"VW BANK FRANCE",Détail!$A:$A,">="&DATE(2025,9,1),Détail!$A:$A,"<"&EDATE(DATE(2025,9,1),1)) -> -872.67
A15: Octobre 2025 | B15: =SUMIFS(Détail!$E:$E,Détail!$D:$D,"VW BANK FRANCE",Détail!$A:$A,">="&DATE(2025,10,1),Détail!$A:$A,"<"&EDATE(DATE(2025,10,1),1)) -> -872.67
A16: Novembre 2025 | B16: =SUMIFS(Détail!$E:$E,Détail!$D:$D,"VW BANK FRANCE",Détail!$A:$A,">="&DATE(2025,11,1),Détail!$A:$A,"<"&EDATE(DATE(2025,11,1),1)) -> -872.67
A17: Décembre 2025 | B17: =SUMIFS(Détail!$E:$E,Détail!$D:$D,"VW BANK FRANCE",Détail!$A:$A,">="&DATE(2025,12,1),Détail!$A:$A,"<"&EDATE(DATE(2025,12,1),1)) -> -872.67
A19: Carburant — Total | C19: =SUMIF(Détail!$D:$D,"TOTAL",Détail!$E:$E) -> -4043.49
A20: Mois | B20: Montant
A21: Janvier 2025 | B21: =SUMIFS(Détail!$E:$E,Détail!$D:$D,"TOTAL",Détail!$A:$A,">="&DATE(2025,1,1),Détail!$A:$A,"<"&EDATE(DATE(2025,1,1),1)) -> -343.16
A22: Février 2025 | B22: =SUMIFS(Détail!$E:$E,Détail!$D:$D,"TOTAL",Détail!$A:$A,">="&DATE(2025,2,1),Détail!$A:$A,"<"&EDATE(DATE(2025,2,1),1)) -> -282.01
A23: Mars 2025 | B23: =SUMIFS(Détail!$E:$E,Détail!$D:$D,"TOTAL",Détail!$A:$A,">="&DATE(2025,3,1),Détail!$A:$A,"<"&EDATE(DATE(2025,3,1),1)) -> -271.28
A24: Avril 2025 | B24: =SUMIFS(Détail!$E:$E,Détail!$D:$D,"TOTAL",Détail!$A:$A,">="&DATE(2025,4,1),Détail!$A:$A,"<"&EDATE(DATE(2025,4,1),1)) -> -189.62
A25: Mai 2025 | B25: =SUMIFS(Détail!$E:$E,Détail!$D:$D,"TOTAL",Détail!$A:$A,">="&DATE(2025,5,1),Détail!$A:$A,"<"&EDATE(DATE(2025,5,1),1)) -> -451.3
A26: Juin 2025 | B26: =SUMIFS(Détail!$E:$E,Détail!$D:$D,"TOTAL",Détail!$A:$A,">="&DATE(2025,6,1),Détail!$A:$A,"<"&EDATE(DATE(2025,6,1),1)) -> -456.05
A27: Juillet 2025 | B27: =SUMIFS(Détail!$E:$E,Détail!$D:$D,"TOTAL",Détail!$A:$A,">="&DATE(2025,7,1),Détail!$A:$A,"<"&EDATE(DATE(2025,7,1),1)) -> -566.09
A28: Août 2025 | B28: =SUMIFS(Détail!$E:$E,Détail!$D:$D,"TOTAL",Détail!$A:$A,">="&DATE(2025,8,1),Détail!$A:$A,"<"&EDATE(DATE(2025,8,1),1)) -> -229.45
A29: Septembre 2025 | B29: =SUMIFS(Détail!$E:$E,Détail!$D:$D,"TOTAL",Détail!$A:$A,">="&DATE(2025,9,1),Détail!$A:$A,"<"&EDATE(DATE(2025,9,1),1)) -> -525.42
A30: Octobre 2025 | B30: =SUMIFS(Détail!$E:$E,Détail!$D:$D,"TOTAL",Détail!$A:$A,">="&DATE(2025,10,1),Détail!$A:$A,"<"&EDATE(DATE(2025,10,1),1)) -> -295.96
A31: Novembre 2025 | B31: =SUMIFS(Détail!$E:$E,Détail!$D:$D,"TOTAL",Détail!$A:$A,">="&DATE(2025,11,1),Détail!$A:$A,"<"&EDATE(DATE(2025,11,1),1)) -> -390.86
A32: Décembre 2025 | B32: =SUMIFS(Détail!$E:$E,Détail!$D:$D,"TOTAL",Détail!$A:$A,">="&DATE(2025,12,1),Détail!$A:$A,"<"&EDATE(DATE(2025,12,1),1)) -> -42.29
A34: Carburant — Esso | C34: =SUMIF(Détail!$D:$D,"ESSO CHAMPIGNY",Détail!$E:$E)+SUMIF(Détail!$D:$D,"ESSO ST THIBAUL",Détail!$E:$E)+SUMIF(Détail!$D:$D,"ESSO31817ROC1",Détail!$E:$E)+SUMIF(Détail!$D:$D,"ESSO AULNAY",Détail!$E:$E)+SUMIF(Détail!$D:$D,"ESSO31735ROC3",Détail!$E:$E)+SUMIF(Détail!$D:$D,"ESSO ATTAINVILL",Détail!$E:$E)+SUMIF(Détail!$D:$D,"ESSO31775ROC3",Détail!$E:$E)+SUMIF(Détail!$D:$D,"ESSO31753ROC1",Détail!$E:$E)+SUMIF(Détail!$D:$D,"ESSO CHAMPILAVA",Détail!$E:$E) -> -2915
A35: Mois | B35: Montant
A36: Janvier 2025 | B36: =SUMIFS(Détail!$E:$E,Détail!$D:$D,"ESSO CHAMPIGNY",Détail!$A:$A,">="&DATE(2025,1,1),Détail!$A:$A,"<"&EDATE(DATE(2025,1,1),1))+SUMIFS(Détail!$E:$E,Détail!$D:$D,"ESSO ST THIBAUL",Détail!$A:$A,">="&DATE(2025,1,1),Détail!$A:$A,"<"&EDATE(DATE(2025,1,1),1))+SUMIFS(Détail!$E:$E,Détail!$D:$D,"ESSO31817ROC1",Détail!$A:$A,">="&DATE(2025,1,1),Détail!$A:$A,"<"&EDATE(DATE(2025,1,1),1))+SUMIFS(Détail!$E:$E,Détail!$D:$D,"ESSO AULNAY",Détail!$A:$A,">="&DATE(2025,1,1),Détail!$A:$A,"<"&EDATE(DATE(2025,1,1),1))+SUMIFS(Détail!$E:$E,Détail!$D:$D,"ESSO31735ROC3",Détail!$A:$A,">="&DATE(2025,1,1),Détail!$A:$A,"<"&EDATE(DATE(2025,1,1),1))+SUMIFS(Détail!$E:$E,Détail!$D:$D,"ESSO ATTAINVILL",Détail!$A:$A,">="&DATE(2025,1,1),Détail!$A:$A,"<"&EDATE(DATE(2025,1,1),1))+SUMIFS(Détail!$E:$E,Détail!$D:$D,"ESSO31775ROC3",Détail!$A:$A,">="&DATE(2025,1,1),Détail!$A:$A,"<"&EDATE(DATE(2025,1,1),1))+SUMIFS(Détail!$E:$E,Détail!$D:$D,"ESSO31753ROC1",Détail!$A:$A,">="&DATE(2025,1,1),Détail!$A:$A,"<"&EDATE(DATE(2025,1,1),1))+SUMIFS(Détail!$E:$E,Détail!$D:$D,"ESSO CHAMPILAVA",Détail!$A:$A,">="&DATE(2025,1,1),Détail!$A:$A,"<"&EDATE(DATE(2025,1,1),1)) -> -392.87
